Workbook

Sheet Tabe of contents
A4: Table of contents
A7: Tab | B7: Content
A8: Prices S_ACS | B8: Sulfur, ACS prices and the freight cost from different region to Morocco
A9: Phosphate historical prices | B9: Annual phosphate prices
A10: Phosphate monthly prices | B10: Monthly phosphate prices
A11: Generated data | B11: Data used to generate forecasts
A12: Cockpit_monthly | B12: Monthly simulation result on forecasted data
A13: Cockpit_yearly | B13: Yearly simulation result on forecasted data
A14: Cockpit_Formula_7 | B14: Simulation result on forecasted data of formula 7
A15: Yearly_prices_forecast_CRU | B15: Yearly forecasted formula prices from CRU
A16: Yearly_prices_forecast_S&P | B16: Yearly forecasted formula prices from S&P
A17: Monthly_prices_forecast_direct | B17: Monthly forecasted prices for linked index formulas
A18: Monthly_prices_forcast_variat | B18: Monthly forecasted prices for index variation formulas
A19: Formula_7 | B19: Monthly forecasted prices for formula 7

Sheet Inputs >

Sheet Prices S_ACS
AB1: ConvCost=20+0,05×(SFOBME​+Fret)
J2: used for ACS production cost estimation
E3: Sulphuric Acid Bulk FOB | F3: Sulphuric Acid Bulk FOB | G3: Sulphuric Acid Bulk FOB | H3: Sulphuric Acid Bulk CFR | I3: Sulphur Bulk FOB | J3: Sulphur Bulk CFR | M3: Sulphuric Acid Bulk FOB | N3: Sulphuric Acid Bulk FOB | O3: Sulphuric Acid Bulk FOB | P3: Sulphur Bulk FOB | Q3: Sulphur Bulk CFR
E4: Japan/South Korea Spot | F4: NW Europe 30 days Spot | G4: China Spot | H4: North Africa, Spot | I4: Middle East Spot | J4: North Africa | M4: Japan/South Korea Spot | N4: NW Europe 30 days Spot | O4: China Spot | P4: Middle East Spot | Q4: North Africa | S4: Prix cibles Sulphuric Acid | AB4: Formule 1: Market Basket | AE4: Formule 2: Indice Composite basé sur Europe, chine et acid base ME
B5: Year | C5: Quarter | D5: Month | E5: ACS FOB Japan | F5: ACS FOB NW Europe | G5: ACS FOB China Spot | H5: ACS CFR North Africa Spot | I5: Sulphur Bulk FOB Middle East | J5: Sulphur Bulk CFR North Africa | M5: Fret Japan to Morocco | N5: Fret NW EU to Morocco | O5: Fret China to Morocco | P5: Fret Middle East to Morocco | Q5: Freight adjustment (CRU) | S5: ACS CFR North Africa | T5: IPP ACS Origine Europe | U5: IPP ACS origine Japon | V5: Ipp ACS Origine Chine | W5: Sulfur ME to CFR Morocco | X5: Sulfur North Africa to CFR Morocco | Y5: ACS S based from Sulfur ME | Z5: ACS S based from Sulfur North Africa | AB5: IPP_Acid = 40% × IPP_NWE + 30% × IPP_Japan + 30% × IPP_China | AC5: Gain par rapport à production sur place | AE5: IPP_Acid = min((70% × IPP_NWE + 30% × IPP_China); Acid S Based ME) | AF5: Gain par rapport à production sur place
B6: 2002 | C6: 2 | D6: 5 | F6: 6 | J6: 33 | M6: 53.686275 | N6: 23.388235 | O6: =IFERROR(M6*0.9, "") -> 48.317647 | P6: 29.165429 | Q6: 20 | S6: =T6*S7/T7 -> 78.098657 | T6: =IF(F6=0, "", F6+N6) -> 29.388235 | U6: =IFERROR( E6+M6, "") | V6: =IFERROR( G6+O6, "") | W6: =IFERROR(I6+P6, "") | X6: =J6+Q6 -> 53 | Y6: =IFERROR((I6+P6)*0.33+18, "") | Z6: =IF(J6=0,0,(J6+Q6)*0.33+18) -> 35.49 | AB6: =IF(OR(T6="", U6="", V6=""), "", MAX(S6,T6)*40%+U6*30%+V6*30%) | AC6: =IF(AB6="", "", MAX(Y6, Z6)-AB6) | AE6: =IFERROR(MIN((MAX(S6,T6)*70%+V6*30%), Z6), "") | AF6: =IF(AE6="", "", MAX(AB6, AC6)-AE6)
B7: 2002 | C7: 2 | D7: 6 | F7: 6 | J7: 33 | M7: 53.686275 | N7: 23.388235 | O7: =IFERROR(M7*0.9, "") -> 48.317647 | P7: 29.165429 | Q7: 20 | S7: =T7*S8/T8 -> 78.098657 | T7: =IF(F7=0, "", F7+N7) -> 29.388235 | U7: =IFERROR( E7+M7, "") | V7: =IFERROR( G7+O7, "") | W7: =IFERROR(I7+P7, "") | X7: =J7+Q7 -> 53 | Y7: =IFERROR((I7+P7)*0.33+18, "") | Z7: =IF(J7=0,0,(J7+Q7)*0.33+18) -> 35.49 | AB7: =IF(OR(T7="", U7="", V7=""), "", MAX(S7,T7)*40%+U7*30%+V7*30%) | AC7: =IF(AB7="", "", MAX(Y7, Z7)-AB7) | AE7: =IFERROR(MIN((MAX(S7,T7)*70%+V7*30%), Z7), "") | AF7: =IF(AE7="", "", MAX(AB7, AC7)-AE7)
B8: 2002 | C8: 3 | D8: 7 | F8: 8 | J8: 39 | M8: 53.686275 | N8: 23.388235 | O8: =IFERROR(M8*0.9, "") -> 48.317647 | P8: 29.165429 | Q8: 20 | S8: =T8*S9/T9 -> 83.413617 | T8: =IF(F8=0, "", F8+N8) -> 31.388235 | U8: =IFERROR( E8+M8, "") | V8: =IFERROR( G8+O8, "") | W8: =IFERROR(I8+P8, "") | X8: =J8+Q8 -> 59 | Y8: =IFERROR((I8+P8)*0.33+18, "") | Z8: =IF(J8=0,0,(J8+Q8)*0.33+18) -> 37.47 | AB8: =IF(OR(T8="", U8="", V8=""), "", MAX(S8,T8)*40%+U8*30%+V8*30%) | AC8: =IF(AB8="", "", MAX(Y8, Z8)-AB8) | AE8: =IFERROR(MIN((MAX(S8,T8)*70%+V8*30%), Z8), "") | AF8: =IF(AE8="", "", MAX(AB8, AC8)-AE8)
B9: 2002 | C9: 3 | D9: 8 | F9: 8 | J9: 38.5 | M9: 53.686275 | N9: 23.388235 | O9: =IFERROR(M9*0.9, "") -> 48.317647 | P9: 29.165429 | Q9: 20 | S9: =T9*S10/T10 -> 83.413617 | T9: =IF(F9=0, "", F9+N9) -> 31.388235 | U9: =IFERROR( E9+M9, "") | V9: =IFERROR( G9+O9, "") | W9: =IFERROR(I9+P9, "") | X9: =J9+Q9 -> 58.5 | Y9: =IFERROR((I9+P9)*0.33+18, "") | Z9: =IF(J9=0,0,(J9+Q9)*0.33+18) -> 37.305 | AB9: =IF(OR(T9="", U9="", V9=""), "", MAX(S9,T9)*40%+U9*30%+V9*30%) | AC9: =IF(AB9="", "", MAX(Y9, Z9)-AB9) | AE9: =IFERROR(MIN((MAX(S9,T9)*70%+V9*30%), Z9), "") | AF9: =IF(AE9="", "", MAX(AB9, AC9)-AE9)
B10: 2002 | C10: 3 | D10: 9 | F10: 8 | J10: 38 | M10: 53.686275 | N10: 23.388235 | O10: =IFERROR(M10*0.9, "") -> 48.317647 | P10: 29.165429 | Q10: 20 | S10: =T10*S11/T11 -> 83.413617 | T10: =IF(F10=0, "", F10+N10) -> 31.388235 | U10: =IFERROR( E10+M10, "") | V10: =IFERROR( G10+O10, "") | W10: =IFERROR(I10+P10, "") | X10: =J10+Q10 -> 58 | Y10: =IFERROR((I10+P10)*0.33+18, "") | Z10: =IF(J10=0,0,(J10+Q10)*0.33+18) -> 37.14 | AB10: =IF(OR(T10="", U10="", V10=""), "", MAX(S10,T10)*40%+U10*30%+V10*30%) | AC10: =IF(AB10="", "", MAX(Y10, Z10)-AB10) | AE10: =IFERROR(MIN((MAX(S10,T10)*70%+V10*30%), Z10), "") | AF10: =IF(AE10="", "", MAX(AB10, AC10)-AE10)
B11: 2002 | C11: 4 | D11: 10 | F11: 8 | J11: 38 | M11: 53.686275 | N11: 23.388235 | O11: =IFERROR(M11*0.9, "") -> 48.317647 | P11: 29.165429 | Q11: 20 | S11: =T11*S12/T12 -> 83.413617 | T11: =IF(F11=0, "", F11+N11) -> 31.388235 | U11: =IFERROR( E11+M11, "") | V11: =IFERROR( G11+O11, "") | W11: =IFERROR(I11+P11, "") | X11: =J11+Q11 -> 58 | Y11: =IFERROR((I11+P11)*0.33+18, "") | Z11: =IF(J11=0,0,(J11+Q11)*0.33+18) -> 37.14 | AB11: =IF(OR(T11="", U11="", V11=""), "", MAX(S11,T11)*40%+U11*30%+V11*30%) | AC11: =IF(AB11="", "", MAX(Y11, Z11)-AB11) | AE11: =IFERROR(MIN((MAX(S11,T11)*70%+V11*30%), Z11), "") | AF11: =IF(AE11="", "", MAX(AB11, AC11)-AE11)
B12: 2002 | C12: 4 | D12: 11 | F12: 11 | J12: 39 | M12: 53.686275 | N12: 23.388235 | O12: =IFERROR(M12*0.9, "") -> 48.317647 | P12: 29.165429 | Q12: 20 | S12: =T12*S13/T13 -> 91.386058 | T12: =IF(F12=0, "", F12+N12) -> 34.388235 | U12: =IFERROR( E12+M12, "") | V12: =IFERROR( G12+O12, "") | W12: =IFERROR(I12+P12, "") | X12: =J12+Q12 -> 59 | Y12: =IFERROR((I12+P12)*0.33+18, "") | Z12: =IF(J12=0,0,(J12+Q12)*0.33+18) -> 37.47 | AB12: =IF(OR(T12="", U12="", V12=""), "", MAX(S12,T12)*40%+U12*30%+V12*30%) | AC12: =IF(AB12="", "", MAX(Y12, Z12)-AB12) | AE12: =IFERROR(MIN((MAX(S12,T12)*70%+V12*30%), Z12), "") | AF12: =IF(AE12="", "", MAX(AB12, AC12)-AE12)
B13: 2002 | C13: 4 | D13: 12 | F13: 11 | J13: 39 | M13: 53.686275 | N13: 23.388235 | O13: =IFERROR(M13*0.9, "") -> 48.317647 | P13: 29.165429 | Q13: 20 | S13: =T13*S14/T14 -> 91.386058 | T13: =IF(F13=0, "", F13+N13) -> 34.388235 | U13: =IFERROR( E13+M13, "") | V13: =IFERROR( G13+O13, "") | W13: =IFERROR(I13+P13, "") | X13: =J13+Q13 -> 59 | Y13: =IFERROR((I13+P13)*0.33+18, "") | Z13: =IF(J13=0,0,(J13+Q13)*0.33+18) -> 37.47 | AB13: =IF(OR(T13="", U13="", V13=""), "", MAX(S13,T13)*40%+U13*30%+V13*30%) | AC13: =IF(AB13="", "", MAX(Y13, Z13)-AB13) | AE13: =IFERROR(MIN((MAX(S13,T13)*70%+V13*30%), Z13), "") | AF13: =IF(AE13="", "", MAX(AB13, AC13)-AE13)
B14: 2003 | C14: 1 | D14: 1 | F14: 11.666667 | J14: 57.333333 | M14: 53.686275 | N14: 23.388235 | O14: =IFERROR(M14*0.9, "") -> 48.317647 | P14: 29.165429 | Q14: 20 | S14: =T14*S15/T15 -> 93.157712 | T14: =IF(F14=0, "", F14+N14) -> 35.054902 | U14: =IFERROR( E14+M14, "") | V14: =IFERROR( G14+O14, "") | W14: =IFERROR(I14+P14, "") | X14: =J14+Q14 -> 77.333333 | Y14: =IFERROR((I14+P14)*0.33+18, "") | Z14: =IF(J14=0,0,(J14+Q14)*0.33+18) -> 43.52 | AB14: =IF(OR(T14="", U14="", V14=""), "", MAX(S14,T14)*40%+U14*30%+V14*30%) | AC14: =IF(AB14="", "", MAX(Y14, Z14)-AB14) | AE14: =IFERROR(MIN((MAX(S14,T14)*70%+V14*30%), Z14), "") | AF14: =IF(AE14="", "", MAX(AB14, AC14)-AE14)
B15: 2003 | C15: 1 | D15: 2 | F15: 13 | J15: 61 | M15: 53.686275 | N15: 23.388235 | O15: =IFERROR(M15*0.9, "") -> 48.317647 | P15: 29.165429 | Q15: 20 | S15: =T15*S16/T16 -> 96.701019 | T15: =IF(F15=0, "", F15+N15) -> 36.388235 | U15: =IFERROR( E15+M15, "") | V15: =IFERROR( G15+O15, "") | W15: =IFERROR(I15+P15, "") | X15: =J15+Q15 -> 81 | Y15: =IFERROR((I15+P15)*0.33+18, "") | Z15: =IF(J15=0,0,(J15+Q15)*0.33+18) -> 44.73 | AB15: =IF(OR(T15="", U15="", V15=""), "", MAX(S15,T15)*40%+U15*30%+V15*30%) | AC15: =IF(AB15="", "", MAX(Y15, Z15)-AB15) | AE15: =IFERROR(MIN((MAX(S15,T15)*70%+V15*30%), Z15), "") | AF15: =IF(AE15="", "", MAX(AB15, AC15)-AE15)
B16: 2003 | C16: 1 | D16: 3 | F16: 13 | J16: 62 | M16: 53.686275 | N16: 23.388235 | O16: =IFERROR(M16*0.9, "") -> 48.317647 | P16: 29.165429 | Q16: 20 | S16: =T16*S17/T17 -> 96.701019 | T16: =IF(F16=0, "", F16+N16) -> 36.388235 | U16: =IFERROR( E16+M16, "") | V16: =IFERROR( G16+O16, "") | W16: =IFERROR(I16+P16, "") | X16: =J16+Q16 -> 82 | Y16: =IFERROR((I16+P16)*0.33+18, "") | Z16: =IF(J16=0,0,(J16+Q16)*0.33+18) -> 45.06 | AB16: =IF(OR(T16="", U16="", V16=""), "", MAX(S16,T16)*40%+U16*30%+V16*30%) | AC16: =IF(AB16="", "", MAX(Y16, Z16)-AB16) | AE16: =IFERROR(MIN((MAX(S16,T16)*70%+V16*30%), Z16), "") | AF16: =IF(AE16="", "", MAX(AB16, AC16)-AE16)
B17: 2003 | C17: 2 | D17: 4 | F17: 13 | J17: 60.5 | M17: 53.686275 | N17: 23.388235 | O17: =IFERROR(M17*0.9, "") -> 48.317647 | P17: 29.165429 | Q17: 20 | S17: =T17*S18/T18 -> 96.701019 | T17: =IF(F17=0, "", F17+N17) -> 36.388235 | U17: =IFERROR( E17+M17, "") | V17: =IFERROR( G17+O17, "") | W17: =IFERROR(I17+P17, "") | X17: =J17+Q17 -> 80.5 | Y17: =IFERROR((I17+P17)*0.33+18, "") | Z17: =IF(J17=0,0,(J17+Q17)*0.33+18) -> 44.565 | AB17: =IF(OR(T17="", U17="", V17=""), "", MAX(S17,T17)*40%+U17*30%+V17*30%) | AC17: =IF(AB17="", "", MAX(Y17, Z17)-AB17) | AE17: =IFERROR(MIN((MAX(S17,T17)*70%+V17*30%), Z17), "") | AF17: =IF(AE17="", "", MAX(AB17, AC17)-AE17)
B18: 2003 | C18: 2 | D18: 5 | F18: 13 | J18: 60.5 | M18: 53.686275 | N18: 23.388235 | O18: =IFERROR(M18*0.9, "") -> 48.317647 | P18: 29.165429 | Q18: 20 | S18: =T18*S19/T19 -> 96.701019 | T18: =IF(F18=0, "", F18+N18) -> 36.388235 | U18: =IFERROR( E18+M18, "") | V18: =IFERROR( G18+O18, "") | W18: =IFERROR(I18+P18, "") | X18: =J18+Q18 -> 80.5 | Y18: =IFERROR((I18+P18)*0.33+18, "") | Z18: =IF(J18=0,0,(J18+Q18)*0.33+18) -> 44.565 | AB18: =IF(OR(T18="", U18="", V18=""), "", MAX(S18,T18)*40%+U18*30%+V18*30%) | AC18: =IF(AB18="", "", MAX(Y18, Z18)-AB18) | AE18: =IFERROR(MIN((MAX(S18,T18)*70%+V18*30%), Z18), "") | AF18: =IF(AE18="", "", MAX(AB18, AC18)-AE18)
B19: 2003 | C19: 2 | D19: 6 | F19: 17.5 | I19: 63 | J19: 60.5 | M19: 53.686275 | N19: 23.388235 | O19: =IFERROR(M19*0.9, "") -> 48.317647 | P19: 29.165429 | Q19: 20 | S19: =T19*S20/T20 -> 108.65968 | T19: =IF(F19=0, "", F19+N19) -> 40.888235 | U19: =IFERROR( E19+M19, "") | V19: =IFERROR( G19+O19, "") | W19: =IFERROR(I19+P19, "") -> 92.165429 | X19: =J19+Q19 -> 80.5 | Y19: =IFERROR((I19+P19)*0.33+18, "") -> 48.414592 | Z19: =IF(J19=0,0,(J19+Q19)*0.33+18) -> 44.565 | AB19: =IF(OR(T19="", U19="", V19=""), "", MAX(S19,T19)*40%+U19*30%+V19*30%) | AC19: =IF(AB19="", "", MAX(Y19, Z19)-AB19) | AE19: =IFERROR(MIN((MAX(S19,T19)*70%+V19*30%), Z19), "") | AF19: =IF(AE19="", "", MAX(AB19, AC19)-AE19)
B20: 2003 | C20: 3 | D20: 7 | F20: 22 | I20: 59 | J20: 65.333333 | M20: 53.686275 | N20: 23.388235 | O20: =IFERROR(M20*0.9, "") -> 48.317647 | P20: 29.165429 | Q20: 20 | S20: =T20*S21/T21 -> 120.61834 | T20: =IF(F20=0, "", F20+N20) -> 45.388235 | U20: =IFERROR( E20+M20, "") | V20: =IFERROR( G20+O20, "") | W20: =IFERROR(I20+P20, "") -> 88.165429 | X20: =J20+Q20 -> 85.333333 | Y20: =IFERROR((I20+P20)*0.33+18, "") -> 47.094592 | Z20: =IF(J20=0,0,(J20+Q20)*0.33+18) -> 46.16 | AB20: =IF(OR(T20="", U20="", V20=""), "", MAX(S20,T20)*40%+U20*30%+V20*30%) | AC20: =IF(AB20="", "", MAX(Y20, Z20)-AB20) | AE20: =IFERROR(MIN((MAX(S20,T20)*70%+V20*30%), Z20), "") | AF20: =IF(AE20="", "", MAX(AB20, AC20)-AE20)
B21: 2003 | C21: 3 | D21: 8 | F21: 22 | I21: 58 | J21: 69.5 | M21: 53.686275 | N21: 23.388235 | O21: =IFERROR(M21*0.9, "") -> 48.317647 | P21: 29.165429 | Q21: 20 | S21: =T21*S22/T22 -> 120.61834 | T21: =IF(F21=0, "", F21+N21) -> 45.388235 | U21: =IFERROR( E21+M21, "") | V21: =IFERROR( G21+O21, "") | W21: =IFERROR(I21+P21, "") -> 87.165429 | X21: =J21+Q21 -> 89.5 | Y21: =IFERROR((I21+P21)*0.33+18, "") -> 46.764592 | Z21: =IF(J21=0,0,(J21+Q21)*0.33+18) -> 47.535 | AB21: =IF(OR(T21="", U21="", V21=""), "", MAX(S21,T21)*40%+U21*30%+V21*30%) | AC21: =IF(AB21="", "", MAX(Y21, Z21)-AB21) | AE21: =IFERROR(MIN((MAX(S21,T21)*70%+V21*30%), Z21), "") | AF21: =IF(AE21="", "", MAX(AB21, AC21)-AE21)
B22: 2003 | C22: 3 | D22: 9 | F22: 22 | I22: 61.5 | J22: 69.5 | M22: 53.686275 | N22: 23.388235 | O22: =IFERROR(M22*0.9, "") -> 48.317647 | P22: 29.165429 | Q22: 20 | S22: =T22*S23/T23 -> 120.61834 | T22: =IF(F22=0, "", F22+N22) -> 45.388235 | U22: =IFERROR( E22+M22, "") | V22: =IFERROR( G22+O22, "") | W22: =IFERROR(I22+P22, "") -> 90.665429 | X22: =J22+Q22 -> 89.5 | Y22: =IFERROR((I22+P22)*0.33+18, "") -> 47.919592 | Z22: =IF(J22=0,0,(J22+Q22)*0.33+18) -> 47.535 | AB22: =IF(OR(T22="", U22="", V22=""), "", MAX(S22,T22)*40%+U22*30%+V22*30%) | AC22: =IF(AB22="", "", MAX(Y22, Z22)-AB22) | AE22: =IFERROR(MIN((MAX(S22,T22)*70%+V22*30%), Z22), "") | AF22: =IF(AE22="", "", MAX(AB22, AC22)-AE22)
B23: 2003 | C23: 4 | D23: 10 | F23: 28 | I23: 63 | J23: 69.75 | M23: 53.686275 | N23: 23.388235 | O23: =IFERROR(M23*0.9, "") -> 48.317647 | P23: 29.165429 | Q23: 20 | S23: =T23*S24/T24 -> 136.56322 | T23: =IF(F23=0, "", F23+N23) -> 51.388235 | U23: =IFERROR( E23+M23, "") | V23: =IFERROR( G23+O23, "") | W23: =IFERROR(I23+P23, "") -> 92.165429 | X23: =J23+Q23 -> 89.75 | Y23: =IFERROR((I23+P23)*0.33+18, "") -> 48.414592 | Z23: =IF(J23=0,0,(J23+Q23)*0.33+18) -> 47.6175 | AB23: =IF(OR(T23="", U23="", V23=""), "", MAX(S23,T23)*40%+U23*30%+V23*30%) | AC23: =IF(AB23="", "", MAX(Y23, Z23)-AB23) | AE23: =IFERROR(MIN((MAX(S23,T23)*70%+V23*30%), Z23), "") | AF23: =IF(AE23="", "", MAX(AB23, AC23)-AE23)
B24: 2003 | C24: 4 | D24: 11 | F24: 28 | I24: 68 | J24: 71 | M24: 53.686275 | N24: 23.388235 | O24: =IFERROR(M24*0.9, "") -> 48.317647 | P24: 29.165429 | Q24: 20 | S24: =T24*S25/T25 -> 136.56322 | T24: =IF(F24=0, "", F24+N24) -> 51.388235 | U24: =IFERROR( E24+M24, "") | V24: =IFERROR( G24+O24, "") | W24: =IFERROR(I24+P24, "") -> 97.165429 | X24: =J24+Q24 -> 91 | Y24: =IFERROR((I24+P24)*0.33+18, "") -> 50.064592 | Z24: =IF(J24=0,0,(J24+Q24)*0.33+18) -> 48.03 | AB24: =IF(OR(T24="", U24="", V24=""), "", MAX(S24,T24)*40%+U24*30%+V24*30%) | AC24: =IF(AB24="", "", MAX(Y24, Z24)-AB24) | AE24: =IFERROR(MIN((MAX(S24,T24)*70%+V24*30%), Z24), "") | AF24: =IF(AE24="", "", MAX(AB24, AC24)-AE24)
B25: 2003 | C25: 4 | D25: 12 | F25: 28 | I25: 72 | J25: 71 | M25: 53.686275 | N25: 23.388235 | O25: =IFERROR(M25*0.9, "") -> 48.317647 | P25: 29.165429 | Q25: 20 | S25: =T25*S26/T26 -> 136.56322 | T25: =IF(F25=0, "", F25+N25) -> 51.388235 | U25: =IFERROR( E25+M25, "") | V25: =IFERROR( G25+O25, "") | W25: =IFERROR(I25+P25, "") -> 101.16543 | X25: =J25+Q25 -> 91 | Y25: =IFERROR((I25+P25)*0.33+18, "") -> 51.384592 | Z25: =IF(J25=0,0,(J25+Q25)*0.33+18) -> 48.03 | AB25: =IF(OR(T25="", U25="", V25=""), "", MAX(S25,T25)*40%+U25*30%+V25*30%) | AC25: =IF(AB25="", "", MAX(Y25, Z25)-AB25) | AE25: =IFERROR(MIN((MAX(S25,T25)*70%+V25*30%), Z25), "") | AF25: =IF(AE25="", "", MAX(AB25, AC25)-AE25)
B26: 2004 | C26: 1 | D26: 1 | F26: 31.5 | I26: 74 | J26: 76 | M26: 53.686275 | N26: 23.388235 | O26: =IFERROR(M26*0.9, "") -> 48.317647 | P26: 29.165429 | Q26: 20 | S26: =T26*S27/T27 -> 145.8644 | T26: =IF(F26=0, "", F26+N26) -> 54.888235 | U26: =IFERROR( E26+M26, "") | V26: =IFERROR( G26+O26, "") | W26: =IFERROR(I26+P26, "") -> 103.16543 | X26: =J26+Q26 -> 96 | Y26: =IFERROR((I26+P26)*0.33+18, "") -> 52.044592 | Z26: =IF(J26=0,0,(J26+Q26)*0.33+18) -> 49.68 | AB26: =IF(OR(T26="", U26="", V26=""), "", MAX(S26,T26)*40%+U26*30%+V26*30%) | AC26: =IF(AB26="", "", MAX(Y26, Z26)-AB26) | AE26: =IFERROR(MIN((MAX(S26,T26)*70%+V26*30%), Z26), "") | AF26: =IF(AE26="", "", MAX(AB26, AC26)-AE26)
B27: 2004 | C27: 1 | D27: 2 | F27: 35 | I27: 66 | J27: 78 | M27: 53.686275 | N27: 23.388235 | O27: =IFERROR(M27*0.9, "") -> 48.317647 | P27: 29.165429 | Q27: 20 | S27: =T27*S28/T28 -> 155.16559 | T27: =IF(F27=0, "", F27+N27) -> 58.388235 | U27: =IFERROR( E27+M27, "") | V27: =IFERROR( G27+O27, "") | W27: =IFERROR(I27+P27, "") -> 95.165429 | X27: =J27+Q27 -> 98 | Y27: =IFERROR((I27+P27)*0.33+18, "") -> 49.404592 | Z27: =IF(J27=0,0,(J27+Q27)*0.33+18) -> 50.34 | AB27: =IF(OR(T27="", U27="", V27=""), "", MAX(S27,T27)*40%+U27*30%+V27*30%) | AC27: =IF(AB27="", "", MAX(Y27, Z27)-AB27) | AE27: =IFERROR(MIN((MAX(S27,T27)*70%+V27*30%), Z27), "") | AF27: =IF(AE27="", "", MAX(AB27, AC27)-AE27)
B28: 2004 | C28: 1 | D28: 3 | F28: 35 | I28: 64.333333 | J28: 77.5 | M28: 53.686275 | N28: 23.388235 | O28: =IFERROR(M28*0.9, "") -> 48.317647 | P28: 29.165429 | Q28: 20 | S28: =T28*S29/T29 -> 155.16559 | T28: =IF(F28=0, "", F28+N28) -> 58.388235 | U28: =IFERROR( E28+M28, "") | V28: =IFERROR( G28+O28, "") | W28: =IFERROR(I28+P28, "") -> 93.498763 | X28: =J28+Q28 -> 97.5 | Y28: =IFERROR((I28+P28)*0.33+18, "") -> 48.854592 | Z28: =IF(J28=0,0,(J28+Q28)*0.33+18) -> 50.175 | AB28: =IF(OR(T28="", U28="", V28=""), "", MAX(S28,T28)*40%+U28*30%+V28*30%) | AC28: =IF(AB28="", "", MAX(Y28, Z28)-AB28) | AE28: =IFERROR(MIN((MAX(S28,T28)*70%+V28*30%), Z28), "") | AF28: =IF(AE28="", "", MAX(AB28, AC28)-AE28)
B29: 2004 | C29: 2 | D29: 4 | F29: 35 | I29: 61.333333 | J29: 77.333333 | M29: 53.686275 | N29: 23.388235 | O29: =IFERROR(M29*0.9, "") -> 48.317647 | P29: 29.165429 | Q29: 20 | S29: =T29*S30/T30 -> 155.16559 | T29: =IF(F29=0, "", F29+N29) -> 58.388235 | U29: =IFERROR( E29+M29, "") | V29: =IFERROR( G29+O29, "") | W29: =IFERROR(I29+P29, "") -> 90.498763 | X29: =J29+Q29 -> 97.333333 | Y29: =IFERROR((I29+P29)*0.33+18, "") -> 47.864592 | Z29: =IF(J29=0,0,(J29+Q29)*0.33+18) -> 50.12 | AB29: =IF(OR(T29="", U29="", V29=""), "", MAX(S29,T29)*40%+U29*30%+V29*30%) | AC29: =IF(AB29="", "", MAX(Y29, Z29)-AB29) | AE29: =IFERROR(MIN((MAX(S29,T29)*70%+V29*30%), Z29), "") | AF29: =IF(AE29="", "", MAX(AB29, AC29)-AE29)
B30: 2004 | C30: 2 | D30: 5 | F30: 35 | I30: 65 | J30: 78 | M30: 53.686275 | N30: 23.388235 | O30: =IFERROR(M30*0.9, "") -> 48.317647 | P30: 29.165429 | Q30: 20 | S30: =T30*S31/T31 -> 155.16559 | T30: =IF(F30=0, "", F30+N30) -> 58.388235 | U30: =IFERROR( E30+M30, "") | V30: =IFERROR( G30+O30, "") | W30: =IFERROR(I30+P30, "") -> 94.165429 | X30: =J30+Q30 -> 98 | Y30: =IFERROR((I30+P30)*0.33+18, "") -> 49.074592 | Z30: =IF(J30=0,0,(J30+Q30)*0.33+18) -> 50.34 | AB30: =IF(OR(T30="", U30="", V30=""), "", MAX(S30,T30)*40%+U30*30%+V30*30%) | AC30: =IF(AB30="", "", MAX(Y30, Z30)-AB30) | AE30: =IFERROR(MIN((MAX(S30,T30)*70%+V30*30%), Z30), "") | AF30: =IF(AE30="", "", MAX(AB30, AC30)-AE30)
... B93: 2009 | C93: 3 | D93: 8 | F93: -5 | I93: 34.75 | J93: 37.5 | M93: 53.686275 | N93: 23.388235 | O93: =IFERROR(M93*0.9, "") -> 48.317647 | P93: 24.5 | Q93: 20 | S93: =T93*S94/T94 -> 48.866373 | T93: =IF(F93=0, "", F93+N93) -> 18.388235 | U93: =IFERROR( E93+M93, "") | V93: =IFERROR( G93+O93, "") | W93: =IFERROR(I93+P93, "") -> 59.25 | X93: =J93+Q93 -> 57.5 | Y93: =IFERROR((I93+P93)*0.33+18, "") -> 37.5525 | Z93: =IF(J93=0,0,(J93+Q93)*0.33+18) -> 36.975 | AB93: =IF(OR(T93="", U93="", V93=""), "", MAX(S93,T93)*40%+U93*30%+V93*30%) | AC93: =IF(AB93="", "", MAX(Y93, Z93)-AB93) | AE93: =IFERROR(MIN((MAX(S93,T93)*70%+V93*30%), Z93), "") | AF93: =IF(AE93="", "", MAX(AB93, AC93)-AE93)
B94: 2009 | C94: 3 | D94: 9 | F94: 0 | I94: 40 | J94: 37.5 | M94: 53.686275 | N94: 23.388235 | O94: =IFERROR(M94*0.9, "") -> 48.317647 | P94: 22.75 | Q94: 20 | S94: =T94*S95/T95 -> 48.866373 | T94: =T93 -> 18.388235 | U94: =IFERROR( E94+M94, "") | V94: =IFERROR( G94+O94, "") | W94: =IFERROR(I94+P94, "") -> 62.75 | X94: =J94+Q94 -> 57.5 | Y94: =IFERROR((I94+P94)*0.33+18, "") -> 38.7075 | Z94: =IF(J94=0,0,(J94+Q94)*0.33+18) -> 36.975 | AB94: =IF(OR(T94="", U94="", V94=""), "", MAX(S94,T94)*40%+U94*30%+V94*30%) | AC94: =IF(AB94="", "", MAX(Y94, Z94)-AB94) | AE94: =IFERROR(MIN((MAX(S94,T94)*70%+V94*30%), Z94), "") | AF94: =IF(AE94="", "", MAX(AB94, AC94)-AE94)
B95: 2009 | C95: 4 | D95: 10 | F95: -5.2 | I95: 44.6 | J95: 37.5 | M95: 53.686275 | N95: 23.388235 | O95: =IFERROR(M95*0.9, "") -> 48.317647 | P95: 22.6 | Q95: 20 | S95: =T95*S96/T96 -> 48.334877 | T95: =IF(F95=0, "", F95+N95) -> 18.188235 | U95: =IFERROR( E95+M95, "") | V95: =IFERROR( G95+O95, "") | W95: =IFERROR(I95+P95, "") -> 67.2 | X95: =J95+Q95 -> 57.5 | Y95: =IFERROR((I95+P95)*0.33+18, "") -> 40.176 | Z95: =IF(J95=0,0,(J95+Q95)*0.33+18) -> 36.975 | AB95: =IF(OR(T95="", U95="", V95=""), "", MAX(S95,T95)*40%+U95*30%+V95*30%) | AC95: =IF(AB95="", "", MAX(Y95, Z95)-AB95) | AE95: =IFERROR(MIN((MAX(S95,T95)*70%+V95*30%), Z95), "") | AF95: =IF(AE95="", "", MAX(AB95, AC95)-AE95)
B96: 2009 | C96: 4 | D96: 11 | F96: -13 | I96: 55.75 | J96: 37.5 | M96: 53.686275 | N96: 23.388235 | O96: =IFERROR(M96*0.9, "") -> 48.317647 | P96: 25.25 | Q96: 20 | S96: =T96*S97/T97 -> 27.606531 | T96: =IF(F96=0, "", F96+N96) -> 10.388235 | U96: =IFERROR( E96+M96, "") | V96: =IFERROR( G96+O96, "") | W96: =IFERROR(I96+P96, "") -> 81 | X96: =J96+Q96 -> 57.5 | Y96: =IFERROR((I96+P96)*0.33+18, "") -> 44.73 | Z96: =IF(J96=0,0,(J96+Q96)*0.33+18) -> 36.975 | AB96: =IF(OR(T96="", U96="", V96=""), "", MAX(S96,T96)*40%+U96*30%+V96*30%) | AC96: =IF(AB96="", "", MAX(Y96, Z96)-AB96) | AE96: =IFERROR(MIN((MAX(S96,T96)*70%+V96*30%), Z96), "") | AF96: =IF(AE96="", "", MAX(AB96, AC96)-AE96)
B97: 2009 | C97: 4 | D97: 12 | F97: -0.6 | I97: 68.2 | J97: 37.5 | M97: 53.686275 | N97: 23.388235 | O97: =IFERROR(M97*0.9, "") -> 48.317647 | P97: 28.5 | Q97: 20 | S97: =T97*S98/T98 -> 60.559287 | T97: =IF(F97=0, "", F97+N97) -> 22.788235 | U97: =IFERROR( E97+M97, "") | V97: =IFERROR( G97+O97, "") | W97: =IFERROR(I97+P97, "") -> 96.7 | X97: =J97+Q97 -> 57.5 | Y97: =IFERROR((I97+P97)*0.33+18, "") -> 49.911 | Z97: =IF(J97=0,0,(J97+Q97)*0.33+18) -> 36.975 | AB97: =IF(OR(T97="", U97="", V97=""), "", MAX(S97,T97)*40%+U97*30%+V97*30%) | AC97: =IF(AB97="", "", MAX(Y97, Z97)-AB97) | AE97: =IFERROR(MIN((MAX(S97,T97)*70%+V97*30%), Z97), "") | AF97: =IF(AE97="", "", MAX(AB97, AC97)-AE97)
B98: 2010 | C98: 1 | D98: 1 | F98: 20 | I98: 122.75 | J98: 63.875 | M98: 53.686275 | N98: 23.388235 | O98: =IFERROR(M98*0.9, "") -> 48.317647 | P98: 30.25 | Q98: 20 | S98: =T98*S99/T99 -> 115.30338 | T98: =IF(F98=0, "", F98+N98) -> 43.388235 | U98: =IFERROR( E98+M98, "") | V98: =IFERROR( G98+O98, "") | W98: =IFERROR(I98+P98, "") -> 153 | X98: =J98+Q98 -> 83.875 | Y98: =IFERROR((I98+P98)*0.33+18, "") -> 68.49 | Z98: =IF(J98=0,0,(J98+Q98)*0.33+18) -> 45.67875 | AB98: =IF(OR(T98="", U98="", V98=""), "", MAX(S98,T98)*40%+U98*30%+V98*30%) | AC98: =IF(AB98="", "", MAX(Y98, Z98)-AB98) | AE98: =IFERROR(MIN((MAX(S98,T98)*70%+V98*30%), Z98), "") | AF98: =IF(AE98="", "", MAX(AB98, AC98)-AE98)
B99: 2010 | C99: 1 | D99: 2 | F99: 47.5 | I99: 167 | J99: 67.625 | M99: 53.686275 | N99: 23.388235 | O99: =IFERROR(M99*0.9, "") -> 48.317647 | P99: 28.25 | Q99: 20 | S99: =T99*S100/T100 -> 188.38409 | T99: =IF(F99=0, "", F99+N99) -> 70.888235 | U99: =IFERROR( E99+M99, "") | V99: =IFERROR( G99+O99, "") | W99: =IFERROR(I99+P99, "") -> 195.25 | X99: =J99+Q99 -> 87.625 | Y99: =IFERROR((I99+P99)*0.33+18, "") -> 82.4325 | Z99: =IF(J99=0,0,(J99+Q99)*0.33+18) -> 46.91625 | AB99: =IF(OR(T99="", U99="", V99=""), "", MAX(S99,T99)*40%+U99*30%+V99*30%) | AC99: =IF(AB99="", "", MAX(Y99, Z99)-AB99) | AE99: =IFERROR(MIN((MAX(S99,T99)*70%+V99*30%), Z99), "") | AF99: =IF(AE99="", "", MAX(AB99, AC99)-AE99)
B100: 2010 | C100: 1 | D100: 3 | F100: 50 | I100: 181 | J100: 67 | M100: 53.686275 | N100: 23.388235 | O100: =IFERROR(M100*0.9, "") -> 48.317647 | P100: 33.25 | Q100: 20 | S100: =T100*S101/T101 -> 195.02779 | T100: =IF(F100=0, "", F100+N100) -> 73.388235 | U100: =IFERROR( E100+M100, "") | V100: =IFERROR( G100+O100, "") | W100: =IFERROR(I100+P100, "") -> 214.25 | X100: =J100+Q100 -> 87 | Y100: =IFERROR((I100+P100)*0.33+18, "") -> 88.7025 | Z100: =IF(J100=0,0,(J100+Q100)*0.33+18) -> 46.71 | AB100: =IF(OR(T100="", U100="", V100=""), "", MAX(S100,T100)*40%+U100*30%+V100*30%) | AC100: =IF(AB100="", "", MAX(Y100, Z100)-AB100) | AE100: =IFERROR(MIN((MAX(S100,T100)*70%+V100*30%), Z100), "") | AF100: =IF(AE100="", "", MAX(AB100, AC100)-AE100)
B101: 2010 | C101: 2 | D101: 4 | F101: 50 | I101: 178.6 | J101: 67 | M101: 53.686275 | N101: 23.388235 | O101: =IFERROR(M101*0.9, "") -> 48.317647 | P101: 31.8 | Q101: 20 | S101: =T101*S102/T102 -> 195.02779 | T101: =IF(F101=0, "", F101+N101) -> 73.388235 | U101: =IFERROR( E101+M101, "") | V101: =IFERROR( G101+O101, "") | W101: =IFERROR(I101+P101, "") -> 210.4 | X101: =J101+Q101 -> 87 | Y101: =IFERROR((I101+P101)*0.33+18, "") -> 87.432 | Z101: =IF(J101=0,0,(J101+Q101)*0.33+18) -> 46.71 | AB101: =IF(OR(T101="", U101="", V101=""), "", MAX(S101,T101)*40%+U101*30%+V101*30%) | AC101: =IF(AB101="", "", MAX(Y101, Z101)-AB101) | AE101: =IFERROR(MIN((MAX(S101,T101)*70%+V101*30%), Z101), "") | AF101: =IF(AE101="", "", MAX(AB101, AC101)-AE101)
B102: 2010 | C102: 2 | D102: 5 | F102: 50 | I102: 121.5 | J102: 67.625 | M102: 53.686275 | N102: 23.388235 | O102: =IFERROR(M102*0.9, "") -> 48.317647 | P102: 32.5 | Q102: 20 | S102: =T102*S103/T103 -> 195.02779 | T102: =IF(F102=0, "", F102+N102) -> 73.388235 | U102: =IFERROR( E102+M102, "") | V102: =IFERROR( G102+O102, "") | W102: =IFERROR(I102+P102, "") -> 154 | X102: =J102+Q102 -> 87.625 | Y102: =IFERROR((I102+P102)*0.33+18, "") -> 68.82 | Z102: =IF(J102=0,0,(J102+Q102)*0.33+18) -> 46.91625 | AB102: =IF(OR(T102="", U102="", V102=""), "", MAX(S102,T102)*40%+U102*30%+V102*30%) | AC102: =IF(AB102="", "", MAX(Y102, Z102)-AB102) | AE102: =IFERROR(MIN((MAX(S102,T102)*70%+V102*30%), Z102), "") | AF102: =IF(AE102="", "", MAX(AB102, AC102)-AE102)
B103: 2010 | C103: 2 | D103: 6 | F103: 50 | I103: 80.75 | J103: 69.5 | M103: 53.686275 | N103: 23.388235 | O103: =IFERROR(M103*0.9, "") -> 48.317647 | P103: 27 | Q103: 20 | S103: =T103*S104/T104 -> 195.02779 | T103: =IF(F103=0, "", F103+N103) -> 73.388235 | U103: =IFERROR( E103+M103, "") | V103: =IFERROR( G103+O103, "") | W103: =IFERROR(I103+P103, "") -> 107.75 | X103: =J103+Q103 -> 89.5 | Y103: =IFERROR((I103+P103)*0.33+18, "") -> 53.5575 | Z103: =IF(J103=0,0,(J103+Q103)*0.33+18) -> 47.535 | AB103: =IF(OR(T103="", U103="", V103=""), "", MAX(S103,T103)*40%+U103*30%+V103*30%) | AC103: =IF(AB103="", "", MAX(Y103, Z103)-AB103) | AE103: =IFERROR(MIN((MAX(S103,T103)*70%+V103*30%), Z103), "") | AF103: =IF(AE103="", "", MAX(AB103, AC103)-AE103)
B104: 2010 | C104: 3 | D104: 7 | F104: 50 | I104: 66.6 | J104: 70.1 | M104: 53.686275 | N104: 23.388235 | O104: =IFERROR(M104*0.9, "") -> 48.317647 | P104: 24.4 | Q104: 20 | S104: =T104*S105/T105 -> 195.02779 | T104: =IF(F104=0, "", F104+N104) -> 73.388235 | U104: =IFERROR( E104+M104, "") | V104: =IFERROR( G104+O104, "") | W104: =IFERROR(I104+P104, "") -> 91 | X104: =J104+Q104 -> 90.1 | Y104: =IFERROR((I104+P104)*0.33+18, "") -> 48.03 | Z104: =IF(J104=0,0,(J104+Q104)*0.33+18) -> 47.733 | AB104: =IF(OR(T104="", U104="", V104=""), "", MAX(S104,T104)*40%+U104*30%+V104*30%) | AC104: =IF(AB104="", "", MAX(Y104, Z104)-AB104) | AE104: =IFERROR(MIN((MAX(S104,T104)*70%+V104*30%), Z104), "") | AF104: =IF(AE104="", "", MAX(AB104, AC104)-AE104)
B105: 2010 | C105: 3 | D105: 8 | F105: 51.25 | I105: 123 | J105: 70.125 | M105: 53.686275 | N105: 23.388235 | O105: =IFERROR(M105*0.9, "") -> 48.317647 | P105: 28.25 | Q105: 20 | S105: =T105*S106/T106 -> 198.34964 | T105: =IF(F105=0, "", F105+N105) -> 74.638235 | U105: =IFERROR( E105+M105, "") | V105: =IFERROR( G105+O105, "") | W105: =IFERROR(I105+P105, "") -> 151.25 | X105: =J105+Q105 -> 90.125 | Y105: =IFERROR((I105+P105)*0.33+18, "") -> 67.9125 | Z105: =IF(J105=0,0,(J105+Q105)*0.33+18) -> 47.74125 | AB105: =IF(OR(T105="", U105="", V105=""), "", MAX(S105,T105)*40%+U105*30%+V105*30%) | AC105: =IF(AB105="", "", MAX(Y105, Z105)-AB105) | AE105: =IFERROR(MIN((MAX(S105,T105)*70%+V105*30%), Z105), "") | AF105: =IF(AE105="", "", MAX(AB105, AC105)-AE105)
B106: 2010 | C106: 3 | D106: 9 | F106: 55 | I106: 148.4 | J106: 72 | M106: 53.686275 | N106: 23.388235 | O106: =IFERROR(M106*0.9, "") -> 48.317647 | P106: 29.6 | Q106: 20 | S106: =T106*S107/T107 -> 208.31519 | T106: =IF(F106=0, "", F106+N106) -> 78.388235 | U106: =IFERROR( E106+M106, "") | V106: =IFERROR( G106+O106, "") | W106: =IFERROR(I106+P106, "") -> 178 | X106: =J106+Q106 -> 92 | Y106: =IFERROR((I106+P106)*0.33+18, "") -> 76.74 | Z106: =IF(J106=0,0,(J106+Q106)*0.33+18) -> 48.36 | AB106: =IF(OR(T106="", U106="", V106=""), "", MAX(S106,T106)*40%+U106*30%+V106*30%) | AC106: =IF(AB106="", "", MAX(Y106, Z106)-AB106) | AE106: =IFERROR(MIN((MAX(S106,T106)*70%+V106*30%), Z106), "") | AF106: =IF(AE106="", "", MAX(AB106, AC106)-AE106)
... B127: 2012 | C127: 2 | D127: 6 | F127: 50 | I127: 187.5 | J127: 217.625 | M127: 53.686275 | N127: 23.388235 | O127: =IFERROR(M127*0.9, "") -> 48.317647 | P127: 26.5 | Q127: 20 | S127: =T127*S128/T128 -> 195.02779 | T127: =IF(F127=0, "", F127+N127) -> 73.388235 | U127: =IFERROR( E127+M127, "") | V127: =IFERROR( G127+O127, "") | W127: =IFERROR(I127+P127, "") -> 214 | X127: =J127+Q127 -> 237.625 | Y127: =IFERROR((I127+P127)*0.33+18, "") -> 88.62 | Z127: =IF(J127=0,0,(J127+Q127)*0.33+18) -> 96.41625 | AB127: =IF(OR(T127="", U127="", V127=""), "", MAX(S127,T127)*40%+U127*30%+V127*30%) | AC127: =IF(AB127="", "", MAX(Y127, Z127)-AB127) | AE127: =IFERROR(MIN((MAX(S127,T127)*70%+V127*30%), Z127), "") | AF127: =IF(AE127="", "", MAX(AB127, AC127)-AE127)
B128: 2012 | C128: 3 | D128: 7 | E128: 39 | F128: 50 | I128: 176.25 | J128: 209.125 | M128: 53.686275 | N128: 23.388235 | O128: =IFERROR(M128*0.9, "") -> 48.317647 | P128: 26 | Q128: 20 | S128: =T128*S129/T129 -> 195.02779 | T128: =IF(F128=0, "", F128+N128) -> 73.388235 | U128: =IFERROR( E128+M128, "") -> 92.686275 | V128: =IFERROR( G128+O128, "") | W128: =IFERROR(I128+P128, "") -> 202.25 | X128: =J128+Q128 -> 229.125 | Y128: =IFERROR((I128+P128)*0.33+18, "") -> 84.7425 | Z128: =IF(J128=0,0,(J128+Q128)*0.33+18) -> 93.61125 | AB128: =IF(OR(T128="", U128="", V128=""), "", MAX(S128,T128)*40%+U128*30%+V128*30%) | AC128: =IF(AB128="", "", MAX(Y128, Z128)-AB128) | AE128: =IFERROR(MIN((MAX(S128,T128)*70%+V128*30%), Z128), "") | AF128: =IF(AE128="", "", MAX(AB128, AC128)-AE128)
B129: 2012 | C129: 3 | D129: 8 | E129: 43 | F129: 51.4 | I129: 177.6 | J129: 191.5 | M129: 53.686275 | N129: 23.388235 | O129: =IFERROR(M129*0.9, "") -> 48.317647 | P129: 26.4 | Q129: 20 | S129: =T129*S130/T130 -> 198.74826 | T129: =IF(F129=0, "", F129+N129) -> 74.788235 | U129: =IFERROR( E129+M129, "") -> 96.686275 | V129: =IFERROR( G129+O129, "") | W129: =IFERROR(I129+P129, "") -> 204 | X129: =J129+Q129 -> 211.5 | Y129: =IFERROR((I129+P129)*0.33+18, "") -> 85.32 | Z129: =IF(J129=0,0,(J129+Q129)*0.33+18) -> 87.795 | AB129: =IF(OR(T129="", U129="", V129=""), "", MAX(S129,T129)*40%+U129*30%+V129*30%) | AC129: =IF(AB129="", "", MAX(Y129, Z129)-AB129) | AE129: =IFERROR(MIN((MAX(S129,T129)*70%+V129*30%), Z129), "") | AF129: =IF(AE129="", "", MAX(AB129, AC129)-AE129)
B130: 2012 | C130: 3 | D130: 9 | E130: 45 | F130: 53 | I130: 186.5 | J130: 191.5 | M130: 53.686275 | N130: 23.388235 | O130: =IFERROR(M130*0.9, "") -> 48.317647 | P130: 26.25 | Q130: 20 | S130: =T130*S131/T131 -> 203.00023 | T130: =IF(F130=0, "", F130+N130) -> 76.388235 | U130: =IFERROR( E130+M130, "") -> 98.686275 | V130: =IFERROR( G130+O130, "") | W130: =IFERROR(I130+P130, "") -> 212.75 | X130: =J130+Q130 -> 211.5 | Y130: =IFERROR((I130+P130)*0.33+18, "") -> 88.2075 | Z130: =IF(J130=0,0,(J130+Q130)*0.33+18) -> 87.795 | AB130: =IF(OR(T130="", U130="", V130=""), "", MAX(S130,T130)*40%+U130*30%+V130*30%) | AC130: =IF(AB130="", "", MAX(Y130, Z130)-AB130) | AE130: =IFERROR(MIN((MAX(S130,T130)*70%+V130*30%), Z130), "") | AF130: =IF(AE130="", "", MAX(AB130, AC130)-AE130)
B131: 2012 | C131: 4 | D131: 10 | E131: 38.25 | F131: 56.75 | I131: 170.75 | J131: 191.5 | M131: 53.686275 | N131: 23.388235 | O131: =IFERROR(M131*0.9, "") -> 48.317647 | P131: 26 | Q131: 20 | S131: =T131*S132/T132 -> 212.96578 | T131: =IF(F131=0, "", F131+N131) -> 80.138235 | U131: =IFERROR( E131+M131, "") -> 91.936275 | V131: =IFERROR( G131+O131, "") | W131: =IFERROR(I131+P131, "") -> 196.75 | X131: =J131+Q131 -> 211.5 | Y131: =IFERROR((I131+P131)*0.33+18, "") -> 82.9275 | Z131: =IF(J131=0,0,(J131+Q131)*0.33+18) -> 87.795 | AB131: =IF(OR(T131="", U131="", V131=""), "", MAX(S131,T131)*40%+U131*30%+V131*30%) | AC131: =IF(AB131="", "", MAX(Y131, Z131)-AB131) | AE131: =IFERROR(MIN((MAX(S131,T131)*70%+V131*30%), Z131), "") | AF131: =IF(AE131="", "", MAX(AB131, AC131)-AE131)
B132: 2012 | C132: 4 | D132: 11 | E132: 18 | F132: 53.4 | I132: 154.2 | J132: 183.5 | M132: 53.686275 | N132: 23.388235 | O132: =IFERROR(M132*0.9, "") -> 48.317647 | P132: 25 | Q132: 20 | S132: =T132*S133/T133 -> 204.06322 | T132: =IF(F132=0, "", F132+N132) -> 76.788235 | U132: =IFERROR( E132+M132, "") -> 71.686275 | V132: =IFERROR( G132+O132, "") | W132: =IFERROR(I132+P132, "") -> 179.2 | X132: =J132+Q132 -> 203.5 | Y132: =IFERROR((I132+P132)*0.33+18, "") -> 77.136 | Z132: =IF(J132=0,0,(J132+Q132)*0.33+18) -> 85.155 | AB132: =IF(OR(T132="", U132="", V132=""), "", MAX(S132,T132)*40%+U132*30%+V132*30%) | AC132: =IF(AB132="", "", MAX(Y132, Z132)-AB132) | AE132: =IFERROR(MIN((MAX(S132,T132)*70%+V132*30%), Z132), "") | AF132: =IF(AE132="", "", MAX(AB132, AC132)-AE132)
B133: 2012 | C133: 4 | D133: 12 | E133: 10 | F133: 43 | I133: 146.5 | J133: 172.5 | M133: 53.686275 | N133: 23.388235 | O133: =IFERROR(M133*0.9, "") -> 48.317647 | P133: 26 | Q133: 20 | S133: =T133*S134/T134 -> 176.42543 | T133: =IF(F133=0, "", F133+N133) -> 66.388235 | U133: =IFERROR( E133+M133, "") -> 63.686275 | V133: =IFERROR( G133+O133, "") | W133: =IFERROR(I133+P133, "") -> 172.5 | X133: =J133+Q133 -> 192.5 | Y133: =IFERROR((I133+P133)*0.33+18, "") -> 74.925 | Z133: =IF(J133=0,0,(J133+Q133)*0.33+18) -> 81.525 | AB133: =IF(OR(T133="", U133="", V133=""), "", MAX(S133,T133)*40%+U133*30%+V133*30%) | AC133: =IF(AB133="", "", MAX(Y133, Z133)-AB133) | AE133: =IFERROR(MIN((MAX(S133,T133)*70%+V133*30%), Z133), "") | AF133: =IF(AE133="", "", MAX(AB133, AC133)-AE133)
B134: 2013 | C134: 1 | D134: 1 | E134: 7.2 | F134: 26.2 | I134: 145.2 | J134: 160.4 | M134: 53.686275 | N134: 23.388235 | O134: =IFERROR(M134*0.9, "") -> 48.317647 | P134: 27 | Q134: 20 | S134: =T134*S135/T135 -> 131.77976 | T134: =IF(F134=0, "", F134+N134) -> 49.588235 | U134: =IFERROR( E134+M134, "") -> 60.886275 | V134: =IFERROR( G134+O134, "") | W134: =IFERROR(I134+P134, "") -> 172.2 | X134: =J134+Q134 -> 180.4 | Y134: =IFERROR((I134+P134)*0.33+18, "") -> 74.826 | Z134: =IF(J134=0,0,(J134+Q134)*0.33+18) -> 77.532 | AB134: =IF(OR(T134="", U134="", V134=""), "", MAX(S134,T134)*40%+U134*30%+V134*30%) | AC134: =IF(AB134="", "", MAX(Y134, Z134)-AB134) | AE134: =IFERROR(MIN((MAX(S134,T134)*70%+V134*30%), Z134), "") | AF134: =IF(AE134="", "", MAX(AB134, AC134)-AE134)
B135: 2013 | C135: 1 | D135: 2 | E135: 3 | F135: 13.75 | I135: 149 | J135: 152.5 | M135: 53.686275 | N135: 23.388235 | O135: =IFERROR(M135*0.9, "") -> 48.317647 | P135: 27.25 | Q135: 20 | S135: =T135*S136/T136 -> 98.694129 | T135: =IF(F135=0, "", F135+N135) -> 37.138235 | U135: =IFERROR( E135+M135, "") -> 56.686275 | V135: =IFERROR( G135+O135, "") | W135: =IFERROR(I135+P135, "") -> 176.25 | X135: =J135+Q135 -> 172.5 | Y135: =IFERROR((I135+P135)*0.33+18, "") -> 76.1625 | Z135: =IF(J135=0,0,(J135+Q135)*0.33+18) -> 74.925 | AB135: =IF(OR(T135="", U135="", V135=""), "", MAX(S135,T135)*40%+U135*30%+V135*30%) | AC135: =IF(AB135="", "", MAX(Y135, Z135)-AB135) | AE135: =IFERROR(MIN((MAX(S135,T135)*70%+V135*30%), Z135), "") | AF135: =IF(AE135="", "", MAX(AB135, AC135)-AE135)
B136: 2013 | C136: 1 | D136: 3 | E136: 3 | F136: 10 | I136: 150 | J136: 152.5 | M136: 53.686275 | N136: 23.388235 | O136: =IFERROR(M136*0.9, "") -> 48.317647 | P136: 28 | Q136: 20 | S136: =T136*S137/T137 -> 88.728578 | T136: =IF(F136=0, "", F136+N136) -> 33.388235 | U136: =IFERROR( E136+M136, "") -> 56.686275 | V136: =IFERROR( G136+O136, "") | W136: =IFERROR(I136+P136, "") -> 178 | X136: =J136+Q136 -> 172.5 | Y136: =IFERROR((I136+P136)*0.33+18, "") -> 76.74 | Z136: =IF(J136=0,0,(J136+Q136)*0.33+18) -> 74.925 | AB136: =IF(OR(T136="", U136="", V136=""), "", MAX(S136,T136)*40%+U136*30%+V136*30%) | AC136: =IF(AB136="", "", MAX(Y136, Z136)-AB136) | AE136: =IFERROR(MIN((MAX(S136,T136)*70%+V136*30%), Z136), "") | AF136: =IF(AE136="", "", MAX(AB136, AC136)-AE136)
B137: 2013 | C137: 2 | D137: 4 | E137: 3 | F137: 10 | I137: 151 | J137: 152.5 | M137: 53.686275 | N137: 23.388235 | O137: =IFERROR(M137*0.9, "") -> 48.317647 | P137: 28.25 | Q137: 20 | S137: =T137*S138/T138 -> 88.728578 | T137: =IF(F137=0, "", F137+N137) -> 33.388235 | U137: =IFERROR( E137+M137, "") -> 56.686275 | V137: =IFERROR( G137+O137, "") | W137: =IFERROR(I137+P137, "") -> 179.25 | X137: =J137+Q137 -> 172.5 | Y137: =IFERROR((I137+P137)*0.33+18, "") -> 77.1525 | Z137: =IF(J137=0,0,(J137+Q137)*0.33+18) -> 74.925 | AB137: =IF(OR(T137="", U137="", V137=""), "", MAX(S137,T137)*40%+U137*30%+V137*30%) | AC137: =IF(AB137="", "", MAX(Y137, Z137)-AB137) | AE137: =IFERROR(MIN((MAX(S137,T137)*70%+V137*30%), Z137), "") | AF137: =IF(AE137="", "", MAX(AB137, AC137)-AE137)
B138: 2013 | C138: 2 | D138: 5 | E138: 8.6 | F138: 10 | I138: 140.6 | J138: 149.5 | M138: 53.686275 | N138: 23.388235 | O138: =IFERROR(M138*0.9, "") -> 48.317647 | P138: 27.4 | Q138: 20 | S138: =T138*S139/T139 -> 88.728578 | T138: =IF(F138=0, "", F138+N138) -> 33.388235 | U138: =IFERROR( E138+M138, "") -> 62.286275 | V138: =IFERROR( G138+O138, "") | W138: =IFERROR(I138+P138, "") -> 168 | X138: =J138+Q138 -> 169.5 | Y138: =IFERROR((I138+P138)*0.33+18, "") -> 73.44 | Z138: =IF(J138=0,0,(J138+Q138)*0.33+18) -> 73.935 | AB138: =IF(OR(T138="", U138="", V138=""), "", MAX(S138,T138)*40%+U138*30%+V138*30%) | AC138: =IF(AB138="", "", MAX(Y138, Z138)-AB138) | AE138: =IFERROR(MIN((MAX(S138,T138)*70%+V138*30%), Z138), "") | AF138: =IF(AE138="", "", MAX(AB138, AC138)-AE138)
B139: 2013 | C139: 2 | D139: 6 | E139: 3 | F139: 13.5 | I139: 112.25 | J139: 145 | M139: 53.686275 | N139: 23.388235 | O139: =IFERROR(M139*0.9, "") -> 48.317647 | P139: 26.5 | Q139: 20 | S139: =T139*S140/T140 -> 98.029759 | T139: =IF(F139=0, "", F139+N139) -> 36.888235 | U139: =IFERROR( E139+M139, "") -> 56.686275 | V139: =IFERROR( G139+O139, "") | W139: =IFERROR(I139+P139, "") -> 138.75 | X139: =J139+Q139 -> 165 | Y139: =IFERROR((I139+P139)*0.33+18, "") -> 63.7875 | Z139: =IF(J139=0,0,(J139+Q139)*0.33+18) -> 72.45 | AB139: =IF(OR(T139="", U139="", V139=""), "", MAX(S139,T139)*40%+U139*30%+V139*30%) | AC139: =IF(AB139="", "", MAX(Y139, Z139)-AB139) | AE139: =IFERROR(MIN((MAX(S139,T139)*70%+V139*30%), Z139), "") | AF139: =IF(AE139="", "", MAX(AB139, AC139)-AE139)
... B232: 2021 | C232: 1 | D232: 3 | E232: 33.75 | F232: 84.5 | I232: 188.25 | J232: 87 | M232: 38.333333 | N232: 12 | O232: =IFERROR(M232*0.9, "") -> 34.5 | P232: 34 | Q232: 20 | S232: =T232*S233/T233 -> 256.44685 | T232: =IF(F232=0, "", F232+N232) -> 96.5 | U232: =IFERROR( E232+M232, "") -> 72.083333 | V232: =IFERROR( G232+O232, "") | W232: =IFERROR(I232+P232, "") -> 222.25 | X232: =J232+Q232 -> 107 | Y232: =IFERROR((I232+P232)*0.33+18, "") -> 91.3425 | Z232: =IF(J232=0,0,(J232+Q232)*0.33+18) -> 53.31 | AB232: =IF(OR(T232="", U232="", V232=""), "", MAX(S232,T232)*40%+U232*30%+V232*30%) | AC232: =IF(AB232="", "", MAX(Y232, Z232)-AB232) | AE232: =IFERROR(MIN((MAX(S232,T232)*70%+V232*30%), Z232), "") | AF232: =IF(AE232="", "", MAX(AB232, AC232)-AE232)
B233: 2021 | C233: 2 | D233: 4 | E233: 48.4 | F233: 97 | G233: 87.75 | I233: 185 | J233: 133.8 | M233: 41.866667 | N233: 11.466667 | O233: =IFERROR(M233*0.9, "") -> 37.68 | P233: 37.2 | Q233: 20 | S233: =T233*S234/T234 -> 288.24803 | T233: =IF(F233=0, "", F233+N233) -> 108.46667 | U233: =IFERROR( E233+M233, "") -> 90.266667 | V233: =IFERROR( G233+O233, "") -> 125.43 | W233: =IFERROR(I233+P233, "") -> 222.2 | X233: =J233+Q233 -> 153.8 | Y233: =IFERROR((I233+P233)*0.33+18, "") -> 91.326 | Z233: =IF(J233=0,0,(J233+Q233)*0.33+18) -> 68.754 | AB233: =IF(OR(T233="", U233="", V233=""), "", MAX(S233,T233)*40%+U233*30%+V233*30%) -> 180.00821 | AC233: =IF(AB233="", "", MAX(Y233, Z233)-AB233) -> -88.682213 | AE233: =IFERROR(MIN((MAX(S233,T233)*70%+V233*30%), Z233), "") -> 68.754 | AF233: =IF(AE233="", "", MAX(AB233, AC233)-AE233) -> 111.25421
B234: 2021 | C234: 2 | D234: 5 | E234: 52 | F234: 113.75 | G234: 95 | I234: 185 | J234: 204 | M234: 45.166667 | N234: 10.666667 | O234: =IFERROR(M234*0.9, "") -> 40.65 | P234: 42 | Q234: 20 | S234: =T234*S235/T235 -> 330.63484 | T234: =IF(F234=0, "", F234+N234) -> 124.41667 | U234: =IFERROR( E234+M234, "") -> 97.166667 | V234: =IFERROR( G234+O234, "") -> 135.65 | W234: =IFERROR(I234+P234, "") -> 227 | X234: =J234+Q234 -> 224 | Y234: =IFERROR((I234+P234)*0.33+18, "") -> 92.91 | Z234: =IF(J234=0,0,(J234+Q234)*0.33+18) -> 91.92 | AB234: =IF(OR(T234="", U234="", V234=""), "", MAX(S234,T234)*40%+U234*30%+V234*30%) -> 202.09894 | AC234: =IF(AB234="", "", MAX(Y234, Z234)-AB234) -> -109.18894 | AE234: =IFERROR(MIN((MAX(S234,T234)*70%+V234*30%), Z234), "") -> 91.92 | AF234: =IF(AE234="", "", MAX(AB234, AC234)-AE234) -> 110.17894
B235: 2021 | C235: 2 | D235: 6 | E235: 60.5 | F235: 132.5 | G235: 117.5 | I235: 186 | J235: 204 | M235: 45.333333 | N235: 10.666667 | O235: =IFERROR(M235*0.9, "") -> 40.8 | P235: 46.75 | Q235: 20 | S235: =T235*S236/T236 -> 380.4626 | T235: =IF(F235=0, "", F235+N235) -> 143.16667 | U235: =IFERROR( E235+M235, "") -> 105.83333 | V235: =IFERROR( G235+O235, "") -> 158.3 | W235: =IFERROR(I235+P235, "") -> 232.75 | X235: =J235+Q235 -> 224 | Y235: =IFERROR((I235+P235)*0.33+18, "") -> 94.8075 | Z235: =IF(J235=0,0,(J235+Q235)*0.33+18) -> 91.92 | AB235: =IF(OR(T235="", U235="", V235=""), "", MAX(S235,T235)*40%+U235*30%+V235*30%) -> 231.42504 | AC235: =IF(AB235="", "", MAX(Y235, Z235)-AB235) -> -136.61754 | AE235: =IFERROR(MIN((MAX(S235,T235)*70%+V235*30%), Z235), "") -> 91.92 | AF235: =IF(AE235="", "", MAX(AB235, AC235)-AE235) -> 139.50504
B236: 2021 | C236: 3 | D236: 7 | E236: 74.6 | F236: 160 | G236: 133 | I236: 175.2 | J236: 204 | M236: 46.933333 | N236: 10.666667 | O236: =IFERROR(M236*0.9, "") -> 42.24 | P236: 54.6 | Q236: 20 | S236: =T236*S237/T237 -> 453.54331 | T236: =IF(F236=0, "", F236+N236) -> 170.66667 | U236: =IFERROR( E236+M236, "") -> 121.53333 | V236: =IFERROR( G236+O236, "") -> 175.24 | W236: =IFERROR(I236+P236, "") -> 229.8 | X236: =J236+Q236 -> 224 | Y236: =IFERROR((I236+P236)*0.33+18, "") -> 93.834 | Z236: =IF(J236=0,0,(J236+Q236)*0.33+18) -> 91.92 | AB236: =IF(OR(T236="", U236="", V236=""), "", MAX(S236,T236)*40%+U236*30%+V236*30%) -> 270.44932 | AC236: =IF(AB236="", "", MAX(Y236, Z236)-AB236) -> -176.61532 | AE236: =IFERROR(MIN((MAX(S236,T236)*70%+V236*30%), Z236), "") -> 91.92 | AF236: =IF(AE236="", "", MAX(AB236, AC236)-AE236) -> 178.52932
B237: 2021 | C237: 3 | D237: 8 | E237: 80 | F237: 182.5 | G237: 139 | I237: 169.75 | J237: 201 | M237: 53.333333 | N237: 10 | O237: =IFERROR(M237*0.9, "") -> 48 | P237: 58.25 | Q237: 20 | S237: =T237*S238/T238 -> 511.56496 | T237: =IF(F237=0, "", F237+N237) -> 192.5 | U237: =IFERROR( E237+M237, "") -> 133.33333 | V237: =IFERROR( G237+O237, "") -> 187 | W237: =IFERROR(I237+P237, "") -> 228 | X237: =J237+Q237 -> 221 | Y237: =IFERROR((I237+P237)*0.33+18, "") -> 93.24 | Z237: =IF(J237=0,0,(J237+Q237)*0.33+18) -> 90.93 | AB237: =IF(OR(T237="", U237="", V237=""), "", MAX(S237,T237)*40%+U237*30%+V237*30%) -> 300.72598 | AC237: =IF(AB237="", "", MAX(Y237, Z237)-AB237) -> -207.48598 | AE237: =IFERROR(MIN((MAX(S237,T237)*70%+V237*30%), Z237), "") -> 90.93 | AF237: =IF(AE237="", "", MAX(AB237, AC237)-AE237) -> 209.79598
B238: 2021 | C238: 3 | D238: 9 | E238: 90 | F238: 192 | G238: 163 | I238: 181.6 | J238: 201 | M238: 54.666667 | N238: 9.3333333 | O238: =IFERROR(M238*0.9, "") -> 49.2 | P238: 56.8 | Q238: 20 | S238: =T238*S239/T239 -> 535.03937 | T238: =IF(F238=0, "", F238+N238) -> 201.33333 | U238: =IFERROR( E238+M238, "") -> 144.66667 | V238: =IFERROR( G238+O238, "") -> 212.2 | W238: =IFERROR(I238+P238, "") -> 238.4 | X238: =J238+Q238 -> 221 | Y238: =IFERROR((I238+P238)*0.33+18, "") -> 96.672 | Z238: =IF(J238=0,0,(J238+Q238)*0.33+18) -> 90.93 | AB238: =IF(OR(T238="", U238="", V238=""), "", MAX(S238,T238)*40%+U238*30%+V238*30%) -> 321.07575 | AC238: =IF(AB238="", "", MAX(Y238, Z238)-AB238) -> -224.40375 | AE238: =IFERROR(MIN((MAX(S238,T238)*70%+V238*30%), Z238), "") -> 90.93 | AF238: =IF(AE238="", "", MAX(AB238, AC238)-AE238) -> 230.14575
B239: 2021 | C239: 4 | D239: 10 | E239: 105 | F239: 200 | G239: 168 | I239: 207.5 | J239: 210 | M239: 54.666667 | N239: 10.333333 | O239: =IFERROR(M239*0.9, "") -> 49.2 | P239: 52.5 | Q239: 20 | S239: =T239*S240/T240 -> 558.95669 | T239: =IF(F239=0, "", F239+N239) -> 210.33333 | U239: =IFERROR( E239+M239, "") -> 159.66667 | V239: =IFERROR( G239+O239, "") -> 217.2 | W239: =IFERROR(I239+P239, "") -> 260 | X239: =J239+Q239 -> 230 | Y239: =IFERROR((I239+P239)*0.33+18, "") -> 103.8 | Z239: =IF(J239=0,0,(J239+Q239)*0.33+18) -> 93.9 | AB239: =IF(OR(T239="", U239="", V239=""), "", MAX(S239,T239)*40%+U239*30%+V239*30%) -> 336.64268 | AC239: =IF(AB239="", "", MAX(Y239, Z239)-AB239) -> -232.84268 | AE239: =IFERROR(MIN((MAX(S239,T239)*70%+V239*30%), Z239), "") -> 93.9 | AF239: =IF(AE239="", "", MAX(AB239, AC239)-AE239) -> 242.74268
B240: 2021 | C240: 4 | D240: 11 | E240: 105 | F240: 200 | G240: 158.75 | I240: 245 | J240: 213 | M240: 56.666667 | N240: 11.333333 | O240: =IFERROR(M240*0.9, "") -> 51 | P240: 38.75 | Q240: 20 | S240: =T240*S241/T241 -> 561.61417 | T240: =IF(F240=0, "", F240+N240) -> 211.33333 | U240: =IFERROR( E240+M240, "") -> 161.66667 | V240: =IFERROR( G240+O240, "") -> 209.75 | W240: =IFERROR(I240+P240, "") -> 283.75 | X240: =J240+Q240 -> 233 | Y240: =IFERROR((I240+P240)*0.33+18, "") -> 111.6375 | Z240: =IF(J240=0,0,(J240+Q240)*0.33+18) -> 94.89 | AB240: =IF(OR(T240="", U240="", V240=""), "", MAX(S240,T240)*40%+U240*30%+V240*30%) -> 336.07067 | AC240: =IF(AB240="", "", MAX(Y240, Z240)-AB240) -> -224.43317 | AE240: =IFERROR(MIN((MAX(S240,T240)*70%+V240*30%), Z240), "") -> 94.89 | AF240: =IF(AE240="", "", MAX(AB240, AC240)-AE240) -> 241.18067
B241: 2021 | C241: 4 | D241: 12 | E241: 103.5 | F241: 212.5 | G241: 141.25 | I241: 273.25 | J241: 213 | M241: 50.133333 | N241: 10.4 | O241: =IFERROR(M241*0.9, "") -> 45.12 | P241: 34 | Q241: 20 | S241: =T241*S242/T242 -> 592.35236 | T241: =IF(F241=0, "", F241+N241) -> 222.9 | U241: =IFERROR( E241+M241, "") -> 153.63333 | V241: =IFERROR( G241+O241, "") -> 186.37 | W241: =IFERROR(I241+P241, "") -> 307.25 | X241: =J241+Q241 -> 233 | Y241: =IFERROR((I241+P241)*0.33+18, "") -> 119.3925 | Z241: =IF(J241=0,0,(J241+Q241)*0.33+18) -> 94.89 | AB241: =IF(OR(T241="", U241="", V241=""), "", MAX(S241,T241)*40%+U241*30%+V241*30%) -> 338.94194 | AC241: =IF(AB241="", "", MAX(Y241, Z241)-AB241) -> -219.54944 | AE241: =IFERROR(MIN((MAX(S241,T241)*70%+V241*30%), Z241), "") -> 94.89 | AF241: =IF(AE241="", "", MAX(AB241, AC241)-AE241) -> 244.05194
B242: 2022 | C242: 1 | D242: 1 | E242: 87.25 | F242: 220 | G242: 140 | I242: 303.75 | J242: 279 | M242: 63.333333 | N242: 13.333333 | O242: =IFERROR(M242*0.9, "") -> 57 | P242: 36.5 | Q242: 20 | S242: =T242*S243/T243 -> 620.07874 | T242: =IF(F242=0, "", F242+N242) -> 233.33333 | U242: =IFERROR( E242+M242, "") -> 150.58333 | V242: =IFERROR( G242+O242, "") -> 197 | W242: =IFERROR(I242+P242, "") -> 340.25 | X242: =J242+Q242 -> 299 | Y242: =IFERROR((I242+P242)*0.33+18, "") -> 130.2825 | Z242: =IF(J242=0,0,(J242+Q242)*0.33+18) -> 116.67 | AB242: =IF(OR(T242="", U242="", V242=""), "", MAX(S242,T242)*40%+U242*30%+V242*30%) -> 352.3065 | AC242: =IF(AB242="", "", MAX(Y242, Z242)-AB242) -> -222.024 | AE242: =IFERROR(MIN((MAX(S242,T242)*70%+V242*30%), Z242), "") -> 116.67 | AF242: =IF(AE242="", "", MAX(AB242, AC242)-AE242) -> 235.6365
B243: 2022 | C243: 1 | D243: 2 | E243: 83.5 | F243: 220 | G243: 135.75 | I243: 313.75 | J243: 301 | M243: 62.666667 | N243: 14 | O243: =IFERROR(M243*0.9, "") -> 56.4 | P243: 44.5 | Q243: 20 | S243: =T243*S244/T244 -> 621.85039 | T243: =IF(F243=0, "", F243+N243) -> 234 | U243: =IFERROR( E243+M243, "") -> 146.16667 | V243: =IFERROR( G243+O243, "") -> 192.15 | W243: =IFERROR(I243+P243, "") -> 358.25 | X243: =J243+Q243 -> 321 | Y243: =IFERROR((I243+P243)*0.33+18, "") -> 136.2225 | Z243: =IF(J243=0,0,(J243+Q243)*0.33+18) -> 123.93 | AB243: =IF(OR(T243="", U243="", V243=""), "", MAX(S243,T243)*40%+U243*30%+V243*30%) -> 350.23516 | AC243: =IF(AB243="", "", MAX(Y243, Z243)-AB243) -> -214.01266 | AE243: =IFERROR(MIN((MAX(S243,T243)*70%+V243*30%), Z243), "") -> 123.93 | AF243: =IF(AE243="", "", MAX(AB243, AC243)-AE243) -> 226.30516
B244: 2022 | C244: 1 | D244: 3 | E244: 81.8 | F244: 220 | G244: 129.6 | I244: 393 | J244: 301 | M244: 66.666667 | N244: 16 | O244: =IFERROR(M244*0.9, "") -> 60 | P244: 67.6 | Q244: 20 | S244: =T244*S245/T245 -> 627.16535 | T244: =IF(F244=0, "", F244+N244) -> 236 | U244: =IFERROR( E244+M244, "") -> 148.46667 | V244: =IFERROR( G244+O244, "") -> 189.6 | W244: =IFERROR(I244+P244, "") -> 460.6 | X244: =J244+Q244 -> 321 | Y244: =IFERROR((I244+P244)*0.33+18, "") -> 169.998 | Z244: =IF(J244=0,0,(J244+Q244)*0.33+18) -> 123.93 | AB244: =IF(OR(T244="", U244="", V244=""), "", MAX(S244,T244)*40%+U244*30%+V244*30%) -> 352.28614 | AC244: =IF(AB244="", "", MAX(Y244, Z244)-AB244) -> -182.28814 | AE244: =IFERROR(MIN((MAX(S244,T244)*70%+V244*30%), Z244), "") -> 123.93 | AF244: =IF(AE244="", "", MAX(AB244, AC244)-AE244) -> 228.35614
... B260: 2023 | C260: 3 | D260: 7 | E260: -3.75 | F260: 10 | G260: -3.75 | I260: 69.5 | J260: 89 | M260: 71.666667 | N260: 21.333333 | O260: =IFERROR(M260*0.9, "") -> 64.5 | P260: 25.75 | Q260: 20 | S260: =T260*S261/T261 -> 83.267717 | T260: =IF(F260=0, "", F260+N260) -> 31.333333 | U260: =IFERROR( E260+M260, "") -> 67.916667 | V260: =IFERROR( G260+O260, "") -> 60.75 | W260: =IFERROR(I260+P260, "") -> 95.25 | X260: =J260+Q260 -> 109 | Y260: =IFERROR((I260+P260)*0.33+18, "") -> 49.4325 | Z260: =IF(J260=0,0,(J260+Q260)*0.33+18) -> 53.97 | AB260: =IF(OR(T260="", U260="", V260=""), "", MAX(S260,T260)*40%+U260*30%+V260*30%) -> 71.907087 | AC260: =IF(AB260="", "", MAX(Y260, Z260)-AB260) -> -17.937087 | AE260: =IFERROR(MIN((MAX(S260,T260)*70%+V260*30%), Z260), "") -> 53.97 | AF260: =IF(AE260="", "", MAX(AB260, AC260)-AE260) -> 17.937087
B261: 2023 | C261: 3 | D261: 8 | E261: -1 | F261: 16 | G261: 7 | H261: 90 | I261: 91.6 | J261: 77 | K261: =DATE(B261,D261,1) -> 45139 | M261: 72 | N261: 17.866667 | O261: =IFERROR(M261*0.9, "") -> 64.8 | P261: 28.8 | Q261: 20 | S261: =H261 -> 90 | T261: =IF(F261=0, "", F261+N261) -> 33.866667 | U261: =IFERROR( E261+M261, "") -> 71 | V261: =IFERROR( G261+O261, "") -> 71.8 | W261: =IFERROR(I261+P261, "") -> 120.4 | X261: =J261+Q261 -> 97 | Y261: =IFERROR((I261+P261)*0.33+18, "") -> 57.732 | Z261: =IF(J261=0,0,(J261+Q261)*0.33+18) -> 50.01 | AB261: =IF(OR(T261="", U261="", V261=""), "", MAX(S261,T261)*40%+U261*30%+V261*30%) -> 78.84 | AC261: =IF(AB261="", "", MAX(Y261, Z261)-AB261) -> -21.108 | AE261: =IFERROR(MIN((MAX(S261,T261)*70%+V261*30%), Z261), "") -> 50.01 | AF261: =IF(AE261="", "", MAX(AB261, AC261)-AE261) -> 28.83
B262: 2023 | C262: 3 | D262: 9 | E262: 12.75 | F262: 47 | G262: 34.5 | H262: 90 | I262: 107.25 | J262: 77 | K262: =DATE(B262,D262,1) -> 45170 | M262: 68 | N262: 18 | O262: =IFERROR(M262*0.9, "") -> 61.2 | P262: 31.75 | Q262: 20 | S262: =H262 -> 90 | T262: =IF(F262=0, "", F262+N262) -> 65 | U262: =IFERROR( E262+M262, "") -> 80.75 | V262: =IFERROR( G262+O262, "") -> 95.7 | W262: =IFERROR(I262+P262, "") -> 139 | X262: =J262+Q262 -> 97 | Y262: =IFERROR((I262+P262)*0.33+18, "") -> 63.87 | Z262: =IF(J262=0,0,(J262+Q262)*0.33+18) -> 50.01 | AB262: =IF(OR(T262="", U262="", V262=""), "", MAX(S262,T262)*40%+U262*30%+V262*30%) -> 88.935 | AC262: =IF(AB262="", "", MAX(Y262, Z262)-AB262) -> -25.065 | AE262: =IFERROR(MIN((MAX(S262,T262)*70%+V262*30%), Z262), "") -> 50.01 | AF262: =IF(AE262="", "", MAX(AB262, AC262)-AE262) -> 38.925
B263: 2023 | C263: 4 | D263: 10 | E263: 18 | F263: 68.75 | G263: 41.75 | H263: 100 | I263: 107.75 | J263: 96 | K263: =DATE(B263,D263,1) -> 45200 | M263: 69.666667 | N263: 20.166667 | O263: =IFERROR(M263*0.9, "") -> 62.7 | P263: 30 | Q263: 20 | S263: =H263 -> 100 | T263: =IF(F263=0, "", F263+N263) -> 88.916667 | U263: =IFERROR( E263+M263, "") -> 87.666667 | V263: =IFERROR( G263+O263, "") -> 104.45 | W263: =IFERROR(I263+P263, "") -> 137.75 | X263: =J263+Q263 -> 116 | Y263: =IFERROR((I263+P263)*0.33+18, "") -> 63.4575 | Z263: =IF(J263=0,0,(J263+Q263)*0.33+18) -> 56.28 | AB263: =IF(OR(T263="", U263="", V263=""), "", MAX(S263,T263)*40%+U263*30%+V263*30%) -> 97.635 | AC263: =IF(AB263="", "", MAX(Y263, Z263)-AB263) -> -34.1775 | AE263: =IFERROR(MIN((MAX(S263,T263)*70%+V263*30%), Z263), "") -> 56.28 | AF263: =IF(AE263="", "", MAX(AB263, AC263)-AE263) -> 41.355
B264: 2023 | C264: 4 | D264: 11 | E264: 14.4 | F264: 58 | G264: 34.4 | H264: 100 | I264: 92.8 | J264: 115 | K264: =DATE(B264,D264,1) -> 45231 | M264: 70.933333 | N264: 21.333333 | O264: =IFERROR(M264*0.9, "") -> 63.84 | P264: 29.4 | Q264: 20 | S264: =H264 -> 100 | T264: =IF(F264=0, "", F264+N264) -> 79.333333 | U264: =IFERROR( E264+M264, "") -> 85.333333 | V264: =IFERROR( G264+O264, "") -> 98.24 | W264: =IFERROR(I264+P264, "") -> 122.2 | X264: =J264+Q264 -> 135 | Y264: =IFERROR((I264+P264)*0.33+18, "") -> 58.326 | Z264: =IF(J264=0,0,(J264+Q264)*0.33+18) -> 62.55 | AB264: =IF(OR(T264="", U264="", V264=""), "", MAX(S264,T264)*40%+U264*30%+V264*30%) -> 95.072 | AC264: =IF(AB264="", "", MAX(Y264, Z264)-AB264) -> -32.522 | AE264: =IFERROR(MIN((MAX(S264,T264)*70%+V264*30%), Z264), "") -> 62.55 | AF264: =IF(AE264="", "", MAX(AB264, AC264)-AE264) -> 32.522
B265: 2023 | C265: 4 | D265: 12 | E265: 6.6666667 | F265: 49.333333 | G265: 23 | H265: 95 | I265: 79.666667 | J265: 115 | K265: =DATE(B265,D265,1) -> 45261 | M265: 56.666667 | N265: 16 | O265: =IFERROR(M265*0.9, "") -> 51 | P265: 23.25 | Q265: 20 | S265: =H265 -> 95 | T265: =IF(F265=0, "", F265+N265) -> 65.333333 | U265: =IFERROR( E265+M265, "") -> 63.333333 | V265: =IFERROR( G265+O265, "") -> 74 | W265: =IFERROR(I265+P265, "") -> 102.91667 | X265: =J265+Q265 -> 135 | Y265: =IFERROR((I265+P265)*0.33+18, "") -> 51.9625 | Z265: =IF(J265=0,0,(J265+Q265)*0.33+18) -> 62.55 | AB265: =IF(OR(T265="", U265="", V265=""), "", MAX(S265,T265)*40%+U265*30%+V265*30%) -> 79.2 | AC265: =IF(AB265="", "", MAX(Y265, Z265)-AB265) -> -16.65 | AE265: =IFERROR(MIN((MAX(S265,T265)*70%+V265*30%), Z265), "") -> 62.55 | AF265: =IF(AE265="", "", MAX(AB265, AC265)-AE265) -> 16.65
B266: 2024 | C266: 1 | D266: 1 | E266: 2.75 | F266: 41.5 | G266: 14.75 | H266: 83.5 | I266: 72.75 | J266: 105 | K266: =DATE(B266,D266,1) -> 45292 | M266: 82.666667 | N266: 21.333333 | O266: =IFERROR(M266*0.9, "") -> 74.4 | P266: 36 | Q266: 20 | S266: =H266 -> 83.5 | T266: =IF(F266=0, "", F266+N266) -> 62.833333 | U266: =IFERROR( E266+M266, "") -> 85.416667 | V266: =IFERROR( G266+O266, "") -> 89.15 | W266: =IFERROR(I266+P266, "") -> 108.75 | X266: =J266+Q266 -> 125 | Y266: =IFERROR((I266+P266)*0.33+18, "") -> 53.8875 | Z266: =IF(J266=0,0,(J266+Q266)*0.33+18) -> 59.25 | AB266: =IF(OR(T266="", U266="", V266=""), "", MAX(S266,T266)*40%+U266*30%+V266*30%) -> 85.77 | AC266: =IF(AB266="", "", MAX(Y266, Z266)-AB266) -> -26.52 | AE266: =IFERROR(MIN((MAX(S266,T266)*70%+V266*30%), Z266), "") -> 59.25 | AF266: =IF(AE266="", "", MAX(AB266, AC266)-AE266) -> 26.52
B267: 2024 | C267: 1 | D267: 2 | E267: -2.4 | F267: 42 | G267: 10.6 | H267: 80 | I267: 71 | J267: 95 | K267: =DATE(B267,D267,1) -> 45323 | M267: 83.733333 | N267: 22.4 | O267: =IFERROR(M267*0.9, "") -> 75.36 | P267: 39.2 | Q267: 20 | S267: =H267 -> 80 | T267: =IF(F267=0, "", F267+N267) -> 64.4 | U267: =IFERROR( E267+M267, "") -> 81.333333 | V267: =IFERROR( G267+O267, "") -> 85.96 | W267: =IFERROR(I267+P267, "") -> 110.2 | X267: =J267+Q267 -> 115 | Y267: =IFERROR((I267+P267)*0.33+18, "") -> 54.366 | Z267: =IF(J267=0,0,(J267+Q267)*0.33+18) -> 55.95 | AB267: =IF(OR(T267="", U267="", V267=""), "", MAX(S267,T267)*40%+U267*30%+V267*30%) -> 82.188 | AC267: =IF(AB267="", "", MAX(Y267, Z267)-AB267) -> -26.238 | AE267: =IFERROR(MIN((MAX(S267,T267)*70%+V267*30%), Z267), "") -> 55.95 | AF267: =IF(AE267="", "", MAX(AB267, AC267)-AE267) -> 26.238
B268: 2024 | C268: 1 | D268: 3 | E268: 0 | F268: 51 | G268: 13 | H268: 81.5 | I268: 81 | J268: 95 | K268: =DATE(B268,D268,1) -> 45352 | M268: 84 | N268: 22.666667 | O268: =IFERROR(M268*0.9, "") -> 75.6 | P268: 39.25 | Q268: 20 | S268: =H268 -> 81.5 | T268: =IF(F268=0, "", F268+N268) -> 73.666667 | U268: =IFERROR( E268+M268, "") -> 84 | V268: =IFERROR( G268+O268, "") -> 88.6 | W268: =IFERROR(I268+P268, "") -> 120.25 | X268: =J268+Q268 -> 115 | Y268: =IFERROR((I268+P268)*0.33+18, "") -> 57.6825 | Z268: =IF(J268=0,0,(J268+Q268)*0.33+18) -> 55.95 | AB268: =IF(OR(T268="", U268="", V268=""), "", MAX(S268,T268)*40%+U268*30%+V268*30%) -> 84.38 | AC268: =IF(AB268="", "", MAX(Y268, Z268)-AB268) -> -26.6975 | AE268: =IFERROR(MIN((MAX(S268,T268)*70%+V268*30%), Z268), "") -> 55.95 | AF268: =IF(AE268="", "", MAX(AB268, AC268)-AE268) -> 28.43
B269: 2024 | C269: 2 | D269: 4 | E269: 2.5 | F269: 60.5 | G269: 24 | H269: 105 | I269: 86.25 | J269: 100 | K269: =DATE(B269,D269,1) -> 45383 | M269: 85.333333 | N269: 21.333333 | O269: =IFERROR(M269*0.9, "") -> 76.8 | P269: 39 | Q269: 20 | S269: =H269 -> 105 | T269: =IF(F269=0, "", F269+N269) -> 81.833333 | U269: =IFERROR( E269+M269, "") -> 87.833333 | V269: =IFERROR( G269+O269, "") -> 100.8 | W269: =IFERROR(I269+P269, "") -> 125.25 | X269: =J269+Q269 -> 120 | Y269: =IFERROR((I269+P269)*0.33+18, "") -> 59.3325 | Z269: =IF(J269=0,0,(J269+Q269)*0.33+18) -> 57.6 | AB269: =IF(OR(T269="", U269="", V269=""), "", MAX(S269,T269)*40%+U269*30%+V269*30%) -> 98.59 | AC269: =IF(AB269="", "", MAX(Y269, Z269)-AB269) -> -39.2575 | AE269: =IFERROR(MIN((MAX(S269,T269)*70%+V269*30%), Z269), "") -> 57.6 | AF269: =IF(AE269="", "", MAX(AB269, AC269)-AE269) -> 40.99
B270: 2024 | C270: 2 | D270: 5 | E270: 3.4 | F270: 72.2 | G270: 24.4 | H270: 120 | I270: 83.2 | J270: 100 | K270: =DATE(B270,D270,1) -> 45413 | M270: 86.133333 | N270: 21.333333 | O270: =IFERROR(M270*0.9, "") -> 77.52 | P270: 41 | Q270: 20 | S270: =H270 -> 120 | T270: =IF(F270=0, "", F270+N270) -> 93.533333 | U270: =IFERROR( E270+M270, "") -> 89.533333 | V270: =IFERROR( G270+O270, "") -> 101.92 | W270: =IFERROR(I270+P270, "") -> 124.2 | X270: =J270+Q270 -> 120 | Y270: =IFERROR((I270+P270)*0.33+18, "") -> 58.986 | Z270: =IF(J270=0,0,(J270+Q270)*0.33+18) -> 57.6 | AB270: =IF(OR(T270="", U270="", V270=""), "", MAX(S270,T270)*40%+U270*30%+V270*30%) -> 105.436 | AC270: =IF(AB270="", "", MAX(Y270, Z270)-AB270) -> -46.45 | AE270: =IFERROR(MIN((MAX(S270,T270)*70%+V270*30%), Z270), "") -> 57.6 | AF270: =IF(AE270="", "", MAX(AB270, AC270)-AE270) -> 47.836
B271: 2024 | C271: 2 | D271: 6 | E271: 4 | F271: 75 | G271: 29 | H271: 122.5 | I271: 79 | J271: 100 | K271: =DATE(B271,D271,1) -> 45444 | M271: 86.666667 | N271: 21.333333 | O271: =IFERROR(M271*0.9, "") -> 78 | P271: 42.25 | Q271: 20 | S271: =H271 -> 122.5 | T271: =IF(F271=0, "", F271+N271) -> 96.333333 | U271: =IFERROR( E271+M271, "") -> 90.666667 | V271: =IFERROR( G271+O271, "") -> 107 | W271: =IFERROR(I271+P271, "") -> 121.25 | X271: =J271+Q271 -> 120 | Y271: =IFERROR((I271+P271)*0.33+18, "") -> 58.0125 | Z271: =IF(J271=0,0,(J271+Q271)*0.33+18) -> 57.6 | AB271: =IF(OR(T271="", U271="", V271=""), "", MAX(S271,T271)*40%+U271*30%+V271*30%) -> 108.3 | AC271: =IF(AB271="", "", MAX(Y271, Z271)-AB271) -> -50.2875 | AE271: =IFERROR(MIN((MAX(S271,T271)*70%+V271*30%), Z271), "") -> 57.6 | AF271: =IF(AE271="", "", MAX(AB271, AC271)-AE271) -> 50.7
B272: 2024 | C272: 3 | D272: 7 | E272: 9 | F272: 80 | G272: 38.75 | H272: 125 | I272: 89.25 | J272: 99.5 | K272: =DATE(B272,D272,1) -> 45474 | M272: 86.666667 | N272: 20 | O272: =IFERROR(M272*0.9, "") -> 78 | P272: 39.75 | Q272: 20 | S272: =H272 -> 125 | T272: =IF(F272=0, "", F272+N272) -> 100 | U272: =IFERROR( E272+M272, "") -> 95.666667 | V272: =IFERROR( G272+O272, "") -> 116.75 | W272: =IFERROR(I272+P272, "") -> 129 | X272: =J272+Q272 -> 119.5 | Y272: =IFERROR((I272+P272)*0.33+18, "") -> 60.57 | Z272: =IF(J272=0,0,(J272+Q272)*0.33+18) -> 57.435 | AB272: =IF(OR(T272="", U272="", V272=""), "", MAX(S272,T272)*40%+U272*30%+V272*30%) -> 113.725 | AC272: =IF(AB272="", "", MAX(Y272, Z272)-AB272) -> -53.155 | AE272: =IFERROR(MIN((MAX(S272,T272)*70%+V272*30%), Z272), "") -> 57.435 | AF272: =IF(AE272="", "", MAX(AB272, AC272)-AE272) -> 56.29
... B284: 2025 | C284: 3 | D284: 7 | E284: 52 | F284: 124 | G284: 94.2 | H284: 170 | I284: 260 | J284: 256 | K284: =DATE(B284,D284,1) -> 45839 | M284: 67.6 | N284: 14.666667 | O284: =IFERROR(M284*0.9, "") -> 60.84 | P284: 35 | Q284: 20 | S284: =H284 -> 170 | T284: =IF(F284=0, "", F284+N284) -> 138.66667 | U284: =IFERROR( E284+M284, "") -> 119.6 | V284: =IFERROR( G284+O284, "") -> 155.04 | W284: =IFERROR(I284+P284, "") -> 295 | X284: =J284+Q284 -> 276 | Y284: =IFERROR((I284+P284)*0.33+18, "") -> 115.35 | Z284: =IF(J284=0,0,(J284+Q284)*0.33+18) -> 109.08 | AB284: =IF(OR(T284="", U284="", V284=""), "", MAX(S284,T284)*40%+U284*30%+V284*30%) -> 150.392 | AC284: =IF(AB284="", "", MAX(Y284, Z284)-AB284) -> -35.042 | AE284: =IFERROR(MIN((MAX(S284,T284)*70%+V284*30%), Z284), "") -> 109.08 | AF284: =IF(AE284="", "", MAX(AB284, AC284)-AE284) -> 41.312
B285: 2025 | C285: 3 | D285: 8 | F285: 116.25 | G285: 96 | H285: 165 | I285: 274.75 | J285: 268 | K285: =DATE(B285,D285,1) -> 45870 | M285: 66 | N285: 14.666667 | O285: =IFERROR(M285*0.9, "") -> 59.4 | P285: 35.75 | Q285: 20 | S285: =H285 -> 165 | T285: =IF(F285=0, "", F285+N285) -> 130.91667 | U285: =U284*(V285/V284) -> 119.87771 | V285: =IFERROR( G285+O285, "") -> 155.4 | W285: =IFERROR(I285+P285, "") -> 310.5 | X285: =J285+Q285 -> 288 | Y285: =IFERROR((I285+P285)*0.33+18, "") -> 120.465 | Z285: =IF(J285=0,0,(J285+Q285)*0.33+18) -> 113.04 | AB285: =IF(OR(T285="", U285="", V285=""), "", MAX(S285,T285)*40%+U285*30%+V285*30%) -> 148.58331 | AC285: =IF(AB285="", "", MAX(Y285, Z285)-AB285) -> -28.118313 | AE285: =IFERROR(MIN((MAX(S285,T285)*70%+V285*30%), Z285), "") -> 113.04 | AF285: =IF(AE285="", "", MAX(AB285, AC285)-AE285) -> 35.543313
B286: 2025 | C286: 3 | D286: 9 | F286: 79.5 | G286: 76 | H286: 130 | I286: 307.75 | J286: 268 | K286: =DATE(B286,D286,1) -> 45901 | M286: 66 | N286: 14.666667 | O286: =IFERROR(M286*0.9, "") -> 59.4 | P286: 35.5 | Q286: 20 | S286: =H286 -> 130 | T286: =IF(F286=0, "", F286+N286) -> 94.166667 | U286: =U285*(V286/V285) -> 104.44943 | V286: =IFERROR( G286+O286, "") -> 135.4 | W286: =IFERROR(I286+P286, "") -> 343.25 | X286: =J286+Q286 -> 288 | Y286: =IFERROR((I286+P286)*0.33+18, "") -> 131.2725 | Z286: =IF(J286=0,0,(J286+Q286)*0.33+18) -> 113.04 | AB286: =IF(OR(T286="", U286="", V286=""), "", MAX(S286,T286)*40%+U286*30%+V286*30%) -> 123.95483 | AC286: =IF(AB286="", "", MAX(Y286, Z286)-AB286) -> 7.3176703 | AE286: =IFERROR(MIN((MAX(S286,T286)*70%+V286*30%), Z286), "") -> 113.04 | AF286: =IF(AE286="", "", MAX(AB286, AC286)-AE286) -> 10.91483
B287: 2025 | C287: 4 | D287: 10 | F287: 80.2 | G287: 79.2 | H287: 130 | I287: 359.8 | J287: 301.6 | K287: =DATE(B287,D287,1) -> 45931 | M287: 66 | N287: 13.6 | O287: =IFERROR(M287*0.9, "") -> 59.4 | P287: 31 | Q287: 20 | S287: =H287 -> 130 | T287: =IF(F287=0, "", F287+N287) -> 93.8 | U287: =U286*(V287/V286) -> 106.91796 | V287: =IFERROR( G287+O287, "") -> 138.6 | W287: =IFERROR(I287+P287, "") -> 390.8 | X287: =J287+Q287 -> 321.6 | Y287: =IFERROR((I287+P287)*0.33+18, "") -> 146.964 | Z287: =IF(J287=0,0,(J287+Q287)*0.33+18) -> 124.128 | AB287: =IF(OR(T287="", U287="", V287=""), "", MAX(S287,T287)*40%+U287*30%+V287*30%) -> 125.65539 | AC287: =IF(AB287="", "", MAX(Y287, Z287)-AB287) -> 21.308613 | AE287: =IFERROR(MIN((MAX(S287,T287)*70%+V287*30%), Z287), "") -> 124.128 | AF287: =IF(AE287="", "", MAX(AB287, AC287)-AE287) -> 1.527387
B288: 2025 | C288: 4 | D288: 11 | F288: 97.75 | G288: 105.75 | H288: 132.5 | I288: 452 | J288: 310 | K288: =DATE(B288,D288,1) -> 45962 | M288: 66 | N288: 14.666667 | O288: =IFERROR(M288*0.9, "") -> 59.4 | P288: 32 | Q288: 20 | S288: =H288 -> 132.5 | T288: =IF(F288=0, "", F288+N288) -> 112.41667 | U288: =U287*(V288/V287) -> 127.39899 | V288: =IFERROR( G288+O288, "") -> 165.15 | W288: =IFERROR(I288+P288, "") -> 484 | X288: =J288+Q288 -> 330 | Y288: =IFERROR((I288+P288)*0.33+18, "") -> 177.72 | Z288: =IF(J288=0,0,(J288+Q288)*0.33+18) -> 126.9 | AB288: =IF(OR(T288="", U288="", V288=""), "", MAX(S288,T288)*40%+U288*30%+V288*30%) -> 140.7647 | AC288: =IF(AB288="", "", MAX(Y288, Z288)-AB288) -> 36.955302 | AE288: =IFERROR(MIN((MAX(S288,T288)*70%+V288*30%), Z288), "") -> 126.9 | AF288: =IF(AE288="", "", MAX(AB288, AC288)-AE288) -> 13.864698
B289: 2025 | C289: 4 | D289: 12 | F289: 106 | G289: 113 | H289: 136 | I289: 507 | J289: 310 | K289: =DATE(B289,D289,1) -> 45992 | M289: 66 | N289: 14.666667 | O289: =IFERROR(M289*0.9, "") -> 59.4 | P289: 32.666667 | Q289: 20 | S289: =H289 -> 136 | T289: =IF(F289=0, "", F289+N289) -> 120.66667 | U289: =U288*(V289/V288) -> 132.99174 | V289: =IFERROR( G289+O289, "") -> 172.4 | W289: =IFERROR(I289+P289, "") -> 539.66667 | X289: =J289+Q289 -> 330 | Y289: =IFERROR(W289*0.33+18, "") -> 196.09 | Z289: =IF(J289=0,0,X289*0.33+18) -> 126.9 | AB289: =IF(OR(T289="", U289="", V289=""), "", MAX(S289,T289)*40%+U289*30%+V289*30%) -> 146.01752 | AC289: =IF(AB289="", "", MAX(Y289, Z289)-AB289) -> 50.072477 | AE289: =IFERROR(MIN((MAX(S289,T289)*70%+V289*30%), Z289), "") -> 126.9 | AF289: =IF(AE289="", "", MAX(AB289, AC289)-AE289) -> 19.117523
B291: 2026 | T291: 83.482143 | U291: 155.67083 | V291: 143.65417 | W291: 384.95976 | X291: 384.31322 | Y291: =W291*0.33+18 -> 145.03672 | Z291: =X291*0.33+18 -> 144.82336 | AB291: =IF(OR(T291="", U291="", V291=""), "", MAX(S291,T291)*40%+U291*30%+V291*30%) -> 123.19036 | AC291: =IF(AB291="", "", MAX(Y291, Z291)-AB291) -> 21.846365 | AE291: =IFERROR(MIN((MAX(S291,T291)*70%+V291*30%), Z291), "") -> 101.53375 | AF291: =IF(AE291="", "", MAX(AB291, AC291)-AE291) -> 21.656607
B292: 2027 | T292: 80.929219 | U292: 125.92922 | V292: 125.32922 | W292: 274.13203 | X292: 273.30844 | Y292: =W292*0.33+18 -> 108.46357 | Z292: =X292*0.33+18 -> 108.19178 | AB292: =IF(OR(T292="", U292="", V292=""), "", MAX(S292,T292)*40%+U292*30%+V292*30%) -> 107.74922 | AC292: =IF(AB292="", "", MAX(Y292, Z292)-AB292) -> 0.71435076 | AE292: =IFERROR(MIN((MAX(S292,T292)*70%+V292*30%), Z292), "") -> 94.249219 | AF292: =IF(AE292="", "", MAX(AB292, AC292)-AE292) -> 13.5
B293: 2028 | T293: 66.644459 | U293: 120.64446 | V293: 120.04446 | W293: 246.8432 | X293: 246.23543 | Y293: =W293*0.33+18 -> 99.458256 | Z293: =X293*0.33+18 -> 99.257691 | AB293: =IF(OR(T293="", U293="", V293=""), "", MAX(S293,T293)*40%+U293*30%+V293*30%) -> 98.864459 | AC293: =IF(AB293="", "", MAX(Y293, Z293)-AB293) -> 0.59379657 | AE293: =IFERROR(MIN((MAX(S293,T293)*70%+V293*30%), Z293), "") -> 82.664459 | AF293: =IF(AE293="", "", MAX(AB293, AC293)-AE293) -> 16.2
B294: 2029 | T294: 65.394434 | U294: 114.39443 | V294: 113.79443 | W294: 239.17879 | X294: 238.64587 | Y294: =W294*0.33+18 -> 96.929001 | Z294: =X294*0.33+18 -> 96.753136 | AB294: =IF(OR(T294="", U294="", V294=""), "", MAX(S294,T294)*40%+U294*30%+V294*30%) -> 94.614434 | AC294: =IF(AB294="", "", MAX(Y294, Z294)-AB294) -> 2.3145674 | AE294: =IFERROR(MIN((MAX(S294,T294)*70%+V294*30%), Z294), "") -> 79.914434 | AF294: =IF(AE294="", "", MAX(AB294, AC294)-AE294) -> 14.7
B295: 2030 | T295: 61.438116 | U295: 108.43812 | V295: 107.83812 | W295: 243.75994 | X295: 243.21409 | Y295: =W295*0.33+18 -> 98.440779 | Z295: =X295*0.33+18 -> 98.260649 | AB295: =IF(OR(T295="", U295="", V295=""), "", MAX(S295,T295)*40%+U295*30%+V295*30%) -> 89.458116 | AC295: =IF(AB295="", "", MAX(Y295, Z295)-AB295) -> 8.9826628 | AE295: =IFERROR(MIN((MAX(S295,T295)*70%+V295*30%), Z295), "") -> 75.358116 | AF295: =IF(AE295="", "", MAX(AB295, AC295)-AE295) -> 14.1
B296: 2031
B297: 2032
B298: 2033
B299: 2034
B300: 2035
B301: 2036
...

Sheet Phosphate historical prices
C2: DAP | D2: DAP | E2: DAP | F2: DAP | G2: DAP | H2: DAP | I2: MAP | J2: MAP | K2: TSP | L2: TSP | M2: Phosphoric acid (100% P2O5) | N2: Phosphoric acid (100% P2O5) | O2: Phosphoric acid (100% P2O5) Non-food grade | P2: DAP | Q2: MAP
C3: NOLA | D3: Morocco | E3: Jordan | F3: Saudi Arabia | G3: India | H3: China | I3: Baltic/Black Sea | J3: Brazil | K3: Morocco | L3: Brazil | M3: North Africa | N3: India 30 days | O3: NW Europe | P3: US Gulf/Tampa | Q3: US Gulf/Tampa
C4: FOB | D4: FOB | E4: FOB | F4: FOB | G4: CFR | H4: FOB | I4: FOB | J4: CFR | K4: FOB | L4: CFR | M4: FOB | N4: CFR | O4: CFR | P4: FOB | Q4: FOB
C5: DAP FOB NOLA | D5: DAP FOB Morocco | E5: DAP FOB Jordan | F5: DAP FOB Saudi Arabia | G5: DAP CFR India | H5: DAP FOB China | I5: MAP FOB Baltic/Black Sea | J5: MAP CFR Brazil | K5: TSP FOB Morocco | L5: TSP CFR Brazil | M5: Phosphoric acid (100% P2O5) FOB North Africa | N5: Phosphoric acid (100% P2O5) CFR India 30 days | O5: Phosphoric acid (100% P2O5) Non-food grade CFR NW Europe | P5: DAP FOB US Gulf/Tampa | Q5: MAP FOB US Gulf/Tampa
B6: 2000 | C6: - | D6: 160.26136 | E6: 165.67941 | F6: - | G6: - | H6: - | I6: 147.45425 | J6: 167.81338 | K6: 129.14183 | L6: - | M6: 308.79808 | N6: 369.69231 | O6: 372.06731 | P6: 153.62303 | Q6: -
B7: 2001 | C7: - | D7: 151.95986 | E7: 161.45382 | F7: - | G7: - | H7: - | I7: 142.26821 | J7: 161.9113 | K7: 125.17439 | L7: - | M7: 290.75 | N7: 348.61458 | O7: 344.6875 | P7: 147.29451 | Q7: -
B8: 2002 | C8: - | D8: 158.11939 | E8: 169.43429 | F8: - | G8: 172.95299 | H8: - | I8: 146.18269 | J8: 168.70175 | K8: 126.67548 | L8: - | M8: 282.82692 | N8: 337.67308 | O8: 330.92308 | P8: 157.65946 | Q8: -
B9: 2003 | C9: 187.38785 | D9: 182.96078 | E9: 191.66667 | F9: - | G9: 199.61765 | H9: - | I9: 175.13725 | J9: 200.29412 | K9: 146.33333 | L9: - | M9: 288.27451 | N9: 340.76471 | O9: 332.96078 | P9: 178.56863 | Q9: -
B10: 2004 | C10: 227.93368 | D10: 233.92157 | E10: 252.94118 | F10: - | G10: 246.68627 | H10: - | I10: 215.33333 | J10: 249.29412 | K10: 175.13725 | L10: - | M10: 329.5098 | N10: 384.33333 | O10: 369.80392 | P10: 222.61538 | Q10: 227.85714
B11: 2005 | C11: 252.91307 | D11: 259.14 | E11: 277.08 | F11: - | G11: 289.02 | H11: - | I11: 234.7 | J11: 271.8 | K11: 186.18 | L11: - | M11: 373.56 | N11: 426.5 | O11: 428.46 | P11: 247.4902 | Q11: 247.04082
B12: 2006 | C12: 256.35039 | D12: 264.58 | E12: 278.8 | F12: - | G12: 297.4 | H12: - | I12: 247.24 | J12: 285 | K12: 192.1 | L12: - | M12: 389.5 | N12: 453.96 | O12: 452.14 | P12: 262.76923 | Q12: 260.06122
B13: 2007 | C13: 432.71289 | D13: 420.96 | E13: 417.14286 | F13: - | G13: 458.48649 | H13: - | I13: 410.62 | J13: 458.86 | K13: 343.58 | L13: - | M13: 483.5 | N13: 532.4 | O13: 545 | P13: 423.98039 | Q13: 401.21429
B14: 2008 | C14: 914.93179 | D14: 1054.9756 | E14: 1102.45 | F14: - | G14: 986.14286 | H14: - | I14: 934.54 | J14: 1105.0698 | K14: 924.68421 | L14: - | M14: 1905.76 | N14: 1714.2 | O14: 2062.8163 | P14: 978.32 | Q14: 1163.3548
B15: 2009 | C15: 323.63667 | D15: 336.6383 | E15: 327.11628 | F15: - | G15: 365.28846 | H15: - | I15: 331.90385 | J15: 356.75556 | K15: 258 | L15: - | M15: 540.30769 | N15: 619.13462 | O15: 715.08 | P15: 328.03774 | Q15: 323.47826
B16: 2010 | C16: 508.9051 | D16: 494.94231 | E16: 477.69231 | F16: - | G16: 469.46154 | H16: - | I16: 488.34615 | J16: 529.40385 | K16: 391.38462 | L16: - | M16: 668.94231 | N16: 742.5 | O16: 800.46154 | P16: 501.46154 | Q16: 501.11538
B17: 2011 | C17: 617.46247 | D17: 646.11538 | E17: 593.42308 | F17: 665.29412 | G17: 607.80769 | H17: 614.63462 | I17: 631.53846 | J17: 664.71154 | K17: 541.07692 | L17: - | M17: 978.46154 | N17: 993.84615 | O17: 1118.4038 | P17: 619.25 | Q17: 626.58824
B18: 2012 | C18: 539.39445 | D18: 556.36538 | E18: 561.61538 | F18: 557.5098 | G18: 576.75 | H18: 545.71154 | I18: 539.53846 | J18: 575.96154 | K18: 462.05769 | L18: - | M18: 930.28846 | N18: 909.30769 | O18: 1084.4231 | P18: 539.78846 | Q18: 557.19231
B19: 2013 | C19: 456.81028 | D19: 471.11538 | E19: 461.69231 | F19: 456.11538 | G19: 466.11538 | H19: 442.46154 | I19: 455.38462 | J19: 480.48077 | K19: 381.65385 | L19: - | M19: 778.82692 | N19: 714.84615 | O19: 941.44231 | P19: 445.86538 | Q19: 452.98077
B20: 2014 | C20: 489.16547 | D20: 498.05769 | E20: 463.67308 | F20: 463.01923 | G20: 460.76923 | H20: 448.82692 | I20: 468.94231 | J20: 492.63462 | K20: 391.40385 | L20: 401.26923 | M20: 727.61538 | N20: 715.26923 | O20: 879.84615 | P20: 471.96154 | Q20: 478.07692
B21: 2015 | C21: 458.67571 | D21: 492.28302 | E21: 466.11321 | F21: 461.92453 | G21: 465 | H21: 452.32075 | I21: 462.66038 | J21: 469.77358 | K21: 387.41509 | L21: 373.07547 | M21: 783.58491 | N21: 798.58491 | O21: 945.37736 | P21: 458 | Q21: 459.22642
B22: 2016 | C22: 349.58867 | D22: 361.19231 | E22: 346.86538 | F22: 342.51923 | G22: 343.75 | H22: 332.09615 | I22: 338.28846 | J22: 350.38462 | K22: 288.73077 | L22: 288.28846 | M22: 699.28846 | N22: 626.48077 | O22: 825.88462 | P22: 345.07692 | Q22: 345.40385
B23: 2017 | C23: 356.70277 | D23: 367.82353 | E23: 349.54902 | F23: 363.29412 | G23: 362.78431 | H23: 356.98039 | I23: 349.78431 | J23: 369.17647 | K23: 277.19608 | L23: 282.94118 | M23: 602.11765 | N23: 566.82353 | O23: 705.35294 | P23: 354.03922 | Q23: 354.60784
B24: 2018 | C24: 435.11252 | D24: 428.82353 | E24: 411.01961 | F24: 418.21569 | G24: 423 | H24: 411.96078 | I24: 412.52941 | J24: 438.43137 | K24: 338.07843 | L24: 350.01961 | M24: 764.4902 | N24: 732.43137 | O24: 855.05882 | P24: 419.09804 | Q24: 418.2549
B25: 2019 | C25: 339.36485 | D25: 362.92157 | E25: 349.29412 | F25: 360.58824 | G25: 361.05882 | H25: 348.68627 | I25: 336.27451 | J25: 360.72549 | K25: 313.29412 | L25: 311.62745 | M25: 744.96078 | N25: 690.76471 | O25: 852.05882 | P25: 345.5098 | Q25: 345.47059
B26: 2020 | C26: 343.80036 | D26: 322.30769 | E26: 316.75 | F26: 323.13462 | G26: 331.38462 | H26: 322.23077 | I26: 317.03846 | J26: 337.11538 | K26: 249.15385 | L26: 251.48077 | M26: 687 | N26: 627.75 | O26: 791.55769 | P26: 322.75 | Q26: 321.40385
B27: 2021 | C27: 664.05085 | D27: 650.76471 | E27: 619.93333 | F27: 612.39216 | G27: 618.15686 | H27: 566.31818 | I27: 651.19608 | J27: 691.11765 | K27: 549.23529 | L27: 562.13725 | M27: 1113.902 | N27: 1072.8235 | O27: 1254.1579 | P27: 641.11765 | Q27: 656.46
B28: 2022 | C28: 848.10948 | D28: 968.90196 | E28: 897.96078 | F28: 891.31373 | G28: 875.98039 | H28: 800.78571 | I28: 849.27451 | J28: 911.21569 | K28: 820.94118 | L28: 801.66667 | M28: 1617.5686 | N28: 1540.7843 | O28: 1712.6471 | P28: 898.78431 | Q28: 902.52941
B29: 2023 | C29: 604.3842 | D29: 588.72549 | E29: 557.17647 | F29: 564.31373 | G29: 568.80392 | H29: 556.52941 | I29: 516.72549 | J29: 556.88235 | K29: 449.39216 | L29: 434.35294 | M29: 1011.2941 | N29: 963.33333 | O29: 1151.1373 | P29: 560.27451 | Q29: 552.15686
B30: 2024 | C30: 620.01427 | D30: 585.54902 | E30: 581.98039 | F30: 590.54902 | G30: 587.4902 | H30: 578.84444 | I30: 554.76471 | J30: 602.62745 | K30: 436.07843 | L30: 465.05882 | M30: 994.8 | N30: 979.84314 | O30: 1117.0588 | P30: 560 | Q30: 560
B31: 2025 | C31: 768.9175 | D31: 711.31581 | E31: 712.79613 | F31: 707.28352 | G31: 719.76538 | H31: 703.39359 | I31: 643.65346 | J31: 690.28846 | K31: 520.54204 | L31: 556.1859 | M31: 1241.4936 | N31: 1189 | O31: 1277.7616
B32: 2026 | C32: 735.41419 | D32: 681.48333 | E32: 675.35556 | F32: 663.00721 | G32: 699.26667 | H32: 680.26667 | I32: 611.46179 | J32: 668.33333 | K32: 502.43006 | L32: 528.75 | M32: 1244.6548 | N32: 1200 | O32: 1368.3766
B33: 2027 | C33: 678.88993 | D33: 629.38889 | E33: 617.25833 | F33: 614.23491 | G33: 653.84767 | H33: 632.11583 | I33: 581.80452 | J33: 635.63044 | K33: 486.71209 | L33: 508.95956 | M33: 1231.8886 | N33: 1192.3937 | O33: 1354.0114
B34: 2028 | C34: 635.78578 | D34: 594.50002 | E34: 584.12857 | F34: 581.92523 | G34: 610.20233 | H34: 599.505 | I34: 560.62028 | J34: 611.99582 | K34: 471.78529 | L34: 494.49045 | M34: 1142.9244 | N34: 1107.9364 | O34: 1260.3934
B35: 2029 | C35: 591.73817 | D35: 561.00871 | E35: 553.37073 | F35: 552.41348 | G35: 568.69042 | H35: 561.83037 | I35: 530.88171 | J35: 578.50923 | K35: 445.5145 | L35: 468.76322 | M35: 1051.2796 | N35: 1024.7139 | O35: 1163.1748
B36: 2030 | C36: 561.90093 | D36: 538.7978 | E36: 533.0051 | F36: 532.72286 | G36: 541.8769 | H36: 537.49544 | I36: 508.91313 | J36: 553.80148 | K36: 421.71637 | L36: 445.79866 | M36: 998.30959 | N36: 976.89824 | O36: 1106.924

Sheet Phosphate monthly prices
D1: DAP Bulk FOB | G1: DAP Bulk FOB | J1: DAP Bulk FOB | M1: DAP Bulk FOB | P1: DAP Bulk FOB | S1: DAP Bulk FOB | V1: DAP Bulk FOB | Y1: DAP Bulk FOB | AB1: DAP Bulk FOB | AE1: DAP Bulk FOB | AH1: DAP Bulk FOB | AK1: DAP Bulk FOB | AN1: DAP Bulk FOB | AQ1: DAP Bulk FOB | AT1: DAP Bulk FOB | AW1: DAP Bulk FOB | AZ1: DAP Bulk FOB | BC1: DAP Bulk FOB | BF1: DAP Bulk FOB | BI1: DAP Bulk FOB | BL1: DAP Bulk FOB | BO1: DAP Bulk FOB | BR1: DAP Bulk FOB | BU1: DAP Bulk CFR | BX1: DAP Bulk CFR | CA1: DAP Bulk CFR | CD1: DAP Bagged CFR | CG1: DAP Bulk CFR | CJ1: DAP Bagged CPT | CM1: DAP Bagged EXW | CP1: DAP Bulk FCA | CS1: DAP Bulk DEL | CV1: DAP Bulk DEL | CY1: MAP Granular Bulk FOB | DB1: MAP Granular Bulk FOB | DE1: MAP Granular Bulk FOB | DH1: MAP Granular Bulk FOB | DK1: MAP Granular Bulk FOB | DN1: MAP Granular Bulk FOB | DQ1: MAP Granular Bulk FOB | DT1: MAP Bulk FOB | DW1: MAP Granular Bulk FOB | DZ1: MAP Bulk FOB | EC1: MAP Granular Bulk FOB | EF1: MAP Granular Bulk FOB | EI1: MAP Granular Bulk FOB | EL1: MAP Granular Bulk FOB | EO1: MAP Bagged EXW | ER1: MAP Bagged EXW | EU1: MAP Granular Bulk CFR | EX1: MAP Granular Bulk CFR | FA1: MAP Granular Bulk CFR | FD1: MAP Granular Bulk DEL | FG1: TSP Granular Bulk FOB | FJ1: TSP Granular Bulk FOB | FM1: TSP Granular Bulk FCA | FP1: TSP Granular Bulk FOB | FS1: TSP Bulk FOB | FV1: TSP Granular Bulk FOB | FY1: TSP Granular Bulk CFR | GB1: Phosphoric Acid Bulk FOB | GE1: Phosphoric Acid Bulk CFR | GH1: Phosphoric Acid Bulk CFR | GK1: Phosphoric Acid Bulk CFR | GN1: Phosphoric Acid Bulk CFR | GQ1: Phosphoric Acid Bulk FOB | GT1: Phosphoric Acid Bulk CFR | GW1: Phosphoric Acid Bulk FOB | GZ1: Phosphate Rock Bulk FOB | HC1: Phosphate Rock Bulk CFR | HF1: Phosphate Rock Bulk CFR | HI1: Phosphate Rock Bulk CFR | HL1: Phosphate Rock Bulk FOB | HO1: Phosphate Rock Bulk FOB | HR1: Phosphate Rock Bulk FOB | HU1: Phosphate Rock Bulk FOB | HX1: Phosphate Rock Bulk FOB | IA1: Phosphate Rock Bulk FOB
D2: US Gulf/Tampa Spot | G2: US Central Florida Spot | J2: US New Orleans barge Spot | M2: US Midwest Spot | P2: US Midwest East Spot | S2: US Midwest West Spot | V2: US Southern Plains Spot | Y2: US South Spot | AB2: US Twin Cities Spot | AE2: US Tulsa Spot | AH2: US Cincinnati Spot | AK2: Mexico Spot/Contract | AN2: NW Mexico Spot | AQ2: US Gulf 2x4mm Spot | AT2: Argentina Spot | AW2: Baltic/Black Sea Spot | AZ2: North Africa Spot | BC2: Tunisia Spot | BF2: Morocco Spot | BI2: Jordan Spot | BL2: Saudi Arabia Spot | BO2: Australia Spot | BR2: China Spot | BU2: India Spot | BX2: Pakistan Spot | CA2: China Spot | CD2: China Spot | CG2: Argentina/Uruguay Spot | CJ2: China wholesale Spot | CM2: China (excludes export sales) Spot | CP2: Terneuzen/Ghent Spot | CS2: US California Spot | CV2: US Northwest Spot | CY2: Baltic/Black Sea Spot | DB2: US New Orleans barge Spot | DE2: US Twin Cities Spot | DH2: US Tulsa Spot | DK2: US Cincinnati Spot | DN2: US Midwest Spot | DQ2: US Southern Plains Spot | DT2: US Central Florida Spot | DW2: US Gulf/Tampa Spot | DZ2: Brazil plant Spot | EC2: Morocco Spot | EF2: Mexico Spot/Contract | EI2: China 11-44 Spot | EL2: Saudi Arabia Spot | EO2: China 11-44-0 (excludes export sales) Spot | ER2: China 10-50-0 (excludes export sales) Spot | EU2: Argentina Spot | EX2: Brazil Spot | FA2: Brazil 11-44 Spot | FD2: Western Canada Spot | FG2: Tunisia Spot | FJ2: Morocco Spot | FM2: Benelux Spot | FP2: US Central Florida Spot | FS2: Tampa/US gulf Spot | FV2: China Spot | FY2: Brazil Spot | GB2: North Africa Quarterly 100% P2O5 Contract | GE2: India Quarterly 100% P2O5 Contract | GH2: NW Europe Quarterly 100% P2O5 Spot/Contract | GK2: NW Europe (non-food grade) Quarterly 100% P2O5 Spot/Contract | GN2: Mediterranean 100% P2O5 Spot | GQ2: US Tampa Spot | GT2: Brazil Quarterly 100% P2O5 Spot/Contract | GW2: US Gulf 100% P205 Spot | GZ2: Morocco (68-72% BPL) Spot/Contract | HC2: India (71-75% BPL) Spot/Contract | HF2: India (71-80% BPL) Spot/Contract | HI2: India (65-70% BPL) Spot/Contract | HL2: Egypt (60-68% BPL) Spot/Contract | HO2: Jordan Quarterly (66-72% BPL) Contract | HR2: Jordan Quarterly (73-75% BPL) Contract | HU2: Russia (78-87% BPL) Spot/Contract | HX2: Peru (63-68% BPL) Spot/Contract | IA2: Algeria (63-66% BPL) Spot/Contract
D3: USD/t | G3: USD/st | J3: USD/st | M3: USD/st | P3: USD/st | S3: USD/st | V3: USD/st | Y3: USD/st | AB3: USD/st | AE3: USD/st | AH3: USD/st | AK3: USD/t | AN3: MXN/t | AQ3: USD/t | AT3: ARS/t | AW3: USD/t | AZ3: USD/t | BC3: USD/t | BF3: USD/t | BI3: USD/t | BL3: USD/t | BO3: USD/t | BR3: USD/t | BU3: USD/t | BX3: USD/t | CA3: USD/t | CD3: RMB/t | CG3: USD/t | CJ3: RMB/t | CM3: RMB/t | CP3: USD/t | CS3: USD/st | CV3: USD/st | CY3: USD/t | DB3: USD/st | DE3: USD/st | DH3: USD/st | DK3: USD/st | DN3: USD/st | DQ3: USD/st | DT3: USD/st | DW3: USD/t | DZ3: BRL/t | EC3: USD/t | EF3: USD/t | EI3: USD/t | EL3: USD/t | EO3: RMB/t | ER3: RMB/t | EU3: USD/t | EX3: USD/t | FA3: USD/t | FD3: CAD/t | FG3: USD/t | FJ3: USD/t | FM3: USD/t | FP3: USD/st | FS3: USD/t | FV3: USD/t | FY3: USD/t | GB3: USD/t | GE3: USD/t | GH3: USD/t | GK3: USD/t | GN3: USD/t | GQ3: USD/t | GT3: USD/t | GW3: USD/t | GZ3: USD/t | HC3: USD/t | HF3: USD/t | HI3: USD/t | HL3: USD/t | HO3: USD/t | HR3: USD/t | HU3: USD/t | HX3: USD/t | IA3: USD/t
A4: Year | B4: Quarter | C4: Month | D4: Max | E4: Min | F4: Avg | G4: Max | H4: Min | I4: Avg | J4: Max | K4: Min | L4: Avg | M4: Max | N4: Min | O4: Avg | P4: Max | Q4: Min | R4: Avg | S4: Max | T4: Min | U4: Avg | V4: Max | W4: Min | X4: Avg | Y4: Max | Z4: Min | AA4: Avg | AB4: Max | AC4: Min | AD4: Avg | AE4: Max | AF4: Min | AG4: Avg | AH4: Max | AI4: Min | AJ4: Avg | AK4: Max | AL4: Min | AM4: Avg | AN4: Max | AO4: Min | AP4: Avg | AQ4: Max | AR4: Min | AS4: Avg | AT4: Max | AU4: Min | AV4: Avg | AW4: Max | AX4: Min | AY4: Avg | AZ4: Max | BA4: Min | BB4: Avg | BC4: Max | BD4: Min | BE4: Avg | BF4: Max | BG4: Min | BH4: Avg | BI4: Max | BJ4: Min | BK4: Avg | BL4: Max | BM4: Min | BN4: Avg | BO4: Max | BP4: Min | BQ4: Avg | BR4: Max | BS4: Min | BT4: Avg | BU4: Max | BV4: Min | BW4: Avg | BX4: Max | BY4: Min | BZ4: Avg | CA4: Max | CB4: Min | CC4: Avg | CD4: Max | CE4: Min | CF4: Avg | CG4: Max | CH4: Min | CI4: Avg | CJ4: Max | CK4: Min | CL4: Avg | CM4: Max | CN4: Min | CO4: Avg | CP4: Max | CQ4: Min | CR4: Avg | CS4: Max | CT4: Min | CU4: Avg | CV4: Max | CW4: Min | CX4: Avg | CY4: Max | CZ4: Min | DA4: Avg | DB4: Max | DC4: Min | DD4: Avg | DE4: Max | DF4: Min | DG4: Avg | DH4: Max | DI4: Min | DJ4: Avg | DK4: Max | DL4: Min | DM4: Avg | DN4: Max | DO4: Min | DP4: Avg | DQ4: Max | DR4: Min | DS4: Avg | DT4: Max | DU4: Min | DV4: Avg | DW4: Max | DX4: Min | DY4: Avg | DZ4: Max | EA4: Min | EB4: Avg | EC4: Max | ED4: Min | EE4: Avg | EF4: Max | EG4: Min | EH4: Avg | EI4: Max | EJ4: Min | EK4: Avg | EL4: Max | EM4: Min | EN4: Avg | EO4: Max | EP4: Min | EQ4: Avg | ER4: Max | ES4: Min | ET4: Avg | EU4: Max | EV4: Min | EW4: Avg | EX4: Max | EY4: Min | EZ4: Avg | FA4: Max | FB4: Min | FC4: Avg | FD4: Max | FE4: Min | FF4: Avg | FG4: Max | FH4: Min | FI4: Avg | FJ4: Max | FK4: Min | FL4: Avg | FM4: Max | FN4: Min | FO4: Avg | FP4: Max | FQ4: Min | FR4: Avg | FS4: Max | FT4: Min | FU4: Avg | FV4: Max | FW4: Min | FX4: Avg | FY4: Max | FZ4: Min | GA4: Avg | GB4: Max | GC4: Min | GD4: Avg | GE4: Max | GF4: Min | GG4: Avg | GH4: Max | GI4: Min | GJ4: Avg | GK4: Max | GL4: Min | GM4: Avg | GN4: Max | GO4: Min | GP4: Avg | GQ4: Max | GR4: Min | GS4: Avg | GT4: Max | GU4: Min | GV4: Avg | GW4: Max | GX4: Min | GY4: Avg | GZ4: Max | HA4: Min | HB4: Avg | HC4: Max | HD4: Min | HE4: Avg | HF4: Max | HG4: Min | HH4: Avg | HI4: Max | HJ4: Min | HK4: Avg | HL4: Max | HM4: Min | HN4: Avg | HO4: Max | HP4: Min | HQ4: Avg | HR4: Max | HS4: Min | HT4: Avg | HU4: Max | HV4: Min | HW4: Avg | HX4: Max | HY4: Min | HZ4: Avg | IA4: Max | IB4: Min | IC4: Avg
A5: 1987 | B5: 2 | C5: 4 | AZ5: 175 | BA5: 170 | BB5: 173 | BF5: 175 | BG5: 170 | BH5: 173 | BI5: 180 | BJ5: 170 | BK5: 175 | CP5: 205 | CQ5: 200 | CR5: 203 | FJ5: 146 | FK5: 143 | FL5: 145 | FS5: 135 | FT5: 130 | FU5: 133 | GB5: 260 | GC5: 250 | GD5: 255 | GE5: 325 | GF5: 325 | GG5: 325 | GH5: 325 | GI5: 315 | GJ5: 320 | GW5: 255 | GX5: 250 | GY5: 253
A6: 1987 | B6: 2 | C6: 5 | AZ6: 175 | BA6: 170 | BB6: 173 | BF6: 175 | BG6: 170 | BH6: 173 | BI6: 168.75 | BJ6: 162.5 | BK6: 166 | CP6: 205 | CQ6: 200 | CR6: 203 | FJ6: 146 | FK6: 143 | FL6: 145 | FS6: 136.5 | FT6: 131 | FU6: 134 | GB6: 260 | GC6: 248 | GD6: 254 | GE6: 325 | GF6: 325 | GG6: 325 | GH6: 325 | GI6: 315 | GJ6: 320 | GW6: 255 | GX6: 250 | GY6: 253
A7: 1987 | B7: 2 | C7: 6 | AZ7: 187.5 | BA7: 180 | BB7: 184 | BF7: 187.5 | BG7: 180 | BH7: 184 | BI7: 180 | BJ7: 173.75 | BK7: 177.25 | CP7: 205 | CQ7: 200 | CR7: 203 | FJ7: 146 | FK7: 143 | FL7: 145 | FS7: 141.25 | FT7: 137 | FU7: 139.5 | GB7: 260 | GC7: 248 | GD7: 254 | GE7: 325 | GF7: 325 | GG7: 325 | GH7: 325 | GI7: 315 | GJ7: 320 | GW7: 255 | GX7: 250 | GY7: 253
A8: 1987 | B8: 3 | C8: 7 | AZ8: 199 | BA8: 193 | BB8: 196.4 | BF8: 199 | BG8: 193 | BH8: 196.4 | BI8: 196 | BJ8: 191 | BK8: 194 | CP8: 205 | CQ8: 200 | CR8: 203 | FJ8: 147.6 | FK8: 144.4 | FL8: 146.4 | FS8: 146.6 | FT8: 143.8 | FU8: 145.4 | GB8: 260 | GC8: 248 | GD8: 254 | GE8: 325 | GF8: 325 | GG8: 325 | GH8: 327 | GI8: 319 | GJ8: 323 | GW8: 255 | GX8: 250 | GY8: 253
A9: 1987 | B9: 3 | C9: 8 | AZ9: 210 | BA9: 203.75 | BB9: 207.25 | BF9: 210 | BG9: 203.75 | BH9: 207.25 | BI9: 208.75 | BJ9: 203.75 | BK9: 206.75 | FJ9: 154.25 | FK9: 151 | FL9: 153 | FS9: 153.25 | FT9: 149.75 | FU9: 151.75 | GB9: 260 | GC9: 254 | GD9: 257.5 | GE9: 325 | GF9: 325 | GG9: 325 | GH9: 335 | GI9: 325 | GJ9: 330 | GW9: 258 | GX9: 255 | GY9: 257
A10: 1987 | B10: 3 | C10: 9 | AZ10: 210 | BA10: 205 | BB10: 208 | BF10: 210 | BG10: 205 | BH10: 208 | BI10: 207.5 | BJ10: 202.5 | BK10: 205.5 | CP10: 215 | CQ10: 215 | CR10: 215 | FJ10: 155 | FK10: 152 | FL10: 154 | FS10: 152.25 | FT10: 148.75 | FU10: 150.75 | GB10: 260 | GC10: 251 | GD10: 256 | GE10: 325 | GF10: 325 | GG10: 325 | GH10: 335 | GI10: 325 | GJ10: 330 | GW10: 258 | GX10: 255 | GY10: 257
A11: 1987 | B11: 4 | C11: 10 | AZ11: 207.2 | BA11: 201 | BB11: 204.6 | BF11: 207.2 | BG11: 201 | BH11: 204.6 | BI11: 198.8 | BJ11: 195 | BK11: 197.2 | CP11: 215 | CQ11: 215 | CR11: 215 | FJ11: 154.6 | FK11: 151.6 | FL11: 153.6 | FS11: 148.2 | FT11: 144.8 | FU11: 147 | GB11: 256 | GC11: 251 | GD11: 253.6 | GE11: 350 | GF11: 350 | GG11: 350 | GH11: 328 | GI11: 322 | GJ11: 325.4 | GW11: 255.6 | GX11: 251 | GY11: 253.8
A12: 1987 | B12: 4 | C12: 11 | AZ12: 207.75 | BA12: 201.25 | BB12: 205 | BF12: 207.75 | BG12: 201.25 | BH12: 205 | BI12: 200.5 | BJ12: 196.25 | BK12: 198.75 | CP12: 215 | CQ12: 215 | CR12: 215 | FJ12: 153 | FK12: 150 | FL12: 152 | FS12: 145 | FT12: 142.5 | FU12: 144 | GB12: 255 | GC12: 251 | GD12: 253 | GE12: 350 | GF12: 350 | GG12: 350 | GH12: 330 | GI12: 325 | GJ12: 328 | GW12: 255 | GX12: 250 | GY12: 253
A13: 1987 | B13: 4 | C13: 12 | AZ13: 217.5 | BA13: 212.5 | BB13: 215.5 | BF13: 217.5 | BG13: 212.5 | BH13: 215.5 | BI13: 215 | BJ13: 211 | BK13: 213.5 | CP13: 245 | CQ13: 240 | CR13: 243 | FJ13: 157 | FK13: 152.75 | FL13: 155.25 | FS13: 148 | FT13: 144 | FU13: 146.5 | GB13: 275 | GC13: 270.5 | GD13: 273 | GE13: 367.5 | GF13: 367.5 | GG13: 367.5 | GH13: 347.5 | GI13: 333.75 | GJ13: 340.75 | GW13: 275 | GX13: 270 | GY13: 273
A14: 1988 | B14: 1 | C14: 1 | AZ14: 226.25 | BA14: 217.25 | BB14: 222.25 | BF14: 226.25 | BG14: 217.25 | BH14: 222.25 | BI14: 223.75 | BJ14: 220.25 | BK14: 222.25 | CP14: 243.75 | CQ14: 238 | CR14: 241.25 | FJ14: 165 | FK14: 160 | FL14: 163 | FS14: 156.5 | FT14: 154 | FU14: 155.5 | GB14: 295 | GC14: 290 | GD14: 293 | GE14: 385 | GF14: 385 | GG14: 385 | GH14: 362.5 | GI14: 350 | GJ14: 356.5 | GW14: 295 | GX14: 290 | GY14: 293
A15: 1988 | B15: 1 | C15: 2 | AZ15: 220 | BA15: 210 | BB15: 215 | BF15: 220 | BG15: 210 | BH15: 215 | BI15: 218 | BJ15: 217 | BK15: 218 | CP15: 240 | CQ15: 232 | CR15: 236 | FJ15: 162.5 | FK15: 157.25 | FL15: 160.25 | FS15: 156.75 | FT15: 153.5 | FU15: 155.5 | GB15: 302.5 | GC15: 293.75 | GD15: 298.25 | GE15: 385 | GF15: 385 | GG15: 385 | GH15: 367.5 | GI15: 362.5 | GJ15: 365.5 | GW15: 298.75 | GX15: 318.75 | GY15: 309.25
A16: 1988 | B16: 1 | C16: 3 | AZ16: 220 | BA16: 215 | BB16: 218 | BF16: 220 | BG16: 215 | BH16: 218 | BI16: 210 | BJ16: 206 | BK16: 208.4 | CP16: 234 | CQ16: 227.8 | CR16: 231.2 | FJ16: 159.6 | FK16: 155 | FL16: 157.6 | FS16: 156 | FT16: 152 | FU16: 154 | GB16: 310 | GC16: 305 | GD16: 308 | GE16: 385 | GF16: 385 | GG16: 385 | GH16: 370 | GI16: 365 | GJ16: 368 | GW16: 310 | GX16: 305 | GY16: 308
A17: 1988 | B17: 2 | C17: 4 | AZ17: 213.75 | BA17: 208.75 | BB17: 211.75 | BF17: 213.75 | BG17: 208.75 | BH17: 211.75 | BI17: 206.5 | BJ17: 202 | BK17: 204.5 | CP17: 230 | CQ17: 225 | CR17: 228 | FJ17: 163.5 | FK17: 156.5 | FL17: 160 | FS17: 156 | FT17: 152 | FU17: 154 | GB17: 332.5 | GC17: 327.5 | GD17: 330.5 | GE17: 385 | GF17: 385 | GG17: 385 | GH17: 370 | GI17: 365 | GJ17: 368 | GW17: 310 | GX17: 305 | GY17: 308
A18: 1988 | B18: 2 | C18: 5 | AZ18: 213 | BA18: 207.5 | BB18: 210.5 | BF18: 213 | BG18: 207.5 | BH18: 210.5 | BI18: 205 | BJ18: 200 | BK18: 203 | CP18: 230 | CQ18: 225 | CR18: 228 | FJ18: 164 | FK18: 158.5 | FL18: 161.5 | FS18: 156 | FT18: 152 | FU18: 154 | GB18: 340 | GC18: 335 | GD18: 338 | GE18: 385 | GF18: 385 | GG18: 385 | GH18: 370 | GI18: 365 | GJ18: 368 | GW18: 325 | GX18: 320 | GY18: 323
A19: 1988 | B19: 2 | C19: 6 | AZ19: 216 | BA19: 211.6 | BB19: 214.2 | BF19: 216 | BG19: 211.6 | BH19: 214.2 | BI19: 218 | BJ19: 213 | BK19: 216 | CP19: 230 | CQ19: 225 | CR19: 228 | FJ19: 163 | FK19: 160 | FL19: 162 | FS19: 156.8 | FT19: 152.6 | FU19: 154.8 | GB19: 340 | GC19: 335 | GD19: 338 | GE19: 417.8 | GF19: 417.8 | GG19: 417.8 | GH19: 370 | GI19: 365 | GJ19: 368 | GW19: 330 | GX19: 325 | GY19: 328
A20: 1988 | B20: 3 | C20: 7 | AZ20: 220 | BA20: 215 | BB20: 218 | BF20: 220 | BG20: 215 | BH20: 218 | BI20: 222.5 | BJ20: 218.5 | BK20: 221 | CP20: 235 | CQ20: 230 | CR20: 233 | FJ20: 170 | FK20: 163 | FL20: 167 | FS20: 160 | FT20: 155 | FU20: 158 | GB20: 355 | GC20: 350 | GD20: 353 | GE20: 426 | GF20: 426 | GG20: 426 | GH20: 400 | GI20: 390 | GJ20: 395 | GW20: 355 | GX20: 350 | GY20: 353
A21: 1988 | B21: 3 | C21: 8 | AZ21: 220 | BA21: 215 | BB21: 218 | BF21: 220 | BG21: 215 | BH21: 218 | BI21: 220 | BJ21: 217 | BK21: 219 | CP21: 240 | CQ21: 235 | CR21: 238 | FJ21: 167.5 | FK21: 163 | FL21: 165.5 | FS21: 161.5 | FT21: 157.5 | FU21: 160 | GB21: 355 | GC21: 350 | GD21: 353 | GE21: 426 | GF21: 426 | GG21: 426 | GH21: 400 | GI21: 390 | GJ21: 395 | GW21: 355 | GX21: 350 | GY21: 353
... A43: 1990 | B43: 2 | C43: 6 | AZ43: 190 | BA43: 180 | BB43: 185 | BF43: 190 | BG43: 180 | BH43: 185 | BI43: 180 | BJ43: 175 | BK43: 178 | CP43: 185 | CQ43: 179 | CR43: 182 | FJ43: 139 | FK43: 133.25 | FL43: 136.5 | FS43: 130.5 | FT43: 128 | FU43: 129.25 | GB43: 325 | GC43: 305 | GD43: 315 | GE43: 377 | GF43: 376 | GG43: 377 | GH43: 360 | GI43: 350 | GJ43: 355 | GW43: 285 | GX43: 278 | GY43: 282
A44: 1990 | B44: 3 | C44: 7 | D44: 179.33333 | E44: 176.33333 | F44: 178.33333 | G44: 150 | H44: 147 | I44: 149 | J44: 161.66667 | K44: 159.66667 | L44: 160.66667 | P44: 174.33333 | Q44: 172 | R44: 173.33333 | S44: 170 | T44: 168 | U44: 169 | AZ44: 193.75 | BA44: 187.5 | BB44: 191 | BF44: 193.75 | BG44: 187.5 | BH44: 191 | BI44: 195 | BJ44: 190 | BK44: 193 | CP44: 203.75 | CQ44: 194.75 | CR44: 199.25 | CS44: 210 | CT44: 209 | CU44: 210 | CV44: 205 | CW44: 205 | CX44: 205 | DT44: 157.33333 | DU44: 153.66667 | DV44: 155.66667 | FJ44: 143.5 | FK44: 140 | FL44: 142 | FP44: 123.33333 | FQ44: 118.33333 | FR44: 121.33333 | FS44: 132 | FT44: 129.5 | FU44: 130.75 | GB44: 325 | GC44: 305 | GD44: 315 | GE44: 377 | GF44: 376 | GG44: 377 | GH44: 360 | GI44: 350 | GJ44: 355 | GW44: 300 | GX44: 295 | GY44: 298
A45: 1990 | B45: 3 | C45: 8 | D45: 175.25 | E45: 172.25 | F45: 174.25 | G45: 151.5 | H45: 149 | I45: 150.5 | J45: 160.5 | K45: 159 | L45: 160 | P45: 174.25 | Q45: 171.25 | R45: 173.25 | S45: 170.25 | T45: 168.25 | U45: 169.25 | AZ45: 195.4 | BA45: 191 | BB45: 193.6 | BF45: 195.4 | BG45: 191 | BH45: 193.6 | BI45: 195 | BJ45: 190 | BK45: 193 | CP45: 212 | CQ45: 202 | CR45: 207 | CS45: 218.75 | CT45: 211.25 | CU45: 215 | CV45: 205 | CW45: 205 | CX45: 205 | DT45: 161.25 | DU45: 156.5 | DV45: 159 | FJ45: 146.6 | FK45: 141 | FL45: 144.2 | FP45: 129.25 | FQ45: 126 | FR45: 128 | FS45: 138.8 | FT45: 132.4 | FU45: 135.6 | GB45: 325 | GC45: 305 | GD45: 315 | GE45: 377 | GF45: 376 | GG45: 377 | GH45: 360 | GI45: 350 | GJ45: 355 | GW45: 300 | GX45: 295 | GY45: 298
A46: 1990 | B46: 3 | C46: 9 | D46: 182 | E46: 176.75 | F46: 179.5 | G46: 155.25 | H46: 151.5 | I46: 153.75 | J46: 166 | K46: 164.75 | L46: 165.75 | P46: 176 | Q46: 173.75 | R46: 175 | S46: 173.25 | T46: 170.5 | U46: 172.25 | AZ46: 199.5 | BA46: 196 | BB46: 198 | BF46: 199.5 | BG46: 196 | BH46: 198 | BI46: 195 | BJ46: 188.75 | BK46: 192.25 | CP46: 217.5 | CQ46: 210 | CR46: 214 | CS46: 227.5 | CT46: 210 | CU46: 218.75 | CV46: 195 | CW46: 180 | CX46: 188 | DT46: 168.5 | DU46: 161 | DV46: 164.75 | FJ46: 152.5 | FK46: 147.5 | FL46: 150.5 | FP46: 131.25 | FQ46: 128.25 | FR46: 130 | FS46: 147.5 | FT46: 141 | FU46: 144.5 | GB46: 327.5 | GC46: 305 | GD46: 316.5 | GE46: 392.75 | GF46: 376 | GG46: 384.75 | GH46: 372.5 | GI46: 356.5 | GJ46: 364.5 | GW46: 305 | GX46: 296.25 | GY46: 301
A47: 1990 | B47: 4 | C47: 10 | D47: 189 | E47: 185.75 | F47: 187.75 | G47: 159.25 | H47: 155.25 | I47: 157.75 | J47: 165.75 | K47: 164.25 | L47: 165.5 | P47: 179.5 | Q47: 175.25 | R47: 177.75 | S47: 180 | T47: 176 | U47: 178.25 | AZ47: 208.75 | BA47: 203.25 | BB47: 206.5 | BF47: 208.75 | BG47: 203.25 | BH47: 206.5 | BI47: 200 | BJ47: 197.25 | BK47: 198.75 | CP47: 226.25 | CQ47: 223.25 | CR47: 225.25 | CS47: 230 | CT47: 210 | CU47: 220 | CV47: 194 | CW47: 180 | CX47: 187.33333 | DT47: 169 | DU47: 163 | DV47: 166 | FJ47: 159.5 | FK47: 152.5 | FL47: 156.25 | FP47: 139.25 | FQ47: 136.75 | FR47: 138.25 | FS47: 153.75 | FT47: 145.25 | FU47: 149.75 | GB47: 330 | GC47: 305 | GD47: 318 | GE47: 410 | GF47: 376 | GG47: 393 | GH47: 410 | GI47: 376 | GJ47: 393 | GW47: 310 | GX47: 300 | GY47: 305
A48: 1990 | B48: 4 | C48: 11 | D48: 187.4 | E48: 185 | F48: 186.4 | G48: 157.4 | H48: 154.2 | I48: 155.8 | J48: 165.4 | K48: 162.8 | L48: 164.4 | P48: 180 | Q48: 175.8 | R48: 178.2 | S48: 180 | T48: 176.4 | U48: 178.2 | AZ48: 213.8 | BA48: 208 | BB48: 211.2 | BF48: 213.8 | BG48: 208 | BH48: 211.2 | BI48: 200 | BJ48: 198 | BK48: 199 | CP48: 228.4 | CQ48: 224 | CR48: 226.6 | CS48: 230 | CT48: 210 | CU48: 220 | CV48: 205 | CW48: 190 | CX48: 198 | DT48: 169 | DU48: 163 | DV48: 166 | FJ48: 163 | FK48: 155 | FL48: 159 | FP48: 139.6 | FQ48: 138 | FR48: 138.8 | FS48: 155 | FT48: 150 | FU48: 153 | GB48: 330 | GC48: 305 | GD48: 318 | GE48: 404.6 | GF48: 376 | GG48: 390.6 | GH48: 398 | GI48: 376 | GJ48: 387 | GW48: 310 | GX48: 300 | GY48: 305
A49: 1990 | B49: 4 | C49: 12 | D49: 182.25 | E49: 179 | F49: 181 | G49: 150.25 | H49: 148 | I49: 149.25 | J49: 159.5 | K49: 158 | L49: 159 | P49: 178 | Q49: 174.25 | R49: 176.5 | S49: 178 | T49: 174.25 | U49: 176.5 | AZ49: 212 | BA49: 208.66667 | BB49: 210.33333 | BF49: 212 | BG49: 208.66667 | BH49: 210.33333 | BI49: 200 | BJ49: 198 | BK49: 199 | CP49: 225.66667 | CQ49: 220.66667 | CR49: 223.66667 | CS49: 230 | CT49: 210 | CU49: 220 | CV49: 205 | CW49: 190 | CX49: 198 | DT49: 169 | DU49: 163 | DV49: 166 | FJ49: 163 | FK49: 159.33333 | FL49: 161.66667 | FP49: 132.75 | FQ49: 128.75 | FR49: 131 | FS49: 153.66667 | FT49: 149 | FU49: 151.66667 | GB49: 321.66667 | GC49: 305 | GD49: 313.66667 | GE49: 401.66667 | GF49: 376 | GG49: 389.33333 | GH49: 390 | GI49: 376 | GJ49: 383 | GW49: 310 | GX49: 300 | GY49: 305
A50: 1991 | B50: 1 | C50: 1 | D50: 180 | E50: 175.5 | F50: 178 | G50: 148 | H50: 146.25 | I50: 147.5 | J50: 158 | K50: 156.5 | L50: 157.75 | P50: 178 | Q50: 173 | R50: 176 | S50: 178 | T50: 173 | U50: 176 | AZ50: 211 | BA50: 208.4 | BB50: 210 | BF50: 211 | BG50: 208.4 | BH50: 210 | BI50: 200 | BJ50: 197.8 | BK50: 199 | CP50: 225 | CQ50: 221.8 | CR50: 223.6 | CS50: 230 | CT50: 210 | CU50: 220 | CV50: 205 | CW50: 190 | CX50: 198 | DT50: 169 | DU50: 163 | DV50: 166 | FJ50: 163 | FK50: 157.8 | FL50: 160.6 | FP50: 127 | FQ50: 122.66667 | FR50: 125.33333 | FS50: 155 | FT50: 150 | FU50: 153 | GB50: 310 | GC50: 305 | GD50: 308 | GE50: 395 | GF50: 391.2 | GG50: 393.2 | GH50: 366 | GI50: 355.2 | GJ50: 360.6 | GW50: 290 | GX50: 280 | GY50: 285
A51: 1991 | B51: 1 | C51: 2 | D51: 184.75 | E51: 182.75 | F51: 183.75 | G51: 151.5 | H51: 148.75 | I51: 150.25 | J51: 163.5 | K51: 159.75 | L51: 161.75 | P51: 177 | Q51: 172 | R51: 175 | S51: 177 | T51: 172 | U51: 175 | AZ51: 211.75 | BA51: 207.5 | BB51: 210 | BF51: 211.75 | BG51: 207.5 | BH51: 210 | BI51: 210 | BJ51: 200 | BK51: 205 | CP51: 225 | CQ51: 222.25 | CR51: 223.75 | CS51: 230 | CT51: 210 | CU51: 220 | CV51: 205 | CW51: 190 | CX51: 198 | DT51: 169 | DU51: 163 | DV51: 166 | FJ51: 160 | FK51: 157 | FL51: 159 | FP51: 126 | FQ51: 121 | FR51: 123.5 | FS51: 155 | FT51: 150 | FU51: 153 | GB51: 330 | GC51: 311 | GD51: 320.5 | GE51: 395 | GF51: 395 | GG51: 395 | GH51: 360 | GI51: 350 | GJ51: 355 | GW51: 288 | GX51: 277.5 | GY51: 282.75
A52: 1991 | B52: 1 | C52: 3 | D52: 183.25 | E52: 181.5 | F52: 182.5 | G52: 153.25 | H52: 149.5 | I52: 151.5 | J52: 164.5 | K52: 162.75 | L52: 163.75 | P52: 177.25 | Q52: 172.75 | R52: 175.5 | S52: 176.5 | T52: 169.5 | U52: 173.5 | AZ52: 208 | BA52: 206 | BB52: 207 | BF52: 208 | BG52: 206 | BH52: 207 | BI52: 210 | BJ52: 202.5 | BK52: 206.5 | CP52: 230.25 | CQ52: 226.5 | CR52: 228.75 | CS52: 230 | CT52: 210 | CU52: 220 | CV52: 202.5 | CW52: 190 | CX52: 196.5 | DT52: 169 | DU52: 163 | DV52: 166 | FJ52: 161 | FK52: 157 | FL52: 159.5 | FP52: 126.5 | FQ52: 124.5 | FR52: 125.5 | FS52: 150 | FT52: 145 | FU52: 148 | GB52: 327.5 | GC52: 310.25 | GD52: 319 | GE52: 398.75 | GF52: 398 | GG52: 398.75 | GH52: 360 | GI52: 350 | GJ52: 355 | GW52: 287 | GX52: 275 | GY52: 281
A53: 1991 | B53: 2 | C53: 4 | D53: 180 | E53: 177 | F53: 178.75 | G53: 153.5 | H53: 149.25 | I53: 151.5 | J53: 166.75 | K53: 165.5 | L53: 166.5 | P53: 180 | Q53: 175 | R53: 178 | S53: 179 | T53: 174.5 | U53: 177.25 | AZ53: 208 | BA53: 206 | BB53: 207 | BF53: 208 | BG53: 206 | BH53: 207 | BI53: 210 | BJ53: 201.25 | BK53: 205.75 | CP53: 226.25 | CQ53: 223 | CR53: 225 | CS53: 225 | CT53: 210 | CU53: 218 | CV53: 195 | CW53: 187.5 | CX53: 191.5 | DT53: 169 | DU53: 163 | DV53: 166 | FJ53: 161 | FK53: 157.5 | FL53: 159.5 | FP53: 126 | FQ53: 123.25 | FR53: 125 | FS53: 144.75 | FT53: 140.75 | FU53: 143.25 | GB53: 325 | GC53: 309 | GD53: 317 | GE53: 400 | GF53: 399 | GG53: 400 | GH53: 361.25 | GI53: 351.25 | GJ53: 356.25 | GW53: 287 | GX53: 275 | GY53: 281
A54: 1991 | B54: 2 | C54: 5 | D54: 177.6 | E54: 175 | F54: 176.6 | G54: 153.2 | H54: 151 | I54: 152.2 | J54: 166.4 | K54: 164.6 | L54: 165.4 | P54: 179.2 | Q54: 175 | R54: 177.6 | S54: 179.2 | T54: 175 | U54: 177.6 | AZ54: 208 | BA54: 205.25 | BB54: 207 | BF54: 208 | BG54: 205.25 | BH54: 207 | BI54: 210 | BJ54: 200 | BK54: 205 | CP54: 218.75 | CQ54: 216.25 | CR54: 218 | CS54: 225 | CT54: 210 | CU54: 218 | CV54: 193 | CW54: 185 | CX54: 189.2 | DT54: 169 | DU54: 163 | DV54: 166 | FJ54: 149.5 | FK54: 146.75 | FL54: 148.25 | FP54: 125 | FQ54: 121.6 | FR54: 123.8 | FS54: 132.5 | FT54: 129.25 | FU54: 131.25 | GB54: 325 | GC54: 309 | GD54: 317 | GE54: 400 | GF54: 399 | GG54: 400 | GH54: 360 | GI54: 350 | GJ54: 355 | GW54: 287 | GX54: 276.25 | GY54: 281.75
A55: 1991 | B55: 2 | C55: 6 | D55: 178.5 | E55: 176.5 | F55: 177.5 | G55: 152 | H55: 148.5 | I55: 150.25 | J55: 159 | K55: 157.5 | L55: 158.75 | P55: 176.5 | Q55: 172.5 | R55: 175 | S55: 176.5 | T55: 172.5 | U55: 175 | AZ55: 200.75 | BA55: 195.25 | BB55: 198.5 | BF55: 200.75 | BG55: 195.25 | BH55: 198.5 | BI55: 202.5 | BJ55: 199 | BK55: 201 | CP55: 214.5 | CQ55: 211.5 | CR55: 213.25 | CS55: 225 | CT55: 210 | CU55: 218 | CV55: 195 | CW55: 185 | CX55: 190 | DT55: 169 | DU55: 163 | DV55: 166 | FJ55: 143.5 | FK55: 140 | FL55: 142.25 | FP55: 122 | FQ55: 119.25 | FR55: 121 | FS55: 130 | FT55: 129 | FU55: 130 | GB55: 325 | GC55: 309 | GD55: 317 | GE55: 400 | GF55: 399 | GG55: 400 | GH55: 360 | GI55: 350 | GJ55: 355 | GW55: 285.5 | GX55: 276.25 | GY55: 281
A56: 1991 | B56: 3 | C56: 7 | D56: 185 | E56: 182.75 | F56: 184 | G56: 153.25 | H56: 151.25 | I56: 152.25 | J56: 164 | K56: 162.75 | L56: 163.75 | P56: 178.25 | Q56: 175 | R56: 177 | S56: 178.25 | T56: 175 | U56: 177 | AZ56: 201.25 | BA56: 194 | BB56: 198 | BF56: 201.25 | BG56: 194 | BH56: 198 | BI56: 202.5 | BJ56: 199 | BK56: 201 | CP56: 215 | CQ56: 212 | CR56: 214 | CS56: 225 | CT56: 210 | CU56: 218 | CV56: 202.5 | CW56: 185 | CX56: 193.75 | DT56: 169 | DU56: 163 | DV56: 166 | FJ56: 143 | FK56: 138 | FL56: 141 | FP56: 122.5 | FQ56: 119.5 | FR56: 121.5 | FS56: 132 | FT56: 130 | FU56: 131 | GB56: 322.5 | GC56: 309 | GD56: 316 | GE56: 410 | GF56: 409 | GG56: 410 | GH56: 360 | GI56: 350 | GJ56: 355 | GW56: 285 | GX56: 280 | GY56: 283
A57: 1991 | B57: 3 | C57: 8 | D57: 175 | E57: 171 | F57: 173.2 | G57: 152.8 | H57: 150 | I57: 151.6 | J57: 162.5 | K57: 160.5 | L57: 161.75 | P57: 181.6 | Q57: 178.8 | R57: 180.4 | S57: 179.2 | T57: 175 | U57: 177.6 | AZ57: 203 | BA57: 198 | BB57: 201 | BF57: 203 | BG57: 198 | BH57: 201 | BI57: 205 | BJ57: 200 | BK57: 203 | CS57: 225 | CT57: 210 | CU57: 218 | CV57: 205 | CW57: 185 | CX57: 195 | DT57: 169 | DU57: 163 | DV57: 166 | FJ57: 143 | FK57: 138 | FL57: 141 | FP57: 121.8 | FQ57: 118.8 | FR57: 120.8 | FS57: 128.8 | FT57: 125.2 | FU57: 127 | GB57: 320 | GC57: 309 | GD57: 315 | GE57: 420 | GF57: 419 | GG57: 420 | GH57: 360 | GI57: 350 | GJ57: 355 | GW57: 285 | GX57: 280 | GY57: 283
A58: 1991 | B58: 3 | C58: 9 | D58: 171 | E58: 167.75 | F58: 169.5 | G58: 149.75 | H58: 144 | I58: 147 | J58: 160.5 | K58: 158.5 | L58: 159.75 | P58: 181 | Q58: 175.25 | R58: 178.25 | S58: 178 | T58: 172 | U58: 175 | AZ58: 199.75 | BA58: 191.5 | BB58: 196 | BF58: 199.75 | BG58: 191.5 | BH58: 196 | BI58: 205 | BJ58: 200 | BK58: 203 | CS58: 222.5 | CT58: 210 | CU58: 216.5 | CV58: 205 | CW58: 185 | CX58: 195 | DT58: 166.5 | DU58: 161.25 | DV58: 164 | FJ58: 143 | FK58: 138 | FL58: 141 | FP58: 118.25 | FQ58: 116.25 | FR58: 117.25 | FS58: 124.25 | FT58: 120.75 | FU58: 123 | GB58: 313.75 | GC58: 303.5 | GD58: 308.75 | GE58: 420 | GF58: 419 | GG58: 420 | GH58: 360 | GI58: 350 | GJ58: 355 | GW58: 282.5 | GX58: 275 | GY58: 279
A59: 1991 | B59: 4 | C59: 10 | D59: 167 | E59: 164.25 | F59: 165.75 | G59: 145.4 | H59: 142.4 | I59: 144 | J59: 156 | K59: 154.4 | L59: 155.4 | P59: 175.8 | Q59: 171.2 | R59: 173.6 | S59: 175.8 | T59: 170.4 | U59: 173.4 | AZ59: 193.4 | BA59: 185 | BB59: 189.2 | BF59: 193.4 | BG59: 185 | BH59: 189.2 | BI59: 205 | BJ59: 200 | BK59: 203 | CP59: 203 | CQ59: 199 | CR59: 201 | CS59: 217 | CT59: 207 | CU59: 212 | CV59: 185 | CW59: 175 | CX59: 180 | DT59: 157.4 | DU59: 153.6 | DV59: 156 | FJ59: 143 | FK59: 138 | FL59: 141 | FP59: 115.4 | FQ59: 112.6 | FR59: 114.2 | FS59: 122.8 | FT59: 119.4 | FU59: 121.2 | GB59: 310 | GC59: 303 | GD59: 306.8 | GE59: 413.6 | GF59: 411.8 | GG59: 413 | GH59: 358 | GI59: 348 | GJ59: 353 | GW59: 283 | GX59: 276 | GY59: 280
A60: 1991 | B60: 4 | C60: 11 | D60: 154 | E60: 151.5 | F60: 153 | G60: 134 | H60: 132 | I60: 133 | J60: 142.75 | K60: 141 | L60: 142 | P60: 172.25 | Q60: 170 | R60: 171.25 | S60: 172.25 | T60: 168 | U60: 170.25 | AZ60: 180.25 | BA60: 175.25 | BB60: 177.75 | BF60: 180.25 | BG60: 175.25 | BH60: 177.75 | CP60: 195 | CQ60: 190 | CR60: 193 | CS60: 215 | CT60: 205 | CU60: 210 | CV60: 185 | CW60: 175 | CX60: 180 | DT60: 155 | DU60: 150 | DV60: 153 | FJ60: 143 | FK60: 138 | FL60: 141 | FP60: 114 | FQ60: 112 | FR60: 113 | FS60: 122 | FT60: 118 | FU60: 120 | GB60: 310 | GC60: 305 | GD60: 308 | GE60: 405 | GF60: 405 | GG60: 405 | GH60: 360 | GI60: 375 | GJ60: 367.5 | GW60: 280 | GX60: 275 | GY60: 278
A61: 1991 | B61: 4 | C61: 12 | D61: 156.5 | E61: 155.5 | F61: 156.25 | G61: 133 | H61: 131.25 | I61: 132.25 | J61: 143 | K61: 141.75 | L61: 142.75 | P61: 164.25 | Q61: 161.75 | R61: 163.25 | S61: 161.25 | T61: 156.25 | U61: 159.25 | AZ61: 178 | BA61: 175 | BB61: 177 | BF61: 178 | BG61: 175 | BH61: 177 | CP61: 190 | CQ61: 187 | CR61: 189 | CS61: 215 | CT61: 205 | CU61: 210 | CV61: 185 | CW61: 175 | CX61: 180 | DT61: 155 | DU61: 150 | DV61: 153 | FJ61: 143 | FK61: 138 | FL61: 141 | FP61: 108 | FQ61: 105.5 | FR61: 107 | FS61: 122 | FT61: 118 | FU61: 120 | GB61: 310 | GC61: 305 | GD61: 308 | GE61: 405 | GF61: 405 | GG61: 405 | GH61: 360 | GI61: 350 | GJ61: 355 | GW61: 280 | GX61: 275 | GY61: 278
A62: 1992 | B62: 1 | C62: 1 | D62: 162.5 | E62: 160.5 | F62: 161.75 | G62: 135.25 | H62: 133 | I62: 134.5 | J62: 144.66667 | K62: 144.33333 | L62: 144.66667 | P62: 160.5 | Q62: 158 | R62: 159.25 | S62: 160 | T62: 155 | U62: 158 | AZ62: 184.2 | BA62: 179 | BB62: 181.8 | BF62: 184.2 | BG62: 179 | BH62: 181.8 | BI62: 200 | BJ62: 195 | BK62: 198 | CP62: 199 | CQ62: 194.8 | CR62: 197.4 | CS62: 215 | CT62: 205 | CU62: 210 | CV62: 185 | CW62: 175 | CX62: 180 | DT62: 148.5 | DU62: 144.75 | DV62: 147 | FJ62: 143 | FK62: 138 | FL62: 141 | FP62: 108 | FQ62: 106 | FR62: 107 | FS62: 122 | FT62: 118 | FU62: 120 | GB62: 305 | GC62: 296 | GD62: 300.6 | GE62: 405 | GF62: 405 | GG62: 405 | GH62: 358 | GI62: 348 | GJ62: 353 | GW62: 279 | GX62: 274 | GY62: 277
A63: 1992 | B63: 1 | C63: 2 | D63: 164 | E63: 161.75 | F63: 163 | G63: 140 | H63: 138 | I63: 139 | J63: 148.5 | K63: 146.5 | L63: 147.5 | P63: 162 | Q63: 158 | R63: 160 | S63: 160 | T63: 155 | U63: 158 | AZ63: 186 | BA63: 175 | BB63: 180.5 | BF63: 186 | BG63: 175 | BH63: 180.5 | BI63: 197.5 | BJ63: 192.5 | BK63: 195.5 | CP63: 203.5 | CQ63: 200 | CR63: 202 | CS63: 215 | CT63: 205 | CU63: 210 | CV63: 186.25 | CW63: 176.25 | CX63: 181.25 | DT63: 146 | DU63: 144 | DV63: 145 | FJ63: 143 | FK63: 138 | FL63: 141 | FP63: 108 | FQ63: 106 | FR63: 107 | FS63: 122 | FT63: 118 | FU63: 120 | GB63: 300 | GC63: 290 | GD63: 295 | GE63: 405 | GF63: 405 | GG63: 405 | GH63: 350 | GI63: 340 | GJ63: 345 | GW63: 275 | GX63: 268.75 | GY63: 272.25
A64: 1992 | B64: 1 | C64: 3 | D64: 156.25 | E64: 153.75 | F64: 155.25 | G64: 135.25 | H64: 133.5 | I64: 134.75 | J64: 144.75 | K64: 143.25 | L64: 144.5 | P64: 165.75 | Q64: 161 | R64: 163.75 | S64: 166 | T64: 161 | U64: 163.75 | AZ64: 184.25 | BA64: 160 | BB64: 172.25 | BF64: 184.25 | BG64: 160 | BH64: 172.25 | BI64: 193.75 | BJ64: 188.75 | BK64: 191.75 | CP64: 200.5 | CQ64: 198.5 | CR64: 199.5 | CS64: 215 | CT64: 205 | CU64: 210 | CV64: 188.75 | CW64: 178.75 | CX64: 183.75 | DT64: 142.75 | DU64: 140.75 | DV64: 142 | FJ64: 140 | FK64: 129 | FL64: 135 | FP64: 108 | FQ64: 106 | FR64: 107 | FS64: 122 | FT64: 118 | FU64: 120 | GB64: 300 | GC64: 289 | GD64: 294.5 | GE64: 395 | GF64: 392 | GG64: 393.75 | GH64: 350 | GI64: 340 | GJ64: 345 | GW64: 275 | GX64: 265 | GY64: 270
A65: 1992 | B65: 2 | C65: 4 | D65: 152.2 | E65: 149.6 | F65: 151.2 | G65: 131.4 | H65: 129.6 | I65: 130.8 | J65: 144.2 | K65: 141.8 | L65: 143.2 | P65: 165.8 | Q65: 158 | R65: 162.4 | S65: 166.2 | T65: 160 | U65: 163.4 | AZ65: 180 | BA65: 165 | BB65: 173 | BF65: 180 | BG65: 165 | BH65: 173 | BI65: 180 | BJ65: 170 | BK65: 175 | CP65: 198 | CQ65: 196 | CR65: 197 | CS65: 215 | CT65: 205 | CU65: 210 | CV65: 181 | CW65: 171 | CX65: 176 | DT65: 137.6 | DU65: 136.6 | DV65: 137.6 | FJ65: 140 | FK65: 131.4 | FL65: 136.2 | FP65: 109.2 | FQ65: 107.6 | FR65: 108.4 | FS65: 122.4 | FT65: 118 | FU65: 120.4 | GB65: 300 | GC65: 290 | GD65: 295 | GE65: 366 | GF65: 365 | GG65: 366 | GH65: 349 | GI65: 339 | GJ65: 344 | GW65: 275 | GX65: 262 | GY65: 269
A66: 1992 | B66: 2 | C66: 5 | D66: 152 | E66: 149.5 | F66: 151 | G66: 128.25 | H66: 125.75 | I66: 127.25 | J66: 141.25 | K66: 138.75 | L66: 140.25 | P66: 165 | Q66: 158 | R66: 162 | S66: 165 | T66: 160 | U66: 163 | AZ66: 178.33333 | BA66: 165 | BB66: 172 | BF66: 178.33333 | BG66: 165 | BH66: 172 | BI66: 180 | BJ66: 170 | BK66: 175 | CP66: 198 | CQ66: 196 | CR66: 197 | CS66: 215 | CT66: 205 | CU66: 210 | CV66: 172.5 | CW66: 165 | CX66: 169 | DT66: 136 | DU66: 132.5 | DV66: 134.25 | FJ66: 140 | FK66: 135 | FL66: 138 | FP66: 110 | FQ66: 106 | FR66: 108.5 | FS66: 123 | FT66: 118 | FU66: 121 | GB66: 300 | GC66: 290 | GD66: 295 | GE66: 366 | GF66: 365 | GG66: 366 | GH66: 345 | GI66: 335 | GJ66: 340 | GW66: 275 | GX66: 262 | GY66: 269
A67: 1992 | B67: 2 | C67: 6 | D67: 146.75 | E67: 143.75 | F67: 145.5 | G67: 126 | H67: 124 | I67: 125 | J67: 137.5 | K67: 133.75 | L67: 136 | P67: 165 | Q67: 158 | R67: 162 | S67: 165 | T67: 160 | U67: 163 | AZ67: 175 | BA67: 165 | BB67: 170 | BF67: 175 | BG67: 165 | BH67: 170 | BI67: 180 | BJ67: 170 | BK67: 175 | CP67: 198 | CQ67: 196 | CR67: 197 | CS67: 220 | CT67: 205 | CU67: 213 | CV67: 175 | CW67: 170 | CX67: 173 | DT67: 136 | DU67: 131 | DV67: 134 | FJ67: 140 | FK67: 135 | FL67: 138 | FP67: 110 | FQ67: 105 | FR67: 108 | FS67: 123 | FT67: 118 | FU67: 121 | GB67: 297.5 | GC67: 287.5 | GD67: 292.5 | GE67: 363 | GF67: 360 | GG67: 362 | GH67: 330 | GI67: 325 | GJ67: 328 | GW67: 275 | GX67: 262 | GY67: 269
A68: 1992 | B68: 3 | C68: 7 | D68: 139.6 | E68: 136.8 | F68: 138.4 | G68: 122 | H68: 119.6 | I68: 120.8 | J68: 131.75 | K68: 130.25 | L68: 131.25 | P68: 159 | Q68: 153.2 | R68: 156.6 | S68: 159.4 | T68: 154 | U68: 157.2 | AZ68: 169 | BA68: 161 | BB68: 165.2 | BF68: 169 | BG68: 161 | BH68: 165.2 | BI68: 176 | BJ68: 167 | BK68: 171.6 | CP68: 194.8 | CQ68: 191.6 | CR68: 193.4 | CS68: 205 | CT68: 195 | CU68: 200 | CV68: 180 | CW68: 175 | CX68: 178 | DT68: 131.2 | DU68: 127.6 | DV68: 129.8 | FJ68: 140 | FK68: 135 | FL68: 138 | FP68: 108.6 | FQ68: 103.8 | FR68: 106.6 | FS68: 123 | FT68: 118 | FU68: 121 | GB68: 295 | GC68: 285 | GD68: 290 | GE68: 360 | GF68: 355 | GG68: 358 | GH68: 320 | GI68: 315 | GJ68: 318 | GW68: 275 | GX68: 262 | GY68: 269
A69: 1992 | B69: 3 | C69: 8 | D69: 139.25 | E69: 138.25 | F69: 139 | G69: 122 | H69: 119.5 | I69: 120.75 | J69: 132 | K69: 130.25 | L69: 131 | P69: 152.25 | Q69: 142.5 | R69: 147.5 | S69: 151.25 | T69: 145 | U69: 148.5 | AZ69: 165 | BA69: 155 | BB69: 160 | BF69: 165 | BG69: 155 | BH69: 160 | BI69: 165 | BJ69: 155 | BK69: 160 | CP69: 180 | CQ69: 175 | CR69: 178 | CS69: 202.5 | CT69: 192.5 | CU69: 197.5 | CV69: 180 | CW69: 175 | CX69: 178 | DT69: 127.5 | DU69: 125.75 | DV69: 126.75 | FJ69: 140 | FK69: 135 | FL69: 138 | FP69: 107 | FQ69: 102.25 | FR69: 105 | FS69: 123 | FT69: 118.5 | FU69: 121.25 | GB69: 295 | GC69: 285 | GD69: 290 | GE69: 360 | GF69: 355 | GG69: 358 | GH69: 320 | GI69: 315 | GJ69: 318 | GW69: 275 | GX69: 261 | GY69: 268.5
A70: 1992 | B70: 3 | C70: 9 | D70: 137 | E70: 134.5 | F70: 136 | G70: 120.5 | H70: 119 | I70: 120 | J70: 131.5 | K70: 130.75 | L70: 131.5 | P70: 152.75 | Q70: 143.75 | R70: 148.5 | S70: 150 | T70: 145 | U70: 148 | AZ70: 165 | BA70: 155 | BB70: 160 | BF70: 165 | BG70: 155 | BH70: 160 | BI70: 165 | BJ70: 155 | BK70: 160 | CP70: 180 | CQ70: 175 | CR70: 178 | CS70: 195 | CT70: 185 | CU70: 190 | CV70: 180 | CW70: 175 | CX70: 178 | DT70: 128 | DU70: 126 | DV70: 127 | FJ70: 140 | FK70: 135 | FL70: 138 | FP70: 107 | FQ70: 104 | FR70: 106 | FS70: 123 | FT70: 120 | FU70: 122 | GB70: 297.5 | GC70: 287.5 | GD70: 292.5 | GE70: 360 | GF70: 355 | GG70: 358 | GH70: 325 | GI70: 315 | GJ70: 320.5 | GW70: 272.5 | GX70: 258.5 | GY70: 266
A71: 1992 | B71: 4 | C71: 10 | D71: 138.2 | E71: 134.6 | F71: 136.8 | G71: 120.4 | H71: 116.6 | I71: 118.8 | J71: 130.4 | K71: 128.8 | L71: 130 | P71: 155 | Q71: 144.6 | R71: 149.8 | S71: 150 | T71: 142.6 | U71: 146.6 | AZ71: 163 | BA71: 155 | BB71: 159.2 | BF71: 163 | BG71: 155 | BH71: 159.2 | BI71: 165 | BJ71: 155 | BK71: 160 | CP71: 180 | CQ71: 175 | CR71: 178 | CS71: 195 | CT71: 185 | CU71: 190 | CV71: 180 | CW71: 175 | CX71: 178 | DT71: 127.2 | DU71: 126 | DV71: 126.6 | FJ71: 140 | FK71: 135 | FL71: 138 | FP71: 107 | FQ71: 103.2 | FR71: 105.6 | FS71: 123 | FT71: 120 | FU71: 122 | GB71: 300 | GC71: 290 | GD71: 295 | GE71: 360 | GF71: 355 | GG71: 358 | GH71: 330 | GI71: 315 | GJ71: 323 | GW71: 270 | GX71: 255 | GY71: 263
A72: 1992 | B72: 4 | C72: 11 | D72: 137 | E72: 133 | F72: 135.25 | G72: 116.5 | H72: 112.75 | I72: 114.75 | J72: 128 | K72: 126 | L72: 127 | P72: 155 | Q72: 143 | R72: 149 | S72: 150 | T72: 142 | U72: 146 | AZ72: 162 | BA72: 158 | BB72: 160 | BF72: 162 | BG72: 158 | BH72: 160 | BI72: 165 | BJ72: 155 | BK72: 160 | CP72: 180 | CQ72: 175 | CR72: 178 | CS72: 195 | CT72: 185 | CU72: 190 | CV72: 180 | CW72: 175 | CX72: 178 | DT72: 124 | DU72: 124 | DV72: 124 | FJ72: 140 | FK72: 135 | FL72: 138 | FP72: 106 | FQ72: 102 | FR72: 104.25 | FS72: 123 | FT72: 120 | FU72: 122 | GB72: 300 | GC72: 290 | GD72: 295 | GE72: 342 | GF72: 340.75 | GG72: 341.5 | GH72: 330 | GI72: 315 | GJ72: 323 | GW72: 270 | GX72: 255 | GY72: 263
A73: 1992 | B73: 4 | C73: 12 | D73: 136.4 | E73: 133.8 | F73: 135.2 | G73: 113.2 | H73: 111 | I73: 112.4 | J73: 126 | K73: 124 | L73: 125 | P73: 155 | Q73: 143 | R73: 149 | S73: 150 | T73: 142 | U73: 146 | AZ73: 162 | BA73: 160 | BB73: 161 | BF73: 162 | BG73: 160 | BH73: 161 | BI73: 165 | BJ73: 155 | BK73: 160 | CP73: 180 | CQ73: 175 | CR73: 178 | CS73: 195 | CT73: 185 | CU73: 190 | CV73: 180 | CW73: 175 | CX73: 178 | DT73: 119.4 | DU73: 119.4 | DV73: 119.4 | FJ73: 140 | FK73: 135 | FL73: 138 | FP73: 105 | FQ73: 101.6 | FR73: 103.8 | FS73: 123.5 | FT73: 120.25 | FU73: 122.25 | GB73: 300 | GC73: 280 | GD73: 290 | GE73: 332.4 | GF73: 329.4 | GG73: 331.2 | GH73: 330 | GI73: 315 | GJ73: 323 | GW73: 270 | GX73: 255 | GY73: 263
A74: 1993 | B74: 1 | C74: 1 | D74: 133.66667 | E74: 131 | F74: 132.66667 | G74: 111.33333 | H74: 108.66667 | I74: 110.33333 | J74: 124 | K74: 122 | L74: 123 | P74: 155 | Q74: 138 | R74: 147 | S74: 150 | T74: 142 | U74: 146 | AZ74: 162 | BA74: 160 | BB74: 161 | BF74: 162 | BG74: 160 | BH74: 161 | BI74: 163.75 | BJ74: 155 | BK74: 159.5 | CP74: 176.25 | CQ74: 171.25 | CR74: 174.25 | CS74: 192.5 | CT74: 182.5 | CU74: 187.5 | CV74: 180 | CW74: 175 | CX74: 178 | DT74: 119 | DU74: 118 | DV74: 118.5 | FJ74: 140 | FK74: 135 | FL74: 138 | FP74: 105 | FQ74: 100 | FR74: 103 | FS74: 123.5 | FT74: 120.25 | FU74: 122.25 | GB74: 300 | GC74: 270 | GD74: 285 | GE74: 330 | GF74: 325 | GG74: 328 | GH74: 330 | GI74: 315 | GJ74: 323 | GQ74: 270 | GR74: 255 | GS74: 263 | GW74: 270 | GX74: 255 | GY74: 263
A75: 1993 | B75: 1 | C75: 2 | D75: 127.75 | E75: 125.5 | F75: 126.75 | G75: 111.25 | H75: 109 | I75: 110.25 | J75: 121 | K75: 119 | L75: 120.25 | P75: 151.25 | Q75: 135.75 | R75: 144 | S75: 150 | T75: 142 | U75: 146 | AZ75: 156.75 | BA75: 148.75 | BB75: 152.75 | BF75: 156.75 | BG75: 148.75 | BH75: 152.75 | BI75: 160 | BJ75: 155 | BK75: 158 | CP75: 174.25 | CQ75: 170 | CR75: 172.5 | CS75: 190 | CT75: 180 | CU75: 185 | CV75: 180 | CW75: 175 | CX75: 178 | DT75: 117 | DU75: 115 | DV75: 116 | FJ75: 140 | FK75: 135 | FL75: 138 | FP75: 101 | FQ75: 96.5 | FR75: 99 | FS75: 123 | FT75: 120 | FU75: 122 | GB75: 293.75 | GC75: 261.25 | GD75: 277.5 | GE75: 330 | GF75: 325 | GG75: 328 | GH75: 330 | GI75: 315 | GJ75: 323 | GQ75: 255 | GR75: 243.75 | GS75: 249.5 | GW75: 247.5 | GX75: 237.5 | GY75: 242.5
A76: 1993 | B76: 1 | C76: 3 | D76: 117.25 | E76: 114 | F76: 115.75 | G76: 103.25 | H76: 100.25 | I76: 102 | J76: 114.25 | K76: 113.25 | L76: 114 | P76: 142 | Q76: 133.75 | R76: 138.25 | S76: 142 | T76: 133.75 | U76: 138.25 | AZ76: 150 | BA76: 130 | BB76: 140 | BF76: 150 | BG76: 130 | BH76: 140 | BI76: 155 | BJ76: 140 | BK76: 148 | CP76: 170.5 | CQ76: 168.5 | CR76: 169.5 | CS76: 190 | CT76: 180 | CU76: 185 | CV76: 180 | CW76: 170 | CX76: 175 | DT76: 110.75 | DU76: 107.75 | DV76: 109.75 | FJ76: 140 | FK76: 135 | FL76: 138 | FP76: 98 | FQ76: 94.5 | FR76: 96.75 | FS76: 112 | FT76: 110 | FU76: 111 | GB76: 290 | GC76: 250 | GD76: 270 | GE76: 330 | GF76: 325 | GG76: 328 | GH76: 325 | GI76: 315 | GJ76: 320 | GQ76: 240 | GR76: 230 | GS76: 235 | GW76: 240 | GX76: 230 | GY76: 235
A77: 1993 | B77: 2 | C77: 4 | D77: 156.4 | E77: 149 | F77: 152.8 | G77: 101.8 | H77: 97.6 | I77: 100.2 | J77: 155.4 | K77: 148.4 | L77: 152 | P77: 140.4 | Q77: 127.6 | R77: 134.4 | S77: 140.4 | T77: 130 | U77: 135.2 | AZ77: 143 | BA77: 130 | BB77: 136.8 | BF77: 143 | BG77: 130 | BH77: 136.8 | BI77: 140 | BJ77: 137 | BK77: 139 | CP77: 164.4 | CQ77: 161.4 | CR77: 163 | CS77: 187 | CT77: 177 | CU77: 182 | CV77: 178 | CW77: 168 | CX77: 173 | DT77: 108 | DU77: 105 | DV77: 107 | FJ77: 125 | FK77: 120 | FL77: 123 | FP77: 96 | FQ77: 93 | FR77: 95 | FS77: 111.2 | FT77: 108 | FU77: 109.8 | GB77: 290 | GC77: 250 | GD77: 270 | GE77: 330 | GF77: 325 | GG77: 328 | GH77: 325 | GI77: 315 | GJ77: 320 | GQ77: 240 | GR77: 230 | GS77: 235 | GW77: 240 | GX77: 230 | GY77: 235
A78: 1993 | B78: 2 | C78: 5 | D78: 185 | E78: 175 | F78: 180 | G78: 106 | H78: 102 | I78: 104.5 | J78: 185 | K78: 175 | L78: 180 | P78: 141.25 | Q78: 129.25 | R78: 135.5 | S78: 138.75 | T78: 130 | U78: 134.5 | AZ78: 140 | BA78: 130 | BB78: 135 | BF78: 140 | BG78: 130 | BH78: 135 | BI78: 142.33333 | BJ78: 138 | BK78: 140.66667 | CP78: 160.66667 | CQ78: 152.66667 | CR78: 156.66667 | CS78: 185 | CT78: 175 | CU78: 180 | CV78: 170 | CW78: 160 | CX78: 165 | DT78: 109.5 | DU78: 106.5 | DV78: 108.5 | FJ78: 125 | FK78: 119.33333 | FL78: 122.66667 | FP78: 92 | FQ78: 88 | FR78: 90 | FS78: 110 | FT78: 105 | FU78: 108 | GB78: 290 | GC78: 250 | GD78: 270 | GE78: 330 | GF78: 325 | GG78: 328 | GH78: 325 | GI78: 315 | GJ78: 320 | GQ78: 240 | GR78: 230 | GS78: 235 | GW78: 240 | GX78: 230 | GY78: 235
A79: 1993 | B79: 2 | C79: 6 | D79: 185 | E79: 175 | F79: 180 | G79: 105.5 | H79: 102.75 | I79: 104.5 | J79: 185 | K79: 175 | L79: 180 | P79: 140.5 | Q79: 130 | R79: 135.25 | S79: 140 | T79: 130 | U79: 135 | AZ79: 140 | BA79: 130 | BB79: 135 | BF79: 140 | BG79: 130 | BH79: 135 | BI79: 145 | BJ79: 140 | BK79: 143 | CP79: 160 | CQ79: 150 | CR79: 155 | CS79: 185 | CT79: 175 | CU79: 180 | CV79: 170 | CW79: 160 | CX79: 165 | DT79: 110 | DU79: 107 | DV79: 109 | FJ79: 114.5 | FK79: 109.25 | FL79: 112.25 | FP79: 92 | FQ79: 88 | FR79: 90 | FS79: 108.5 | FT79: 102.5 | FU79: 106 | GB79: 290 | GC79: 250 | GD79: 270 | GE79: 295 | GF79: 290 | GG79: 293 | GH79: 325 | GI79: 315 | GJ79: 320 | GQ79: 237.5 | GR79: 227.5 | GS79: 232.5 | GW79: 232.5 | GX79: 222.5 | GY79: 227.5
A80: 1993 | B80: 3 | C80: 7 | D80: 185 | E80: 175 | F80: 180 | G80: 104.6 | H80: 101.4 | I80: 103.4 | J80: 185 | K80: 175 | L80: 180 | P80: 137.6 | Q80: 127.6 | R80: 132.6 | S80: 137.6 | T80: 127.6 | U80: 132.6 | AZ80: 140 | BA80: 130 | BB80: 135 | BF80: 140 | BG80: 130 | BH80: 135 | BI80: 145 | BJ80: 140 | BK80: 143 | CP80: 158 | CQ80: 150 | CR80: 154.2 | CS80: 185 | CT80: 175 | CU80: 180 | CV80: 170 | CW80: 160 | CX80: 165 | DT80: 110.8 | DU80: 107.4 | DV80: 109.4 | FJ80: 110 | FK80: 105 | FL80: 108 | FP80: 93.2 | FQ80: 88.8 | FR80: 91.2 | FS80: 108.2 | FT80: 102 | FU80: 105.6 | GB80: 282 | GC80: 244 | GD80: 263.2 | GE80: 295 | GF80: 295 | GG80: 295 | GH80: 321 | GI80: 309 | GJ80: 315.2 | GQ80: 230 | GR80: 220 | GS80: 225 | GW80: 230 | GX80: 220 | GY80: 225
A81: 1993 | B81: 3 | C81: 8 | D81: 185 | E81: 175 | F81: 180 | G81: 104.75 | H81: 101.25 | I81: 103.25 | J81: 185 | K81: 175 | L81: 180 | P81: 136.5 | Q81: 125.75 | R81: 131.25 | S81: 136.5 | T81: 125.75 | U81: 131.25 | AZ81: 140 | BA81: 120 | BB81: 130 | BF81: 140 | BG81: 120 | BH81: 130 | BI81: 145 | BJ81: 140 | BK81: 143 | CP81: 155 | CQ81: 150 | CR81: 153 | CS81: 185 | CT81: 175 | CU81: 180 | CV81: 170 | CW81: 160 | CX81: 165 | DT81: 114 | DU81: 108 | DV81: 111 | FJ81: 110 | FK81: 102.75 | FL81: 106.5 | FP81: 95 | FQ81: 88.5 | FR81: 92.25 | FS81: 110 | FT81: 105 | FU81: 108 | GB81: 270 | GC81: 235 | GD81: 253 | GE81: 295 | GF81: 295 | GG81: 295 | GH81: 315 | GI81: 300 | GJ81: 308 | GN81: 290 | GO81: 280 | GP81: 285 | GQ81: 230 | GR81: 212.5 | GS81: 221.25 | GW81: 230 | GX81: 210 | GY81: 220
A82: 1993 | B82: 3 | C82: 9 | D82: 175 | E82: 165 | F82: 170 | G82: 105.8 | H82: 104 | I82: 105 | J82: 175 | K82: 165 | L82: 170 | P82: 136.6 | Q82: 123.2 | R82: 130.4 | S82: 136.2 | T82: 123.2 | U82: 130.2 | AZ82: 147 | BA82: 140 | BB82: 143.8 | BF82: 147 | BG82: 140 | BH82: 143.8 | BI82: 145 | BJ82: 140 | BK82: 143 | CP82: 165 | CQ82: 160 | CR82: 163 | CS82: 175 | CT82: 165 | CU82: 170 | CV82: 170 | CW82: 160 | CX82: 165 | DT82: 112.8 | DU82: 108.4 | DV82: 110.6 | FJ82: 110.8 | FK82: 107.6 | FL82: 109.2 | FP82: 95 | FQ82: 88.6 | FR82: 92 | FS82: 110 | FT82: 114 | FU82: 112.4 | GB82: 270 | GC82: 235 | GD82: 253 | GE82: 295 | GF82: 295 | GG82: 295 | GH82: 315 | GI82: 300 | GJ82: 308 | GN82: 281 | GO82: 271 | GP82: 276 | GQ82: 230 | GR82: 210 | GS82: 220 | GW82: 230 | GX82: 210 | GY82: 220
A83: 1993 | B83: 4 | C83: 10 | D83: 175 | E83: 165 | F83: 170 | G83: 117.25 | H83: 113.75 | I83: 116 | J83: 175 | K83: 165 | L83: 170 | P83: 147 | Q83: 135 | R83: 141.25 | S83: 145.25 | T83: 133.5 | U83: 139.75 | AZ83: 156.25 | BA83: 151.25 | BB83: 154.25 | BF83: 156.25 | BG83: 151.25 | BH83: 154.25 | CP83: 177 | CQ83: 172 | CR83: 175 | CS83: 175 | CT83: 165 | CU83: 170 | CV83: 170 | CW83: 162.5 | CX83: 166.5 | DT83: 121.5 | DU83: 118.25 | DV83: 120 | FJ83: 112.75 | FK83: 110.5 | FL83: 111.75 | FP83: 97.75 | FQ83: 92 | FR83: 95 | FS83: 113.75 | FT83: 108.75 | FU83: 111.75 | GB83: 270 | GC83: 235 | GD83: 253 | GE83: 295 | GF83: 295 | GG83: 295 | GH83: 315 | GI83: 300 | GJ83: 308 | GN83: 282.5 | GO83: 265 | GP83: 273.75 | GQ83: 230 | GR83: 210 | GS83: 220 | GW83: 230 | GX83: 212.5 | GY83: 221.25
A84: 1993 | B84: 4 | C84: 11 | D84: 180 | E84: 168.75 | F84: 174.5 | G84: 129.25 | H84: 128.25 | I84: 129 | J84: 180 | K84: 168.75 | L84: 174.5 | P84: 157.25 | Q84: 146.25 | R84: 152 | S84: 157 | T84: 146.25 | U84: 151.75 | AZ84: 161.25 | BA84: 155 | BB84: 158.5 | BF84: 161.25 | BG84: 155 | BH84: 158.5 | CP84: 176.75 | CQ84: 172.25 | CR84: 175 | CS84: 180 | CT84: 168.75 | CU84: 174.5 | CV84: 170 | CW84: 165 | CX84: 168 | DT84: 133.5 | DU84: 132.25 | DV84: 133.25 | FJ84: 115 | FK84: 112 | FL84: 114 | FP84: 106.5 | FQ84: 103 | FR84: 105 | FS84: 115 | FT84: 110 | FU84: 113 | GB84: 270 | GC84: 235 | GD84: 253 | GE84: 295 | GF84: 295 | GG84: 295 | GH84: 315 | GI84: 300 | GJ84: 308 | GN84: 285 | GO84: 265 | GP84: 275 | GQ84: 230 | GR84: 220 | GS84: 225 | GW84: 230 | GX84: 220 | GY84: 225
A85: 1993 | B85: 4 | C85: 12 | D85: 195 | E85: 184 | F85: 189.6 | G85: 139 | H85: 138.4 | I85: 139 | J85: 195 | K85: 184 | L85: 189.6 | P85: 167 | Q85: 159.8 | R85: 163.8 | S85: 167 | T85: 159.8 | U85: 163.8 | AZ85: 170 | BA85: 160 | BB85: 165 | BF85: 170 | BG85: 160 | BH85: 165 | BI85: 175 | BJ85: 170 | BK85: 173 | CP85: 185.75 | CQ85: 180.75 | CR85: 183.75 | CS85: 195 | CT85: 184 | CU85: 189.6 | CV85: 182 | CW85: 169 | CX85: 176 | DT85: 143 | DU85: 141 | DV85: 142 | FJ85: 122.5 | FK85: 118.5 | FL85: 121 | FP85: 115.2 | FQ85: 112.4 | FR85: 113.8 | FS85: 125 | FT85: 120 | FU85: 123 | GB85: 270 | GC85: 236.25 | GD85: 253.5 | GE85: 305.5 | GF85: 305.5 | GG85: 305.5 | GH85: 315 | GI85: 300 | GJ85: 308 | GN85: 285 | GO85: 265 | GP85: 275 | GQ85: 233 | GR85: 220 | GS85: 226.8 | GW85: 233.75 | GX85: 220 | GY85: 227.25
A86: 1994 | B86: 1 | C86: 1 | D86: 195 | E86: 185 | F86: 190 | G86: 139 | H86: 138 | I86: 139 | J86: 195 | K86: 185 | L86: 190 | P86: 170 | Q86: 163 | R86: 167 | S86: 168 | T86: 160 | U86: 164 | AZ86: 170 | BA86: 162.5 | BB86: 166.5 | BF86: 170 | BG86: 162.5 | BH86: 166.5 | BI86: 176 | BJ86: 172.5 | BK86: 174.5 | CP86: 187.5 | CQ86: 184 | CR86: 186.25 | CS86: 195 | CT86: 185 | CU86: 190 | CV86: 185 | CW86: 170 | CX86: 178 | DT86: 146 | DU86: 142 | DV86: 144 | FJ86: 121.5 | FK86: 116.5 | FL86: 119.5 | FP86: 118 | FQ86: 114 | FR86: 116 | FS86: 130 | FT86: 120 | FU86: 125 | GB86: 270 | GC86: 247.5 | GD86: 259 | GE86: 316 | GF86: 316 | GG86: 316 | GH86: 320 | GI86: 307.5 | GJ86: 314 | GN86: 287.5 | GO86: 275 | GP86: 281.5 | GQ86: 238.75 | GR86: 227.5 | GS86: 233.25 | GW86: 240 | GX86: 230 | GY86: 235 | HC86: 60 | HD86: 56 | HE86: 58
A87: 1994 | B87: 1 | C87: 2 | D87: 195 | E87: 185 | F87: 190 | G87: 139.66667 | H87: 138.33333 | I87: 139.33333 | J87: 183.75 | K87: 176 | L87: 180 | P87: 170.75 | Q87: 164.5 | R87: 168 | S87: 168 | T87: 162.75 | U87: 165.75 | AZ87: 173.75 | BA87: 169.5 | BB87: 172 | BF87: 173.75 | BG87: 169.5 | BH87: 172 | BI87: 178 | BJ87: 175.75 | BK87: 177 | CP87: 185 | CQ87: 182 | CR87: 184 | CS87: 195 | CT87: 185 | CU87: 190 | CV87: 190 | CW87: 176.66667 | CX87: 183.66667 | DT87: 146.5 | DU87: 144.5 | DV87: 145.5 | FJ87: 123.5 | FK87: 118.5 | FL87: 121.5 | FP87: 118.5 | FQ87: 116.75 | FR87: 117.75 | FS87: 130 | FT87: 121.25 | FU87: 125.75 | GB87: 272.5 | GC87: 252.5 | GD87: 262.5 | GE87: 316 | GF87: 316 | GG87: 316 | GH87: 325 | GI87: 315 | GJ87: 320 | GN87: 297.5 | GO87: 285 | GP87: 291.5 | GQ87: 240 | GR87: 230 | GS87: 235 | GW87: 240 | GX87: 230 | GY87: 235 | HC87: 59.25 | HD87: 55.25 | HE87: 57.25
A88: 1994 | B88: 1 | C88: 3 | D88: 195 | E88: 185 | F88: 190 | G88: 145.6 | H88: 143.4 | I88: 144.8 | J88: 195 | K88: 185 | L88: 190 | P88: 174.2 | Q88: 166.2 | R88: 170.2 | S88: 171 | T88: 166.2 | U88: 169 | AZ88: 178.2 | BA88: 173.8 | BB88: 176.2 | BF88: 178.2 | BG88: 173.8 | BH88: 176.2 | BI88: 181.4 | BJ88: 178.8 | BK88: 180.2 | CP88: 187.6 | CQ88: 184.2 | CR88: 186.2 | CS88: 195 | CT88: 185 | CU88: 190 | CV88: 201 | CW88: 191 | CX88: 196 | DT88: 151.6 | DU88: 149.4 | DV88: 150.6 | FJ88: 127.4 | FK88: 121.6 | FL88: 124.6 | FP88: 127 | FQ88: 122.2 | FR88: 124.8 | FS88: 130 | FT88: 125 | FU88: 128 | GB88: 276 | GC88: 256 | GD88: 266 | GE88: 321.8 | GF88: 321.8 | GG88: 321.8 | GH88: 325 | GI88: 315 | GJ88: 320 | GN88: 305 | GO88: 290 | GP88: 298 | GQ88: 246 | GR88: 236 | GS88: 241 | GW88: 248 | GX88: 238 | GY88: 243 | HC88: 59 | HD88: 53.8 | HE88: 56.4
A89: 1994 | B89: 2 | C89: 4 | D89: 195 | E89: 185 | F89: 190 | G89: 151.5 | H89: 148.5 | I89: 150.5 | J89: 195 | K89: 185 | L89: 190 | P89: 181.25 | Q89: 173 | R89: 177.25 | S89: 181.5 | T89: 173 | U89: 177.5 | AZ89: 180 | BA89: 175 | BB89: 178 | BF89: 180 | BG89: 175 | BH89: 178 | BI89: 185.75 | BJ89: 180 | BK89: 183.25 | CP89: 185 | CQ89: 180 | CR89: 183 | CS89: 195 | CT89: 185 | CU89: 190 | CV89: 205 | CW89: 195 | CX89: 200 | DT89: 157.5 | DU89: 154.5 | DV89: 156.5 | FJ89: 134 | FK89: 126.5 | FL89: 130.5 | FP89: 131.5 | FQ89: 128.5 | FR89: 130.5 | FS89: 132.5 | FT89: 127.5 | FU89: 130.5 | GB89: 282.5 | GC89: 260 | GD89: 271.5 | GE89: 346 | GF89: 345 | GG89: 346 | GH89: 325 | GI89: 315 | GJ89: 320 | GN89: 307.5 | GO89: 292.5 | GP89: 300.5 | GQ89: 250 | GR89: 240 | GS89: 245 | GW89: 257.5 | GX89: 242.5 | GY89: 250 | HC89: 59 | HD89: 53 | HE89: 56
A90: 1994 | B90: 2 | C90: 5 | D90: 210 | E90: 200 | F90: 205 | G90: 150.75 | H90: 149.25 | I90: 150.25 | J90: 210 | K90: 200 | L90: 205 | P90: 181.5 | Q90: 170 | R90: 175.75 | S90: 181.75 | T90: 175.75 | U90: 179 | AZ90: 180 | BA90: 175 | BB90: 178 | BF90: 180 | BG90: 175 | BH90: 178 | BI90: 188 | BJ90: 184.33333 | BK90: 186.66667 | CP90: 185 | CQ90: 180 | CR90: 183 | CS90: 210 | CT90: 200 | CU90: 205 | CV90: 205 | CW90: 195 | CX90: 200 | DT90: 157.25 | DU90: 155 | DV90: 156.5 | FJ90: 140 | FK90: 137 | FL90: 139 | FP90: 127 | FQ90: 124 | FR90: 126 | FS90: 135 | FT90: 130 | FU90: 133 | GB90: 285 | GC90: 260 | GD90: 273 | GE90: 346 | GF90: 345 | GG90: 346 | GH90: 325 | GI90: 315 | GJ90: 320 | GN90: 315 | GO90: 300 | GP90: 308 | GQ90: 261.25 | GR90: 243.75 | GS90: 252.5 | GW90: 266.66667 | GX90: 248.33333 | GY90: 257.66667 | HC90: 59 | HD90: 53 | HE90: 56
A91: 1994 | B91: 2 | C91: 6 | D91: 215 | E91: 205 | F91: 210 | G91: 147.4 | H91: 145.2 | I91: 146.4 | J91: 215 | K91: 205 | L91: 210 | P91: 180 | Q91: 170 | R91: 175 | S91: 180.2 | T91: 172.2 | U91: 176.2 | AZ91: 181 | BA91: 175 | BB91: 178.4 | BF91: 181 | BG91: 175 | BH91: 178.4 | BI91: 188 | BJ91: 183.8 | BK91: 186.2 | CP91: 185 | CQ91: 180 | CR91: 183 | CS91: 215 | CT91: 205 | CU91: 210 | CV91: 205 | CW91: 195 | CX91: 200 | DT91: 156 | DU91: 152 | DV91: 154 | FJ91: 140.4 | FK91: 137 | FL91: 139.2 | FP91: 125 | FQ91: 122.2 | FR91: 124 | FS91: 135 | FT91: 130 | FU91: 133 | GB91: 289 | GC91: 265 | GD91: 277 | GE91: 346 | GF91: 345 | GG91: 346 | GH91: 328 | GI91: 317 | GJ91: 322.6 | GN91: 319 | GO91: 305 | GP91: 312.4 | GQ91: 269 | GR91: 260 | GS91: 264.6 | GW91: 271 | GX91: 260 | GY91: 265.6 | HC91: 59 | HD91: 53 | HE91: 56
A92: 1994 | B92: 3 | C92: 7 | D92: 212.5 | E92: 202.5 | F92: 207.5 | G92: 148.5 | H92: 147 | I92: 148.25 | J92: 212.5 | K92: 202.5 | L92: 207.5 | P92: 180 | Q92: 170 | R92: 175 | S92: 179.5 | T92: 172 | U92: 175.75 | AZ92: 186.25 | BA92: 176.5 | BB92: 181.5 | BF92: 186.25 | BG92: 176.5 | BH92: 181.5 | BI92: 187.5 | BJ92: 183.75 | BK92: 185.75 | CP92: 199 | CQ92: 197.5 | CR92: 198.5 | CS92: 212.5 | CT92: 202.5 | CU92: 207.5 | CV92: 205 | CW92: 195 | CX92: 200 | DT92: 156 | DU92: 152 | DV92: 154 | FJ92: 142 | FK92: 137 | FL92: 140 | FP92: 125 | FQ92: 123 | FR92: 124 | FS92: 135 | FT92: 130 | FU92: 133 | GB92: 308.75 | GC92: 272.5 | GD92: 291 | GE92: 346 | GF92: 345 | GG92: 346 | GH92: 340 | GI92: 330 | GJ92: 335 | GN92: 335 | GO92: 326.25 | GP92: 330.75 | GQ92: 275 | GR92: 260 | GS92: 268 | GW92: 275 | GX92: 260 | GY92: 268 | HC92: 59 | HD92: 53 | HE92: 56
A93: 1994 | B93: 3 | C93: 8 | D93: 205 | E93: 195 | F93: 200 | G93: 151.5 | H93: 148.75 | I93: 150.5 | J93: 205 | K93: 195 | L93: 200 | P93: 180.25 | Q93: 170 | R93: 175.25 | S93: 178.75 | T93: 172 | U93: 175.5 | AZ93: 192.25 | BA93: 183.25 | BB93: 188 | BF93: 192.25 | BG93: 183.25 | BH93: 188 | BI93: 188 | BJ93: 186 | BK93: 187 | CP93: 204.5 | CQ93: 201.5 | CR93: 203 | CS93: 205 | CT93: 195 | CU93: 200 | CV93: 205 | CW93: 195 | CX93: 200 | DT93: 157.5 | DU93: 154 | DV93: 156 | FJ93: 142 | FK93: 137 | FL93: 140 | FP93: 131 | FQ93: 127 | FR93: 129 | FS93: 135 | FT93: 130 | FU93: 133 | GB93: 310 | GC93: 282.5 | GD93: 296.75 | GE93: 346 | GF93: 345 | GG93: 346 | GH93: 340 | GI93: 330 | GJ93: 335 | GN93: 335 | GO93: 330 | GP93: 333 | GQ93: 275 | GR93: 260 | GS93: 268 | GW93: 275 | GX93: 260 | GY93: 268 | HC93: 59 | HD93: 53 | HE93: 56
A94: 1994 | B94: 3 | C94: 9 | D94: 206 | E94: 197 | F94: 202 | G94: 153.6 | H94: 150.4 | I94: 152.2 | J94: 206 | K94: 197 | L94: 202 | P94: 182.6 | Q94: 175 | R94: 178.8 | S94: 182.6 | T94: 175 | U94: 178.8 | AZ94: 199.4 | BA94: 192 | BB94: 196 | BF94: 199.4 | BG94: 192 | BH94: 196 | BI94: 189.6 | BJ94: 186.8 | BK94: 188.2 | CP94: 215.8 | CQ94: 211.6 | CR94: 214 | CS94: 206 | CT94: 197 | CU94: 202 | CV94: 211 | CW94: 195 | CX94: 203 | DT94: 159.8 | DU94: 154.4 | DV94: 157.4 | FJ94: 146.6 | FK94: 141.6 | FL94: 144.4 | FP94: 133 | FQ94: 127.2 | FR94: 130.2 | FS94: 135 | FT94: 130 | FU94: 133 | GB94: 316 | GC94: 292 | GD94: 304.4 | GE94: 368.2 | GF94: 368 | GG94: 368.2 | GH94: 349 | GI94: 342 | GJ94: 345.8 | GN94: 344 | GO94: 336 | GP94: 340.2 | GQ94: 281 | GR94: 270 | GS94: 275.6 | GW94: 282 | GX94: 272 | GY94: 277 | HC94: 59 | HD94: 53 | HE94: 56
A95: 1994 | B95: 4 | C95: 10 | D95: 212.25 | E95: 202.25 | F95: 207.25 | G95: 159 | H95: 155 | I95: 157 | J95: 212.25 | K95: 202.25 | L95: 207.25 | P95: 194 | Q95: 180.75 | R95: 187.5 | S95: 194 | T95: 180.75 | U95: 187.5 | AZ95: 207.75 | BA95: 200 | BB95: 204.25 | BF95: 207.75 | BG95: 200 | BH95: 204.25 | BI95: 205 | BJ95: 200 | BK95: 203 | CP95: 226.5 | CQ95: 222.25 | CR95: 224.75 | CS95: 212.25 | CT95: 202.25 | CU95: 207.25 | CV95: 217 | CW95: 206.25 | CX95: 212 | DT95: 162 | DU95: 159 | DV95: 160.5 | FJ95: 150 | FK95: 147 | FL95: 149 | FP95: 133 | FQ95: 128.75 | FR95: 131 | FS95: 138.75 | FT95: 134.5 | FU95: 137 | GB95: 321.25 | GC95: 295 | GD95: 308.5 | GE95: 373 | GF95: 373 | GG95: 373 | GH95: 356.25 | GI95: 351.25 | GJ95: 354.25 | GN95: 351.25 | GO95: 341.25 | GP95: 346.25 | GQ95: 285 | GR95: 275 | GS95: 280 | GW95: 285 | GX95: 275 | GY95: 280 | HC95: 59 | HD95: 56 | HE95: 58
A96: 1994 | B96: 4 | C96: 11 | D96: 219 | E96: 209 | F96: 214 | G96: 162 | H96: 155.25 | I96: 158.75 | J96: 219 | K96: 209 | L96: 214 | P96: 194 | Q96: 183 | R96: 188.5 | S96: 194 | T96: 183 | U96: 188.5 | AZ96: 211 | BA96: 207.5 | BB96: 209.5 | BF96: 211 | BG96: 207.5 | BH96: 209.5 | CP96: 223.5 | CQ96: 220.5 | CR96: 222.25 | CS96: 219 | CT96: 209 | CU96: 214 | CV96: 220 | CW96: 210 | CX96: 215 | DT96: 168 | DU96: 160 | DV96: 164 | FJ96: 147 | FK96: 145 | FL96: 146 | FP96: 137 | FQ96: 130.5 | FR96: 134 | FS96: 140 | FT96: 138 | FU96: 139 | GB96: 327.5 | GC96: 295 | GD96: 311.25 | GE96: 373 | GF96: 373 | GG96: 373 | GH96: 360 | GI96: 355 | GJ96: 358 | GN96: 356.75 | GO96: 347.5 | GP96: 352.25 | GQ96: 285 | GR96: 275 | GS96: 280 | GW96: 285 | GX96: 275 | GY96: 280 | HC96: 59 | HD96: 56.5 | HE96: 58
A97: 1994 | B97: 4 | C97: 12 | D97: 221.4 | E97: 211.4 | F97: 216.4 | G97: 164 | H97: 157.8 | I97: 161 | J97: 221.4 | K97: 211.4 | L97: 216.4 | P97: 194.2 | Q97: 183.4 | R97: 188.8 | S97: 194.2 | T97: 180.4 | U97: 187.6 | AZ97: 211 | BA97: 206.5 | BB97: 209 | BF97: 211 | BG97: 206.5 | BH97: 209 | CP97: 222 | CQ97: 216 | CR97: 219 | CS97: 221.4 | CT97: 211.4 | CU97: 216.4 | CV97: 222 | CW97: 212 | CX97: 217 | DT97: 168.6 | DU97: 162.6 | DV97: 165.8 | FJ97: 147 | FK97: 145 | FL97: 146 | FP97: 137.6 | FQ97: 132.4 | FR97: 135.4 | FS97: 140 | FT97: 138 | FU97: 139 | GB97: 335 | GC97: 295 | GD97: 315 | GE97: 373 | GF97: 373 | GG97: 373 | GH97: 361 | GI97: 355 | GJ97: 358.5 | GN97: 362 | GO97: 355 | GP97: 359 | GQ97: 285 | GR97: 275 | GS97: 280 | GW97: 285 | GX97: 275 | GY97: 280 | HC97: 59 | HD97: 57 | HE97: 58
A98: 1995 | B98: 1 | C98: 1 | D98: 238 | E98: 232.5 | F98: 235.75 | G98: 176.66667 | H98: 174.66667 | I98: 175.66667 | J98: 238 | K98: 232.5 | L98: 235.75 | P98: 201.75 | Q98: 190 | R98: 196 | S98: 201.75 | T98: 190 | U98: 196 | AZ98: 213.5 | BA98: 210 | BB98: 212 | BF98: 213.5 | BG98: 210 | BH98: 212 | CP98: 224.75 | CQ98: 219.5 | CR98: 222.5 | CS98: 238 | CT98: 232.5 | CU98: 235.75 | CV98: 232 | CW98: 225 | CX98: 228.75 | DT98: 177.5 | DU98: 173.75 | DV98: 176 | FJ98: 152 | FK98: 150 | FL98: 151 | FP98: 145 | FQ98: 138.75 | FR98: 142.25 | FS98: 145 | FT98: 139.75 | FU98: 142.75 | GB98: 345 | GC98: 305 | GD98: 325 | GE98: 373 | GF98: 373 | GG98: 373 | GH98: 380 | GI98: 375 | GJ98: 378 | GN98: 380 | GO98: 375 | GP98: 378 | GQ98: 285 | GR98: 275 | GS98: 280 | GW98: 285 | GX98: 275 | GY98: 280 | HC98: 59.5 | HD98: 57 | HE98: 58.25
A99: 1995 | B99: 1 | C99: 2 | D99: 246 | E99: 238.33333 | F99: 242.66667 | G99: 183.75 | H99: 180.25 | I99: 182 | J99: 232.5 | K99: 226 | L99: 229.75 | P99: 209 | Q99: 202 | R99: 206 | S99: 209 | T99: 202 | U99: 206 | AZ99: 218.75 | BA99: 212.75 | BB99: 216 | BF99: 218.75 | BG99: 212.75 | BH99: 216 | BI99: 234 | BJ99: 233 | BK99: 234 | CP99: 230 | CQ99: 227 | CR99: 229 | CS99: 246 | CT99: 238.33333 | CU99: 242.66667 | CV99: 241.33333 | CW99: 233.33333 | CX99: 237.66667 | DT99: 188.5 | DU99: 184 | DV99: 186.5 | FJ99: 156.25 | FK99: 150.5 | FL99: 153.75 | FP99: 151 | FQ99: 140 | FR99: 145.5 | FS99: 150 | FT99: 145 | FU99: 148 | GB99: 345 | GC99: 305 | GD99: 325 | GE99: 373 | GF99: 373 | GG99: 373 | GH99: 380 | GI99: 375 | GJ99: 378 | GN99: 380 | GO99: 375 | GP99: 378 | GQ99: 285 | GR99: 275 | GS99: 280 | GW99: 285 | GX99: 275 | GY99: 280 | HC99: 61 | HD99: 57 | HE99: 59
A100: 1995 | B100: 1 | C100: 3 | D100: 258 | E100: 245 | F100: 252 | G100: 193.2 | H100: 190.2 | I100: 192 | J100: 258 | K100: 245 | L100: 252 | P100: 218.4 | Q100: 210 | R100: 214.2 | S100: 217.2 | T100: 210 | U100: 213.8 | AZ100: 220 | BA100: 215 | BB100: 218 | BF100: 220 | BG100: 215 | BH100: 218 | BI100: 232 | BJ100: 231 | BK100: 232 | CP100: 231.2 | CQ100: 227 | CR100: 229.6 | CS100: 258 | CT100: 245 | CU100: 252 | CV100: 254 | CW100: 237 | CX100: 245.8 | DT100: 197.2 | DU100: 191.8 | DV100: 194.8 | FJ100: 161 | FK100: 152.6 | FL100: 156.8 | FP100: 155 | FQ100: 146 | FR100: 150.8 | FS100: 150 | FT100: 145 | FU100: 148 | GB100: 347 | GC100: 311 | GD100: 329.2 | GE100: 388.2 | GF100: 388.2 | GG100: 388.2 | GH100: 383 | GI100: 376 | GJ100: 380 | GN100: 380 | GO100: 375 | GP100: 378 | GQ100: 289 | GR100: 280 | GS100: 284.6 | GW100: 293 | GX100: 283 | GY100: 288.2 | HC100: 61 | HD100: 57 | HE100: 59
A101: 1995 | B101: 2 | C101: 4 | D101: 258 | E101: 245 | F101: 252 | G101: 190.25 | H101: 186 | I101: 188.5 | J101: 258 | K101: 245 | L101: 252 | P101: 223 | Q101: 214.5 | R101: 218.75 | S101: 223 | T101: 213.5 | U101: 218.25 | AZ101: 220 | BA101: 216 | BB101: 218.5 | BF101: 220 | BG101: 216 | BH101: 218.5 | BI101: 232 | BJ101: 231 | BK101: 232 | CP101: 234 | CQ101: 229.5 | CR101: 232 | CS101: 258 | CT101: 245 | CU101: 252 | CV101: 254 | CW101: 235 | CX101: 245 | DT101: 198 | DU101: 193 | DV101: 196 | FJ101: 165 | FK101: 157.25 | FL101: 161.5 | FP101: 150.5 | FQ101: 145 | FR101: 148.25 | FS101: 150 | FT101: 145 | FU101: 148 | GB101: 355 | GC101: 320 | GD101: 338 | GE101: 411 | GF101: 411 | GG101: 411 | GH101: 395 | GI101: 380 | GJ101: 388 | GN101: 387.5 | GO101: 377.5 | GP101: 383 | GQ101: 305 | GR101: 290 | GS101: 298 | GW101: 305 | GX101: 290 | GY101: 298 | HC101: 61 | HD101: 57 | HE101: 59
A102: 1995 | B102: 2 | C102: 5 | D102: 256.5 | E102: 242.5 | F102: 250 | G102: 183.5 | H102: 177 | I102: 180.5 | J102: 256.5 | K102: 242.5 | L102: 250 | P102: 221.5 | Q102: 212.75 | R102: 217.25 | S102: 221.5 | T102: 212.75 | U102: 217.25 | AZ102: 220 | BA102: 217 | BB102: 219 | BF102: 220 | BG102: 217 | BH102: 219 | BI102: 232 | BJ102: 231 | BK102: 232 | CP102: 235.66667 | CQ102: 232.66667 | CR102: 234.33333 | CS102: 256.5 | CT102: 242.5 | CU102: 250 | CV102: 252.5 | CW102: 232.5 | CX102: 243 | DT102: 194.5 | DU102: 189.5 | DV102: 192.5 | FJ102: 166.33333 | FK102: 159.33333 | FL102: 163.33333 | FP102: 141.5 | FQ102: 135.25 | FR102: 138.75 | FS102: 150 | FT102: 145 | FU102: 148 | GB102: 355 | GC102: 320 | GD102: 338 | GE102: 411 | GF102: 411 | GG102: 411 | GH102: 395 | GI102: 380 | GJ102: 388 | GN102: 395 | GO102: 380 | GP102: 388 | GQ102: 306 | GR102: 290 | GS102: 298.5 | GW102: 305 | GX102: 290 | GY102: 298 | HC102: 61 | HD102: 57 | HE102: 59
A103: 1995 | B103: 2 | C103: 6 | D103: 251 | E103: 236 | F103: 244 | G103: 175.2 | H103: 169.4 | I103: 172.6 | J103: 251 | K103: 236 | L103: 244 | P103: 215.6 | Q103: 208.2 | R103: 212.2 | S103: 215.6 | T103: 207.8 | U103: 212 | AZ103: 218 | BA103: 210.4 | BB103: 214.4 | BF103: 218 | BG103: 210.4 | BH103: 214.4 | BI103: 229.6 | BJ103: 223.6 | BK103: 227 | CP103: 235 | CQ103: 234 | CR103: 235 | CS103: 251 | CT103: 236 | CU103: 244 | CV103: 246.6 | CW103: 228 | CX103: 237.8 | DT103: 182.8 | DU103: 178.4 | DV103: 181 | FJ103: 167 | FK103: 163 | FL103: 165 | FP103: 135 | FQ103: 129.6 | FR103: 132.8 | FS103: 150 | FT103: 145 | FU103: 148 | GB103: 355 | GC103: 320 | GD103: 338 | GE103: 411 | GF103: 411 | GG103: 411 | GH103: 395 | GI103: 380 | GJ103: 388 | GN103: 395 | GO103: 380 | GP103: 388 | GQ103: 305 | GR103: 290 | GS103: 298 | GW103: 305 | GX103: 290 | GY103: 298 | HC103: 61 | HD103: 57 | HE103: 59
A104: 1995 | B104: 3 | C104: 7 | D104: 237.5 | E104: 222.5 | F104: 230.5 | G104: 172.75 | H104: 167.5 | I104: 170.25 | J104: 237.5 | K104: 222.5 | L104: 230.5 | P104: 209.25 | Q104: 197.5 | R104: 203.5 | S104: 208.75 | T104: 197.5 | U104: 203.25 | AZ104: 222 | BA104: 216.25 | BB104: 219.5 | BF104: 222 | BG104: 216.25 | BH104: 219.5 | BI104: 229.5 | BJ104: 221 | BK104: 225.75 | CP104: 235 | CQ104: 234 | CR104: 235 | CS104: 237.5 | CT104: 222.5 | CU104: 230.5 | CV104: 232.5 | CW104: 217.5 | CX104: 225.5 | DT104: 178.75 | DU104: 175 | DV104: 177.25 | FJ104: 166.5 | FK104: 162.25 | FL104: 164.5 | FP104: 132.75 | FQ104: 128 | FR104: 130.5 | FS104: 150 | FT104: 145 | FU104: 148 | GB104: 365 | GC104: 320 | GD104: 343 | GE104: 411 | GF104: 411 | GG104: 411 | GH104: 400 | GI104: 385 | GJ104: 393 | GN104: 395 | GO104: 380 | GP104: 388 | GQ104: 305 | GR104: 290 | GS104: 298 | GW104: 305 | GX104: 290 | GY104: 298 | HC104: 62 | HD104: 58 | HE104: 60
A105: 1995 | B105: 3 | C105: 8 | D105: 235 | E105: 220 | F105: 228 | G105: 175.4 | H105: 171.2 | I105: 173.6 | J105: 235 | K105: 220 | L105: 228 | P105: 208.4 | Q105: 201 | R105: 204.8 | S105: 205 | T105: 201 | U105: 203.4 | AZ105: 228.4 | BA105: 222.2 | BB105: 225.4 | BF105: 228.4 | BG105: 222.2 | BH105: 225.4 | BI105: 230 | BJ105: 226.8 | BK105: 228.6 | CP105: 241.4 | CQ105: 239.4 | CR105: 240.4 | CS105: 235 | CT105: 220 | CU105: 228 | CV105: 230 | CW105: 215 | CX105: 223 | DT105: 179.5 | DU105: 176.5 | DV105: 178.25 | FJ105: 165 | FK105: 160 | FL105: 163 | FP105: 136.2 | FQ105: 131.8 | FR105: 134.4 | FS105: 150 | FT105: 145 | FU105: 148 | GB105: 365 | GC105: 320 | GD105: 343 | GE105: 411 | GF105: 411 | GG105: 411 | GH105: 400 | GI105: 385 | GJ105: 393 | GN105: 395 | GO105: 380 | GP105: 388 | GQ105: 305 | GR105: 292 | GS105: 299 | GW105: 305 | GX105: 294 | GY105: 300 | HC105: 62.6 | HD105: 58.6 | HE105: 60.6
A106: 1995 | B106: 3 | C106: 9 | D106: 230 | E106: 225 | F106: 228 | G106: 181 | H106: 177.75 | I106: 179.5 | J106: 230 | K106: 225 | L106: 228 | P106: 205 | Q106: 198 | R106: 202 | S106: 200 | T106: 198 | U106: 199 | AZ106: 230 | BA106: 227.25 | BB106: 228.75 | BF106: 230 | BG106: 227.25 | BH106: 228.75 | BI106: 234 | BJ106: 230 | BK106: 232 | CP106: 247.75 | CQ106: 245.75 | CR106: 246.75 | CS106: 230 | CT106: 225 | CU106: 228 | CV106: 220 | CW106: 215 | CX106: 218 | DT106: 186 | DU106: 182.5 | DV106: 184.5 | FJ106: 165 | FK106: 160 | FL106: 163 | FP106: 145 | FQ106: 142 | FR106: 144 | FS106: 150 | FT106: 145 | FU106: 148 | GB106: 365 | GC106: 320 | GD106: 343 | GE106: 412.5 | GF106: 412.25 | GG106: 412.5 | GH106: 400 | GI106: 385 | GJ106: 393 | GN106: 398.75 | GO106: 387.5 | GP106: 393.25 | GQ106: 305 | GR106: 300 | GS106: 303 | GW106: 305 | GX106: 300 | GY106: 303 | HC106: 63 | HD106: 59 | HE106: 61
A107: 1995 | B107: 4 | C107: 10 | D107: 235 | E107: 230 | F107: 233 | G107: 188 | H107: 184.75 | I107: 186.75 | J107: 235 | K107: 230 | L107: 233 | P107: 209.5 | Q107: 202.75 | R107: 206.5 | S107: 208.25 | T107: 202.75 | U107: 205.75 | AZ107: 245.75 | BA107: 240.25 | BB107: 243.5 | BF107: 245.75 | BG107: 240.25 | BH107: 243.5 | BI107: 246.5 | BJ107: 241 | BK107: 244 | CP107: 262.5 | CQ107: 258.75 | CR107: 260.75 | CS107: 235 | CT107: 230 | CU107: 233 | CV107: 232 | CW107: 225 | CX107: 229 | DT107: 191 | DU107: 187.75 | DV107: 189.75 | FJ107: 167.5 | FK107: 162.5 | FL107: 165.5 | FP107: 145 | FQ107: 142 | FR107: 144 | FS107: 152.5 | FT107: 147.5 | FU107: 150.5 | GB107: 375 | GC107: 325 | GD107: 350 | GE107: 417 | GF107: 416 | GG107: 417 | GH107: 410 | GI107: 398.75 | GJ107: 404.5 | GN107: 405 | GO107: 395 | GP107: 400 | GQ107: 305 | GR107: 300 | GS107: 303 | GW107: 305 | GX107: 300 | GY107: 303 | HC107: 63.75 | HD107: 59.75 | HE107: 61.75
A108: 1995 | B108: 4 | C108: 11 | D108: 250 | E108: 241 | F108: 245.6 | G108: 201.6 | H108: 198 | I108: 199.8 | J108: 250 | K108: 241 | L108: 245.6 | P108: 234.6 | Q108: 226.2 | R108: 230.6 | S108: 234.6 | T108: 226.2 | U108: 230.6 | AZ108: 254 | BA108: 249 | BB108: 252 | BF108: 254 | BG108: 249 | BH108: 252 | BI108: 255 | BJ108: 250 | BK108: 253 | CP108: 267.6 | CQ108: 263 | CR108: 265.6 | CS108: 250 | CT108: 241 | CU108: 245.6 | CV108: 241.4 | CW108: 233 | CX108: 237.4 | DT108: 204.8 | DU108: 202.2 | DV108: 204 | FJ108: 175 | FK108: 170 | FL108: 173 | FP108: 153 | FQ108: 148.4 | FR108: 151.2 | FS108: 164 | FT108: 157.4 | FU108: 161.2 | GB108: 375 | GC108: 325 | GD108: 350 | GE108: 417 | GF108: 416 | GG108: 417 | GH108: 410 | GI108: 400 | GJ108: 405 | GN108: 405 | GO108: 395 | GP108: 400 | GQ108: 305 | GR108: 300 | GS108: 303 | GW108: 308 | GX108: 303 | GY108: 306 | HC108: 64 | HD108: 60 | HE108: 62
A109: 1995 | B109: 4 | C109: 12 | D109: 262.5 | E109: 248.75 | F109: 256 | G109: 215.5 | H109: 209.25 | I109: 212.75 | J109: 262.5 | K109: 248.75 | L109: 256 | P109: 250 | Q109: 245 | R109: 248 | S109: 248.75 | T109: 243.75 | U109: 246.75 | AZ109: 261.66667 | BA109: 255 | BB109: 258.66667 | BF109: 261.66667 | BG109: 255 | BH109: 258.66667 | BI109: 260 | BJ109: 250 | BK109: 255 | CP109: 271.33333 | CQ109: 268.33333 | CR109: 270 | CS109: 262.5 | CT109: 248.75 | CU109: 256 | CV109: 256.25 | CW109: 246.25 | CX109: 251.25 | DT109: 220.25 | DU109: 217.25 | DV109: 219.25 | FJ109: 175 | FK109: 170 | FL109: 173 | FP109: 168 | FQ109: 162.5 | FR109: 165.75 | FS109: 165 | FT109: 160 | FU109: 163 | GB109: 375 | GC109: 325 | GD109: 350 | GE109: 417 | GF109: 416 | GG109: 417 | GH109: 410 | GI109: 400 | GJ109: 405 | GN109: 405 | GO109: 395 | GP109: 400 | GQ109: 310 | GR109: 305 | GS109: 308 | GW109: 313.33333 | GX109: 305 | GY109: 309.66667 | HC109: 64 | HD109: 60 | HE109: 62
A110: 1996 | B110: 1 | C110: 1 | D110: 265 | E110: 250 | F110: 258 | G110: 214.66667 | H110: 210.33333 | I110: 213 | J110: 265 | K110: 250 | L110: 258 | P110: 247.5 | Q110: 240 | R110: 244 | S110: 246.25 | T110: 240.5 | U110: 243.75 | AZ110: 260 | BA110: 255 | BB110: 258 | BF110: 260 | BG110: 255 | BH110: 258 | BI110: 260 | BJ110: 253.75 | BK110: 257.25 | CP110: 273.5 | CQ110: 271.5 | CR110: 272.5 | CS110: 265 | CT110: 250 | CU110: 258 | CV110: 267.5 | CW110: 250 | CX110: 258.75 | DT110: 220.25 | DU110: 217 | DV110: 219 | FJ110: 175 | FK110: 170 | FL110: 173 | FP110: 172.5 | FQ110: 167.5 | FR110: 170.5 | FS110: 165 | FT110: 160 | FU110: 163 | GB110: 375 | GC110: 325 | GD110: 350 | GE110: 417 | GF110: 416 | GG110: 417 | GH110: 410 | GI110: 400 | GJ110: 405 | GN110: 405 | GO110: 395 | GP110: 400 | GQ110: 315 | GR110: 305 | GS110: 310.5 | GW110: 320 | GX110: 305 | GY110: 313 | HC110: 64 | HD110: 60 | HE110: 62
... A113: 1996 | B113: 2 | C113: 4 | D113: 265 | E113: 250 | F113: 258 | G113: 202 | H113: 197.5 | I113: 200 | J113: 265 | K113: 250 | L113: 258 | P113: 242.5 | Q113: 237.5 | R113: 240.5 | S113: 243.75 | T113: 238.75 | U113: 241.75 | AZ113: 238.75 | BA113: 220 | BB113: 229.5 | BF113: 238.75 | BG113: 220 | BH113: 229.5 | BI113: 240 | BJ113: 233.75 | BK113: 237.25 | CP113: 266 | CQ113: 263.25 | CR113: 264.75 | CS113: 265 | CT113: 250 | CU113: 258 | CV113: 270 | CW113: 250 | CX113: 260 | DT113: 211.33333 | DU113: 207.33333 | DV113: 209.66667 | FJ113: 175 | FK113: 170 | FL113: 173 | FP113: 170 | FQ113: 170 | FR113: 170 | FS113: 177 | FT113: 170 | FU113: 174 | GB113: 375 | GC113: 325 | GD113: 350 | GE113: 417 | GF113: 416 | GG113: 417 | GH113: 410 | GI113: 400 | GJ113: 405 | GN113: 405 | GO113: 395 | GP113: 400 | GQ113: 320 | GR113: 305 | GS113: 313 | GW113: 320 | GX113: 305 | GY113: 313 | HC113: 64 | HD113: 60 | HE113: 62
A114: 1996 | B114: 2 | C114: 5 | D114: 265 | E114: 250 | F114: 258 | G114: 189.6 | H114: 184 | I114: 187 | J114: 265 | K114: 250 | L114: 258 | P114: 233.4 | Q114: 228.4 | R114: 231.4 | S114: 237 | T114: 232 | U114: 235 | AZ114: 232.5 | BA114: 218.75 | BB114: 226 | BF114: 232.5 | BG114: 218.75 | BH114: 226 | BI114: 230 | BJ114: 222.5 | BK114: 226.5 | CP114: 258 | CQ114: 253 | CR114: 256 | CS114: 265 | CT114: 250 | CU114: 258 | CV114: 254 | CW114: 246 | CX114: 250.4 | CY114: 195 | CZ114: 190 | DA114: 193 | DT114: 199.2 | DU114: 192.6 | DV114: 196.2 | FJ114: 175 | FK114: 170 | FL114: 173 | FP114: 164 | FQ114: 164 | FR114: 164 | FS114: 177 | FT114: 170 | FU114: 174 | GB114: 375 | GC114: 325 | GD114: 350 | GE114: 417 | GF114: 416 | GG114: 417 | GH114: 410 | GI114: 400 | GJ114: 405 | GN114: 405 | GO114: 395 | GP114: 400 | GQ114: 320 | GR114: 305 | GS114: 313 | GW114: 320 | GX114: 305 | GY114: 313 | HC114: 64 | HD114: 60 | HE114: 62
A115: 1996 | B115: 2 | C115: 6 | D115: 240 | E115: 200 | F115: 220 | G115: 187.25 | H115: 180.25 | I115: 184 | J115: 240 | K115: 200 | L115: 220 | P115: 226.25 | Q115: 221.25 | R115: 224.25 | S115: 231.25 | T115: 226.25 | U115: 229.25 | AZ115: 225 | BA115: 215 | BB115: 220 | BF115: 225 | BG115: 215 | BH115: 220 | BI115: 220 | BJ115: 210 | BK115: 215 | CP115: 258 | CQ115: 253 | CR115: 256 | CS115: 240 | CT115: 200 | CU115: 220 | CV115: 235 | CW115: 200 | CX115: 218 | CY115: 202 | CZ115: 197.5 | DA115: 200.25 | DT115: 194 | DU115: 187 | DV115: 191 | FJ115: 175 | FK115: 170.75 | FL115: 173.25 | FP115: 167.25 | FQ115: 167.25 | FR115: 167.25 | FS115: 179.25 | FT115: 170 | FU115: 174.75 | GB115: 375 | GC115: 325 | GD115: 350 | GE115: 417 | GF115: 416 | GG115: 417 | GH115: 410 | GI115: 400 | GJ115: 405 | GN115: 405 | GO115: 395 | GP115: 400 | GQ115: 320 | GR115: 305 | GS115: 313 | GW115: 320 | GX115: 305 | GY115: 313 | HC115: 64 | HD115: 60 | HE115: 62
A116: 1996 | B116: 3 | C116: 7 | D116: 245 | E116: 222.5 | F116: 234 | G116: 187.75 | H116: 182.25 | I116: 185.25 | J116: 245 | K116: 222.5 | L116: 234 | P116: 221.25 | Q116: 213.75 | R116: 217.75 | S116: 217.5 | T116: 210 | U116: 214 | AZ116: 227.75 | BA116: 216.25 | BB116: 222 | BF116: 227.75 | BG116: 216.25 | BH116: 222 | BI116: 225 | BJ116: 215 | BK116: 220 | CS116: 245 | CT116: 222.5 | CU116: 234 | CV116: 242.5 | CW116: 228.75 | CX116: 236 | CY116: 214.75 | CZ116: 210 | DA116: 212.75 | DT116: 194 | DU116: 187 | DV116: 191 | FJ116: 175.75 | FK116: 173 | FL116: 174.5 | FP116: 165 | FQ116: 165 | FR116: 165 | FS116: 180 | FT116: 171.25 | FU116: 175.75 | GB116: 375 | GC116: 325 | GD116: 350 | GE116: 417 | GF116: 417 | GG116: 417 | GH116: 410 | GI116: 400 | GJ116: 405 | GN116: 405 | GO116: 395 | GP116: 400 | GQ116: 320 | GR116: 305 | GS116: 313 | GW116: 320 | GX116: 305 | GY116: 313 | HC116: 64 | HD116: 60 | HE116: 62
A117: 1996 | B117: 3 | C117: 8 | D117: 256 | E117: 243 | F117: 250 | G117: 189 | H117: 184.4 | I117: 187.2 | J117: 256 | K117: 243 | L117: 250 | P117: 215 | Q117: 208 | R117: 211.8 | S117: 215 | T117: 205 | U117: 210 | AZ117: 230 | BA117: 221 | BB117: 225.6 | BF117: 230 | BG117: 221 | BH117: 225.6 | BI117: 236 | BJ117: 222.6 | BK117: 229.8 | CP117: 250 | CQ117: 248 | CR117: 249 | CS117: 256 | CT117: 243 | CU117: 250 | CV117: 249 | CW117: 240 | CX117: 244.6 | CY117: 218.2 | CZ117: 215.2 | DA117: 216.8 | DT117: 194.4 | DU117: 188.2 | DV117: 191.8 | FJ117: 180 | FK117: 175.6 | FL117: 178.2 | FP117: 165 | FQ117: 165 | FR117: 165 | FS117: 180 | FT117: 177.2 | FU117: 179 | GB117: 375 | GC117: 325 | GD117: 350 | GE117: 417 | GF117: 417 | GG117: 417 | GH117: 410 | GI117: 400 | GJ117: 405 | GN117: 405 | GO117: 395 | GP117: 400 | GQ117: 320 | GR117: 305 | GS117: 313 | GW117: 320 | GX117: 305 | GY117: 313 | HC117: 64 | HD117: 60 | HE117: 62
A118: 1996 | B118: 3 | C118: 9 | D118: 255 | E118: 247.5 | F118: 251.75 | G118: 182 | H118: 175 | I118: 179 | J118: 255 | K118: 247.5 | L118: 251.75 | P118: 212.5 | Q118: 207.5 | R118: 210.5 | S118: 212.5 | T118: 205 | U118: 209 | AZ118: 235 | BA118: 227.5 | BB118: 231.5 | BF118: 235 | BG118: 227.5 | BH118: 231.5 | BI118: 231.25 | BJ118: 222 | BK118: 226.75 | CP118: 248.5 | CQ118: 240.5 | CR118: 244.75 | CS118: 255 | CT118: 247.5 | CU118: 251.75 | CV118: 250 | CW118: 240 | CX118: 245 | CY118: 216.75 | CZ118: 212.25 | DA118: 214.75 | DT118: 192.5 | DU118: 186 | DV118: 189.75 | FJ118: 185 | FK118: 181.5 | FL118: 183.5 | FP118: 163.75 | FQ118: 163 | FR118: 163.5 | FS118: 183 | FT118: 180 | FU118: 182 | GB118: 375 | GC118: 325 | GD118: 350 | GE118: 417 | GF118: 417 | GG118: 417 | GH118: 410 | GI118: 400 | GJ118: 405 | GN118: 405 | GO118: 395 | GP118: 400 | GQ118: 320 | GR118: 305 | GS118: 313 | GW118: 320 | GX118: 305 | GY118: 313 | HC118: 64 | HD118: 60 | HE118: 62
A119: 1996 | B119: 4 | C119: 10 | D119: 255 | E119: 250 | F119: 253 | G119: 181.8 | H119: 178 | I119: 180.4 | J119: 255 | K119: 250 | L119: 253 | P119: 218 | Q119: 210 | R119: 214.2 | S119: 218 | T119: 210 | U119: 214.2 | V119: 210.75 | W119: 210 | X119: 210.75 | AZ119: 227.6 | BA119: 224.2 | BB119: 226.2 | BF119: 227.6 | BG119: 224.2 | BH119: 226.2 | BI119: 230 | BJ119: 223.2 | BK119: 226.8 | CP119: 240 | CQ119: 232.4 | CR119: 236.2 | CS119: 255 | CT119: 250 | CU119: 253 | CV119: 250 | CW119: 240 | CX119: 245 | CY119: 206.6 | CZ119: 196.6 | DA119: 201.6 | DT119: 187.2 | DU119: 183.2 | DV119: 185.6 | FJ119: 188 | FK119: 182.6 | FL119: 185.6 | FP119: 167.6 | FQ119: 167 | FR119: 167.4 | FS119: 185 | FT119: 180 | FU119: 183 | GB119: 375 | GC119: 325 | GD119: 350 | GE119: 417 | GF119: 417 | GG119: 417 | GH119: 410 | GI119: 400 | GJ119: 405 | GN119: 405 | GO119: 395 | GP119: 400 | GQ119: 320 | GR119: 305 | GS119: 313 | GW119: 328 | GX119: 305 | GY119: 317 | HC119: 64 | HD119: 60 | HE119: 62
A120: 1996 | B120: 4 | C120: 11 | D120: 255 | E120: 250 | F120: 253 | G120: 182 | H120: 180.75 | I120: 181.5 | J120: 255 | K120: 250 | L120: 253 | P120: 211.5 | Q120: 207.75 | R120: 210 | S120: 210 | T120: 207 | U120: 208.75 | V120: 202.25 | W120: 197.25 | X120: 200 | AZ120: 224 | BA120: 220 | BB120: 222 | BF120: 224 | BG120: 220 | BH120: 222 | BI120: 230 | BJ120: 227.25 | BK120: 228.75 | CP120: 240 | CQ120: 234 | CR120: 237 | CS120: 255 | CT120: 250 | CU120: 253 | CV120: 250 | CW120: 240 | CX120: 245 | CY120: 199.5 | CZ120: 190 | DA120: 194.75 | DT120: 188 | DU120: 186.5 | DV120: 187.5 | FJ120: 185 | FK120: 179 | FL120: 182 | FP120: 169.25 | FQ120: 169.25 | FR120: 169.25 | FS120: 185 | FT120: 180 | FU120: 183 | GB120: 375 | GC120: 325 | GD120: 350 | GE120: 417 | GF120: 417 | GG120: 417 | GH120: 410 | GI120: 400 | GJ120: 405 | GN120: 405 | GO120: 395 | GP120: 400 | GQ120: 327.5 | GR120: 305 | GS120: 316.75 | GW120: 330 | GX120: 305 | GY120: 318 | HC120: 64 | HD120: 60 | HE120: 62
A121: 1996 | B121: 4 | C121: 12 | D121: 255 | E121: 250 | F121: 253 | G121: 180.75 | H121: 179.5 | I121: 180.25 | J121: 255 | K121: 250 | L121: 253 | P121: 213.25 | Q121: 210.25 | R121: 212 | S121: 211.5 | T121: 208.5 | U121: 210.5 | V121: 205 | W121: 202 | X121: 204 | AZ121: 224 | BA121: 220 | BB121: 222 | BF121: 224 | BG121: 220 | BH121: 222 | BI121: 230 | BJ121: 228 | BK121: 229 | CP121: 240 | CQ121: 236 | CR121: 238.33333 | CS121: 255 | CT121: 250 | CU121: 253 | CV121: 250 | CW121: 240 | CX121: 245 | CY121: 198 | CZ121: 190 | DA121: 194 | DT121: 186.75 | DU121: 185.5 | DV121: 186.25 | FJ121: 185 | FK121: 179 | FL121: 182 | FP121: 170 | FQ121: 169.25 | FR121: 169.75 | FS121: 185 | FT121: 180 | FU121: 183 | GB121: 375 | GC121: 325 | GD121: 350 | GE121: 417 | GF121: 417 | GG121: 417 | GH121: 410 | GI121: 400 | GJ121: 405 | GN121: 405 | GO121: 395 | GP121: 400 | GQ121: 330 | GR121: 305 | GS121: 318 | GW121: 333.33333 | GX121: 305 | GY121: 319.33333 | HC121: 64 | HD121: 60 | HE121: 62
A122: 1997 | B122: 1 | C122: 1 | D122: 255 | E122: 250 | F122: 253 | G122: 179 | H122: 176.33333 | I122: 177.66667 | J122: 255 | K122: 250 | L122: 253 | P122: 210 | Q122: 205 | R122: 208 | S122: 210 | T122: 205 | U122: 208 | V122: 201.25 | W122: 198.25 | X122: 200.25 | AZ122: 221 | BA122: 217.4 | BB122: 219.4 | BF122: 221 | BG122: 217.4 | BH122: 219.4 | BI122: 229.2 | BJ122: 224 | BK122: 226.6 | CP122: 240 | CQ122: 237 | CR122: 239 | CS122: 255 | CT122: 250 | CU122: 253 | CV122: 250 | CW122: 240 | CX122: 245 | CY122: 195.6 | CZ122: 188.4 | DA122: 192.4 | DT122: 185 | DU122: 181.75 | DV122: 183.5 | FJ122: 182.6 | FK122: 178.2 | FL122: 180.6 | FP122: 170 | FQ122: 167 | FR122: 169 | FS122: 183.8 | FT122: 180 | FU122: 182.2 | GB122: 375 | GC122: 325 | GD122: 350 | GE122: 417 | GF122: 417 | GG122: 417 | GH122: 410 | GI122: 402 | GJ122: 406.2 | GN122: 405 | GO122: 395 | GP122: 400 | GQ122: 333.75 | GR122: 305 | GS122: 319.75 | GW122: 343 | GX122: 305 | GY122: 324 | HC122: 64 | HD122: 60 | HE122: 62
A123: 1997 | B123: 1 | C123: 2 | D123: 255 | E123: 250 | F123: 253 | G123: 179 | H123: 177 | I123: 178 | J123: 255 | K123: 250 | L123: 253 | P123: 211 | Q123: 206 | R123: 209 | S123: 211 | T123: 206 | U123: 209 | V123: 200 | W123: 195 | X123: 198 | AZ123: 214.25 | BA123: 210 | BB123: 212.25 | BF123: 214.25 | BG123: 210 | BH123: 212.25 | BI123: 228 | BJ123: 218 | BK123: 223 | CP123: 232.5 | CQ123: 230 | CR123: 231.5 | CS123: 255 | CT123: 250 | CU123: 253 | CV123: 250 | CW123: 240 | CX123: 245 | CY123: 193.5 | CZ123: 187.5 | DA123: 190.75 | DT123: 185 | DU123: 183 | DV123: 184 | FJ123: 176 | FK123: 171.75 | FL123: 174.25 | FP123: 166.25 | FQ123: 164.5 | FR123: 165.5 | FS123: 182 | FT123: 180 | FU123: 181 | GB123: 383.75 | GC123: 328.75 | GD123: 356.5 | GE123: 421 | GF123: 421 | GG123: 421 | GH123: 417.5 | GI123: 408.75 | GJ123: 413.25 | GN123: 408.75 | GO123: 400 | GP123: 404.5 | GQ123: 345 | GR123: 305 | GS123: 325 | GW123: 355 | GX123: 307.5 | GY123: 331.25 | HC123: 64 | HD123: 60 | HE123: 62
...

Sheet Generated data
A6: Ratio €/$ | B6: 1.2
A11: Annual average data for forecasting base on S&P
A13: Year | B13: ACS CFR North Africa | C13: ACS NW EU | D13: ACS Japan | E13: ACS China | F13: S ME to CFR | G13: S North Africa to CFR Morocco | H13: DAP Bulk North Africa | I13: Petcoke CFR Morocco | J13: Clinker CFR Morocco | K13: FRET EU->MA
A14: 2026 | B14: 135 | C14: =B14-20 -> 115 | D14: 127.2 | E14: 143 | F14: 145 | G14: 296 | H14: 904 | I14: 197 | J14: 95 | K14: 21
A15: 2027 | B15: 128 | C15: =B15-20 -> 108 | D15: 103.2 | E15: 120 | F15: 132 | G15: 282 | H15: 823 | I15: 185 | J15: 102 | K15: 19
A16: 2028 | B16: 111 | C16: =B16-20 -> 91 | D16: 107.2 | E16: 115 | F16: 120 | G16: 258 | H16: 844 | I16: 173 | J16: 140 | K16: 25
A17: 2029 | B17: 103 | C17: =B17-20 -> 83 | D17: 123.2 | E17: 138 | F17: 138 | G17: 240 | H17: 804 | I17: 161 | J17: 130 | K17: 22
A18: 2030 | B18: 128 | C18: =B18-20 -> 108 | D18: 123 | E18: 140 | F18: 132 | G18: 273 | H18: 759 | I18: 183 | J18: 135 | K18: 17
A19: 2031 | B19: 125 | C19: =B19-20 -> 105 | D19: 119 | E19: 136 | F19: 140 | G19: 269 | H19: 840 | I19: 187 | J19: 122 | K19: 19
A20: 2032 | B20: 131 | C20: =B20-20 -> 111 | D20: 128 | E20: 143 | F20: 143 | G20: 284 | H20: 930 | I20: 179 | J20: 147 | K20: 21
A21: 2033 | B21: 124 | C21: =B21-20 -> 104 | D21: 131 | E21: 142 | F21: 130 | G21: 291 | H21: 922 | I21: 189 | J21: 138 | K21: 26
A22: 2034 | B22: 120 | C22: =B22-20 -> 100 | D22: 122 | E22: 132 | F22: 142 | G22: 280 | H22: 902 | I22: 194 | J22: 132 | K22: 27
A23: 2035 | B23: 127 | C23: =B23-20 -> 107 | D23: 127 | E23: 139 | F23: 137 | G23: 286 | H23: 870 | I23: 187 | J23: 139 | K23: 20

Sheet Outputs >
A1: *

Sheet Cockpit_monthly
B2: General inputs
H3: 1
N7: ACS Price vs Different Pricing Formulas | U7: GAP Between ACS Price and Pricing Formulas
B9: Formula 1: Sulfur indexing only
D11: P = a·(S*coef*conv cost) + b
B13: Parameters
B15: Formula coefficient | D15: a | E15: 1.3 | G15: b | H15: 25
B17: Sulfur index weighting | D17: Sulfur ME | E17: 0.7 | G17: Sulfur NA | H17: 0.3
B19: Cost inputs | D19: Converstion ratio | E19: 0.33 | G19: Production cost | H19: 20 | I19: $
B21: Floor&Cap | D21: Floor | E21: 110 | F21: $ | G21: Cap | H21: 220 | I21: $
B24: Formula 2: Smooth sulfur indexing
D26: P = a·(Smooth(S)*coef + conv cost) + b
B28: Parameters
B30: Formula coefficient | D30: a | E30: 1.4 | G30: b | H30: 15
B32: Sulfur index weighting | D32: Sulfur ME | E32: 0.7 | G32: Sulfur NA | H32: 0.3
B34: Cost inputs | D34: Converstion ratio | E34: 0.33 | G34: Production cost | H34: 20 | I34: $
B36: Floor&Cap | D36: Floor | E36: 110 | F36: $ | G36: Cap | H36: 220 | I36: $
B39: Formula 3: Last month indexing
D41: P = a·ACS(m-1)
B43: Parameters
B45: Formula coefficient | D45: a | E45: 1
B47: Sulfur index weighting | D47: ACS NA | E47: 0.05 | G47: ACS EU | H47: 0.75
D48: ACS JP | E48: 0 | G48: ACS CH | H48: 0.2
B50: Floor&Cap | D50: Floor | E50: 110 | F50: $ | G50: Cap | H50: 220 | I50: $
B53: Formula 4: Variation of S & DAP indexing
D55: P= ACS0*(a+ bS/S0 + cDAP/DAP0)
B57: Parameters
B59: Formula coefficient | D59: a | E59: 0.7 | G59: b | H59: 0.1 | J59: c | K59: 0.2
B61: Sulfur index weighting | D61: ACS0 | E61: 110 | F61: $ | G61: S0 | H61: 130 | I61: $ | J61: DAP0 | K61: 500 | L61: $
B63: Floor&Cap | D63: Floor | E63: 110 | F63: $ | G63: Cap | H63: 230 | I63: $
B67: Formula 5: Variation of smooth S & smooth DAP indexing
D69: P= ACS0*(a+ b*smooth(S)/S0 + c*smooth(DAP)/DAP0)
B71: Parameters
B73: Formula coefficient | D73: a | E73: 0.8 | G73: b | H73: 0.1 | J73: c | K73: 0.1
B75: Sulfur index weighting | D75: ACS0 | E75: 110 | F75: $ | G75: S0 | H75: 130 | I75: $ | J75: DAP0 | K75: 500 | L75: $
B77: Floor&Cap | D77: Floor | E77: 110 | F77: $ | G77: Cap | H77: 230 | I77: $
B81: Formula 6: Variation of Sulfur, DAP, Petcoke and Clinker indexing
D83: P= ACS0*(a+b.S/S0 +c.DAP/DAP0 +d.PC/PC0 + e.(1-CLK/CLK0))
B85: Parameters
B87: Formula coefficient | D87: a | E87: 0.6 | G87: b | H87: 0.05 | J87: c | K87: 0.2
D88: d | E88: 0.05 | G88: e | H88: 0.1
B90: Sulfur index weighting | D90: ACS0 | E90: 110 | F90: $ | G90: S0 | H90: 130 | I90: $ | J90: DAP0 | K90: 500 | L90: $
D91: PC0 | E91: 140 | F91: $ | G91: CLK0 | H91: 130 | I91: $
B93: Floor&Cap | D93: Floor | E93: =E63 -> 110 | F93: $ | G93: Cap | H93: =H63 -> 230 | I93: $

Sheet Cockpit_yearly
B2: General inputs
G3: 1
N7: CRU data forecast | U7: S&P data forecast
B9: Formula 1: Sulfur indexing only
D11: P = a·(S*coef*conv cost) + b
B13: Parameters
B15: Formula coefficient | D15: a | E15: 1.3 | G15: b | H15: 25
B17: Sulfur index weighting | D17: Sulfur ME | E17: 0.7 | G17: Sulfur NA | H17: 0.3
B19: Cost inputs | D19: Converstion ratio | E19: 0.33 | G19: Production cost | H19: 20 | I19: $
B21: Floor&Cap | D21: Floor | E21: 110 | F21: $ | G21: Cap | H21: 220 | I21: $
B24: Formula 3: Last year indexing
D26: P = a·ACS(y-1)
B28: Parameters
B30: Formula coefficient | D30: a | E30: 1
B32: Sulfur index weighting | D32: ACS NA | E32: 0.05 | G32: ACS EU | H32: 0.75
D33: ACS JP | E33: 0 | G33: ACS CH | H33: 0.2
B35: Floor&Cap | D35: Floor | E35: =E21 -> 110 | F35: $ | G35: Cap | H35: =H21 -> 220 | I35: $
B39: Formula 4: Variation of S & DAP indexing
D41: P= ACS0*(a+ bS/S0 + cDAP/DAP0)
B43: Parameters
B45: Formula coefficient | D45: a | E45: 0.7 | G45: b | H45: 0.25 | J45: c | K45: 0.05
B47: Sulfur index weighting | D47: ACS0 | E47: 110 | F47: $ | G47: S0 | H47: 130 | I47: $ | J47: DAP0 | K47: 500 | L47: $
B49: Floor&Cap | D49: Floor | E49: =E21 -> 110 | F49: $ | G49: Cap | H49: =H21 -> 220 | I49: $
B53: Formula 6: Variation of Sulfur, DAP, Cokepit and Clinker indexing
D55: P= ACS0*(a+b.S/S0 +c.DAP/DAP0 +d.PC/PC0 + e.(1-CLK/CLK0))
B57: Parameters
B59: Formula coefficient | D59: a | E59: 0.2 | G59: b | H59: 0.2 | J59: c | K59: 0.2
D60: d | E60: 0.2 | G60: e | H60: 0.2
B62: Sulfur index weighting | D62: ACS0 | E62: 110 | F62: $ | G62: S0 | H62: 130 | I62: $ | J62: DAP0 | K62: 500 | L62: $
D63: PC0 | E63: 100 | F63: $ | G63: CLK0 | H63: 100 | I63: $
B65: Floor&Cap | D65: Floor | E65: =E35 -> 110 | F65: $ | G65: Cap | H65: =H35 -> 220 | I65: $

Sheet Cockpit_Formula_7
B2: General inputs
H3: 2
N7: ACS Price S&P vs Different Pricing Formulas | U7: GAP Between ACS S&P Price and Pricing Formulas
B9: Formula 1: Fixed and sport prices combined
D11: Formula 7: P= 𝑎×𝐴𝐶𝑆f+b×(ACS_FOB_EU+c×FRET_EU_MA)
B13: Parameters
B15: Formula coefficient | D15: a | E15: 0.7 | G15: b | H15: 0.3 | J15: c | K15: 0.2
B17: Sulfur index weighting | D17: ACS Fixed | E17: 110 | G17: Inflation | H17: 0.05

Sheet Simulators

Sheet Yearly_prices_forecast_CRU
L1: Formula 1: P = a·(S*coef*conv cost) + b | O1: Formula 3: P = a·ACS(y-1) | R1: Formula 4: P= ACS0*(a+ bS/S0 + cDAP/DAP0) | U1: Formula 6: P= ACS0*(a+b.S/S0 +c.DAP/DAP0 +d.PC/PC0 + e.(1-CLK/CLK0))
L3: a | M3: =Cockpit_yearly!E15 -> 1.3 | O3: a | P3: =Cockpit_yearly!E30 -> 1 | R3: a | S3: =Cockpit_yearly!E45 -> 0.7 | U3: a | V3: =Cockpit_yearly!E59 -> 0.2
L4: b | M4: =Cockpit_yearly!H15 -> 25 | O4: Coef ACS NA | P4: =Cockpit_yearly!E32 -> 0.05 | R4: b | S4: =Cockpit_yearly!H45 -> 0.25 | U4: b | V4: =Cockpit_yearly!H59 -> 0.2
L5: Coef S ME | M5: =Cockpit_yearly!E17 -> 0.7 | O5: Coef ACS EU | P5: =Cockpit_yearly!H32 -> 0.75 | R5: c | S5: =Cockpit_yearly!K45 -> 0.05 | U5: c | V5: =Cockpit_yearly!K59 -> 0.2
L6: Coef S NA | M6: =Cockpit_yearly!H17 -> 0.3 | O6: Coef ACS Jp | P6: =Cockpit_yearly!E33 -> 0 | R6: ACS0 | S6: =Cockpit_yearly!E47 -> 110 | U6: d | V6: =Cockpit_yearly!E60 -> 0.2
L7: Conv cost | M7: 0.33 | O7: Coef ACS Ch | P7: =Cockpit_yearly!H33 -> 0.2 | R7: S0 | S7: =Cockpit_yearly!H47 -> 130 | U7: e | V7: =Cockpit_yearly!H60 -> 0.2
L8: Cout de prod | M8: 20 | O8: Floor | P8: =IF(Cockpit_yearly!$G$3=2,(Cockpit_yearly!E35)*'Generated data'!$B$6,Cockpit_yearly!E35) -> 110 | R8: DAP0 | S8: =Cockpit_yearly!K47 -> 500 | U8: ACS0 | V8: =Cockpit_yearly!E62 -> 110
L9: Floor | M9: =IF(Cockpit_yearly!$G$3=2,(Cockpit_yearly!E21)*'Generated data'!$B$6,Cockpit_yearly!E21) -> 110 | O9: Cap | P9: =IF(Cockpit_yearly!$G$3=2,(Cockpit_yearly!H35)*'Generated data'!$B$6,Cockpit_yearly!H35) -> 220 | R9: Floor | S9: =IF(Cockpit_yearly!$G$3=2,(Cockpit_yearly!E49)*'Generated data'!$B$6,Cockpit_yearly!E49) -> 110 | U9: S0 | V9: =Cockpit_yearly!H62 -> 130
L10: Cap | M10: =IF(Cockpit_yearly!$G$3=2,(Cockpit_yearly!H21)*'Generated data'!$B$6,Cockpit_yearly!H21) -> 220 | R10: Cap | S10: =IF(Cockpit_yearly!$G$3=2,(Cockpit_yearly!H49)*'Generated data'!$B$6,Cockpit_yearly!H49) -> 220 | U10: DAP0 | V10: =Cockpit_yearly!K62 -> 500
U11: PC0 | V11: =Cockpit_yearly!E63 -> 100
U12: CLK0 | V12: =Cockpit_yearly!H63 -> 100
U13: Floor | V13: =IF(Cockpit_yearly!$G$3=2,(Cockpit_yearly!E65)*'Generated data'!$B$6,Cockpit_yearly!E65) -> 110
U14: Cap | V14: =IF(Cockpit_yearly!$G$3=2,(Cockpit_yearly!H65)*'Generated data'!$B$6,Cockpit_yearly!H65) -> 220
A16: Year | B16: ACS CFR North Africa (NW Europe variation) | C16: FOB NW Europe | D16: ACS Japan | E16: ACS China | F16: S ME to CFR Morocco | G16: S North Africa to CFR Morocco | H16: DAP Bulk North Africa | I16: Petcoke CFR Morocco | J16: Clinker CFR Morocco | L16: Price | M16: Gap Formula 1_ACS | O16: Price | P16: Gap Formula 3_ACS | R16: Price | S16: Gap Formula 4_ACS2 | U16: Price | V16: Gap Formula 6_ACS
A17: 2022 | B17: =IF(Cockpit_yearly!$G$3=2,(217.961025157233)*'Generated data'!$B$6,217.961025157233) -> 217.96103 | C17: 155.41667 | D17: =89.5833333333333+77.2 -> 166.78333 | E17: 159.4 | F17: 321.6 | G17: 275.37255 | H17: 968.90196 | I17: 188 | J17: 120 | L17: =IF(Cockpit_yearly!$G$3=2,($M$3*(($M$5*G17+$M$6*F17)*$M$7+$M$8)+$M$4)*'Generated data'!$B$6,$M$3*(($M$5*G17+$M$6*F17)*$M$7+$M$8)+$M$4) -> 175.0843 | M17: =B17-L17 -> 42.876729 | O17: =IF(Cockpit_yearly!$G$3=2,($P$3*($P$4*B17+$P$5*D17+$P$6*E17+$P$7*F17))*'Generated data'!$B$6,$P$3*($P$4*B17+$P$5*D17+$P$6*E17+$P$7*F17)) -> 200.30555 | P17: =B17-O17 -> 17.655474 | R17: =IF(Cockpit_yearly!$G$3=2,($S$6*($S$3+$S$4*(G17/$S$7)+$S$5*(H17/$S$8)))*'Generated data'!$B$6,$S$6*($S$3+$S$4*(G17/$S$7)+$S$5*(H17/$S$8))) -> 145.90981 | S17: =+B17-R17 -> 72.051218 | U17: =IF(Cockpit_yearly!$G$3=2,($V$8*($V$3+$V$4*(F17/$V$9)+$V$5*(H17/$V$10)+$V$6*(I17/$V$11)+$V$7*(J17/$V$12)))*'Generated data'!$B$6,$V$8*($V$3+$V$4*(F17/$V$9)+$V$5*(H17/$V$10)+$V$6*(I17/$V$11)+$V$7*(J17/$V$12))) -> 186.8163 | V17: =+B17-U17 -> 31.144723
A18: 2023 | B18: =IF(Cockpit_yearly!$G$3=2,(41.8391672955975)*'Generated data'!$B$6,41.8391672955975) -> 41.839167 | C18: 29.833333 | D18: =77.2+11.9166666666667 -> 89.116667 | E18: 81.3 | F18: 129.3 | G18: 121 | H18: 588.72549 | I18: 140 | J18: 105 | L18: =IF(Cockpit_yearly!$G$3=2,($M$3*(($M$5*G18+$M$6*F18)*$M$7+$M$8)+$M$4)*'Generated data'!$B$6,$M$3*(($M$5*G18+$M$6*F18)*$M$7+$M$8)+$M$4) -> 103.97721 | M18: =B18-L18 -> -62.138043 | O18: =IF(Cockpit_yearly!$G$3=2,($P$3*($P$4*B18+$P$5*D18+$P$6*E18+$P$7*F18))*'Generated data'!$B$6,$P$3*($P$4*B18+$P$5*D18+$P$6*E18+$P$7*F18)) -> 94.789458 | P18: =B18-O18 -> -52.950291 | R18: =IF(Cockpit_yearly!$G$3=2,($S$6*($S$3+$S$4*(G18/$S$7)+$S$5*(H18/$S$8)))*'Generated data'!$B$6,$S$6*($S$3+$S$4*(G18/$S$7)+$S$5*(H18/$S$8))) -> 109.07213 | S18: =+B18-R18 -> -67.232967 | U18: =IF(Cockpit_yearly!$G$3=2,($V$8*($V$3+$V$4*(F18/$V$9)+$V$5*(H18/$V$10)+$V$6*(I18/$V$11)+$V$7*(J18/$V$12)))*'Generated data'!$B$6,$V$8*($V$3+$V$4*(F18/$V$9)+$V$5*(H18/$V$10)+$V$6*(I18/$V$11)+$V$7*(J18/$V$12))) -> 123.68546 | V18: =+B18-U18 -> -81.846293
A19: 2024 | B19: =IF(Cockpit_yearly!$G$3=2,(105.416002515723)*'Generated data'!$B$6,105.416002515723) -> 105.416 | C19: 75.166667 | D19: =77.2+25.9166666666667 -> 103.11667 | E19: 110.5 | F19: 142 | G19: 105.44231 | H19: 585.54902 | I19: 97 | J19: 98 | L19: =IF(Cockpit_yearly!$G$3=2,($M$3*(($M$5*G19+$M$6*F19)*$M$7+$M$8)+$M$4)*'Generated data'!$B$6,$M$3*(($M$5*G19+$M$6*F19)*$M$7+$M$8)+$M$4) -> 100.93973 | M19: =B19-L19 -> 4.4762775 | O19: =IF(Cockpit_yearly!$G$3=2,($P$3*($P$4*B19+$P$5*D19+$P$6*E19+$P$7*F19))*'Generated data'!$B$6,$P$3*($P$4*B19+$P$5*D19+$P$6*E19+$P$7*F19)) -> 111.0083 | P19: =B19-O19 -> -5.5922976 | R19: =IF(Cockpit_yearly!$G$3=2,($S$6*($S$3+$S$4*(G19/$S$7)+$S$5*(H19/$S$8)))*'Generated data'!$B$6,$S$6*($S$3+$S$4*(G19/$S$7)+$S$5*(H19/$S$8))) -> 105.74614 | S19: =+B19-R19 -> -0.33014025 | U19: =IF(Cockpit_yearly!$G$3=2,($V$8*($V$3+$V$4*(F19/$V$9)+$V$5*(H19/$V$10)+$V$6*(I19/$V$11)+$V$7*(J19/$V$12)))*'Generated data'!$B$6,$V$8*($V$3+$V$4*(F19/$V$9)+$V$5*(H19/$V$10)+$V$6*(I19/$V$11)+$V$7*(J19/$V$12))) -> 114.69493 | V19: =+B19-U19 -> -9.2789236
A20: 2025 | B20: =IF(Cockpit_yearly!$G$3=2,(142.94)*'Generated data'!$B$6,142.94) -> 142.94 | C20: 101.92308 | D20: =77.2+49 -> 126.2 | E20: 145.4 | F20: 334.1 | G20: 248.57692 | H20: 711.31581 | I20: 96 | J20: 96 | L20: =IF(Cockpit_yearly!$G$3=2,($M$3*(($M$5*G20+$M$6*F20)*$M$7+$M$8)+$M$4)*'Generated data'!$B$6,$M$3*(($M$5*G20+$M$6*F20)*$M$7+$M$8)+$M$4) -> 168.64632 | M20: =B20-L20 -> -25.70632 | O20: =IF(Cockpit_yearly!$G$3=2,($P$3*($P$4*B20+$P$5*D20+$P$6*E20+$P$7*F20))*'Generated data'!$B$6,$P$3*($P$4*B20+$P$5*D20+$P$6*E20+$P$7*F20)) -> 168.617 | P20: =B20-O20 -> -25.677 | R20: =IF(Cockpit_yearly!$G$3=2,($S$6*($S$3+$S$4*(G20/$S$7)+$S$5*(H20/$S$8)))*'Generated data'!$B$6,$S$6*($S$3+$S$4*(G20/$S$7)+$S$5*(H20/$S$8))) -> 137.40805 | S20: =+B20-R20 -> 5.5319462 | U20: =IF(Cockpit_yearly!$G$3=2,($V$8*($V$3+$V$4*(F20/$V$9)+$V$5*(H20/$V$10)+$V$6*(I20/$V$11)+$V$7*(J20/$V$12)))*'Generated data'!$B$6,$V$8*($V$3+$V$4*(F20/$V$9)+$V$5*(H20/$V$10)+$V$6*(I20/$V$11)+$V$7*(J20/$V$12))) -> 152.0779 | V20: =+B20-U20 -> -9.1378957
A21: 2026 | B21: =IF(Cockpit_yearly!$G$3=2,(117.077877358491)*'Generated data'!$B$6,117.077877358491) -> 117.07788 | C21: 83.482143 | D21: =77.2+89.6708333333333 -> 166.87083 | E21: 143.65417 | F21: 384.95976 | G21: 364.31322 | H21: 681.48333 | I21: 98 | J21: 99 | L21: =IF(Cockpit_yearly!$G$3=2,($M$3*(($M$5*G21+$M$6*F21)*$M$7+$M$8)+$M$4)*'Generated data'!$B$6,$M$3*(($M$5*G21+$M$6*F21)*$M$7+$M$8)+$M$4) -> 209.94758 | M21: =B21-L21 -> -92.869704 | O21: =IF(Cockpit_yearly!$G$3=2,($P$3*($P$4*B21+$P$5*D21+$P$6*E21+$P$7*F21))*'Generated data'!$B$6,$P$3*($P$4*B21+$P$5*D21+$P$6*E21+$P$7*F21)) -> 207.99897 | P21: =B21-O21 -> -90.921094 | R21: =IF(Cockpit_yearly!$G$3=2,($S$6*($S$3+$S$4*(G21/$S$7)+$S$5*(H21/$S$8)))*'Generated data'!$B$6,$S$6*($S$3+$S$4*(G21/$S$7)+$S$5*(H21/$S$8))) -> 161.56257 | S21: =+B21-R21 -> -44.484697 | U21: =IF(Cockpit_yearly!$G$3=2,($V$8*($V$3+$V$4*(F21/$V$9)+$V$5*(H21/$V$10)+$V$6*(I21/$V$11)+$V$7*(J21/$V$12)))*'Generated data'!$B$6,$V$8*($V$3+$V$4*(F21/$V$9)+$V$5*(H21/$V$10)+$V$6*(I21/$V$11)+$V$7*(J21/$V$12))) -> 160.4723 | V21: =+B21-U21 -> -43.394426
A22: 2027 | B22: =IF(Cockpit_yearly!$G$3=2,(113.497579380938)*'Generated data'!$B$6,113.497579380938) -> 113.49758 | C22: 80.929219 | D22: =77.2+59.9292186499674 -> 137.12922 | E22: 125.32922 | F22: 274.13203 | G22: 253.30844 | H22: 629.38889 | I22: 101 | J22: 102 | L22: =IF(Cockpit_yearly!$G$3=2,($M$3*(($M$5*G22+$M$6*F22)*$M$7+$M$8)+$M$4)*'Generated data'!$B$6,$M$3*(($M$5*G22+$M$6*F22)*$M$7+$M$8)+$M$4) -> 162.34932 | M22: =B22-L22 -> -48.851736 | O22: =IF(Cockpit_yearly!$G$3=2,($P$3*($P$4*B22+$P$5*D22+$P$6*E22+$P$7*F22))*'Generated data'!$B$6,$P$3*($P$4*B22+$P$5*D22+$P$6*E22+$P$7*F22)) -> 163.3482 | P22: =B22-O22 -> -49.850619 | R22: =IF(Cockpit_yearly!$G$3=2,($S$6*($S$3+$S$4*(G22/$S$7)+$S$5*(H22/$S$8)))*'Generated data'!$B$6,$S$6*($S$3+$S$4*(G22/$S$7)+$S$5*(H22/$S$8))) -> 137.50775 | S22: =+B22-R22 -> -24.010175 | U22: =IF(Cockpit_yearly!$G$3=2,($V$8*($V$3+$V$4*(F22/$V$9)+$V$5*(H22/$V$10)+$V$6*(I22/$V$11)+$V$7*(J22/$V$12)))*'Generated data'!$B$6,$V$8*($V$3+$V$4*(F22/$V$9)+$V$5*(H22/$V$10)+$V$6*(I22/$V$11)+$V$7*(J22/$V$12))) -> 140.74469 | V22: =+B22-U22 -> -27.247106
A23: 2028 | B23: =IF(Cockpit_yearly!$G$3=2,(93.4642017872692)*'Generated data'!$B$6,93.4642017872692) -> 93.464202 | C23: 66.644459 | D23: =77.2+54.6444594117659 -> 131.84446 | E23: 120.04446 | F23: 246.8432 | G23: 226.23543 | H23: 594.50002 | I23: 104 | J23: 105 | L23: =IF(Cockpit_yearly!$G$3=2,($M$3*(($M$5*G23+$M$6*F23)*$M$7+$M$8)+$M$4)*'Generated data'!$B$6,$M$3*(($M$5*G23+$M$6*F23)*$M$7+$M$8)+$M$4) -> 150.70722 | M23: =B23-L23 -> -57.243016 | O23: =IF(Cockpit_yearly!$G$3=2,($P$3*($P$4*B23+$P$5*D23+$P$6*E23+$P$7*F23))*'Generated data'!$B$6,$P$3*($P$4*B23+$P$5*D23+$P$6*E23+$P$7*F23)) -> 152.92519 | P23: =B23-O23 -> -59.460993 | R23: =IF(Cockpit_yearly!$G$3=2,($S$6*($S$3+$S$4*(G23/$S$7)+$S$5*(H23/$S$8)))*'Generated data'!$B$6,$S$6*($S$3+$S$4*(G23/$S$7)+$S$5*(H23/$S$8))) -> 131.39699 | S23: =+B23-R23 -> -37.932792 | U23: =IF(Cockpit_yearly!$G$3=2,($V$8*($V$3+$V$4*(F23/$V$9)+$V$5*(H23/$V$10)+$V$6*(I23/$V$11)+$V$7*(J23/$V$12)))*'Generated data'!$B$6,$V$8*($V$3+$V$4*(F23/$V$9)+$V$5*(H23/$V$10)+$V$6*(I23/$V$11)+$V$7*(J23/$V$12))) -> 135.91147 | V23: =+B23-U23 -> -42.447264
A24: 2029 | B24: =IF(Cockpit_yearly!$G$3=2,(91.7111285410652)*'Generated data'!$B$6,91.7111285410652) -> 91.711129 | C24: 65.394434 | D24: =77.2+48.3944340911794 -> 125.59443 | E24: 113.79443 | F24: 239.17879 | G24: 218.64587 | H24: 561.00871 | I24: 107 | J24: 108 | L24: =IF(Cockpit_yearly!$G$3=2,($M$3*(($M$5*G24+$M$6*F24)*$M$7+$M$8)+$M$4)*'Generated data'!$B$6,$M$3*(($M$5*G24+$M$6*F24)*$M$7+$M$8)+$M$4) -> 147.44166 | M24: =B24-L24 -> -55.730536 | O24: =IF(Cockpit_yearly!$G$3=2,($P$3*($P$4*B24+$P$5*D24+$P$6*E24+$P$7*F24))*'Generated data'!$B$6,$P$3*($P$4*B24+$P$5*D24+$P$6*E24+$P$7*F24)) -> 146.61714 | P24: =B24-O24 -> -54.906012 | R24: =IF(Cockpit_yearly!$G$3=2,($S$6*($S$3+$S$4*(G24/$S$7)+$S$5*(H24/$S$8)))*'Generated data'!$B$6,$S$6*($S$3+$S$4*(G24/$S$7)+$S$5*(H24/$S$8))) -> 129.42311 | S24: =+B24-R24 -> -37.711978 | U24: =IF(Cockpit_yearly!$G$3=2,($V$8*($V$3+$V$4*(F24/$V$9)+$V$5*(H24/$V$10)+$V$6*(I24/$V$11)+$V$7*(J24/$V$12)))*'Generated data'!$B$6,$V$8*($V$3+$V$4*(F24/$V$9)+$V$5*(H24/$V$10)+$V$6*(I24/$V$11)+$V$7*(J24/$V$12))) -> 134.46079 | V24: =+B24-U24 -> -42.749666
A25: 2030 | B25: =IF(Cockpit_yearly!$G$3=2,(86.1626689361307)*'Generated data'!$B$6,86.1626689361307) -> 86.162669 | C25: 61.438116 | D25: =77.2+42.4381162297108 -> 119.63812 | E25: 107.83812 | F25: 243.75994 | G25: 223.21409 | H25: 538.7978 | I25: 110 | J25: 112 | L25: =IF(Cockpit_yearly!$G$3=2,($M$3*(($M$5*G25+$M$6*F25)*$M$7+$M$8)+$M$4)*'Generated data'!$B$6,$M$3*(($M$5*G25+$M$6*F25)*$M$7+$M$8)+$M$4) -> 149.40309 | M25: =B25-L25 -> -63.240425 | O25: =IF(Cockpit_yearly!$G$3=2,($P$3*($P$4*B25+$P$5*D25+$P$6*E25+$P$7*F25))*'Generated data'!$B$6,$P$3*($P$4*B25+$P$5*D25+$P$6*E25+$P$7*F25)) -> 142.78871 | P25: =B25-O25 -> -56.626039 | R25: =IF(Cockpit_yearly!$G$3=2,($S$6*($S$3+$S$4*(G25/$S$7)+$S$5*(H25/$S$8)))*'Generated data'!$B$6,$S$6*($S$3+$S$4*(G25/$S$7)+$S$5*(H25/$S$8))) -> 130.14514 | S25: =+B25-R25 -> -43.982472 | U25: =IF(Cockpit_yearly!$G$3=2,($V$8*($V$3+$V$4*(F25/$V$9)+$V$5*(H25/$V$10)+$V$6*(I25/$V$11)+$V$7*(J25/$V$12)))*'Generated data'!$B$6,$V$8*($V$3+$V$4*(F25/$V$9)+$V$5*(H25/$V$10)+$V$6*(I25/$V$11)+$V$7*(J25/$V$12))) -> 135.79878 | V25: =+B25-U25 -> -49.636116

Sheet Yearly_prices_forecast_S&P
O1: Formula 1: P = a·(S*coef*conv cost) + b | R1: Formula 3: P = a·ACS(y-1) | U1: Formula 4: P= ACS0*(a+ bS/S0 + cDAP/DAP0) | X1: Formula 6: P= ACS0*(a+b.S/S0 +c.DAP/DAP0 +d.PC/PC0 + e.(1-CLK/CLK0))
O3: a | P3: =Cockpit_yearly!E15 -> 1.3 | R3: a | S3: =Cockpit_yearly!E30 -> 1 | U3: a | V3: =Cockpit_yearly!E45 -> 0.7 | X3: a | Y3: =Cockpit_yearly!E59 -> 0.2
O4: b | P4: =Cockpit_yearly!H15 -> 25 | R4: Coef ACS NA | S4: =Cockpit_yearly!E32 -> 0.05 | U4: b | V4: =Cockpit_yearly!H45 -> 0.25 | X4: b | Y4: =Cockpit_yearly!H59 -> 0.2
O5: Coef S ME | P5: =Cockpit_yearly!E17 -> 0.7 | R5: Coef ACS EU | S5: =Cockpit_yearly!H32 -> 0.75 | U5: c | V5: =Cockpit_yearly!K45 -> 0.05 | X5: c | Y5: =Cockpit_yearly!K59 -> 0.2
O6: Coef S NA | P6: =Cockpit_yearly!H17 -> 0.3 | R6: Coef ACS Jp | S6: =Cockpit_yearly!E33 -> 0 | U6: ACS0 | V6: =Cockpit_yearly!E47 -> 110 | X6: d | Y6: =Cockpit_yearly!E60 -> 0.2
O7: Conv cost | P7: 0.33 | R7: Coef ACS Ch | S7: =Cockpit_yearly!H33 -> 0.2 | U7: S0 | V7: =Cockpit_yearly!H47 -> 130 | X7: e | Y7: =Cockpit_yearly!H60 -> 0.2
O8: Cout de prod | P8: 20 | R8: Floor | S8: =IF(Cockpit_yearly!$G$3=2,(Cockpit_yearly!E35)*'Generated data'!$B$6,Cockpit_yearly!E35) -> 110 | U8: DAP0 | V8: =Cockpit_yearly!K47 -> 500 | X8: ACS0 | Y8: =Cockpit_yearly!E62 -> 110
O9: Floor | P9: =IF(Cockpit_yearly!$G$3=2,(Cockpit_yearly!E21)*'Generated data'!$B$6,Cockpit_yearly!E21) -> 110 | R9: Cap | S9: =IF(Cockpit_yearly!$G$3=2,(Cockpit_yearly!H35)*'Generated data'!$B$6,Cockpit_yearly!H35) -> 220 | U9: Floor | V9: =IF(Cockpit_yearly!$G$3=2,(Cockpit_yearly!E49)*'Generated data'!$B$6,Cockpit_yearly!E49) -> 110 | X9: S0 | Y9: =Cockpit_yearly!H62 -> 130
O10: Cap | P10: =IF(Cockpit_yearly!$G$3=2,(Cockpit_yearly!H21)*'Generated data'!$B$6,Cockpit_yearly!H21) -> 220 | U10: Cap | V10: =IF(Cockpit_yearly!$G$3=2,(Cockpit_yearly!H49)*'Generated data'!$B$6,Cockpit_yearly!H49) -> 220 | X10: DAP0 | Y10: =Cockpit_yearly!K62 -> 500
X11: PC0 | Y11: =Cockpit_yearly!E63 -> 100
X12: CLK0 | Y12: =Cockpit_yearly!H63 -> 100
X13: Floor | Y13: =IF(Cockpit_yearly!$G$3=2,(Cockpit_yearly!E65)*'Generated data'!$B$6,Cockpit_yearly!E65) -> 110
X14: Cap | Y14: =IF(Cockpit_yearly!$G$3=2,(Cockpit_yearly!H65)*'Generated data'!$B$6,Cockpit_yearly!H65) -> 220
A16: Year | B16: ACS CFR North Africa (NW Europe+Freight) | C16: ACS CFR North Africa (NW Europe variation) | D16: FOB NW Europe | E16: ACS Japan | F16: ACS China | G16: S ME to CFR Morocco | H16: S North Africa to CFR Morocco | I16: DAP Bulk North Africa | J16: Floor | K16: Gap | L16: Petcoke CFR Morocco | M16: Clinker CFR Morocco | O16: Price | P16: Gap Formula 1_ACS | R16: Price | S16: Gap Formula 3_ACS | U16: Price | V16: Gap Formula 4_ACS | X16: Price | Y16: Gap Formula 6_ACS
A17: 2022 | B17: =+D17+20 -> 175.41667 | C17: =IF(Cockpit_yearly!$G$3=2,(217.961025157233)*'Generated data'!$B$6,217.961025157233) -> 217.96103 | D17: 155.41667 | E17: =89.5833333333333+77.2 -> 166.78333 | F17: 159.4 | G17: 321.6 | H17: 275.37255 | I17: 968.90196 | J17: =$P$9 -> 110 | K17: =$P$10 -> 220 | L17: 188 | M17: 120 | O17: =IF(Cockpit_yearly!$G$3=2,($P$3*(($P$5*H17+$P$6*G17)*$P$7+$P$8)+$P$4)*'Generated data'!$B$6,$P$3*(($P$5*H17+$P$6*G17)*$P$7+$P$8)+$P$4) -> 175.0843 | P17: =C17-O17 -> 42.876729 | R17: =$S$3*($S$4*B17+$S$5*E17+$S$6*F17+$S$7*G17) -> 198.17833 | S17: =C17-R17 -> 19.782692 | U17: =IF(Cockpit_yearly!$G$3=2,($V$6*($V$3+$V$4*(H17/$V$7)+$V$5*(I17/$V$8)))*'Generated data'!$B$6,$V$6*($V$3+$V$4*(H17/$V$7)+$V$5*(I17/$V$8))) -> 145.90981 | V17: =+C17-U17 -> 72.051218 | X17: =IF(Cockpit_yearly!$G$3=2,($Y$8*($Y$3+$Y$4*(G17/$Y$9)+$Y$5*(I17/$Y$10)+$Y$6*(L17/$Y$11)+$Y$7*(1-M17/$Y$12)))*'Generated data'!$B$6,$Y$8*($Y$3+$Y$4*(G17/$Y$9)+$Y$5*(I17/$Y$10)+$Y$6*(L17/$Y$11)+$Y$7*(1-M17/$Y$12))) -> 156.0163 | Y17: =+C17-X17 -> 61.944723
A18: 2023 | B18: =+D18+20 -> 49.833333 | C18: =IF(Cockpit_yearly!$G$3=2,(41.8391672955975)*'Generated data'!$B$6,41.8391672955975) -> 41.839167 | D18: 29.833333 | E18: =77.2+11.9166666666667 -> 89.116667 | F18: 81.3 | G18: 129.3 | H18: 121 | I18: 588.72549 | J18: =$P$9 -> 110 | K18: =$P$10 -> 220 | L18: 140 | M18: 105 | O18: =IF(Cockpit_yearly!$G$3=2,($P$3*(($P$5*H18+$P$6*G18)*$P$7+$P$8)+$P$4)*'Generated data'!$B$6,$P$3*(($P$5*H18+$P$6*G18)*$P$7+$P$8)+$P$4) -> 103.97721 | P18: =C18-O18 -> -62.138043 | R18: =$S$3*($S$4*B18+$S$5*E18+$S$6*F18+$S$7*G18) -> 95.189167 | S18: =C18-R18 -> -53.349999 | U18: =IF(Cockpit_yearly!$G$3=2,($V$6*($V$3+$V$4*(H18/$V$7)+$V$5*(I18/$V$8)))*'Generated data'!$B$6,$V$6*($V$3+$V$4*(H18/$V$7)+$V$5*(I18/$V$8))) -> 109.07213 | V18: =+C18-U18 -> -67.232967 | X18: =IF(Cockpit_yearly!$G$3=2,($Y$8*($Y$3+$Y$4*(G18/$Y$9)+$Y$5*(I18/$Y$10)+$Y$6*(L18/$Y$11)+$Y$7*(1-M18/$Y$12)))*'Generated data'!$B$6,$Y$8*($Y$3+$Y$4*(G18/$Y$9)+$Y$5*(I18/$Y$10)+$Y$6*(L18/$Y$11)+$Y$7*(1-M18/$Y$12))) -> 99.48546 | Y18: =+C18-X18 -> -57.646293
A19: 2024 | B19: =+D19+20 -> 95.166667 | C19: =IF(Cockpit_yearly!$G$3=2,(105.416002515723)*'Generated data'!$B$6,105.416002515723) -> 105.416 | D19: 75.166667 | E19: =77.2+25.9166666666667 -> 103.11667 | F19: 110.5 | G19: 142 | H19: 105.44231 | I19: 585.54902 | J19: =$P$9 -> 110 | K19: =$P$10 -> 220 | L19: 97 | M19: 98 | O19: =IF(Cockpit_yearly!$G$3=2,($P$3*(($P$5*H19+$P$6*G19)*$P$7+$P$8)+$P$4)*'Generated data'!$B$6,$P$3*(($P$5*H19+$P$6*G19)*$P$7+$P$8)+$P$4) -> 100.93973 | P19: =C19-O19 -> 4.4762775 | R19: =$S$3*($S$4*B19+$S$5*E19+$S$6*F19+$S$7*G19) -> 110.49583 | S19: =C19-R19 -> -5.0798308 | U19: =IF(Cockpit_yearly!$G$3=2,($V$6*($V$3+$V$4*(H19/$V$7)+$V$5*(I19/$V$8)))*'Generated data'!$B$6,$V$6*($V$3+$V$4*(H19/$V$7)+$V$5*(I19/$V$8))) -> 105.74614 | V19: =+C19-U19 -> -0.33014025 | X19: =IF(Cockpit_yearly!$G$3=2,($Y$8*($Y$3+$Y$4*(G19/$Y$9)+$Y$5*(I19/$Y$10)+$Y$6*(L19/$Y$11)+$Y$7*(1-M19/$Y$12)))*'Generated data'!$B$6,$Y$8*($Y$3+$Y$4*(G19/$Y$9)+$Y$5*(I19/$Y$10)+$Y$6*(L19/$Y$11)+$Y$7*(1-M19/$Y$12))) -> 93.574926 | Y19: =+C19-X19 -> 11.841076
A20: 2025 | B20: =+D20+20 -> 121.92308 | C20: =IF(Cockpit_yearly!$G$3=2,(142.94)*'Generated data'!$B$6,142.94) -> 142.94 | D20: 101.92308 | E20: =77.2+49 -> 126.2 | F20: 145.4 | G20: 334.1 | H20: 248.57692 | I20: 711.31581 | J20: =$P$9 -> 110 | K20: =$P$10 -> 220 | L20: 96 | M20: 96 | O20: =IF(Cockpit_yearly!$G$3=2,($P$3*(($P$5*H20+$P$6*G20)*$P$7+$P$8)+$P$4)*'Generated data'!$B$6,$P$3*(($P$5*H20+$P$6*G20)*$P$7+$P$8)+$P$4) -> 168.64632 | P20: =C20-O20 -> -25.70632 | R20: =$S$3*($S$4*B20+$S$5*E20+$S$6*F20+$S$7*G20) -> 167.56615 | S20: =C20-R20 -> -24.626154 | U20: =IF(Cockpit_yearly!$G$3=2,($V$6*($V$3+$V$4*(H20/$V$7)+$V$5*(I20/$V$8)))*'Generated data'!$B$6,$V$6*($V$3+$V$4*(H20/$V$7)+$V$5*(I20/$V$8))) -> 137.40805 | V20: =+C20-U20 -> 5.5319462 | X20: =IF(Cockpit_yearly!$G$3=2,($Y$8*($Y$3+$Y$4*(G20/$Y$9)+$Y$5*(I20/$Y$10)+$Y$6*(L20/$Y$11)+$Y$7*(1-M20/$Y$12)))*'Generated data'!$B$6,$Y$8*($Y$3+$Y$4*(G20/$Y$9)+$Y$5*(I20/$Y$10)+$Y$6*(L20/$Y$11)+$Y$7*(1-M20/$Y$12))) -> 131.8379 | Y20: =+C20-X20 -> 11.102104
A21: 2026 | B21: =+D21+20 -> 83.444503 | C21: =IF(Cockpit_yearly!$G$3=2,('Generated data'!B14)*'Generated data'!$B$6,'Generated data'!B14) -> 135 | D21: 63.444503 | E21: 127.2 | F21: 126.8497 | G21: 102 | H21: 118 | I21: 681.48333 | J21: =$P$9 -> 110 | K21: =$P$10 -> 220 | L21: 95.66 | M21: 129 | O21: =IF(Cockpit_yearly!$G$3=2,($P$3*(($P$5*H21+$P$6*G21)*$P$7+$P$8)+$P$4)*'Generated data'!$B$6,$P$3*(($P$5*H21+$P$6*G21)*$P$7+$P$8)+$P$4) -> 99.5628 | P21: =C21-O21 -> 35.4372 | R21: =$S$3*($S$4*B21+$S$5*E21+$S$6*F21+$S$7*G21) -> 119.97223 | S21: =C21-R21 -> 15.027775 | U21: =IF(Cockpit_yearly!$G$3=2,($V$6*($V$3+$V$4*(H21/$V$7)+$V$5*(I21/$V$8)))*'Generated data'!$B$6,$V$6*($V$3+$V$4*(H21/$V$7)+$V$5*(I21/$V$8))) -> 109.45786 | V21: =+C21-U21 -> 25.542145 | X21: =IF(Cockpit_yearly!$G$3=2,($Y$8*($Y$3+$Y$4*(G21/$Y$9)+$Y$5*(I21/$Y$10)+$Y$6*(L21/$Y$11)+$Y$7*(1-M21/$Y$12)))*'Generated data'!$B$6,$Y$8*($Y$3+$Y$4*(G21/$Y$9)+$Y$5*(I21/$Y$10)+$Y$6*(L21/$Y$11)+$Y$7*(1-M21/$Y$12))) -> 83.912005 | Y21: =+C21-X21 -> 51.087995
A22: 2027 | B22: =+D22+20 -> 83.869938 | C22: =IF(Cockpit_yearly!$G$3=2,('Generated data'!B15)*'Generated data'!$B$6,'Generated data'!B15) -> 128 | D22: 63.869938 | E22: 103.2 | F22: 103.64977 | G22: 108 | H22: 120 | I22: 629.38889 | J22: =$P$9 -> 110 | K22: =$P$10 -> 220 | L22: 70.34 | M22: 208.04 | O22: =IF(Cockpit_yearly!$G$3=2,($P$3*(($P$5*H22+$P$6*G22)*$P$7+$P$8)+$P$4)*'Generated data'!$B$6,$P$3*(($P$5*H22+$P$6*G22)*$P$7+$P$8)+$P$4) -> 100.9356 | P22: =C22-O22 -> 27.0644 | R22: =$S$3*($S$4*B22+$S$5*E22+$S$6*F22+$S$7*G22) -> 103.1935 | S22: =C22-R22 -> 24.806503 | U22: =IF(Cockpit_yearly!$G$3=2,($V$6*($V$3+$V$4*(H22/$V$7)+$V$5*(I22/$V$8)))*'Generated data'!$B$6,$V$6*($V$3+$V$4*(H22/$V$7)+$V$5*(I22/$V$8))) -> 109.30789 | V22: =+C22-U22 -> 18.692107 | X22: =IF(Cockpit_yearly!$G$3=2,($Y$8*($Y$3+$Y$4*(G22/$Y$9)+$Y$5*(I22/$Y$10)+$Y$6*(L22/$Y$11)+$Y$7*(1-M22/$Y$12)))*'Generated data'!$B$6,$Y$8*($Y$3+$Y$4*(G22/$Y$9)+$Y$5*(I22/$Y$10)+$Y$6*(L22/$Y$11)+$Y$7*(1-M22/$Y$12))) -> 59.676034 | Y22: =+C22-X22 -> 68.323966
A23: 2028 | B23: =+D23+20 -> 90.378682 | C23: =IF(Cockpit_yearly!$G$3=2,('Generated data'!B16)*'Generated data'!$B$6,'Generated data'!B16) -> 111 | D23: 70.378682 | E23: 107.2 | F23: 108.01244 | G23: 127 | H23: 140 | I23: 594.50002 | J23: =$P$9 -> 110 | K23: =$P$10 -> 220 | L23: 113.5 | M23: 164.88 | O23: =IF(Cockpit_yearly!$G$3=2,($P$3*(($P$5*H23+$P$6*G23)*$P$7+$P$8)+$P$4)*'Generated data'!$B$6,$P$3*(($P$5*H23+$P$6*G23)*$P$7+$P$8)+$P$4) -> 109.3869 | P23: =C23-O23 -> 1.6131 | R23: =$S$3*($S$4*B23+$S$5*E23+$S$6*F23+$S$7*G23) -> 110.31893 | S23: =C23-R23 -> 0.68106589 | U23: =IF(Cockpit_yearly!$G$3=2,($V$6*($V$3+$V$4*(H23/$V$7)+$V$5*(I23/$V$8)))*'Generated data'!$B$6,$V$6*($V$3+$V$4*(H23/$V$7)+$V$5*(I23/$V$8))) -> 113.15488 | V23: =+C23-U23 -> -2.1548849 | X23: =IF(Cockpit_yearly!$G$3=2,($Y$8*($Y$3+$Y$4*(G23/$Y$9)+$Y$5*(I23/$Y$10)+$Y$6*(L23/$Y$11)+$Y$7*(1-M23/$Y$12)))*'Generated data'!$B$6,$Y$8*($Y$3+$Y$4*(G23/$Y$9)+$Y$5*(I23/$Y$10)+$Y$6*(L23/$Y$11)+$Y$7*(1-M23/$Y$12))) -> 80.346709 | Y23: =+C23-X23 -> 30.653291
A24: 2029 | B24: =+D24+20 -> 114.5227 | C24: =IF(Cockpit_yearly!$G$3=2,('Generated data'!B17)*'Generated data'!$B$6,'Generated data'!B17) -> 103 | D24: 94.522701 | E24: 123.2 | F24: 123.64018 | G24: 193.7 | H24: 170 | I24: 561.00871 | J24: =$P$9 -> 110 | K24: =$P$10 -> 220 | L24: 125.5 | M24: 152.88 | O24: =IF(Cockpit_yearly!$G$3=2,($P$3*(($P$5*H24+$P$6*G24)*$P$7+$P$8)+$P$4)*'Generated data'!$B$6,$P$3*(($P$5*H24+$P$6*G24)*$P$7+$P$8)+$P$4) -> 126.98019 | P24: =C24-O24 -> -23.98019 | R24: =$S$3*($S$4*B24+$S$5*E24+$S$6*F24+$S$7*G24) -> 136.86614 | S24: =C24-R24 -> -33.866135 | U24: =IF(Cockpit_yearly!$G$3=2,($V$6*($V$3+$V$4*(H24/$V$7)+$V$5*(I24/$V$8)))*'Generated data'!$B$6,$V$6*($V$3+$V$4*(H24/$V$7)+$V$5*(I24/$V$8))) -> 119.13263 | V24: =+C24-U24 -> -16.132634 | X24: =IF(Cockpit_yearly!$G$3=2,($Y$8*($Y$3+$Y$4*(G24/$Y$9)+$Y$5*(I24/$Y$10)+$Y$6*(L24/$Y$11)+$Y$7*(1-M24/$Y$12)))*'Generated data'!$B$6,$Y$8*($Y$3+$Y$4*(G24/$Y$9)+$Y$5*(I24/$Y$10)+$Y$6*(L24/$Y$11)+$Y$7*(1-M24/$Y$12))) -> 95.440783 | Y24: =+C24-X24 -> 7.5592169
A25: 2030 | B25: =+D25+20 -> 139.81281 | C25: =IF(Cockpit_yearly!$G$3=2,('Generated data'!B18)*'Generated data'!$B$6,'Generated data'!B18) -> 128 | D25: 119.81281 | E25: 139.2 | F25: 140.00267 | G25: 216.7 | H25: 195 | I25: 538.7978 | J25: =$P$9 -> 110 | K25: =$P$10 -> 220 | L25: 137.5 | M25: 140.88 | O25: =IF(Cockpit_yearly!$G$3=2,($P$3*(($P$5*H25+$P$6*G25)*$P$7+$P$8)+$P$4)*'Generated data'!$B$6,$P$3*(($P$5*H25+$P$6*G25)*$P$7+$P$8)+$P$4) -> 137.44779 | P25: =C25-O25 -> -9.44779 | R25: =$S$3*($S$4*B25+$S$5*E25+$S$6*F25+$S$7*G25) -> 154.73064 | S25: =C25-R25 -> -26.730641 | U25: =IF(Cockpit_yearly!$G$3=2,($V$6*($V$3+$V$4*(H25/$V$7)+$V$5*(I25/$V$8)))*'Generated data'!$B$6,$V$6*($V$3+$V$4*(H25/$V$7)+$V$5*(I25/$V$8))) -> 124.17678 | V25: =+C25-U25 -> 3.8232242 | X25: =IF(Cockpit_yearly!$G$3=2,($Y$8*($Y$3+$Y$4*(G25/$Y$9)+$Y$5*(I25/$Y$10)+$Y$6*(L25/$Y$11)+$Y$7*(1-M25/$Y$12)))*'Generated data'!$B$6,$Y$8*($Y$3+$Y$4*(G25/$Y$9)+$Y$5*(I25/$Y$10)+$Y$6*(L25/$Y$11)+$Y$7*(1-M25/$Y$12))) -> 103.63581 | Y25: =+C25-X25 -> 24.364189
A26: 2031 | B26: =+D26+20 -> 151.60803 | C26: =IF(Cockpit_yearly!$G$3=2,('Generated data'!B19)*'Generated data'!$B$6,'Generated data'!B19) -> 125 | D26: 131.60803 | E26: 146.2 | F26: 147.75648 | G26: 236.7 | H26: 216 | I26: 592 | J26: =$P$9 -> 110 | K26: =$P$10 -> 220 | L26: 149.5 | M26: 128.88 | O26: =IF(Cockpit_yearly!$G$3=2,($P$3*(($P$5*H26+$P$6*G26)*$P$7+$P$8)+$P$4)*'Generated data'!$B$6,$P$3*(($P$5*H26+$P$6*G26)*$P$7+$P$8)+$P$4) -> 146.32809 | P26: =C26-O26 -> -21.32809 | R26: =$S$3*($S$4*B26+$S$5*E26+$S$6*F26+$S$7*G26) -> 164.5704 | S26: =C26-R26 -> -39.570402 | U26: =IF(Cockpit_yearly!$G$3=2,($V$6*($V$3+$V$4*(H26/$V$7)+$V$5*(I26/$V$8)))*'Generated data'!$B$6,$V$6*($V$3+$V$4*(H26/$V$7)+$V$5*(I26/$V$8))) -> 129.20431 | V26: =+C26-U26 -> -4.2043077 | X26: =IF(Cockpit_yearly!$G$3=2,($Y$8*($Y$3+$Y$4*(G26/$Y$9)+$Y$5*(I26/$Y$10)+$Y$6*(L26/$Y$11)+$Y$7*(1-M26/$Y$12)))*'Generated data'!$B$6,$Y$8*($Y$3+$Y$4*(G26/$Y$9)+$Y$5*(I26/$Y$10)+$Y$6*(L26/$Y$11)+$Y$7*(1-M26/$Y$12))) -> 114.64132 | Y26: =+C26-X26 -> 10.358677
A27: 2032 | B27: =+D27+20 -> 161.45077 | C27: =IF(Cockpit_yearly!$G$3=2,('Generated data'!B20)*'Generated data'!$B$6,'Generated data'!B20) -> 131 | D27: 141.45077 | E27: 153.2 | F27: 154.26723 | G27: 259.7 | H27: 240 | I27: 622 | J27: =$P$9 -> 110 | K27: =$P$10 -> 220 | L27: 161.5 | M27: 116.88 | O27: =IF(Cockpit_yearly!$G$3=2,($P$3*(($P$5*H27+$P$6*G27)*$P$7+$P$8)+$P$4)*'Generated data'!$B$6,$P$3*(($P$5*H27+$P$6*G27)*$P$7+$P$8)+$P$4) -> 156.49539 | P27: =C27-O27 -> -25.49539 | R27: =$S$3*($S$4*B27+$S$5*E27+$S$6*F27+$S$7*G27) -> 174.91254 | S27: =C27-R27 -> -43.912538 | U27: =IF(Cockpit_yearly!$G$3=2,($V$6*($V$3+$V$4*(H27/$V$7)+$V$5*(I27/$V$8)))*'Generated data'!$B$6,$V$6*($V$3+$V$4*(H27/$V$7)+$V$5*(I27/$V$8))) -> 134.61123 | V27: =+C27-U27 -> -3.6112308 | X27: =IF(Cockpit_yearly!$G$3=2,($Y$8*($Y$3+$Y$4*(G27/$Y$9)+$Y$5*(I27/$Y$10)+$Y$6*(L27/$Y$11)+$Y$7*(1-M27/$Y$12)))*'Generated data'!$B$6,$Y$8*($Y$3+$Y$4*(G27/$Y$9)+$Y$5*(I27/$Y$10)+$Y$6*(L27/$Y$11)+$Y$7*(1-M27/$Y$12))) -> 125.13363 | Y27: =+C27-X27 -> 5.8663692
A28: 2033 | B28: =+D28+20 -> 169.48102 | C28: =IF(Cockpit_yearly!$G$3=2,('Generated data'!B21)*'Generated data'!$B$6,'Generated data'!B21) -> 124 | D28: 149.48102 | E28: 164.2 | F28: 166.01319 | G28: 277.7 | H28: 258 | I28: 652 | J28: =$P$9 -> 110 | K28: =$P$10 -> 220 | L28: 173.5 | M28: 104.88 | O28: =IF(Cockpit_yearly!$G$3=2,($P$3*(($P$5*H28+$P$6*G28)*$P$7+$P$8)+$P$4)*'Generated data'!$B$6,$P$3*(($P$5*H28+$P$6*G28)*$P$7+$P$8)+$P$4) -> 164.21739 | P28: =C28-O28 -> -40.21739 | R28: =$S$3*($S$4*B28+$S$5*E28+$S$6*F28+$S$7*G28) -> 187.16405 | S28: =C28-R28 -> -63.164051 | U28: =IF(Cockpit_yearly!$G$3=2,($V$6*($V$3+$V$4*(H28/$V$7)+$V$5*(I28/$V$8)))*'Generated data'!$B$6,$V$6*($V$3+$V$4*(H28/$V$7)+$V$5*(I28/$V$8))) -> 138.74892 | V28: =+C28-U28 -> -14.748923 | X28: =IF(Cockpit_yearly!$G$3=2,($Y$8*($Y$3+$Y$4*(G28/$Y$9)+$Y$5*(I28/$Y$10)+$Y$6*(L28/$Y$11)+$Y$7*(1-M28/$Y$12)))*'Generated data'!$B$6,$Y$8*($Y$3+$Y$4*(G28/$Y$9)+$Y$5*(I28/$Y$10)+$Y$6*(L28/$Y$11)+$Y$7*(1-M28/$Y$12))) -> 134.77978 | Y28: =+C28-X28 -> -10.779785
A29: 2034 | B29: =+D29+20 -> 180.4727 | C29: =IF(Cockpit_yearly!$G$3=2,('Generated data'!B22)*'Generated data'!$B$6,'Generated data'!B22) -> 120 | D29: 160.4727 | E29: 171.2 | F29: 173.26809 | G29: 299.7 | H29: 282 | I29: 682 | J29: =$P$9 -> 110 | K29: =$P$10 -> 220 | L29: 185.5 | M29: 92.88 | O29: =IF(Cockpit_yearly!$G$3=2,($P$3*(($P$5*H29+$P$6*G29)*$P$7+$P$8)+$P$4)*'Generated data'!$B$6,$P$3*(($P$5*H29+$P$6*G29)*$P$7+$P$8)+$P$4) -> 174.25599 | P29: =C29-O29 -> -54.25599 | R29: =$S$3*($S$4*B29+$S$5*E29+$S$6*F29+$S$7*G29) -> 197.36364 | S29: =C29-R29 -> -77.363635 | U29: =IF(Cockpit_yearly!$G$3=2,($V$6*($V$3+$V$4*(H29/$V$7)+$V$5*(I29/$V$8)))*'Generated data'!$B$6,$V$6*($V$3+$V$4*(H29/$V$7)+$V$5*(I29/$V$8))) -> 144.15585 | V29: =+C29-U29 -> -24.155846 | X29: =IF(Cockpit_yearly!$G$3=2,($Y$8*($Y$3+$Y$4*(G29/$Y$9)+$Y$5*(I29/$Y$10)+$Y$6*(L29/$Y$11)+$Y$7*(1-M29/$Y$12)))*'Generated data'!$B$6,$Y$8*($Y$3+$Y$4*(G29/$Y$9)+$Y$5*(I29/$Y$10)+$Y$6*(L29/$Y$11)+$Y$7*(1-M29/$Y$12))) -> 145.10286 | Y29: =+C29-X29 -> -25.102862
A30: 2035 | B30: =+D30+20 -> 178.21083 | C30: =IF(Cockpit_yearly!$G$3=2,('Generated data'!B23)*'Generated data'!$B$6,'Generated data'!B23) -> 127 | D30: 158.21083 | E30: 176.2 | F30: 178.45592 | G30: 313.7 | H30: 296 | I30: 712 | J30: =$P$9 -> 110 | K30: =$P$10 -> 220 | L30: 197.5 | M30: 80.88 | O30: =IF(Cockpit_yearly!$G$3=2,($P$3*(($P$5*H30+$P$6*G30)*$P$7+$P$8)+$P$4)*'Generated data'!$B$6,$P$3*(($P$5*H30+$P$6*G30)*$P$7+$P$8)+$P$4) -> 180.26199 | P30: =C30-O30 -> -53.26199 | R30: =$S$3*($S$4*B30+$S$5*E30+$S$6*F30+$S$7*G30) -> 203.80054 | S30: =C30-R30 -> -76.800542 | U30: =IF(Cockpit_yearly!$G$3=2,($V$6*($V$3+$V$4*(H30/$V$7)+$V$5*(I30/$V$8)))*'Generated data'!$B$6,$V$6*($V$3+$V$4*(H30/$V$7)+$V$5*(I30/$V$8))) -> 147.44738 | V30: =+C30-U30 -> -20.447385 | X30: =IF(Cockpit_yearly!$G$3=2,($Y$8*($Y$3+$Y$4*(G30/$Y$9)+$Y$5*(I30/$Y$10)+$Y$6*(L30/$Y$11)+$Y$7*(1-M30/$Y$12)))*'Generated data'!$B$6,$Y$8*($Y$3+$Y$4*(G30/$Y$9)+$Y$5*(I30/$Y$10)+$Y$6*(L30/$Y$11)+$Y$7*(1-M30/$Y$12))) -> 154.07209 | Y30: =+C30-X30 -> -27.072092

Sheet Monthly_prices_forecast_direct
N1: Formula 1 : P =𝒂×(𝑺×𝑪_𝒓𝒂𝒕𝒊𝒐+𝑪_𝒄𝒐𝒔𝒕 )+𝒃 | U1: Formula 2 : P = 𝒂×(𝒔𝒎𝒐𝒐𝒕𝒉(𝑺)×𝑪_𝒓𝒂𝒕𝒊𝒐+𝑪_𝒄𝒐𝒔𝒕 )+𝒃 | AB1: Formula 3 : P = 𝒂×ACS_(𝒎−𝟏)
P2: a | Q2: =Cockpit_monthly!E15 -> 1.3 | W2: a | X2: =Cockpit_monthly!E30 -> 1.4 | AD2: a | AE2: =Cockpit_monthly!E45 -> 1
P3: b | Q3: =Cockpit_monthly!H15 -> 25 | W3: b | X3: =Cockpit_monthly!H30 -> 15 | AD3: Coef ACS NA | AE3: =Cockpit_monthly!E47 -> 0.05
P4: Coef S ME | Q4: =Cockpit_monthly!E17 -> 0.7 | W4: Coef S ME | X4: =Cockpit_monthly!E32 -> 0.7 | AD4: Coef ACS EU | AE4: =Cockpit_monthly!H47 -> 0.75
P5: Coef S NA | Q5: =Cockpit_monthly!H17 -> 0.3 | W5: Coef S NA | X5: =Cockpit_monthly!H32 -> 0.3 | AD5: Coef ACS Jp | AE5: =Cockpit_monthly!E48 -> 0
P6: Conv cost | Q6: =Cockpit_monthly!E19 -> 0.33 | W6: Conv cost | X6: =Cockpit_monthly!E34 -> 0.33 | AD6: Coef ACS Ch | AE6: =Cockpit_monthly!H48 -> 0.2
P7: Cout de prod | Q7: =Cockpit_monthly!H19 -> 20 | W7: Cout de prod | X7: =Cockpit_monthly!H34 -> 20 | AD7: Floor | AE7: =Cockpit_monthly!E50 -> 110
P8: Floor | Q8: =Cockpit_monthly!E21 -> 110 | W8: Floor | X8: =Cockpit_monthly!E36 -> 110 | AD8: Cap | AE8: =Cockpit_monthly!H50 -> 220
P9: Cap | Q9: =Cockpit_monthly!H21 -> 220 | W9: Cap | X9: =Cockpit_monthly!H36 -> 220
A11: Date | B11: Year | C11: Quarter | D11: Month | E11: ACS CFR North Africa | F11: ACS NW EU | G11: ACS Japan | H11: ACS China | I11: S ME to CFR | J11: S North Africa to CFR Morocco | K11: Smooth 3 mois S ME to CFR | L11: Smooth S North Africa to CFR Morocco | M11: DAP Bulk North Africa | O11: Formula price | P11: Floor | Q11: CAP | R11: GAP | V11: Formula price | W11: Floor | X11: CAP | Y11: GAP | AC11: Formula price | AD11: Floor | AE11: CAP | AF11: GAP
A12: =_xlfn.CONCAT("Q",C12," ",B12) -> Q1 2022 | B12: 2022 | C12: 1 | D12: 1 | E12: =IF(Cockpit_monthly!$H$3=2,(235.333333333333)*'Generated data'!$B$6,235.333333333333) -> 235.33333 | F12: ='Prices S_ACS'!T239 -> 210.33333 | G12: ='Prices S_ACS'!U239 -> 159.66667 | H12: ='Prices S_ACS'!V239 -> 217.2 | I12: ='Prices S_ACS'!W239 -> 260 | J12: ='Prices S_ACS'!X239 -> 230 | K12: =I12 -> 260 | L12: =J12 -> 230 | M12: ='Phosphate monthly prices'!BH419 -> 726.25 | O12: =IF(Cockpit_monthly!$H$3=2,($Q$2*(($Q$4*J12+$Q$5*I12)*$Q$6+$Q$7)+$Q$3)*'Generated data'!$B$6,$Q$2*(($Q$4*J12+$Q$5*I12)*$Q$6+$Q$7)+$Q$3) -> 153.531 | P12: =$Q$8 -> 110 | Q12: =$Q$9 -> 220 | R12: =E12-O12 -> 81.802333 | V12: =IF(Cockpit_monthly!$H$3=2,($X$2*(($X$4*K12+$X$5*L12)*$X$6+$X$7)+$X$3)*'Generated data'!$B$6,$X$2*(($X$4*K12+$X$5*L12)*$X$6+$X$7)+$X$3) -> 158.962 | W12: =$X$8 -> 110 | X12: =$X$9 -> 220 | Y12: =E12-V12 -> 76.371333 | AC12: =$AE$2*($AE$3*E12+$AE$4*F12+$AE$5*G12+$AE$6*H12) -> 212.95667 | AD12: =$AE$7 -> 110 | AE12: =$AE$8 -> 220 | AF12: =E12-AC12 -> 22.376667
A13: =_xlfn.CONCAT("Q",C13," ",B13) -> Q1 2022 | B13: 2022 | C13: 1 | D13: 2 | E13: =IF(Cockpit_monthly!$H$3=2,(236.333333333333)*'Generated data'!$B$6,236.333333333333) -> 236.33333 | F13: ='Prices S_ACS'!T240 -> 211.33333 | G13: ='Prices S_ACS'!U240 -> 161.66667 | H13: ='Prices S_ACS'!V240 -> 209.75 | I13: ='Prices S_ACS'!W240 -> 283.75 | J13: ='Prices S_ACS'!X240 -> 233 | K13: =I13 -> 283.75 | L13: =J13 -> 233 | M13: ='Phosphate monthly prices'!BH420 -> 850 | O13: =IF(Cockpit_monthly!$H$3=2,($Q$2*(($Q$4*J13+$Q$5*I13)*$Q$6+$Q$7)+$Q$3)*'Generated data'!$B$6,$Q$2*(($Q$4*J13+$Q$5*I13)*$Q$6+$Q$7)+$Q$3) -> 157.48853 | P13: =$Q$8 -> 110 | Q13: =$Q$9 -> 220 | R13: =E13-O13 -> 78.844808 | V13: =IF(Cockpit_monthly!$H$3=2,($X$2*(($X$4*K13+$X$5*L13)*$X$6+$X$7)+$X$3)*'Generated data'!$B$6,$X$2*(($X$4*K13+$X$5*L13)*$X$6+$X$7)+$X$3) -> 167.05855 | W13: =$X$8 -> 110 | X13: =$X$9 -> 220 | Y13: =E13-V13 -> 69.274783 | AC13: =$AE$2*($AE$3*E12+$AE$4*F12+$AE$5*G12+$AE$6*H12) -> 212.95667 | AD13: =$AE$7 -> 110 | AE13: =$AE$8 -> 220 | AF13: =E13-AC13 -> 23.376667
A14: =_xlfn.CONCAT("Q",C14," ",B14) -> Q1 2022 | B14: 2022 | C14: 1 | D14: 3 | E14: =IF(Cockpit_monthly!$H$3=2,(247.9)*'Generated data'!$B$6,247.9) -> 247.9 | F14: ='Prices S_ACS'!T241 -> 222.9 | G14: ='Prices S_ACS'!U241 -> 153.63333 | H14: ='Prices S_ACS'!V241 -> 186.37 | I14: ='Prices S_ACS'!W241 -> 307.25 | J14: ='Prices S_ACS'!X241 -> 233 | K14: =I14 -> 307.25 | L14: =J14 -> 233 | M14: ='Phosphate monthly prices'!BH421 -> 900 | O14: =IF(Cockpit_monthly!$H$3=2,($Q$2*(($Q$4*J14+$Q$5*I14)*$Q$6+$Q$7)+$Q$3)*'Generated data'!$B$6,$Q$2*(($Q$4*J14+$Q$5*I14)*$Q$6+$Q$7)+$Q$3) -> 160.51297 | P14: =$Q$8 -> 110 | Q14: =$Q$9 -> 220 | R14: =E14-O14 -> 87.387025 | V14: =IF(Cockpit_monthly!$H$3=2,($X$2*(($X$4*K14+$X$5*L14)*$X$6+$X$7)+$X$3)*'Generated data'!$B$6,$X$2*(($X$4*K14+$X$5*L14)*$X$6+$X$7)+$X$3) -> 174.65845 | W14: =$X$8 -> 110 | X14: =$X$9 -> 220 | Y14: =E14-V14 -> 73.24155 | AC14: =$AE$2*($AE$3*E13+$AE$4*F13+$AE$5*G13+$AE$6*H13) -> 212.26667 | AD14: =$AE$7 -> 110 | AE14: =$AE$8 -> 220 | AF14: =E14-AC14 -> 35.633333
A15: =_xlfn.CONCAT("Q",C15," ",B15) -> Q2 2022 | B15: 2022 | C15: 2 | D15: 4 | E15: =IF(Cockpit_monthly!$H$3=2,(258.333333333333)*'Generated data'!$B$6,258.333333333333) -> 258.33333 | F15: ='Prices S_ACS'!T242 -> 233.33333 | G15: ='Prices S_ACS'!U242 -> 150.58333 | H15: ='Prices S_ACS'!V242 -> 197 | I15: ='Prices S_ACS'!W242 -> 340.25 | J15: ='Prices S_ACS'!X242 -> 299 | K15: =AVERAGE(I12:I14) -> 283.66667 | L15: =AVERAGE(J12:J14) -> 232 | M15: ='Phosphate monthly prices'!BH422 -> 902.75 | O15: =IF(Cockpit_monthly!$H$3=2,($Q$2*(($Q$4*J15+$Q$5*I15)*$Q$6+$Q$7)+$Q$3)*'Generated data'!$B$6,$Q$2*(($Q$4*J15+$Q$5*I15)*$Q$6+$Q$7)+$Q$3) -> 184.57988 | P15: =$Q$8 -> 110 | Q15: =$Q$9 -> 220 | R15: =E15-O15 -> 73.753458 | V15: =IF(Cockpit_monthly!$H$3=2,($X$2*(($X$4*K15+$X$5*L15)*$X$6+$X$7)+$X$3)*'Generated data'!$B$6,$X$2*(($X$4*K15+$X$5*L15)*$X$6+$X$7)+$X$3) -> 166.893 | W15: =$X$8 -> 110 | X15: =$X$9 -> 220 | Y15: =E15-V15 -> 91.440333 | AC15: =$AE$2*($AE$3*E14+$AE$4*F14+$AE$5*G14+$AE$6*H14) -> 216.844 | AD15: =$AE$7 -> 110 | AE15: =$AE$8 -> 220 | AF15: =E15-AC15 -> 41.489333
