Workbook
Name \a: #REF!
Name \d: #REF!
Name \I: #REF!
Name \p: #REF!
Name \s: #REF!
Name \t: #REF!
Name _1_: #REF!
Name _10n_0: #REF!
Name _11t_0WT: #REF!
Name _12t__WT: #REF!
Name _13W_0WS: #REF!
Name _14WSOL: #REF!
Name _15W__WS: #REF!
Name _2_0: #REF!
Name _3_0G: #REF!
Name _4_0WSOL: #REF!
Name _5_1thru51queries: #REF!
Name _6_8_0WTOT: #REF!
Name _7_8__WTOT: #REF!
Name _8G: #REF!
Name _9n: #REF!
Name aagr1end: #REF!
Name aagr1start: #REF!
Name aagr2end: #REF!
Name aagr2start: #REF!
Name aagr3end: #REF!
Name aagr3start: #REF!
Name aagr4end: #REF!
Name aagr4start: #REF!
Name aagr5end: #REF!
Name aagr5start: #REF!
Name ALL: #REF!
Name AllApps: #REF!
Name annual: #REF!
Name Applications: #REF!
Name area: #REF!
Name ASD: #REF!
Name ASPHTON: #REF!
Name AVGASTON: #REF!
Name AvgCflow: #REF!
Name b: #REF!
Name Base_Year: #REF!
Name Bitumen: #REF!
Name Break: #REF!
Name Canada_East_Projects: #REF!
Name Canada_West_Projects: #REF!
Name CapOpCost: #REF!
Name CapOpCostHi: #REF!
Name Chosen_month: #REF!
Name Chosen_quarter: #REF!
Name Chosen_year: #REF!
Name clean_spreads: #REF!
Name COKETON: #REF!
Name CommercialExAIGMetrics: #REF!
Name CONSTANT1: #N/A
Name CONSTANT2: #N/A
Name CostEsc: #REF!
Name Country: #REF!
Name CRUTON: #REF!
Name CURRENT1: #REF!

Sheet Simulateur sur Avg
AA1: ConvCost=20+0,05×(SFOBME​+Fret)
J2: used for ACS production cost estimation
E3: Sulphuric Acid Bulk FOB | F3: Sulphuric Acid Bulk FOB | G3: Sulphuric Acid Bulk FOB | H3: Sulphuric Acid Bulk CFR | I3: Sulphur Bulk FOB | J3: Sulphur Bulk CFR | L3: Sulphuric Acid Bulk FOB | M3: Sulphuric Acid Bulk FOB | N3: Sulphuric Acid Bulk FOB | O3: Sulphur Bulk FOB | P3: Sulphur Bulk CFR
E4: Japan/South Korea Spot | F4: NW Europe 30 days Spot | G4: China Spot | H4: North Africa, Spot | I4: Middle East Spot | J4: North Africa | L4: Japan/South Korea Spot | M4: NW Europe 30 days Spot | N4: China Spot | O4: Middle East Spot | P4: North Africa | R4: Prix cibles Sulphuric Acid | AA4: Formule 1: Market Basket | AD4: Formule 2: Indice Composite basé sur Europe, chine et acid base ME
B5: Year | C5: Quarter | D5: Month | E5: ACS FOB Japan | F5: ACS FOB NW Europe | G5: ACS FOB China Spot | H5: ACS CFR North Africa Spot | I5: Sulphur Bulk FOB Middle East | J5: Sulphur Bulk CFR North Africa | L5: Fret Japan to Morocco | M5: Fret NW EU to Morocco | N5: Fret China to Morocco | O5: Fret Middle East to Morocco | P5: Freight adjustment (CRU) | R5: ACS CFR North Africa | S5: IPP ACS Origine Europe | T5: IPP ACS origine Japon | U5: Ipp ACS Origine Chine | V5: Sulfur ME to CFR Morocco | W5: Sulfur North Africa to CFR Morocco | X5: ACS S based from Sulfur ME | Y5: ACS S based from Sulfur North Africa | AA5: IPP_Acid = 40% × IPP_NWE + 30% × IPP_Japan + 30% × IPP_China | AB5: Gain par rapport à production sur place | AD5: IPP_Acid = min((70% × IPP_NWE + 30% × IPP_China); Acid S Based ME) | AE5: Gain par rapport à production sur place
B6: 2002 | C6: 2 | D6: 5 | E6: ='CRU historical'!F5 | F6: ='CRU historical'!I5 -> 6 | G6: ='CRU historical'!L5 | H6: ='CRU historical'!O5 | I6: ='CRU historical'!R5 | J6: =AVERAGE('CRU historical'!U5, 'CRU historical'!X5, 'CRU historical'!AA5, 'CRU historical'!AD5) -> 33 | L6: {=IFERROR(SUMPRODUCT(('Sulphuric Acid freights'!$B$3:$B$513=B6)*('Sulphuric Acid freights'!$D$3:$D$513=D6)*('Sulphuric Acid freights'!$P$3:$P$513))/SUMPRODUCT(('Sulphuric Acid freights'!$B$3:$B$513=B6)*('Sulphuric Acid freights'!$D$3:$D$513=D6)*1), AVERAGE('Sulphuric Acid freights'!$P$3:$P$513))*2/3} -> 54.110672 | M6: {=IFERROR(SUMPRODUCT(('Sulphuric Acid freights'!$B$3:$B$513=B6)*('Sulphuric Acid freights'!$D$3:$D$513=D6)*('Sulphuric Acid freights'!$M$3:$M$513))/SUMPRODUCT(('Sulphuric Acid freights'!$B$3:$B$513=B6)*('Sulphuric Acid freights'!$D$3:$D$513=D6)*1)*2/3, AVERAGE('Sulphuric Acid freights'!$M$3:$M$513))} -> 23.573123 | N6: =IFERROR(L6*0.9, "") -> 48.699605 | O6: {=IF(SUMPRODUCT(('Sulphur freight'!$B$3:$B$1976=B6)*('Sulphur freight'!$D$3:$D$1976=D6)*('Sulphur freight'!$G$3:$G$1976))/SUMPRODUCT(('Sulphur freight'!$B$3:$B$1976=B6)*('Sulphur freight'!$D$3:$D$1976=D6)*1)=0, AVERAGE('Sulphur freight'!$G$3:$G$1976),SUMPRODUCT(('Sulphur freight'!$B$3:$B$1976=B6)*('Sulphur freight'!$D$3:$D$1976=D6)*('Sulphur freight'!$G$3:$G$1976))/SUMPRODUCT(('Sulphur freight'!$B$3:$B$1976=B6)*('Sulphur freight'!$D$3:$D$1976=D6)*1))} -> 29.165429 | P6: 20 | R6: =H6 | S6: =IF(F6=0, "", F6+M6) -> 29.573123 | T6: =IFERROR( E6+L6, "") | U6: =IFERROR( G6+N6, "") | V6: =IFERROR(I6+O6, "") | W6: =J6+P6 -> 53 | X6: =IFERROR((I6+O6)*0.33+18, "") | Y6: =IF(J6=0,0,(J6+P6)*0.33+18) -> 35.49 | AA6: =IF(OR(S6="", T6="", U6=""), "", MAX(R6,S6)*40%+T6*30%+U6*30%) | AB6: =IF(AA6="", "", MAX(X6, Y6)-AA6) | AD6: =IFERROR(MIN((MAX(R6,S6)*70%+U6*30%), Y6), "") | AE6: =IF(AD6="", "", MAX(AA6, AB6)-AD6)
B7: 2002 | C7: 2 | D7: 6 | E7: ='CRU historical'!F6 | F7: ='CRU historical'!I6 -> 6 | G7: ='CRU historical'!L6 | H7: ='CRU historical'!O6 | I7: ='CRU historical'!R6 | J7: =AVERAGE('CRU historical'!U6, 'CRU historical'!X6, 'CRU historical'!AA6, 'CRU historical'!AD6) -> 33 | L7: {=IFERROR(SUMPRODUCT(('Sulphuric Acid freights'!$B$3:$B$513=B7)*('Sulphuric Acid freights'!$D$3:$D$513=D7)*('Sulphuric Acid freights'!$P$3:$P$513))/SUMPRODUCT(('Sulphuric Acid freights'!$B$3:$B$513=B7)*('Sulphuric Acid freights'!$D$3:$D$513=D7)*1), AVERAGE('Sulphuric Acid freights'!$P$3:$P$513))*2/3} -> 54.110672 | M7: {=IFERROR(SUMPRODUCT(('Sulphuric Acid freights'!$B$3:$B$513=B7)*('Sulphuric Acid freights'!$D$3:$D$513=D7)*('Sulphuric Acid freights'!$M$3:$M$513))/SUMPRODUCT(('Sulphuric Acid freights'!$B$3:$B$513=B7)*('Sulphuric Acid freights'!$D$3:$D$513=D7)*1)*2/3, AVERAGE('Sulphuric Acid freights'!$M$3:$M$513))} -> 23.573123 | N7: =IFERROR(L7*0.9, "") -> 48.699605 | O7: {=IF(SUMPRODUCT(('Sulphur freight'!$B$3:$B$1976=B7)*('Sulphur freight'!$D$3:$D$1976=D7)*('Sulphur freight'!$G$3:$G$1976))/SUMPRODUCT(('Sulphur freight'!$B$3:$B$1976=B7)*('Sulphur freight'!$D$3:$D$1976=D7)*1)=0, AVERAGE('Sulphur freight'!$G$3:$G$1976),SUMPRODUCT(('Sulphur freight'!$B$3:$B$1976=B7)*('Sulphur freight'!$D$3:$D$1976=D7)*('Sulphur freight'!$G$3:$G$1976))/SUMPRODUCT(('Sulphur freight'!$B$3:$B$1976=B7)*('Sulphur freight'!$D$3:$D$1976=D7)*1))} -> 29.165429 | P7: 20 | R7: =H7 | S7: =IF(F7=0, "", F7+M7) -> 29.573123 | T7: =IFERROR( E7+L7, "") | U7: =IFERROR( G7+N7, "") | V7: =IFERROR(I7+O7, "") | W7: =J7+P7 -> 53 | X7: =IFERROR((I7+O7)*0.33+18, "") | Y7: =IF(J7=0,0,(J7+P7)*0.33+18) -> 35.49 | AA7: =IF(OR(S7="", T7="", U7=""), "", MAX(R7,S7)*40%+T7*30%+U7*30%) | AB7: =IF(AA7="", "", MAX(X7, Y7)-AA7) | AD7: =IFERROR(MIN((MAX(R7,S7)*70%+U7*30%), Y7), "") | AE7: =IF(AD7="", "", MAX(AA7, AB7)-AD7)
B8: 2002 | C8: 3 | D8: 7 | E8: ='CRU historical'!F7 | F8: ='CRU historical'!I7 -> 8 | G8: ='CRU historical'!L7 | H8: ='CRU historical'!O7 | I8: ='CRU historical'!R7 | J8: =AVERAGE('CRU historical'!U7, 'CRU historical'!X7, 'CRU historical'!AA7, 'CRU historical'!AD7) -> 39 | L8: {=IFERROR(SUMPRODUCT(('Sulphuric Acid freights'!$B$3:$B$513=B8)*('Sulphuric Acid freights'!$D$3:$D$513=D8)*('Sulphuric Acid freights'!$P$3:$P$513))/SUMPRODUCT(('Sulphuric Acid freights'!$B$3:$B$513=B8)*('Sulphuric Acid freights'!$D$3:$D$513=D8)*1), AVERAGE('Sulphuric Acid freights'!$P$3:$P$513))*2/3} -> 54.110672 | M8: {=IFERROR(SUMPRODUCT(('Sulphuric Acid freights'!$B$3:$B$513=B8)*('Sulphuric Acid freights'!$D$3:$D$513=D8)*('Sulphuric Acid freights'!$M$3:$M$513))/SUMPRODUCT(('Sulphuric Acid freights'!$B$3:$B$513=B8)*('Sulphuric Acid freights'!$D$3:$D$513=D8)*1)*2/3, AVERAGE('Sulphuric Acid freights'!$M$3:$M$513))} -> 23.573123 | N8: =IFERROR(L8*0.9, "") -> 48.699605 | O8: {=IF(SUMPRODUCT(('Sulphur freight'!$B$3:$B$1976=B8)*('Sulphur freight'!$D$3:$D$1976=D8)*('Sulphur freight'!$G$3:$G$1976))/SUMPRODUCT(('Sulphur freight'!$B$3:$B$1976=B8)*('Sulphur freight'!$D$3:$D$1976=D8)*1)=0, AVERAGE('Sulphur freight'!$G$3:$G$1976),SUMPRODUCT(('Sulphur freight'!$B$3:$B$1976=B8)*('Sulphur freight'!$D$3:$D$1976=D8)*('Sulphur freight'!$G$3:$G$1976))/SUMPRODUCT(('Sulphur freight'!$B$3:$B$1976=B8)*('Sulphur freight'!$D$3:$D$1976=D8)*1))} -> 29.165429 | P8: 20 | R8: =H8 | S8: =IF(F8=0, "", F8+M8) -> 31.573123 | T8: =IFERROR( E8+L8, "") | U8: =IFERROR( G8+N8, "") | V8: =IFERROR(I8+O8, "") | W8: =J8+P8 -> 59 | X8: =IFERROR((I8+O8)*0.33+18, "") | Y8: =IF(J8=0,0,(J8+P8)*0.33+18) -> 37.47 | AA8: =IF(OR(S8="", T8="", U8=""), "", MAX(R8,S8)*40%+T8*30%+U8*30%) | AB8: =IF(AA8="", "", MAX(X8, Y8)-AA8) | AD8: =IFERROR(MIN((MAX(R8,S8)*70%+U8*30%), Y8), "") | AE8: =IF(AD8="", "", MAX(AA8, AB8)-AD8)
B9: 2002 | C9: 3 | D9: 8 | E9: ='CRU historical'!F8 | F9: ='CRU historical'!I8 -> 8 | G9: ='CRU historical'!L8 | H9: ='CRU historical'!O8 | I9: ='CRU historical'!R8 | J9: =AVERAGE('CRU historical'!U8, 'CRU historical'!X8, 'CRU historical'!AA8, 'CRU historical'!AD8) -> 38.5 | L9: {=IFERROR(SUMPRODUCT(('Sulphuric Acid freights'!$B$3:$B$513=B9)*('Sulphuric Acid freights'!$D$3:$D$513=D9)*('Sulphuric Acid freights'!$P$3:$P$513))/SUMPRODUCT(('Sulphuric Acid freights'!$B$3:$B$513=B9)*('Sulphuric Acid freights'!$D$3:$D$513=D9)*1), AVERAGE('Sulphuric Acid freights'!$P$3:$P$513))*2/3} -> 54.110672 | M9: {=IFERROR(SUMPRODUCT(('Sulphuric Acid freights'!$B$3:$B$513=B9)*('Sulphuric Acid freights'!$D$3:$D$513=D9)*('Sulphuric Acid freights'!$M$3:$M$513))/SUMPRODUCT(('Sulphuric Acid freights'!$B$3:$B$513=B9)*('Sulphuric Acid freights'!$D$3:$D$513=D9)*1)*2/3, AVERAGE('Sulphuric Acid freights'!$M$3:$M$513))} -> 23.573123 | N9: =IFERROR(L9*0.9, "") -> 48.699605 | O9: {=IF(SUMPRODUCT(('Sulphur freight'!$B$3:$B$1976=B9)*('Sulphur freight'!$D$3:$D$1976=D9)*('Sulphur freight'!$G$3:$G$1976))/SUMPRODUCT(('Sulphur freight'!$B$3:$B$1976=B9)*('Sulphur freight'!$D$3:$D$1976=D9)*1)=0, AVERAGE('Sulphur freight'!$G$3:$G$1976),SUMPRODUCT(('Sulphur freight'!$B$3:$B$1976=B9)*('Sulphur freight'!$D$3:$D$1976=D9)*('Sulphur freight'!$G$3:$G$1976))/SUMPRODUCT(('Sulphur freight'!$B$3:$B$1976=B9)*('Sulphur freight'!$D$3:$D$1976=D9)*1))} -> 29.165429 | P9: 20 | R9: =H9 | S9: =IF(F9=0, "", F9+M9) -> 31.573123 | T9: =IFERROR( E9+L9, "") | U9: =IFERROR( G9+N9, "") | V9: =IFERROR(I9+O9, "") | W9: =J9+P9 -> 58.5 | X9: =IFERROR((I9+O9)*0.33+18, "") | Y9: =IF(J9=0,0,(J9+P9)*0.33+18) -> 37.305 | AA9: =IF(OR(S9="", T9="", U9=""), "", MAX(R9,S9)*40%+T9*30%+U9*30%) | AB9: =IF(AA9="", "", MAX(X9, Y9)-AA9) | AD9: =IFERROR(MIN((MAX(R9,S9)*70%+U9*30%), Y9), "") | AE9: =IF(AD9="", "", MAX(AA9, AB9)-AD9)
B10: 2002 | C10: 3 | D10: 9 | E10: ='CRU historical'!F9 | F10: ='CRU historical'!I9 -> 8 | G10: ='CRU historical'!L9 | H10: ='CRU historical'!O9 | I10: ='CRU historical'!R9 | J10: =AVERAGE('CRU historical'!U9, 'CRU historical'!X9, 'CRU historical'!AA9, 'CRU historical'!AD9) -> 38 | L10: {=IFERROR(SUMPRODUCT(('Sulphuric Acid freights'!$B$3:$B$513=B10)*('Sulphuric Acid freights'!$D$3:$D$513=D10)*('Sulphuric Acid freights'!$P$3:$P$513))/SUMPRODUCT(('Sulphuric Acid freights'!$B$3:$B$513=B10)*('Sulphuric Acid freights'!$D$3:$D$513=D10)*1), AVERAGE('Sulphuric Acid freights'!$P$3:$P$513))*2/3} -> 54.110672 | M10: {=IFERROR(SUMPRODUCT(('Sulphuric Acid freights'!$B$3:$B$513=B10)*('Sulphuric Acid freights'!$D$3:$D$513=D10)*('Sulphuric Acid freights'!$M$3:$M$513))/SUMPRODUCT(('Sulphuric Acid freights'!$B$3:$B$513=B10)*('Sulphuric Acid freights'!$D$3:$D$513=D10)*1)*2/3, AVERAGE('Sulphuric Acid freights'!$M$3:$M$513))} -> 23.573123 | N10: =IFERROR(L10*0.9, "") -> 48.699605 | O10: {=IF(SUMPRODUCT(('Sulphur freight'!$B$3:$B$1976=B10)*('Sulphur freight'!$D$3:$D$1976=D10)*('Sulphur freight'!$G$3:$G$1976))/SUMPRODUCT(('Sulphur freight'!$B$3:$B$1976=B10)*('Sulphur freight'!$D$3:$D$1976=D10)*1)=0, AVERAGE('Sulphur freight'!$G$3:$G$1976),SUMPRODUCT(('Sulphur freight'!$B$3:$B$1976=B10)*('Sulphur freight'!$D$3:$D$1976=D10)*('Sulphur freight'!$G$3:$G$1976))/SUMPRODUCT(('Sulphur freight'!$B$3:$B$1976=B10)*('Sulphur freight'!$D$3:$D$1976=D10)*1))} -> 29.165429 | P10: 20 | R10: =H10 | S10: =IF(F10=0, "", F10+M10) -> 31.573123 | T10: =IFERROR( E10+L10, "") | U10: =IFERROR( G10+N10, "") | V10: =IFERROR(I10+O10, "") | W10: =J10+P10 -> 58 | X10: =IFERROR((I10+O10)*0.33+18, "") | Y10: =IF(J10=0,0,(J10+P10)*0.33+18) -> 37.14 | AA10: =IF(OR(S10="", T10="", U10=""), "", MAX(R10,S10)*40%+T10*30%+U10*30%) | AB10: =IF(AA10="", "", MAX(X10, Y10)-AA10) | AD10: =IFERROR(MIN((MAX(R10,S10)*70%+U10*30%), Y10), "") | AE10: =IF(AD10="", "", MAX(AA10, AB10)-AD10)
B11: 2002 | C11: 4 | D11: 10 | E11: ='CRU historical'!F10 | F11: ='CRU historical'!I10 -> 8 | G11: ='CRU historical'!L10 | H11: ='CRU historical'!O10 | I11: ='CRU historical'!R10 | J11: =AVERAGE('CRU historical'!U10, 'CRU historical'!X10, 'CRU historical'!AA10, 'CRU historical'!AD10) -> 38 | L11: {=IFERROR(SUMPRODUCT(('Sulphuric Acid freights'!$B$3:$B$513=B11)*('Sulphuric Acid freights'!$D$3:$D$513=D11)*('Sulphuric Acid freights'!$P$3:$P$513))/SUMPRODUCT(('Sulphuric Acid freights'!$B$3:$B$513=B11)*('Sulphuric Acid freights'!$D$3:$D$513=D11)*1), AVERAGE('Sulphuric Acid freights'!$P$3:$P$513))*2/3} -> 54.110672 | M11: {=IFERROR(SUMPRODUCT(('Sulphuric Acid freights'!$B$3:$B$513=B11)*('Sulphuric Acid freights'!$D$3:$D$513=D11)*('Sulphuric Acid freights'!$M$3:$M$513))/SUMPRODUCT(('Sulphuric Acid freights'!$B$3:$B$513=B11)*('Sulphuric Acid freights'!$D$3:$D$513=D11)*1)*2/3, AVERAGE('Sulphuric Acid freights'!$M$3:$M$513))} -> 23.573123 | N11: =IFERROR(L11*0.9, "") -> 48.699605 | O11: {=IF(SUMPRODUCT(('Sulphur freight'!$B$3:$B$1976=B11)*('Sulphur freight'!$D$3:$D$1976=D11)*('Sulphur freight'!$G$3:$G$1976))/SUMPRODUCT(('Sulphur freight'!$B$3:$B$1976=B11)*('Sulphur freight'!$D$3:$D$1976=D11)*1)=0, AVERAGE('Sulphur freight'!$G$3:$G$1976),SUMPRODUCT(('Sulphur freight'!$B$3:$B$1976=B11)*('Sulphur freight'!$D$3:$D$1976=D11)*('Sulphur freight'!$G$3:$G$1976))/SUMPRODUCT(('Sulphur freight'!$B$3:$B$1976=B11)*('Sulphur freight'!$D$3:$D$1976=D11)*1))} -> 29.165429 | P11: 20 | R11: =H11 | S11: =IF(F11=0, "", F11+M11) -> 31.573123 | T11: =IFERROR( E11+L11, "") | U11: =IFERROR( G11+N11, "") | V11: =IFERROR(I11+O11, "") | W11: =J11+P11 -> 58 | X11: =IFERROR((I11+O11)*0.33+18, "") | Y11: =IF(J11=0,0,(J11+P11)*0.33+18) -> 37.14 | AA11: =IF(OR(S11="", T11="", U11=""), "", MAX(R11,S11)*40%+T11*30%+U11*30%) | AB11: =IF(AA11="", "", MAX(X11, Y11)-AA11) | AD11: =IFERROR(MIN((MAX(R11,S11)*70%+U11*30%), Y11), "") | AE11: =IF(AD11="", "", MAX(AA11, AB11)-AD11)
B12: 2002 | C12: 4 | D12: 11 | E12: ='CRU historical'!F11 | F12: ='CRU historical'!I11 -> 11 | G12: ='CRU historical'!L11 | H12: ='CRU historical'!O11 | I12: ='CRU historical'!R11 | J12: =AVERAGE('CRU historical'!U11, 'CRU historical'!X11, 'CRU historical'!AA11, 'CRU historical'!AD11) -> 39 | L12: {=IFERROR(SUMPRODUCT(('Sulphuric Acid freights'!$B$3:$B$513=B12)*('Sulphuric Acid freights'!$D$3:$D$513=D12)*('Sulphuric Acid freights'!$P$3:$P$513))/SUMPRODUCT(('Sulphuric Acid freights'!$B$3:$B$513=B12)*('Sulphuric Acid freights'!$D$3:$D$513=D12)*1), AVERAGE('Sulphuric Acid freights'!$P$3:$P$513))*2/3} -> 54.110672 | M12: {=IFERROR(SUMPRODUCT(('Sulphuric Acid freights'!$B$3:$B$513=B12)*('Sulphuric Acid freights'!$D$3:$D$513=D12)*('Sulphuric Acid freights'!$M$3:$M$513))/SUMPRODUCT(('Sulphuric Acid freights'!$B$3:$B$513=B12)*('Sulphuric Acid freights'!$D$3:$D$513=D12)*1)*2/3, AVERAGE('Sulphuric Acid freights'!$M$3:$M$513))} -> 23.573123 | N12: =IFERROR(L12*0.9, "") -> 48.699605 | O12: {=IF(SUMPRODUCT(('Sulphur freight'!$B$3:$B$1976=B12)*('Sulphur freight'!$D$3:$D$1976=D12)*('Sulphur freight'!$G$3:$G$1976))/SUMPRODUCT(('Sulphur freight'!$B$3:$B$1976=B12)*('Sulphur freight'!$D$3:$D$1976=D12)*1)=0, AVERAGE('Sulphur freight'!$G$3:$G$1976),SUMPRODUCT(('Sulphur freight'!$B$3:$B$1976=B12)*('Sulphur freight'!$D$3:$D$1976=D12)*('Sulphur freight'!$G$3:$G$1976))/SUMPRODUCT(('Sulphur freight'!$B$3:$B$1976=B12)*('Sulphur freight'!$D$3:$D$1976=D12)*1))} -> 29.165429 | P12: 20 | R12: =H12 | S12: =IF(F12=0, "", F12+M12) -> 34.573123 | T12: =IFERROR( E12+L12, "") | U12: =IFERROR( G12+N12, "") | V12: =IFERROR(I12+O12, "") | W12: =J12+P12 -> 59 | X12: =IFERROR((I12+O12)*0.33+18, "") | Y12: =IF(J12=0,0,(J12+P12)*0.33+18) -> 37.47 | AA12: =IF(OR(S12="", T12="", U12=""), "", MAX(R12,S12)*40%+T12*30%+U12*30%) | AB12: =IF(AA12="", "", MAX(X12, Y12)-AA12) | AD12: =IFERROR(MIN((MAX(R12,S12)*70%+U12*30%), Y12), "") | AE12: =IF(AD12="", "", MAX(AA12, AB12)-AD12)
B13: 2002 | C13: 4 | D13: 12 | E13: ='CRU historical'!F12 | F13: ='CRU historical'!I12 -> 11 | G13: ='CRU historical'!L12 | H13: ='CRU historical'!O12 | I13: ='CRU historical'!R12 | J13: =AVERAGE('CRU historical'!U12, 'CRU historical'!X12, 'CRU historical'!AA12, 'CRU historical'!AD12) -> 39 | L13: {=IFERROR(SUMPRODUCT(('Sulphuric Acid freights'!$B$3:$B$513=B13)*('Sulphuric Acid freights'!$D$3:$D$513=D13)*('Sulphuric Acid freights'!$P$3:$P$513))/SUMPRODUCT(('Sulphuric Acid freights'!$B$3:$B$513=B13)*('Sulphuric Acid freights'!$D$3:$D$513=D13)*1), AVERAGE('Sulphuric Acid freights'!$P$3:$P$513))*2/3} -> 54.110672 | M13: {=IFERROR(SUMPRODUCT(('Sulphuric Acid freights'!$B$3:$B$513=B13)*('Sulphuric Acid freights'!$D$3:$D$513=D13)*('Sulphuric Acid freights'!$M$3:$M$513))/SUMPRODUCT(('Sulphuric Acid freights'!$B$3:$B$513=B13)*('Sulphuric Acid freights'!$D$3:$D$513=D13)*1)*2/3, AVERAGE('Sulphuric Acid freights'!$M$3:$M$513))} -> 23.573123 | N13: =IFERROR(L13*0.9, "") -> 48.699605 | O13: {=IF(SUMPRODUCT(('Sulphur freight'!$B$3:$B$1976=B13)*('Sulphur freight'!$D$3:$D$1976=D13)*('Sulphur freight'!$G$3:$G$1976))/SUMPRODUCT(('Sulphur freight'!$B$3:$B$1976=B13)*('Sulphur freight'!$D$3:$D$1976=D13)*1)=0, AVERAGE('Sulphur freight'!$G$3:$G$1976),SUMPRODUCT(('Sulphur freight'!$B$3:$B$1976=B13)*('Sulphur freight'!$D$3:$D$1976=D13)*('Sulphur freight'!$G$3:$G$1976))/SUMPRODUCT(('Sulphur freight'!$B$3:$B$1976=B13)*('Sulphur freight'!$D$3:$D$1976=D13)*1))} -> 29.165429 | P13: 20 | R13: =H13 | S13: =IF(F13=0, "", F13+M13) -> 34.573123 | T13: =IFERROR( E13+L13, "") | U13: =IFERROR( G13+N13, "") | V13: =IFERROR(I13+O13, "") | W13: =J13+P13 -> 59 | X13: =IFERROR((I13+O13)*0.33+18, "") | Y13: =IF(J13=0,0,(J13+P13)*0.33+18) -> 37.47 | AA13: =IF(OR(S13="", T13="", U13=""), "", MAX(R13,S13)*40%+T13*30%+U13*30%) | AB13: =IF(AA13="", "", MAX(X13, Y13)-AA13) | AD13: =IFERROR(MIN((MAX(R13,S13)*70%+U13*30%), Y13), "") | AE13: =IF(AD13="", "", MAX(AA13, AB13)-AD13)
B14: 2003 | C14: 1 | D14: 1 | E14: ='CRU historical'!F13 | F14: ='CRU historical'!I13 -> 11.666667 | G14: ='CRU historical'!L13 | H14: ='CRU historical'!O13 | I14: ='CRU historical'!R13 | J14: =AVERAGE('CRU historical'!U13, 'CRU historical'!X13, 'CRU historical'!AA13, 'CRU historical'!AD13) -> 57.333333 | L14: {=IFERROR(SUMPRODUCT(('Sulphuric Acid freights'!$B$3:$B$513=B14)*('Sulphuric Acid freights'!$D$3:$D$513=D14)*('Sulphuric Acid freights'!$P$3:$P$513))/SUMPRODUCT(('Sulphuric Acid freights'!$B$3:$B$513=B14)*('Sulphuric Acid freights'!$D$3:$D$513=D14)*1), AVERAGE('Sulphuric Acid freights'!$P$3:$P$513))*2/3} -> 54.110672 | M14: {=IFERROR(SUMPRODUCT(('Sulphuric Acid freights'!$B$3:$B$513=B14)*('Sulphuric Acid freights'!$D$3:$D$513=D14)*('Sulphuric Acid freights'!$M$3:$M$513))/SUMPRODUCT(('Sulphuric Acid freights'!$B$3:$B$513=B14)*('Sulphuric Acid freights'!$D$3:$D$513=D14)*1)*2/3, AVERAGE('Sulphuric Acid freights'!$M$3:$M$513))} -> 23.573123 | N14: =IFERROR(L14*0.9, "") -> 48.699605 | O14: {=IF(SUMPRODUCT(('Sulphur freight'!$B$3:$B$1976=B14)*('Sulphur freight'!$D$3:$D$1976=D14)*('Sulphur freight'!$G$3:$G$1976))/SUMPRODUCT(('Sulphur freight'!$B$3:$B$1976=B14)*('Sulphur freight'!$D$3:$D$1976=D14)*1)=0, AVERAGE('Sulphur freight'!$G$3:$G$1976),SUMPRODUCT(('Sulphur freight'!$B$3:$B$1976=B14)*('Sulphur freight'!$D$3:$D$1976=D14)*('Sulphur freight'!$G$3:$G$1976))/SUMPRODUCT(('Sulphur freight'!$B$3:$B$1976=B14)*('Sulphur freight'!$D$3:$D$1976=D14)*1))} -> 29.165429 | P14: 20 | R14: =H14 | S14: =IF(F14=0, "", F14+M14) -> 35.239789 | T14: =IFERROR( E14+L14, "") | U14: =IFERROR( G14+N14, "") | V14: =IFERROR(I14+O14, "") | W14: =J14+P14 -> 77.333333 | X14: =IFERROR((I14+O14)*0.33+18, "") | Y14: =IF(J14=0,0,(J14+P14)*0.33+18) -> 43.52 | AA14: =IF(OR(S14="", T14="", U14=""), "", MAX(R14,S14)*40%+T14*30%+U14*30%) | AB14: =IF(AA14="", "", MAX(X14, Y14)-AA14) | AD14: =IFERROR(MIN((MAX(R14,S14)*70%+U14*30%), Y14), "") | AE14: =IF(AD14="", "", MAX(AA14, AB14)-AD14)
B15: 2003 | C15: 1 | D15: 2 | E15: ='CRU historical'!F14 | F15: ='CRU historical'!I14 -> 13 | G15: ='CRU historical'!L14 | H15: ='CRU historical'!O14 | I15: ='CRU historical'!R14 | J15: =AVERAGE('CRU historical'!U14, 'CRU historical'!X14, 'CRU historical'!AA14, 'CRU historical'!AD14) -> 61 | L15: {=IFERROR(SUMPRODUCT(('Sulphuric Acid freights'!$B$3:$B$513=B15)*('Sulphuric Acid freights'!$D$3:$D$513=D15)*('Sulphuric Acid freights'!$P$3:$P$513))/SUMPRODUCT(('Sulphuric Acid freights'!$B$3:$B$513=B15)*('Sulphuric Acid freights'!$D$3:$D$513=D15)*1), AVERAGE('Sulphuric Acid freights'!$P$3:$P$513))*2/3} -> 54.110672 | M15: {=IFERROR(SUMPRODUCT(('Sulphuric Acid freights'!$B$3:$B$513=B15)*('Sulphuric Acid freights'!$D$3:$D$513=D15)*('Sulphuric Acid freights'!$M$3:$M$513))/SUMPRODUCT(('Sulphuric Acid freights'!$B$3:$B$513=B15)*('Sulphuric Acid freights'!$D$3:$D$513=D15)*1)*2/3, AVERAGE('Sulphuric Acid freights'!$M$3:$M$513))} -> 23.573123 | N15: =IFERROR(L15*0.9, "") -> 48.699605 | O15: {=IF(SUMPRODUCT(('Sulphur freight'!$B$3:$B$1976=B15)*('Sulphur freight'!$D$3:$D$1976=D15)*('Sulphur freight'!$G$3:$G$1976))/SUMPRODUCT(('Sulphur freight'!$B$3:$B$1976=B15)*('Sulphur freight'!$D$3:$D$1976=D15)*1)=0, AVERAGE('Sulphur freight'!$G$3:$G$1976),SUMPRODUCT(('Sulphur freight'!$B$3:$B$1976=B15)*('Sulphur freight'!$D$3:$D$1976=D15)*('Sulphur freight'!$G$3:$G$1976))/SUMPRODUCT(('Sulphur freight'!$B$3:$B$1976=B15)*('Sulphur freight'!$D$3:$D$1976=D15)*1))} -> 29.165429 | P15: 20 | R15: =H15 | S15: =IF(F15=0, "", F15+M15) -> 36.573123 | T15: =IFERROR( E15+L15, "") | U15: =IFERROR( G15+N15, "") | V15: =IFERROR(I15+O15, "") | W15: =J15+P15 -> 81 | X15: =IFERROR((I15+O15)*0.33+18, "") | Y15: =IF(J15=0,0,(J15+P15)*0.33+18) -> 44.73 | AA15: =IF(OR(S15="", T15="", U15=""), "", MAX(R15,S15)*40%+T15*30%+U15*30%) | AB15: =IF(AA15="", "", MAX(X15, Y15)-AA15) | AD15: =IFERROR(MIN((MAX(R15,S15)*70%+U15*30%), Y15), "") | AE15: =IF(AD15="", "", MAX(AA15, AB15)-AD15)
B16: 2003 | C16: 1 | D16: 3 | E16: ='CRU historical'!F15 | F16: ='CRU historical'!I15 -> 13 | G16: ='CRU historical'!L15 | H16: ='CRU historical'!O15 | I16: ='CRU historical'!R15 | J16: =AVERAGE('CRU historical'!U15, 'CRU historical'!X15, 'CRU historical'!AA15, 'CRU historical'!AD15) -> 62 | L16: {=IFERROR(SUMPRODUCT(('Sulphuric Acid freights'!$B$3:$B$513=B16)*('Sulphuric Acid freights'!$D$3:$D$513=D16)*('Sulphuric Acid freights'!$P$3:$P$513))/SUMPRODUCT(('Sulphuric Acid freights'!$B$3:$B$513=B16)*('Sulphuric Acid freights'!$D$3:$D$513=D16)*1), AVERAGE('Sulphuric Acid freights'!$P$3:$P$513))*2/3} -> 54.110672 | M16: {=IFERROR(SUMPRODUCT(('Sulphuric Acid freights'!$B$3:$B$513=B16)*('Sulphuric Acid freights'!$D$3:$D$513=D16)*('Sulphuric Acid freights'!$M$3:$M$513))/SUMPRODUCT(('Sulphuric Acid freights'!$B$3:$B$513=B16)*('Sulphuric Acid freights'!$D$3:$D$513=D16)*1)*2/3, AVERAGE('Sulphuric Acid freights'!$M$3:$M$513))} -> 23.573123 | N16: =IFERROR(L16*0.9, "") -> 48.699605 | O16: {=IF(SUMPRODUCT(('Sulphur freight'!$B$3:$B$1976=B16)*('Sulphur freight'!$D$3:$D$1976=D16)*('Sulphur freight'!$G$3:$G$1976))/SUMPRODUCT(('Sulphur freight'!$B$3:$B$1976=B16)*('Sulphur freight'!$D$3:$D$1976=D16)*1)=0, AVERAGE('Sulphur freight'!$G$3:$G$1976),SUMPRODUCT(('Sulphur freight'!$B$3:$B$1976=B16)*('Sulphur freight'!$D$3:$D$1976=D16)*('Sulphur freight'!$G$3:$G$1976))/SUMPRODUCT(('Sulphur freight'!$B$3:$B$1976=B16)*('Sulphur freight'!$D$3:$D$1976=D16)*1))} -> 29.165429 | P16: 20 | R16: =H16 | S16: =IF(F16=0, "", F16+M16) -> 36.573123 | T16: =IFERROR( E16+L16, "") | U16: =IFERROR( G16+N16, "") | V16: =IFERROR(I16+O16, "") | W16: =J16+P16 -> 82 | X16: =IFERROR((I16+O16)*0.33+18, "") | Y16: =IF(J16=0,0,(J16+P16)*0.33+18) -> 45.06 | AA16: =IF(OR(S16="", T16="", U16=""), "", MAX(R16,S16)*40%+T16*30%+U16*30%) | AB16: =IF(AA16="", "", MAX(X16, Y16)-AA16) | AD16: =IFERROR(MIN((MAX(R16,S16)*70%+U16*30%), Y16), "") | AE16: =IF(AD16="", "", MAX(AA16, AB16)-AD16)
B17: 2003 | C17: 2 | D17: 4 | E17: ='CRU historical'!F16 | F17: ='CRU historical'!I16 -> 13 | G17: ='CRU historical'!L16 | H17: ='CRU historical'!O16 | I17: ='CRU historical'!R16 | J17: =AVERAGE('CRU historical'!U16, 'CRU historical'!X16, 'CRU historical'!AA16, 'CRU historical'!AD16) -> 60.5 | L17: {=IFERROR(SUMPRODUCT(('Sulphuric Acid freights'!$B$3:$B$513=B17)*('Sulphuric Acid freights'!$D$3:$D$513=D17)*('Sulphuric Acid freights'!$P$3:$P$513))/SUMPRODUCT(('Sulphuric Acid freights'!$B$3:$B$513=B17)*('Sulphuric Acid freights'!$D$3:$D$513=D17)*1), AVERAGE('Sulphuric Acid freights'!$P$3:$P$513))*2/3} -> 54.110672 | M17: {=IFERROR(SUMPRODUCT(('Sulphuric Acid freights'!$B$3:$B$513=B17)*('Sulphuric Acid freights'!$D$3:$D$513=D17)*('Sulphuric Acid freights'!$M$3:$M$513))/SUMPRODUCT(('Sulphuric Acid freights'!$B$3:$B$513=B17)*('Sulphuric Acid freights'!$D$3:$D$513=D17)*1)*2/3, AVERAGE('Sulphuric Acid freights'!$M$3:$M$513))} -> 23.573123 | N17: =IFERROR(L17*0.9, "") -> 48.699605 | O17: {=IF(SUMPRODUCT(('Sulphur freight'!$B$3:$B$1976=B17)*('Sulphur freight'!$D$3:$D$1976=D17)*('Sulphur freight'!$G$3:$G$1976))/SUMPRODUCT(('Sulphur freight'!$B$3:$B$1976=B17)*('Sulphur freight'!$D$3:$D$1976=D17)*1)=0, AVERAGE('Sulphur freight'!$G$3:$G$1976),SUMPRODUCT(('Sulphur freight'!$B$3:$B$1976=B17)*('Sulphur freight'!$D$3:$D$1976=D17)*('Sulphur freight'!$G$3:$G$1976))/SUMPRODUCT(('Sulphur freight'!$B$3:$B$1976=B17)*('Sulphur freight'!$D$3:$D$1976=D17)*1))} -> 29.165429 | P17: 20 | R17: =H17 | S17: =IF(F17=0, "", F17+M17) -> 36.573123 | T17: =IFERROR( E17+L17, "") | U17: =IFERROR( G17+N17, "") | V17: =IFERROR(I17+O17, "") | W17: =J17+P17 -> 80.5 | X17: =IFERROR((I17+O17)*0.33+18, "") | Y17: =IF(J17=0,0,(J17+P17)*0.33+18) -> 44.565 | AA17: =IF(OR(S17="", T17="", U17=""), "", MAX(R17,S17)*40%+T17*30%+U17*30%) | AB17: =IF(AA17="", "", MAX(X17, Y17)-AA17) | AD17: =IFERROR(MIN((MAX(R17,S17)*70%+U17*30%), Y17), "") | AE17: =IF(AD17="", "", MAX(AA17, AB17)-AD17)
... B284: 2025 | C284: 3 | D284: 7 | E284: ='CRU historical'!F283 -> 52 | F284: ='CRU historical'!I283 -> 124 | G284: ='CRU historical'!L283 -> 94.2 | H284: ='CRU historical'!O283 -> 170 | I284: ='CRU historical'!R283 -> 260 | J284: =AVERAGE('CRU historical'!U283, 'CRU historical'!X283, 'CRU historical'!AA283, 'CRU historical'!AD283) -> 256 | L284: {=IFERROR(SUMPRODUCT(('Sulphuric Acid freights'!$B$3:$B$513=B284)*('Sulphuric Acid freights'!$D$3:$D$513=D284)*('Sulphuric Acid freights'!$P$3:$P$513))/SUMPRODUCT(('Sulphuric Acid freights'!$B$3:$B$513=B284)*('Sulphuric Acid freights'!$D$3:$D$513=D284)*1), AVERAGE('Sulphuric Acid freights'!$P$3:$P$513))*2/3} -> 67.6 | M284: {=IFERROR(SUMPRODUCT(('Sulphuric Acid freights'!$B$3:$B$513=B284)*('Sulphuric Acid freights'!$D$3:$D$513=D284)*('Sulphuric Acid freights'!$M$3:$M$513))/SUMPRODUCT(('Sulphuric Acid freights'!$B$3:$B$513=B284)*('Sulphuric Acid freights'!$D$3:$D$513=D284)*1)*2/3, AVERAGE('Sulphuric Acid freights'!$M$3:$M$513))} -> 14.666667 | N284: =IFERROR(L284*0.9, "") -> 60.84 | O284: {=IF(SUMPRODUCT(('Sulphur freight'!$B$3:$B$1976=B284)*('Sulphur freight'!$D$3:$D$1976=D284)*('Sulphur freight'!$G$3:$G$1976))/SUMPRODUCT(('Sulphur freight'!$B$3:$B$1976=B284)*('Sulphur freight'!$D$3:$D$1976=D284)*1)=0, AVERAGE('Sulphur freight'!$G$3:$G$1976),SUMPRODUCT(('Sulphur freight'!$B$3:$B$1976=B284)*('Sulphur freight'!$D$3:$D$1976=D284)*('Sulphur freight'!$G$3:$G$1976))/SUMPRODUCT(('Sulphur freight'!$B$3:$B$1976=B284)*('Sulphur freight'!$D$3:$D$1976=D284)*1))} -> 35 | P284: 20 | R284: =H284 -> 170 | S284: =IF(F284=0, "", F284+M284) -> 138.66667 | T284: =IFERROR( E284+L284, "") -> 119.6 | U284: =IFERROR( G284+N284, "") -> 155.04 | V284: =IFERROR(I284+O284, "") -> 295 | W284: =J284+P284 -> 276 | X284: =IFERROR((I284+O284)*0.33+18, "") -> 115.35 | Y284: =IF(J284=0,0,(J284+P284)*0.33+18) -> 109.08 | AA284: =IF(OR(S284="", T284="", U284=""), "", MAX(R284,S284)*40%+T284*30%+U284*30%) -> 150.392 | AB284: =IF(AA284="", "", MAX(X284, Y284)-AA284) -> -35.042 | AD284: =IFERROR(MIN((MAX(R284,S284)*70%+U284*30%), Y284), "") -> 109.08 | AE284: =IF(AD284="", "", MAX(AA284, AB284)-AD284) -> 41.312
B285: 2025 | C285: 3 | D285: 8 | E285: ='CRU historical'!F284 | F285: ='CRU historical'!I284 -> 116.25 | G285: ='CRU historical'!L284 -> 96 | H285: ='CRU historical'!O284 -> 165 | I285: ='CRU historical'!R284 -> 274.75 | J285: =AVERAGE('CRU historical'!U284, 'CRU historical'!X284, 'CRU historical'!AA284, 'CRU historical'!AD284) -> 268 | L285: {=IFERROR(SUMPRODUCT(('Sulphuric Acid freights'!$B$3:$B$513=B285)*('Sulphuric Acid freights'!$D$3:$D$513=D285)*('Sulphuric Acid freights'!$P$3:$P$513))/SUMPRODUCT(('Sulphuric Acid freights'!$B$3:$B$513=B285)*('Sulphuric Acid freights'!$D$3:$D$513=D285)*1), AVERAGE('Sulphuric Acid freights'!$P$3:$P$513))*2/3} -> 66 | M285: {=IFERROR(SUMPRODUCT(('Sulphuric Acid freights'!$B$3:$B$513=B285)*('Sulphuric Acid freights'!$D$3:$D$513=D285)*('Sulphuric Acid freights'!$M$3:$M$513))/SUMPRODUCT(('Sulphuric Acid freights'!$B$3:$B$513=B285)*('Sulphuric Acid freights'!$D$3:$D$513=D285)*1)*2/3, AVERAGE('Sulphuric Acid freights'!$M$3:$M$513))} -> 14.666667 | N285: =IFERROR(L285*0.9, "") -> 59.4 | O285: {=IF(SUMPRODUCT(('Sulphur freight'!$B$3:$B$1976=B285)*('Sulphur freight'!$D$3:$D$1976=D285)*('Sulphur freight'!$G$3:$G$1976))/SUMPRODUCT(('Sulphur freight'!$B$3:$B$1976=B285)*('Sulphur freight'!$D$3:$D$1976=D285)*1)=0, AVERAGE('Sulphur freight'!$G$3:$G$1976),SUMPRODUCT(('Sulphur freight'!$B$3:$B$1976=B285)*('Sulphur freight'!$D$3:$D$1976=D285)*('Sulphur freight'!$G$3:$G$1976))/SUMPRODUCT(('Sulphur freight'!$B$3:$B$1976=B285)*('Sulphur freight'!$D$3:$D$1976=D285)*1))} -> 35.75 | P285: 20 | R285: =H285 -> 165 | S285: =IF(F285=0, "", F285+M285) -> 130.91667 | T285: =T284*(U285/U284) -> 119.87771 | U285: =IFERROR( G285+N285, "") -> 155.4 | V285: =IFERROR(I285+O285, "") -> 310.5 | W285: =J285+P285 -> 288 | X285: =IFERROR((I285+O285)*0.33+18, "") -> 120.465 | Y285: =IF(J285=0,0,(J285+P285)*0.33+18) -> 113.04 | AA285: =IF(OR(S285="", T285="", U285=""), "", MAX(R285,S285)*40%+T285*30%+U285*30%) -> 148.58331 | AB285: =IF(AA285="", "", MAX(X285, Y285)-AA285) -> -28.118313 | AD285: =IFERROR(MIN((MAX(R285,S285)*70%+U285*30%), Y285), "") -> 113.04 | AE285: =IF(AD285="", "", MAX(AA285, AB285)-AD285) -> 35.543313
B286: 2025 | C286: 3 | D286: 9 | E286: ='CRU historical'!F285 | F286: ='CRU historical'!I285 -> 79.5 | G286: ='CRU historical'!L285 -> 76 | H286: ='CRU historical'!O285 -> 130 | I286: ='CRU historical'!R285 -> 307.75 | J286: =AVERAGE('CRU historical'!U285, 'CRU historical'!X285, 'CRU historical'!AA285, 'CRU historical'!AD285) -> 268 | L286: {=IFERROR(SUMPRODUCT(('Sulphuric Acid freights'!$B$3:$B$513=B286)*('Sulphuric Acid freights'!$D$3:$D$513=D286)*('Sulphuric Acid freights'!$P$3:$P$513))/SUMPRODUCT(('Sulphuric Acid freights'!$B$3:$B$513=B286)*('Sulphuric Acid freights'!$D$3:$D$513=D286)*1), AVERAGE('Sulphuric Acid freights'!$P$3:$P$513))*2/3} -> 66 | M286: {=IFERROR(SUMPRODUCT(('Sulphuric Acid freights'!$B$3:$B$513=B286)*('Sulphuric Acid freights'!$D$3:$D$513=D286)*('Sulphuric Acid freights'!$M$3:$M$513))/SUMPRODUCT(('Sulphuric Acid freights'!$B$3:$B$513=B286)*('Sulphuric Acid freights'!$D$3:$D$513=D286)*1)*2/3, AVERAGE('Sulphuric Acid freights'!$M$3:$M$513))} -> 14.666667 | N286: =IFERROR(L286*0.9, "") -> 59.4 | O286: {=IF(SUMPRODUCT(('Sulphur freight'!$B$3:$B$1976=B286)*('Sulphur freight'!$D$3:$D$1976=D286)*('Sulphur freight'!$G$3:$G$1976))/SUMPRODUCT(('Sulphur freight'!$B$3:$B$1976=B286)*('Sulphur freight'!$D$3:$D$1976=D286)*1)=0, AVERAGE('Sulphur freight'!$G$3:$G$1976),SUMPRODUCT(('Sulphur freight'!$B$3:$B$1976=B286)*('Sulphur freight'!$D$3:$D$1976=D286)*('Sulphur freight'!$G$3:$G$1976))/SUMPRODUCT(('Sulphur freight'!$B$3:$B$1976=B286)*('Sulphur freight'!$D$3:$D$1976=D286)*1))} -> 35.5 | P286: 20 | R286: =H286 -> 130 | S286: =IF(F286=0, "", F286+M286) -> 94.166667 | T286: =T285*(U286/U285) -> 104.44943 | U286: =IFERROR( G286+N286, "") -> 135.4 | V286: =IFERROR(I286+O286, "") -> 343.25 | W286: =J286+P286 -> 288 | X286: =IFERROR((I286+O286)*0.33+18, "") -> 131.2725 | Y286: =IF(J286=0,0,(J286+P286)*0.33+18) -> 113.04 | AA286: =IF(OR(S286="", T286="", U286=""), "", MAX(R286,S286)*40%+T286*30%+U286*30%) -> 123.95483 | AB286: =IF(AA286="", "", MAX(X286, Y286)-AA286) -> 7.3176703 | AD286: =IFERROR(MIN((MAX(R286,S286)*70%+U286*30%), Y286), "") -> 113.04 | AE286: =IF(AD286="", "", MAX(AA286, AB286)-AD286) -> 10.91483
B287: 2025 | C287: 4 | D287: 10 | E287: ='CRU historical'!F286 | F287: ='CRU historical'!I286 -> 80.2 | G287: ='CRU historical'!L286 -> 79.2 | H287: ='CRU historical'!O286 -> 130 | I287: ='CRU historical'!R286 -> 359.8 | J287: =AVERAGE('CRU historical'!U286, 'CRU historical'!X286, 'CRU historical'!AA286, 'CRU historical'!AD286) -> 301.6 | L287: {=IFERROR(SUMPRODUCT(('Sulphuric Acid freights'!$B$3:$B$513=B287)*('Sulphuric Acid freights'!$D$3:$D$513=D287)*('Sulphuric Acid freights'!$P$3:$P$513))/SUMPRODUCT(('Sulphuric Acid freights'!$B$3:$B$513=B287)*('Sulphuric Acid freights'!$D$3:$D$513=D287)*1), AVERAGE('Sulphuric Acid freights'!$P$3:$P$513))*2/3} -> 66 | M287: {=IFERROR(SUMPRODUCT(('Sulphuric Acid freights'!$B$3:$B$513=B287)*('Sulphuric Acid freights'!$D$3:$D$513=D287)*('Sulphuric Acid freights'!$M$3:$M$513))/SUMPRODUCT(('Sulphuric Acid freights'!$B$3:$B$513=B287)*('Sulphuric Acid freights'!$D$3:$D$513=D287)*1)*2/3, AVERAGE('Sulphuric Acid freights'!$M$3:$M$513))} -> 13.6 | N287: =IFERROR(L287*0.9, "") -> 59.4 | O287: {=IF(SUMPRODUCT(('Sulphur freight'!$B$3:$B$1976=B287)*('Sulphur freight'!$D$3:$D$1976=D287)*('Sulphur freight'!$G$3:$G$1976))/SUMPRODUCT(('Sulphur freight'!$B$3:$B$1976=B287)*('Sulphur freight'!$D$3:$D$1976=D287)*1)=0, AVERAGE('Sulphur freight'!$G$3:$G$1976),SUMPRODUCT(('Sulphur freight'!$B$3:$B$1976=B287)*('Sulphur freight'!$D$3:$D$1976=D287)*('Sulphur freight'!$G$3:$G$1976))/SUMPRODUCT(('Sulphur freight'!$B$3:$B$1976=B287)*('Sulphur freight'!$D$3:$D$1976=D287)*1))} -> 31 | P287: 20 | R287: =H287 -> 130 | S287: =IF(F287=0, "", F287+M287) -> 93.8 | T287: =T286*(U287/U286) -> 106.91796 | U287: =IFERROR( G287+N287, "") -> 138.6 | V287: =IFERROR(I287+O287, "") -> 390.8 | W287: =J287+P287 -> 321.6 | X287: =IFERROR((I287+O287)*0.33+18, "") -> 146.964 | Y287: =IF(J287=0,0,(J287+P287)*0.33+18) -> 124.128 | AA287: =IF(OR(S287="", T287="", U287=""), "", MAX(R287,S287)*40%+T287*30%+U287*30%) -> 125.65539 | AB287: =IF(AA287="", "", MAX(X287, Y287)-AA287) -> 21.308613 | AD287: =IFERROR(MIN((MAX(R287,S287)*70%+U287*30%), Y287), "") -> 124.128 | AE287: =IF(AD287="", "", MAX(AA287, AB287)-AD287) -> 1.527387
B288: 2025 | C288: 4 | D288: 11 | E288: ='CRU historical'!F287 | F288: ='CRU historical'!I287 -> 97.75 | G288: ='CRU historical'!L287 -> 105.75 | H288: ='CRU historical'!O287 -> 132.5 | I288: ='CRU historical'!R287 -> 452 | J288: =AVERAGE('CRU historical'!U287, 'CRU historical'!X287, 'CRU historical'!AA287, 'CRU historical'!AD287) -> 310 | L288: {=IFERROR(SUMPRODUCT(('Sulphuric Acid freights'!$B$3:$B$513=B288)*('Sulphuric Acid freights'!$D$3:$D$513=D288)*('Sulphuric Acid freights'!$P$3:$P$513))/SUMPRODUCT(('Sulphuric Acid freights'!$B$3:$B$513=B288)*('Sulphuric Acid freights'!$D$3:$D$513=D288)*1), AVERAGE('Sulphuric Acid freights'!$P$3:$P$513))*2/3} -> 66 | M288: {=IFERROR(SUMPRODUCT(('Sulphuric Acid freights'!$B$3:$B$513=B288)*('Sulphuric Acid freights'!$D$3:$D$513=D288)*('Sulphuric Acid freights'!$M$3:$M$513))/SUMPRODUCT(('Sulphuric Acid freights'!$B$3:$B$513=B288)*('Sulphuric Acid freights'!$D$3:$D$513=D288)*1)*2/3, AVERAGE('Sulphuric Acid freights'!$M$3:$M$513))} -> 14.666667 | N288: =IFERROR(L288*0.9, "") -> 59.4 | O288: {=IF(SUMPRODUCT(('Sulphur freight'!$B$3:$B$1976=B288)*('Sulphur freight'!$D$3:$D$1976=D288)*('Sulphur freight'!$G$3:$G$1976))/SUMPRODUCT(('Sulphur freight'!$B$3:$B$1976=B288)*('Sulphur freight'!$D$3:$D$1976=D288)*1)=0, AVERAGE('Sulphur freight'!$G$3:$G$1976),SUMPRODUCT(('Sulphur freight'!$B$3:$B$1976=B288)*('Sulphur freight'!$D$3:$D$1976=D288)*('Sulphur freight'!$G$3:$G$1976))/SUMPRODUCT(('Sulphur freight'!$B$3:$B$1976=B288)*('Sulphur freight'!$D$3:$D$1976=D288)*1))} -> 32 | P288: 20 | R288: =H288 -> 132.5 | S288: =IF(F288=0, "", F288+M288) -> 112.41667 | T288: =T287*(U288/U287) -> 127.39899 | U288: =IFERROR( G288+N288, "") -> 165.15 | V288: =IFERROR(I288+O288, "") -> 484 | W288: =J288+P288 -> 330 | X288: =IFERROR((I288+O288)*0.33+18, "") -> 177.72 | Y288: =IF(J288=0,0,(J288+P288)*0.33+18) -> 126.9 | AA288: =IF(OR(S288="", T288="", U288=""), "", MAX(R288,S288)*40%+T288*30%+U288*30%) -> 140.7647 | AB288: =IF(AA288="", "", MAX(X288, Y288)-AA288) -> 36.955302 | AD288: =IFERROR(MIN((MAX(R288,S288)*70%+U288*30%), Y288), "") -> 126.9 | AE288: =IF(AD288="", "", MAX(AA288, AB288)-AD288) -> 13.864698
B289: 2025 | C289: 4 | D289: 12 | E289: ='CRU historical'!F288 | F289: ='CRU historical'!I288 -> 106 | G289: ='CRU historical'!L288 -> 113 | H289: ='CRU historical'!O288 -> 136 | I289: ='CRU historical'!R288 -> 507 | J289: =AVERAGE('CRU historical'!U288, 'CRU historical'!X288, 'CRU historical'!AA288, 'CRU historical'!AD288) -> 310 | L289: {=IFERROR(SUMPRODUCT(('Sulphuric Acid freights'!$B$3:$B$513=B289)*('Sulphuric Acid freights'!$D$3:$D$513=D289)*('Sulphuric Acid freights'!$P$3:$P$513))/SUMPRODUCT(('Sulphuric Acid freights'!$B$3:$B$513=B289)*('Sulphuric Acid freights'!$D$3:$D$513=D289)*1), AVERAGE('Sulphuric Acid freights'!$P$3:$P$513))*2/3} -> 66 | M289: {=IFERROR(SUMPRODUCT(('Sulphuric Acid freights'!$B$3:$B$513=B289)*('Sulphuric Acid freights'!$D$3:$D$513=D289)*('Sulphuric Acid freights'!$M$3:$M$513))/SUMPRODUCT(('Sulphuric Acid freights'!$B$3:$B$513=B289)*('Sulphuric Acid freights'!$D$3:$D$513=D289)*1)*2/3, AVERAGE('Sulphuric Acid freights'!$M$3:$M$513))} -> 14.666667 | N289: =IFERROR(L289*0.9, "") -> 59.4 | O289: {=IF(SUMPRODUCT(('Sulphur freight'!$B$3:$B$1976=B289)*('Sulphur freight'!$D$3:$D$1976=D289)*('Sulphur freight'!$G$3:$G$1976))/SUMPRODUCT(('Sulphur freight'!$B$3:$B$1976=B289)*('Sulphur freight'!$D$3:$D$1976=D289)*1)=0, AVERAGE('Sulphur freight'!$G$3:$G$1976),SUMPRODUCT(('Sulphur freight'!$B$3:$B$1976=B289)*('Sulphur freight'!$D$3:$D$1976=D289)*('Sulphur freight'!$G$3:$G$1976))/SUMPRODUCT(('Sulphur freight'!$B$3:$B$1976=B289)*('Sulphur freight'!$D$3:$D$1976=D289)*1))} -> 32.666667 | P289: 20 | R289: =H289 -> 136 | S289: =IF(F289=0, "", F289+M289) -> 120.66667 | T289: =T288*(U289/U288) -> 132.99174 | U289: =IFERROR( G289+N289, "") -> 172.4 | V289: =IFERROR(I289+O289, "") -> 539.66667 | W289: =J289+P289 -> 330 | X289: =IFERROR(V289*0.33+18, "") -> 196.09 | Y289: =IF(J289=0,0,W289*0.33+18) -> 126.9 | AA289: =IF(OR(S289="", T289="", U289=""), "", MAX(R289,S289)*40%+T289*30%+U289*30%) -> 146.01752 | AB289: =IF(AA289="", "", MAX(X289, Y289)-AA289) -> 50.072477 | AD289: =IFERROR(MIN((MAX(R289,S289)*70%+U289*30%), Y289), "") -> 126.9 | AE289: =IF(AD289="", "", MAX(AA289, AB289)-AD289) -> 19.117523
B291: 2026 | S291: ='ACS - CRU Outlook'!D18 -> 83.482143 | T291: ='ACS - CRU Outlook'!H18+'Simulateur sur Avg'!$L$289 -> 155.67083 | U291: ='ACS - CRU Outlook'!I18+'Simulateur sur Avg'!$N$289 -> 143.65417 | V291: ='S - CRU Outlook'!C18+$O$289 -> 384.95976 | W291: ='S - CRU Outlook'!J18+$P$289 -> 384.31322 | X291: =V291*0.33+18 -> 145.03672 | Y291: =W291*0.33+18 -> 144.82336 | AA291: =IF(OR(S291="", T291="", U291=""), "", MAX(R291,S291)*40%+T291*30%+U291*30%) -> 123.19036 | AB291: =IF(AA291="", "", MAX(X291, Y291)-AA291) -> 21.846365 | AD291: =IFERROR(MIN((MAX(R291,S291)*70%+U291*30%), Y291), "") -> 101.53375 | AE291: =IF(AD291="", "", MAX(AA291, AB291)-AD291) -> 21.656607
B292: 2027 | S292: ='ACS - CRU Outlook'!D19 -> 80.929219 | T292: ='ACS - CRU Outlook'!H19+'Simulateur sur Avg'!$L$289 -> 125.92922 | U292: ='ACS - CRU Outlook'!I19+'Simulateur sur Avg'!$N$289 -> 125.32922 | V292: ='S - CRU Outlook'!C19+$O$289 -> 274.13203 | W292: ='S - CRU Outlook'!J19+$P$289 -> 273.30844 | X292: =V292*0.33+18 -> 108.46357 | Y292: =W292*0.33+18 -> 108.19178 | AA292: =IF(OR(S292="", T292="", U292=""), "", MAX(R292,S292)*40%+T292*30%+U292*30%) -> 107.74922 | AB292: =IF(AA292="", "", MAX(X292, Y292)-AA292) -> 0.71435076 | AD292: =IFERROR(MIN((MAX(R292,S292)*70%+U292*30%), Y292), "") -> 94.249219 | AE292: =IF(AD292="", "", MAX(AA292, AB292)-AD292) -> 13.5
B293: 2028 | S293: ='ACS - CRU Outlook'!D20 -> 66.644459 | T293: ='ACS - CRU Outlook'!H20+'Simulateur sur Avg'!$L$289 -> 120.64446 | U293: ='ACS - CRU Outlook'!I20+'Simulateur sur Avg'!$N$289 -> 120.04446 | V293: ='S - CRU Outlook'!C20+$O$289 -> 246.8432 | W293: ='S - CRU Outlook'!J20+$P$289 -> 246.23543 | X293: =V293*0.33+18 -> 99.458256 | Y293: =W293*0.33+18 -> 99.257691 | AA293: =IF(OR(S293="", T293="", U293=""), "", MAX(R293,S293)*40%+T293*30%+U293*30%) -> 98.864459 | AB293: =IF(AA293="", "", MAX(X293, Y293)-AA293) -> 0.59379657 | AD293: =IFERROR(MIN((MAX(R293,S293)*70%+U293*30%), Y293), "") -> 82.664459 | AE293: =IF(AD293="", "", MAX(AA293, AB293)-AD293) -> 16.2
B294: 2029 | S294: ='ACS - CRU Outlook'!D21 -> 65.394434 | T294: ='ACS - CRU Outlook'!H21+'Simulateur sur Avg'!$L$289 -> 114.39443 | U294: ='ACS - CRU Outlook'!I21+'Simulateur sur Avg'!$N$289 -> 113.79443 | V294: ='S - CRU Outlook'!C21+$O$289 -> 239.17879 | W294: ='S - CRU Outlook'!J21+$P$289 -> 238.64587 | X294: =V294*0.33+18 -> 96.929001 | Y294: =W294*0.33+18 -> 96.753136 | AA294: =IF(OR(S294="", T294="", U294=""), "", MAX(R294,S294)*40%+T294*30%+U294*30%) -> 94.614434 | AB294: =IF(AA294="", "", MAX(X294, Y294)-AA294) -> 2.3145674 | AD294: =IFERROR(MIN((MAX(R294,S294)*70%+U294*30%), Y294), "") -> 79.914434 | AE294: =IF(AD294="", "", MAX(AA294, AB294)-AD294) -> 14.7
B295: 2030 | S295: ='ACS - CRU Outlook'!D22 -> 61.438116 | T295: ='ACS - CRU Outlook'!H22+'Simulateur sur Avg'!$L$289 -> 108.43812 | U295: ='ACS - CRU Outlook'!I22+'Simulateur sur Avg'!$N$289 -> 107.83812 | V295: ='S - CRU Outlook'!C22+$O$289 -> 243.75994 | W295: ='S - CRU Outlook'!J22+$P$289 -> 243.21409 | X295: =V295*0.33+18 -> 98.440779 | Y295: =W295*0.33+18 -> 98.260649 | AA295: =IF(OR(S295="", T295="", U295=""), "", MAX(R295,S295)*40%+T295*30%+U295*30%) -> 89.458116 | AB295: =IF(AA295="", "", MAX(X295, Y295)-AA295) -> 8.9826628 | AD295: =IFERROR(MIN((MAX(R295,S295)*70%+U295*30%), Y295), "") -> 75.358116 | AE295: =IF(AD295="", "", MAX(AA295, AB295)-AD295) -> 14.1
B296: 2031
B297: 2032
B298: 2033
B299: 2034
B300: 2035
B301: 2036
B302: 2037

Sheet Simulateur furu
AA1: ConvCost=20+0,05×(SFOBME​+Fret)
B2: Scénario | C2: Low | D2: 0.8 | J2: used for ACS production cost estimation
R3: Paramètres
R5: Futur
B12: Projections annuelles moyennes | E12: ACS FOB Japan | F12: ACS FOB NW Europe | G12: ACS FOB China Spot | H12: ACS CFR North Africa Spot | I12: Sulphur Bulk FOB Middle East | J12: Sulphur Bulk CFR North Africa | L12: Fret Japan to Morocco | M12: Fret NW EU to Morocco | N12: Fret China to Morocco | O12: Fret Middle East to Morocco | P12: Freight adjustment (CRU)
B13: 2026 | E13: ='ACS - CRU Outlook'!H18 -> 89.670833 | F13: ='ACS - CRU Outlook'!D18 -> 83.482143 | G13: ='ACS - CRU Outlook'!I18 -> 84.254167 | H13: =F13+25 -> 108.48214 | I13: ='S - CRU Outlook'!C18 -> 352.2931 | J13: ='S - CRU Outlook'!J18 -> 364.31322 | L13: =AVERAGE(L301:L311) -> 70.069697 | M13: =AVERAGE(M301:M311) -> 15.145455 | N13: =AVERAGE(N301:N311) -> 63.062727 | O13: =AVERAGE(O301:O311) -> 32.701515 | P13: =AVERAGE(P301:P311) -> 20
B14: 2027 | E14: ='ACS - CRU Outlook'!H19 -> 59.929219 | F14: ='ACS - CRU Outlook'!D19 -> 80.929219 | G14: ='ACS - CRU Outlook'!I19 -> 65.929219 | H14: =F14+25 -> 105.92922 | I14: ='S - CRU Outlook'!C19 -> 241.46536 | J14: ='S - CRU Outlook'!J19 -> 253.30844 | L14: =L13 -> 70.069697 | M14: =M13 -> 15.145455 | N14: =N13 -> 63.062727 | O14: =O13 -> 32.701515 | P14: =P13 -> 20
B15: 2028 | E15: ='ACS - CRU Outlook'!H20 -> 54.644459 | F15: ='ACS - CRU Outlook'!D20 -> 66.644459 | G15: ='ACS - CRU Outlook'!I20 -> 60.644459 | H15: =F15+25 -> 91.644459 | I15: ='S - CRU Outlook'!C20 -> 214.17653 | J15: ='S - CRU Outlook'!J20 -> 226.23543 | L15: =L14 -> 70.069697 | M15: =M14 -> 15.145455 | N15: =N14 -> 63.062727 | O15: =O14 -> 32.701515 | P15: =P14 -> 20
B16: 2029 | E16: ='ACS - CRU Outlook'!H21 -> 48.394434 | F16: ='ACS - CRU Outlook'!D21 -> 65.394434 | G16: ='ACS - CRU Outlook'!I21 -> 54.394434 | H16: =F16+25 -> 90.394434 | I16: ='S - CRU Outlook'!C21 -> 206.51213 | J16: ='S - CRU Outlook'!J21 -> 218.64587 | L16: =L15 -> 70.069697 | M16: =M15 -> 15.145455 | N16: =N15 -> 63.062727 | O16: =O15 -> 32.701515 | P16: =P15 -> 20
B17: 2030 | E17: ='ACS - CRU Outlook'!H22 -> 42.438116 | F17: ='ACS - CRU Outlook'!D22 -> 61.438116 | G17: ='ACS - CRU Outlook'!I22 -> 48.438116 | H17: =F17+25 -> 86.438116 | I17: ='S - CRU Outlook'!C22 -> 211.09327 | J17: ='S - CRU Outlook'!J22 -> 223.21409 | L17: =L16 -> 70.069697 | M17: =M16 -> 15.145455 | N17: =N16 -> 63.062727 | O17: =O16 -> 32.701515 | P17: =P16 -> 20
B18: 2031 | E18: =E17 -> 42.438116 | F18: =F17 -> 61.438116 | G18: =G17 -> 48.438116 | H18: =H17 -> 86.438116 | I18: =I17 -> 211.09327 | J18: =J17 -> 223.21409 | L18: =L17 -> 70.069697 | M18: =M17 -> 15.145455 | N18: =N17 -> 63.062727 | O18: =O17 -> 32.701515 | P18: =P17 -> 20
B19: 2032 | E19: =E18 -> 42.438116 | F19: =F18 -> 61.438116 | G19: =G18 -> 48.438116 | H19: =H18 -> 86.438116 | I19: =I18 -> 211.09327 | J19: =J18 -> 223.21409 | L19: =L18 -> 70.069697 | M19: =M18 -> 15.145455 | N19: =N18 -> 63.062727 | O19: =O18 -> 32.701515 | P19: =P18 -> 20
B20: 2033 | E20: =E19 -> 42.438116 | F20: =F19 -> 61.438116 | G20: =G19 -> 48.438116 | H20: =H19 -> 86.438116 | I20: =I19 -> 211.09327 | J20: =J19 -> 223.21409 | L20: =L19 -> 70.069697 | M20: =M19 -> 15.145455 | N20: =N19 -> 63.062727 | O20: =O19 -> 32.701515 | P20: =P19 -> 20
B21: 2034 | E21: =E20 -> 42.438116 | F21: =F20 -> 61.438116 | G21: =G20 -> 48.438116 | H21: =H20 -> 86.438116 | I21: =I20 -> 211.09327 | J21: =J20 -> 223.21409 | L21: =L20 -> 70.069697 | M21: =M20 -> 15.145455 | N21: =N20 -> 63.062727 | O21: =O20 -> 32.701515 | P21: =P20 -> 20
B22: 2035 | E22: =E21 -> 42.438116 | F22: =F21 -> 61.438116 | G22: =G21 -> 48.438116 | H22: =H21 -> 86.438116 | I22: =I21 -> 211.09327 | J22: =J21 -> 223.21409 | L22: =L21 -> 70.069697 | M22: =M21 -> 15.145455 | N22: =N21 -> 63.062727 | O22: =O21 -> 32.701515 | P22: =P21 -> 20
B23: 2036 | E23: =E22 -> 42.438116 | F23: =F22 -> 61.438116 | G23: =G22 -> 48.438116 | H23: =H22 -> 86.438116 | I23: =I22 -> 211.09327 | J23: =J22 -> 223.21409 | L23: =L22 -> 70.069697 | M23: =M22 -> 15.145455 | N23: =N22 -> 63.062727 | O23: =O22 -> 32.701515 | P23: =P22 -> 20
E25: Sulphuric Acid Bulk FOB | F25: Sulphuric Acid Bulk FOB | G25: Sulphuric Acid Bulk FOB | H25: Sulphuric Acid Bulk CFR | I25: Sulphur Bulk FOB | J25: Sulphur Bulk CFR | L25: Sulphuric Acid Bulk FOB | M25: Sulphuric Acid Bulk FOB | N25: Sulphuric Acid Bulk FOB | O25: Sulphur Bulk FOB | P25: Sulphur Bulk CFR
E26: Japan/South Korea Spot | F26: NW Europe 30 days Spot | G26: China Spot | H26: North Africa, Spot | I26: Middle East Spot | J26: North Africa | L26: Japan/South Korea Spot | M26: NW Europe 30 days Spot | N26: China Spot | O26: Middle East Spot | P26: North Africa | R26: Prix cibles Sulphuric Acid | AA26: Formule 1: Market Basket | AD26: Formule 2: Indice Composite basé sur Europe, chine et acid base ME
C27: Quarter | D27: Month | E27: ACS FOB Japan | F27: ACS FOB NW Europe | G27: ACS FOB China Spot | H27: ACS CFR North Africa Spot | I27: Sulphur Bulk FOB Middle East | J27: Sulphur Bulk CFR North Africa | L27: Fret Japan to Morocco | M27: Fret NW EU to Morocco | N27: Fret China to Morocco | O27: Fret Middle East to Morocco | P27: Freight adjustment (CRU) | R27: ACS CFR North Africa | S27: IPP ACS Origine Europe | T27: IPP ACS origine Japon | U27: Ipp ACS Origine Chine | V27: Sulfur ME to CFR Morocco | W27: Sulfur North Africa to CFR Morocco | X27: ACS S based from Sulfur ME | Y27: ACS S based from Sulfur North Africa | AA27: IPP_Acid = 40% × IPP_NWE + 30% × IPP_Japan + 30% × IPP_China | AB27: Gain par rapport à production sur place | AD27: IPP_Acid = min((70% × IPP_NWE + 30% × IPP_China); Acid S Based ME) | AE27: Gain par rapport à production sur place
C28: 2 | D28: 5 | E28: ='CRU historical'!F5 | F28: ='CRU historical'!I5 -> 6 | G28: ='CRU historical'!L5 | H28: ='CRU historical'!O5 | I28: ='CRU historical'!R5 | J28: =AVERAGE('CRU historical'!U5, 'CRU historical'!X5, 'CRU historical'!AA5, 'CRU historical'!AD5) -> 33 | L28: {=IFERROR(SUMPRODUCT(('Sulphuric Acid freights'!$B$3:$B$513=B38)*('Sulphuric Acid freights'!$D$3:$D$513=D28)*('Sulphuric Acid freights'!$P$3:$P$513))/SUMPRODUCT(('Sulphuric Acid freights'!$B$3:$B$513=B38)*('Sulphuric Acid freights'!$D$3:$D$513=D28)*1), AVERAGE('Sulphuric Acid freights'!$P$3:$P$513))*2/3} -> 54.110672 | M28: {=IFERROR(SUMPRODUCT(('Sulphuric Acid freights'!$B$3:$B$513=B38)*('Sulphuric Acid freights'!$D$3:$D$513=D28)*('Sulphuric Acid freights'!$M$3:$M$513))/SUMPRODUCT(('Sulphuric Acid freights'!$B$3:$B$513=B38)*('Sulphuric Acid freights'!$D$3:$D$513=D28)*1)*2/3, AVERAGE('Sulphuric Acid freights'!$M$3:$M$513))} -> 23.573123 | N28: =IFERROR(L28*0.9, "") -> 48.699605 | O28: {=IF(SUMPRODUCT(('Sulphur freight'!$B$3:$B$1976=B38)*('Sulphur freight'!$D$3:$D$1976=D28)*('Sulphur freight'!$G$3:$G$1976))/SUMPRODUCT(('Sulphur freight'!$B$3:$B$1976=B38)*('Sulphur freight'!$D$3:$D$1976=D28)*1)=0, AVERAGE('Sulphur freight'!$G$3:$G$1976),SUMPRODUCT(('Sulphur freight'!$B$3:$B$1976=B38)*('Sulphur freight'!$D$3:$D$1976=D28)*('Sulphur freight'!$G$3:$G$1976))/SUMPRODUCT(('Sulphur freight'!$B$3:$B$1976=B38)*('Sulphur freight'!$D$3:$D$1976=D28)*1))} -> 29.165429 | P28: 20 | R28: =H28 | S28: =IF(F28=0, "", F28+M28) -> 29.573123 | T28: =IFERROR( E28+L28, "") | U28: =IFERROR( G28+N28, "") | V28: =IFERROR(I28+O28, "") | W28: =J28+P28 -> 53 | X28: =IFERROR((I28+O28)*0.33+18, "") | Y28: =IF(J28=0,0,(J28+P28)*0.33+18) -> 35.49 | AA28: =IF(OR(S28="", T28="", U28=""), "", MAX(R28,S28)*40%+T28*30%+U28*30%) | AB28: =IF(AA28="", "", MAX(X28, Y28)-AA28) | AD28: =IFERROR(MIN((MAX(R28,S28)*70%+U28*30%), Y28), "") | AE28: =IF(AD28="", "", MAX(AA28, AB28)-AD28)
C29: 2 | D29: 6 | E29: ='CRU historical'!F6 | F29: ='CRU historical'!I6 -> 6 | G29: ='CRU historical'!L6 | H29: ='CRU historical'!O6 | I29: ='CRU historical'!R6 | J29: =AVERAGE('CRU historical'!U6, 'CRU historical'!X6, 'CRU historical'!AA6, 'CRU historical'!AD6) -> 33 | L29: {=IFERROR(SUMPRODUCT(('Sulphuric Acid freights'!$B$3:$B$513=B39)*('Sulphuric Acid freights'!$D$3:$D$513=D29)*('Sulphuric Acid freights'!$P$3:$P$513))/SUMPRODUCT(('Sulphuric Acid freights'!$B$3:$B$513=B39)*('Sulphuric Acid freights'!$D$3:$D$513=D29)*1), AVERAGE('Sulphuric Acid freights'!$P$3:$P$513))*2/3} -> 54.110672 | M29: {=IFERROR(SUMPRODUCT(('Sulphuric Acid freights'!$B$3:$B$513=B39)*('Sulphuric Acid freights'!$D$3:$D$513=D29)*('Sulphuric Acid freights'!$M$3:$M$513))/SUMPRODUCT(('Sulphuric Acid freights'!$B$3:$B$513=B39)*('Sulphuric Acid freights'!$D$3:$D$513=D29)*1)*2/3, AVERAGE('Sulphuric Acid freights'!$M$3:$M$513))} -> 23.573123 | N29: =IFERROR(L29*0.9, "") -> 48.699605 | O29: {=IF(SUMPRODUCT(('Sulphur freight'!$B$3:$B$1976=B39)*('Sulphur freight'!$D$3:$D$1976=D29)*('Sulphur freight'!$G$3:$G$1976))/SUMPRODUCT(('Sulphur freight'!$B$3:$B$1976=B39)*('Sulphur freight'!$D$3:$D$1976=D29)*1)=0, AVERAGE('Sulphur freight'!$G$3:$G$1976),SUMPRODUCT(('Sulphur freight'!$B$3:$B$1976=B39)*('Sulphur freight'!$D$3:$D$1976=D29)*('Sulphur freight'!$G$3:$G$1976))/SUMPRODUCT(('Sulphur freight'!$B$3:$B$1976=B39)*('Sulphur freight'!$D$3:$D$1976=D29)*1))} -> 29.165429 | P29: 20 | R29: =H29 | S29: =IF(F29=0, "", F29+M29) -> 29.573123 | T29: =IFERROR( E29+L29, "") | U29: =IFERROR( G29+N29, "") | V29: =IFERROR(I29+O29, "") | W29: =J29+P29 -> 53 | X29: =IFERROR((I29+O29)*0.33+18, "") | Y29: =IF(J29=0,0,(J29+P29)*0.33+18) -> 35.49 | AA29: =IF(OR(S29="", T29="", U29=""), "", MAX(R29,S29)*40%+T29*30%+U29*30%) | AB29: =IF(AA29="", "", MAX(X29, Y29)-AA29) | AD29: =IFERROR(MIN((MAX(R29,S29)*70%+U29*30%), Y29), "") | AE29: =IF(AD29="", "", MAX(AA29, AB29)-AD29)
C30: 3 | D30: 7 | E30: ='CRU historical'!F7 | F30: ='CRU historical'!I7 -> 8 | G30: ='CRU historical'!L7 | H30: ='CRU historical'!O7 | I30: ='CRU historical'!R7 | J30: =AVERAGE('CRU historical'!U7, 'CRU historical'!X7, 'CRU historical'!AA7, 'CRU historical'!AD7) -> 39 | L30: {=IFERROR(SUMPRODUCT(('Sulphuric Acid freights'!$B$3:$B$513=B40)*('Sulphuric Acid freights'!$D$3:$D$513=D30)*('Sulphuric Acid freights'!$P$3:$P$513))/SUMPRODUCT(('Sulphuric Acid freights'!$B$3:$B$513=B40)*('Sulphuric Acid freights'!$D$3:$D$513=D30)*1), AVERAGE('Sulphuric Acid freights'!$P$3:$P$513))*2/3} -> 54.110672 | M30: {=IFERROR(SUMPRODUCT(('Sulphuric Acid freights'!$B$3:$B$513=B40)*('Sulphuric Acid freights'!$D$3:$D$513=D30)*('Sulphuric Acid freights'!$M$3:$M$513))/SUMPRODUCT(('Sulphuric Acid freights'!$B$3:$B$513=B40)*('Sulphuric Acid freights'!$D$3:$D$513=D30)*1)*2/3, AVERAGE('Sulphuric Acid freights'!$M$3:$M$513))} -> 23.573123 | N30: =IFERROR(L30*0.9, "") -> 48.699605 | O30: {=IF(SUMPRODUCT(('Sulphur freight'!$B$3:$B$1976=B40)*('Sulphur freight'!$D$3:$D$1976=D30)*('Sulphur freight'!$G$3:$G$1976))/SUMPRODUCT(('Sulphur freight'!$B$3:$B$1976=B40)*('Sulphur freight'!$D$3:$D$1976=D30)*1)=0, AVERAGE('Sulphur freight'!$G$3:$G$1976),SUMPRODUCT(('Sulphur freight'!$B$3:$B$1976=B40)*('Sulphur freight'!$D$3:$D$1976=D30)*('Sulphur freight'!$G$3:$G$1976))/SUMPRODUCT(('Sulphur freight'!$B$3:$B$1976=B40)*('Sulphur freight'!$D$3:$D$1976=D30)*1))} -> 29.165429 | P30: 20 | R30: =H30 | S30: =IF(F30=0, "", F30+M30) -> 31.573123 | T30: =IFERROR( E30+L30, "") | U30: =IFERROR( G30+N30, "") | V30: =IFERROR(I30+O30, "") | W30: =J30+P30 -> 59 | X30: =IFERROR((I30+O30)*0.33+18, "") | Y30: =IF(J30=0,0,(J30+P30)*0.33+18) -> 37.47 | AA30: =IF(OR(S30="", T30="", U30=""), "", MAX(R30,S30)*40%+T30*30%+U30*30%) | AB30: =IF(AA30="", "", MAX(X30, Y30)-AA30) | AD30: =IFERROR(MIN((MAX(R30,S30)*70%+U30*30%), Y30), "") | AE30: =IF(AD30="", "", MAX(AA30, AB30)-AD30)
C31: 3 | D31: 8 | E31: ='CRU historical'!F8 | F31: ='CRU historical'!I8 -> 8 | G31: ='CRU historical'!L8 | H31: ='CRU historical'!O8 | I31: ='CRU historical'!R8 | J31: =AVERAGE('CRU historical'!U8, 'CRU historical'!X8, 'CRU historical'!AA8, 'CRU historical'!AD8) -> 38.5 | L31: {=IFERROR(SUMPRODUCT(('Sulphuric Acid freights'!$B$3:$B$513=B41)*('Sulphuric Acid freights'!$D$3:$D$513=D31)*('Sulphuric Acid freights'!$P$3:$P$513))/SUMPRODUCT(('Sulphuric Acid freights'!$B$3:$B$513=B41)*('Sulphuric Acid freights'!$D$3:$D$513=D31)*1), AVERAGE('Sulphuric Acid freights'!$P$3:$P$513))*2/3} -> 54.110672 | M31: {=IFERROR(SUMPRODUCT(('Sulphuric Acid freights'!$B$3:$B$513=B41)*('Sulphuric Acid freights'!$D$3:$D$513=D31)*('Sulphuric Acid freights'!$M$3:$M$513))/SUMPRODUCT(('Sulphuric Acid freights'!$B$3:$B$513=B41)*('Sulphuric Acid freights'!$D$3:$D$513=D31)*1)*2/3, AVERAGE('Sulphuric Acid freights'!$M$3:$M$513))} -> 23.573123 | N31: =IFERROR(L31*0.9, "") -> 48.699605 | O31: {=IF(SUMPRODUCT(('Sulphur freight'!$B$3:$B$1976=B41)*('Sulphur freight'!$D$3:$D$1976=D31)*('Sulphur freight'!$G$3:$G$1976))/SUMPRODUCT(('Sulphur freight'!$B$3:$B$1976=B41)*('Sulphur freight'!$D$3:$D$1976=D31)*1)=0, AVERAGE('Sulphur freight'!$G$3:$G$1976),SUMPRODUCT(('Sulphur freight'!$B$3:$B$1976=B41)*('Sulphur freight'!$D$3:$D$1976=D31)*('Sulphur freight'!$G$3:$G$1976))/SUMPRODUCT(('Sulphur freight'!$B$3:$B$1976=B41)*('Sulphur freight'!$D$3:$D$1976=D31)*1))} -> 29.165429 | P31: 20 | R31: =H31 | S31: =IF(F31=0, "", F31+M31) -> 31.573123 | T31: =IFERROR( E31+L31, "") | U31: =IFERROR( G31+N31, "") | V31: =IFERROR(I31+O31, "") | W31: =J31+P31 -> 58.5 | X31: =IFERROR((I31+O31)*0.33+18, "") | Y31: =IF(J31=0,0,(J31+P31)*0.33+18) -> 37.305 | AA31: =IF(OR(S31="", T31="", U31=""), "", MAX(R31,S31)*40%+T31*30%+U31*30%) | AB31: =IF(AA31="", "", MAX(X31, Y31)-AA31) | AD31: =IFERROR(MIN((MAX(R31,S31)*70%+U31*30%), Y31), "") | AE31: =IF(AD31="", "", MAX(AA31, AB31)-AD31)
C32: 3 | D32: 9 | E32: ='CRU historical'!F9 | F32: ='CRU historical'!I9 -> 8 | G32: ='CRU historical'!L9 | H32: ='CRU historical'!O9 | I32: ='CRU historical'!R9 | J32: =AVERAGE('CRU historical'!U9, 'CRU historical'!X9, 'CRU historical'!AA9, 'CRU historical'!AD9) -> 38 | L32: {=IFERROR(SUMPRODUCT(('Sulphuric Acid freights'!$B$3:$B$513=B42)*('Sulphuric Acid freights'!$D$3:$D$513=D32)*('Sulphuric Acid freights'!$P$3:$P$513))/SUMPRODUCT(('Sulphuric Acid freights'!$B$3:$B$513=B42)*('Sulphuric Acid freights'!$D$3:$D$513=D32)*1), AVERAGE('Sulphuric Acid freights'!$P$3:$P$513))*2/3} -> 54.110672 | M32: {=IFERROR(SUMPRODUCT(('Sulphuric Acid freights'!$B$3:$B$513=B42)*('Sulphuric Acid freights'!$D$3:$D$513=D32)*('Sulphuric Acid freights'!$M$3:$M$513))/SUMPRODUCT(('Sulphuric Acid freights'!$B$3:$B$513=B42)*('Sulphuric Acid freights'!$D$3:$D$513=D32)*1)*2/3, AVERAGE('Sulphuric Acid freights'!$M$3:$M$513))} -> 23.573123 | N32: =IFERROR(L32*0.9, "") -> 48.699605 | O32: {=IF(SUMPRODUCT(('Sulphur freight'!$B$3:$B$1976=B42)*('Sulphur freight'!$D$3:$D$1976=D32)*('Sulphur freight'!$G$3:$G$1976))/SUMPRODUCT(('Sulphur freight'!$B$3:$B$1976=B42)*('Sulphur freight'!$D$3:$D$1976=D32)*1)=0, AVERAGE('Sulphur freight'!$G$3:$G$1976),SUMPRODUCT(('Sulphur freight'!$B$3:$B$1976=B42)*('Sulphur freight'!$D$3:$D$1976=D32)*('Sulphur freight'!$G$3:$G$1976))/SUMPRODUCT(('Sulphur freight'!$B$3:$B$1976=B42)*('Sulphur freight'!$D$3:$D$1976=D32)*1))} -> 29.165429 | P32: 20 | R32: =H32 | S32: =IF(F32=0, "", F32+M32) -> 31.573123 | T32: =IFERROR( E32+L32, "") | U32: =IFERROR( G32+N32, "") | V32: =IFERROR(I32+O32, "") | W32: =J32+P32 -> 58 | X32: =IFERROR((I32+O32)*0.33+18, "") | Y32: =IF(J32=0,0,(J32+P32)*0.33+18) -> 37.14 | AA32: =IF(OR(S32="", T32="", U32=""), "", MAX(R32,S32)*40%+T32*30%+U32*30%) | AB32: =IF(AA32="", "", MAX(X32, Y32)-AA32) | AD32: =IFERROR(MIN((MAX(R32,S32)*70%+U32*30%), Y32), "") | AE32: =IF(AD32="", "", MAX(AA32, AB32)-AD32)
C33: 4 | D33: 10 | E33: ='CRU historical'!F10 | F33: ='CRU historical'!I10 -> 8 | G33: ='CRU historical'!L10 | H33: ='CRU historical'!O10 | I33: ='CRU historical'!R10 | J33: =AVERAGE('CRU historical'!U10, 'CRU historical'!X10, 'CRU historical'!AA10, 'CRU historical'!AD10) -> 38 | L33: {=IFERROR(SUMPRODUCT(('Sulphuric Acid freights'!$B$3:$B$513=B43)*('Sulphuric Acid freights'!$D$3:$D$513=D33)*('Sulphuric Acid freights'!$P$3:$P$513))/SUMPRODUCT(('Sulphuric Acid freights'!$B$3:$B$513=B43)*('Sulphuric Acid freights'!$D$3:$D$513=D33)*1), AVERAGE('Sulphuric Acid freights'!$P$3:$P$513))*2/3} -> 54.110672 | M33: {=IFERROR(SUMPRODUCT(('Sulphuric Acid freights'!$B$3:$B$513=B43)*('Sulphuric Acid freights'!$D$3:$D$513=D33)*('Sulphuric Acid freights'!$M$3:$M$513))/SUMPRODUCT(('Sulphuric Acid freights'!$B$3:$B$513=B43)*('Sulphuric Acid freights'!$D$3:$D$513=D33)*1)*2/3, AVERAGE('Sulphuric Acid freights'!$M$3:$M$513))} -> 23.573123 | N33: =IFERROR(L33*0.9, "") -> 48.699605 | O33: {=IF(SUMPRODUCT(('Sulphur freight'!$B$3:$B$1976=B43)*('Sulphur freight'!$D$3:$D$1976=D33)*('Sulphur freight'!$G$3:$G$1976))/SUMPRODUCT(('Sulphur freight'!$B$3:$B$1976=B43)*('Sulphur freight'!$D$3:$D$1976=D33)*1)=0, AVERAGE('Sulphur freight'!$G$3:$G$1976),SUMPRODUCT(('Sulphur freight'!$B$3:$B$1976=B43)*('Sulphur freight'!$D$3:$D$1976=D33)*('Sulphur freight'!$G$3:$G$1976))/SUMPRODUCT(('Sulphur freight'!$B$3:$B$1976=B43)*('Sulphur freight'!$D$3:$D$1976=D33)*1))} -> 29.165429 | P33: 20 | R33: =H33 | S33: =IF(F33=0, "", F33+M33) -> 31.573123 | T33: =IFERROR( E33+L33, "") | U33: =IFERROR( G33+N33, "") | V33: =IFERROR(I33+O33, "") | W33: =J33+P33 -> 58 | X33: =IFERROR((I33+O33)*0.33+18, "") | Y33: =IF(J33=0,0,(J33+P33)*0.33+18) -> 37.14 | AA33: =IF(OR(S33="", T33="", U33=""), "", MAX(R33,S33)*40%+T33*30%+U33*30%) | AB33: =IF(AA33="", "", MAX(X33, Y33)-AA33) | AD33: =IFERROR(MIN((MAX(R33,S33)*70%+U33*30%), Y33), "") | AE33: =IF(AD33="", "", MAX(AA33, AB33)-AD33)
C34: 4 | D34: 11 | E34: ='CRU historical'!F11 | F34: ='CRU historical'!I11 -> 11 | G34: ='CRU historical'!L11 | H34: ='CRU historical'!O11 | I34: ='CRU historical'!R11 | J34: =AVERAGE('CRU historical'!U11, 'CRU historical'!X11, 'CRU historical'!AA11, 'CRU historical'!AD11) -> 39 | L34: {=IFERROR(SUMPRODUCT(('Sulphuric Acid freights'!$B$3:$B$513=B44)*('Sulphuric Acid freights'!$D$3:$D$513=D34)*('Sulphuric Acid freights'!$P$3:$P$513))/SUMPRODUCT(('Sulphuric Acid freights'!$B$3:$B$513=B44)*('Sulphuric Acid freights'!$D$3:$D$513=D34)*1), AVERAGE('Sulphuric Acid freights'!$P$3:$P$513))*2/3} -> 54.110672 | M34: {=IFERROR(SUMPRODUCT(('Sulphuric Acid freights'!$B$3:$B$513=B44)*('Sulphuric Acid freights'!$D$3:$D$513=D34)*('Sulphuric Acid freights'!$M$3:$M$513))/SUMPRODUCT(('Sulphuric Acid freights'!$B$3:$B$513=B44)*('Sulphuric Acid freights'!$D$3:$D$513=D34)*1)*2/3, AVERAGE('Sulphuric Acid freights'!$M$3:$M$513))} -> 23.573123 | N34: =IFERROR(L34*0.9, "") -> 48.699605 | O34: {=IF(SUMPRODUCT(('Sulphur freight'!$B$3:$B$1976=B44)*('Sulphur freight'!$D$3:$D$1976=D34)*('Sulphur freight'!$G$3:$G$1976))/SUMPRODUCT(('Sulphur freight'!$B$3:$B$1976=B44)*('Sulphur freight'!$D$3:$D$1976=D34)*1)=0, AVERAGE('Sulphur freight'!$G$3:$G$1976),SUMPRODUCT(('Sulphur freight'!$B$3:$B$1976=B44)*('Sulphur freight'!$D$3:$D$1976=D34)*('Sulphur freight'!$G$3:$G$1976))/SUMPRODUCT(('Sulphur freight'!$B$3:$B$1976=B44)*('Sulphur freight'!$D$3:$D$1976=D34)*1))} -> 29.165429 | P34: 20 | R34: =H34 | S34: =IF(F34=0, "", F34+M34) -> 34.573123 | T34: =IFERROR( E34+L34, "") | U34: =IFERROR( G34+N34, "") | V34: =IFERROR(I34+O34, "") | W34: =J34+P34 -> 59 | X34: =IFERROR((I34+O34)*0.33+18, "") | Y34: =IF(J34=0,0,(J34+P34)*0.33+18) -> 37.47 | AA34: =IF(OR(S34="", T34="", U34=""), "", MAX(R34,S34)*40%+T34*30%+U34*30%) | AB34: =IF(AA34="", "", MAX(X34, Y34)-AA34) | AD34: =IFERROR(MIN((MAX(R34,S34)*70%+U34*30%), Y34), "") | AE34: =IF(AD34="", "", MAX(AA34, AB34)-AD34)
C35: 4 | D35: 12 | E35: ='CRU historical'!F12 | F35: ='CRU historical'!I12 -> 11 | G35: ='CRU historical'!L12 | H35: ='CRU historical'!O12 | I35: ='CRU historical'!R12 | J35: =AVERAGE('CRU historical'!U12, 'CRU historical'!X12, 'CRU historical'!AA12, 'CRU historical'!AD12) -> 39 | L35: {=IFERROR(SUMPRODUCT(('Sulphuric Acid freights'!$B$3:$B$513=B45)*('Sulphuric Acid freights'!$D$3:$D$513=D35)*('Sulphuric Acid freights'!$P$3:$P$513))/SUMPRODUCT(('Sulphuric Acid freights'!$B$3:$B$513=B45)*('Sulphuric Acid freights'!$D$3:$D$513=D35)*1), AVERAGE('Sulphuric Acid freights'!$P$3:$P$513))*2/3} -> 54.110672 | M35: {=IFERROR(SUMPRODUCT(('Sulphuric Acid freights'!$B$3:$B$513=B45)*('Sulphuric Acid freights'!$D$3:$D$513=D35)*('Sulphuric Acid freights'!$M$3:$M$513))/SUMPRODUCT(('Sulphuric Acid freights'!$B$3:$B$513=B45)*('Sulphuric Acid freights'!$D$3:$D$513=D35)*1)*2/3, AVERAGE('Sulphuric Acid freights'!$M$3:$M$513))} -> 23.573123 | N35: =IFERROR(L35*0.9, "") -> 48.699605 | O35: {=IF(SUMPRODUCT(('Sulphur freight'!$B$3:$B$1976=B45)*('Sulphur freight'!$D$3:$D$1976=D35)*('Sulphur freight'!$G$3:$G$1976))/SUMPRODUCT(('Sulphur freight'!$B$3:$B$1976=B45)*('Sulphur freight'!$D$3:$D$1976=D35)*1)=0, AVERAGE('Sulphur freight'!$G$3:$G$1976),SUMPRODUCT(('Sulphur freight'!$B$3:$B$1976=B45)*('Sulphur freight'!$D$3:$D$1976=D35)*('Sulphur freight'!$G$3:$G$1976))/SUMPRODUCT(('Sulphur freight'!$B$3:$B$1976=B45)*('Sulphur freight'!$D$3:$D$1976=D35)*1))} -> 29.165429 | P35: 20 | R35: =H35 | S35: =IF(F35=0, "", F35+M35) -> 34.573123 | T35: =IFERROR( E35+L35, "") | U35: =IFERROR( G35+N35, "") | V35: =IFERROR(I35+O35, "") | W35: =J35+P35 -> 59 | X35: =IFERROR((I35+O35)*0.33+18, "") | Y35: =IF(J35=0,0,(J35+P35)*0.33+18) -> 37.47 | AA35: =IF(OR(S35="", T35="", U35=""), "", MAX(R35,S35)*40%+T35*30%+U35*30%) | AB35: =IF(AA35="", "", MAX(X35, Y35)-AA35) | AD35: =IFERROR(MIN((MAX(R35,S35)*70%+U35*30%), Y35), "") | AE35: =IF(AD35="", "", MAX(AA35, AB35)-AD35)
C36: 1 | D36: 1 | E36: ='CRU historical'!F13 | F36: ='CRU historical'!I13 -> 11.666667 | G36: ='CRU historical'!L13 | H36: ='CRU historical'!O13 | I36: ='CRU historical'!R13 | J36: =AVERAGE('CRU historical'!U13, 'CRU historical'!X13, 'CRU historical'!AA13, 'CRU historical'!AD13) -> 57.333333 | L36: {=IFERROR(SUMPRODUCT(('Sulphuric Acid freights'!$B$3:$B$513=B46)*('Sulphuric Acid freights'!$D$3:$D$513=D36)*('Sulphuric Acid freights'!$P$3:$P$513))/SUMPRODUCT(('Sulphuric Acid freights'!$B$3:$B$513=B46)*('Sulphuric Acid freights'!$D$3:$D$513=D36)*1), AVERAGE('Sulphuric Acid freights'!$P$3:$P$513))*2/3} -> 54.110672 | M36: {=IFERROR(SUMPRODUCT(('Sulphuric Acid freights'!$B$3:$B$513=B46)*('Sulphuric Acid freights'!$D$3:$D$513=D36)*('Sulphuric Acid freights'!$M$3:$M$513))/SUMPRODUCT(('Sulphuric Acid freights'!$B$3:$B$513=B46)*('Sulphuric Acid freights'!$D$3:$D$513=D36)*1)*2/3, AVERAGE('Sulphuric Acid freights'!$M$3:$M$513))} -> 23.573123 | N36: =IFERROR(L36*0.9, "") -> 48.699605 | O36: {=IF(SUMPRODUCT(('Sulphur freight'!$B$3:$B$1976=B46)*('Sulphur freight'!$D$3:$D$1976=D36)*('Sulphur freight'!$G$3:$G$1976))/SUMPRODUCT(('Sulphur freight'!$B$3:$B$1976=B46)*('Sulphur freight'!$D$3:$D$1976=D36)*1)=0, AVERAGE('Sulphur freight'!$G$3:$G$1976),SUMPRODUCT(('Sulphur freight'!$B$3:$B$1976=B46)*('Sulphur freight'!$D$3:$D$1976=D36)*('Sulphur freight'!$G$3:$G$1976))/SUMPRODUCT(('Sulphur freight'!$B$3:$B$1976=B46)*('Sulphur freight'!$D$3:$D$1976=D36)*1))} -> 29.165429 | P36: 20 | R36: =H36 | S36: =IF(F36=0, "", F36+M36) -> 35.239789 | T36: =IFERROR( E36+L36, "") | U36: =IFERROR( G36+N36, "") | V36: =IFERROR(I36+O36, "") | W36: =J36+P36 -> 77.333333 | X36: =IFERROR((I36+O36)*0.33+18, "") | Y36: =IF(J36=0,0,(J36+P36)*0.33+18) -> 43.52 | AA36: =IF(OR(S36="", T36="", U36=""), "", MAX(R36,S36)*40%+T36*30%+U36*30%) | AB36: =IF(AA36="", "", MAX(X36, Y36)-AA36) | AD36: =IFERROR(MIN((MAX(R36,S36)*70%+U36*30%), Y36), "") | AE36: =IF(AD36="", "", MAX(AA36, AB36)-AD36)
B37: Year | C37: 1 | D37: 2 | E37: ='CRU historical'!F14 | F37: ='CRU historical'!I14 -> 13 | G37: ='CRU historical'!L14 | H37: ='CRU historical'!O14 | I37: ='CRU historical'!R14 | J37: =AVERAGE('CRU historical'!U14, 'CRU historical'!X14, 'CRU historical'!AA14, 'CRU historical'!AD14) -> 61 | L37: {=IFERROR(SUMPRODUCT(('Sulphuric Acid freights'!$B$3:$B$513=B47)*('Sulphuric Acid freights'!$D$3:$D$513=D37)*('Sulphuric Acid freights'!$P$3:$P$513))/SUMPRODUCT(('Sulphuric Acid freights'!$B$3:$B$513=B47)*('Sulphuric Acid freights'!$D$3:$D$513=D37)*1), AVERAGE('Sulphuric Acid freights'!$P$3:$P$513))*2/3} -> 54.110672 | M37: {=IFERROR(SUMPRODUCT(('Sulphuric Acid freights'!$B$3:$B$513=B47)*('Sulphuric Acid freights'!$D$3:$D$513=D37)*('Sulphuric Acid freights'!$M$3:$M$513))/SUMPRODUCT(('Sulphuric Acid freights'!$B$3:$B$513=B47)*('Sulphuric Acid freights'!$D$3:$D$513=D37)*1)*2/3, AVERAGE('Sulphuric Acid freights'!$M$3:$M$513))} -> 23.573123 | N37: =IFERROR(L37*0.9, "") -> 48.699605 | O37: {=IF(SUMPRODUCT(('Sulphur freight'!$B$3:$B$1976=B47)*('Sulphur freight'!$D$3:$D$1976=D37)*('Sulphur freight'!$G$3:$G$1976))/SUMPRODUCT(('Sulphur freight'!$B$3:$B$1976=B47)*('Sulphur freight'!$D$3:$D$1976=D37)*1)=0, AVERAGE('Sulphur freight'!$G$3:$G$1976),SUMPRODUCT(('Sulphur freight'!$B$3:$B$1976=B47)*('Sulphur freight'!$D$3:$D$1976=D37)*('Sulphur freight'!$G$3:$G$1976))/SUMPRODUCT(('Sulphur freight'!$B$3:$B$1976=B47)*('Sulphur freight'!$D$3:$D$1976=D37)*1))} -> 29.165429 | P37: 20 | R37: =H37 | S37: =IF(F37=0, "", F37+M37) -> 36.573123 | T37: =IFERROR( E37+L37, "") | U37: =IFERROR( G37+N37, "") | V37: =IFERROR(I37+O37, "") | W37: =J37+P37 -> 81 | X37: =IFERROR((I37+O37)*0.33+18, "") | Y37: =IF(J37=0,0,(J37+P37)*0.33+18) -> 44.73 | AA37: =IF(OR(S37="", T37="", U37=""), "", MAX(R37,S37)*40%+T37*30%+U37*30%) | AB37: =IF(AA37="", "", MAX(X37, Y37)-AA37) | AD37: =IFERROR(MIN((MAX(R37,S37)*70%+U37*30%), Y37), "") | AE37: =IF(AD37="", "", MAX(AA37, AB37)-AD37)
B38: 2002 | C38: 1 | D38: 3 | E38: ='CRU historical'!F15 | F38: ='CRU historical'!I15 -> 13 | G38: ='CRU historical'!L15 | H38: ='CRU historical'!O15 | I38: ='CRU historical'!R15 | J38: =AVERAGE('CRU historical'!U15, 'CRU historical'!X15, 'CRU historical'!AA15, 'CRU historical'!AD15) -> 62 | L38: {=IFERROR(SUMPRODUCT(('Sulphuric Acid freights'!$B$3:$B$513=B48)*('Sulphuric Acid freights'!$D$3:$D$513=D38)*('Sulphuric Acid freights'!$P$3:$P$513))/SUMPRODUCT(('Sulphuric Acid freights'!$B$3:$B$513=B48)*('Sulphuric Acid freights'!$D$3:$D$513=D38)*1), AVERAGE('Sulphuric Acid freights'!$P$3:$P$513))*2/3} -> 54.110672 | M38: {=IFERROR(SUMPRODUCT(('Sulphuric Acid freights'!$B$3:$B$513=B48)*('Sulphuric Acid freights'!$D$3:$D$513=D38)*('Sulphuric Acid freights'!$M$3:$M$513))/SUMPRODUCT(('Sulphuric Acid freights'!$B$3:$B$513=B48)*('Sulphuric Acid freights'!$D$3:$D$513=D38)*1)*2/3, AVERAGE('Sulphuric Acid freights'!$M$3:$M$513))} -> 23.573123 | N38: =IFERROR(L38*0.9, "") -> 48.699605 | O38: {=IF(SUMPRODUCT(('Sulphur freight'!$B$3:$B$1976=B48)*('Sulphur freight'!$D$3:$D$1976=D38)*('Sulphur freight'!$G$3:$G$1976))/SUMPRODUCT(('Sulphur freight'!$B$3:$B$1976=B48)*('Sulphur freight'!$D$3:$D$1976=D38)*1)=0, AVERAGE('Sulphur freight'!$G$3:$G$1976),SUMPRODUCT(('Sulphur freight'!$B$3:$B$1976=B48)*('Sulphur freight'!$D$3:$D$1976=D38)*('Sulphur freight'!$G$3:$G$1976))/SUMPRODUCT(('Sulphur freight'!$B$3:$B$1976=B48)*('Sulphur freight'!$D$3:$D$1976=D38)*1))} -> 29.165429 | P38: 20 | R38: =H38 | S38: =IF(F38=0, "", F38+M38) -> 36.573123 | T38: =IFERROR( E38+L38, "") | U38: =IFERROR( G38+N38, "") | V38: =IFERROR(I38+O38, "") | W38: =J38+P38 -> 82 | X38: =IFERROR((I38+O38)*0.33+18, "") | Y38: =IF(J38=0,0,(J38+P38)*0.33+18) -> 45.06 | AA38: =IF(OR(S38="", T38="", U38=""), "", MAX(R38,S38)*40%+T38*30%+U38*30%) | AB38: =IF(AA38="", "", MAX(X38, Y38)-AA38) | AD38: =IFERROR(MIN((MAX(R38,S38)*70%+U38*30%), Y38), "") | AE38: =IF(AD38="", "", MAX(AA38, AB38)-AD38)
B39: 2002 | C39: 2 | D39: 4 | E39: ='CRU historical'!F16 | F39: ='CRU historical'!I16 -> 13 | G39: ='CRU historical'!L16 | H39: ='CRU historical'!O16 | I39: ='CRU historical'!R16 | J39: =AVERAGE('CRU historical'!U16, 'CRU historical'!X16, 'CRU historical'!AA16, 'CRU historical'!AD16) -> 60.5 | L39: {=IFERROR(SUMPRODUCT(('Sulphuric Acid freights'!$B$3:$B$513=B49)*('Sulphuric Acid freights'!$D$3:$D$513=D39)*('Sulphuric Acid freights'!$P$3:$P$513))/SUMPRODUCT(('Sulphuric Acid freights'!$B$3:$B$513=B49)*('Sulphuric Acid freights'!$D$3:$D$513=D39)*1), AVERAGE('Sulphuric Acid freights'!$P$3:$P$513))*2/3} -> 54.110672 | M39: {=IFERROR(SUMPRODUCT(('Sulphuric Acid freights'!$B$3:$B$513=B49)*('Sulphuric Acid freights'!$D$3:$D$513=D39)*('Sulphuric Acid freights'!$M$3:$M$513))/SUMPRODUCT(('Sulphuric Acid freights'!$B$3:$B$513=B49)*('Sulphuric Acid freights'!$D$3:$D$513=D39)*1)*2/3, AVERAGE('Sulphuric Acid freights'!$M$3:$M$513))} -> 23.573123 | N39: =IFERROR(L39*0.9, "") -> 48.699605 | O39: {=IF(SUMPRODUCT(('Sulphur freight'!$B$3:$B$1976=B49)*('Sulphur freight'!$D$3:$D$1976=D39)*('Sulphur freight'!$G$3:$G$1976))/SUMPRODUCT(('Sulphur freight'!$B$3:$B$1976=B49)*('Sulphur freight'!$D$3:$D$1976=D39)*1)=0, AVERAGE('Sulphur freight'!$G$3:$G$1976),SUMPRODUCT(('Sulphur freight'!$B$3:$B$1976=B49)*('Sulphur freight'!$D$3:$D$1976=D39)*('Sulphur freight'!$G$3:$G$1976))/SUMPRODUCT(('Sulphur freight'!$B$3:$B$1976=B49)*('Sulphur freight'!$D$3:$D$1976=D39)*1))} -> 29.165429 | P39: 20 | R39: =H39 | S39: =IF(F39=0, "", F39+M39) -> 36.573123 | T39: =IFERROR( E39+L39, "") | U39: =IFERROR( G39+N39, "") | V39: =IFERROR(I39+O39, "") | W39: =J39+P39 -> 80.5 | X39: =IFERROR((I39+O39)*0.33+18, "") | Y39: =IF(J39=0,0,(J39+P39)*0.33+18) -> 44.565 | AA39: =IF(OR(S39="", T39="", U39=""), "", MAX(R39,S39)*40%+T39*30%+U39*30%) | AB39: =IF(AA39="", "", MAX(X39, Y39)-AA39) | AD39: =IFERROR(MIN((MAX(R39,S39)*70%+U39*30%), Y39), "") | AE39: =IF(AD39="", "", MAX(AA39, AB39)-AD39)
B40: 2002 | C40: 2 | D40: 5 | E40: ='CRU historical'!F17 | F40: ='CRU historical'!I17 -> 13 | G40: ='CRU historical'!L17 | H40: ='CRU historical'!O17 | I40: ='CRU historical'!R17 | J40: =AVERAGE('CRU historical'!U17, 'CRU historical'!X17, 'CRU historical'!AA17, 'CRU historical'!AD17) -> 60.5 | L40: {=IFERROR(SUMPRODUCT(('Sulphuric Acid freights'!$B$3:$B$513=B50)*('Sulphuric Acid freights'!$D$3:$D$513=D40)*('Sulphuric Acid freights'!$P$3:$P$513))/SUMPRODUCT(('Sulphuric Acid freights'!$B$3:$B$513=B50)*('Sulphuric Acid freights'!$D$3:$D$513=D40)*1), AVERAGE('Sulphuric Acid freights'!$P$3:$P$513))*2/3} -> 54.110672 | M40: {=IFERROR(SUMPRODUCT(('Sulphuric Acid freights'!$B$3:$B$513=B50)*('Sulphuric Acid freights'!$D$3:$D$513=D40)*('Sulphuric Acid freights'!$M$3:$M$513))/SUMPRODUCT(('Sulphuric Acid freights'!$B$3:$B$513=B50)*('Sulphuric Acid freights'!$D$3:$D$513=D40)*1)*2/3, AVERAGE('Sulphuric Acid freights'!$M$3:$M$513))} -> 23.573123 | N40: =IFERROR(L40*0.9, "") -> 48.699605 | O40: {=IF(SUMPRODUCT(('Sulphur freight'!$B$3:$B$1976=B50)*('Sulphur freight'!$D$3:$D$1976=D40)*('Sulphur freight'!$G$3:$G$1976))/SUMPRODUCT(('Sulphur freight'!$B$3:$B$1976=B50)*('Sulphur freight'!$D$3:$D$1976=D40)*1)=0, AVERAGE('Sulphur freight'!$G$3:$G$1976),SUMPRODUCT(('Sulphur freight'!$B$3:$B$1976=B50)*('Sulphur freight'!$D$3:$D$1976=D40)*('Sulphur freight'!$G$3:$G$1976))/SUMPRODUCT(('Sulphur freight'!$B$3:$B$1976=B50)*('Sulphur freight'!$D$3:$D$1976=D40)*1))} -> 29.165429 | P40: 20 | R40: =H40 | S40: =IF(F40=0, "", F40+M40) -> 36.573123 | T40: =IFERROR( E40+L40, "") | U40: =IFERROR( G40+N40, "") | V40: =IFERROR(I40+O40, "") | W40: =J40+P40 -> 80.5 | X40: =IFERROR((I40+O40)*0.33+18, "") | Y40: =IF(J40=0,0,(J40+P40)*0.33+18) -> 44.565 | AA40: =IF(OR(S40="", T40="", U40=""), "", MAX(R40,S40)*40%+T40*30%+U40*30%) | AB40: =IF(AA40="", "", MAX(X40, Y40)-AA40) | AD40: =IFERROR(MIN((MAX(R40,S40)*70%+U40*30%), Y40), "") | AE40: =IF(AD40="", "", MAX(AA40, AB40)-AD40)
B41: 2002 | C41: 2 | D41: 6 | E41: ='CRU historical'!F18 | F41: ='CRU historical'!I18 -> 17.5 | G41: ='CRU historical'!L18 | H41: ='CRU historical'!O18 | I41: ='CRU historical'!R18 -> 63 | J41: =AVERAGE('CRU historical'!U18, 'CRU historical'!X18, 'CRU historical'!AA18, 'CRU historical'!AD18) -> 60.5 | L41: {=IFERROR(SUMPRODUCT(('Sulphuric Acid freights'!$B$3:$B$513=B51)*('Sulphuric Acid freights'!$D$3:$D$513=D41)*('Sulphuric Acid freights'!$P$3:$P$513))/SUMPRODUCT(('Sulphuric Acid freights'!$B$3:$B$513=B51)*('Sulphuric Acid freights'!$D$3:$D$513=D41)*1), AVERAGE('Sulphuric Acid freights'!$P$3:$P$513))*2/3} -> 54.110672 | M41: {=IFERROR(SUMPRODUCT(('Sulphuric Acid freights'!$B$3:$B$513=B51)*('Sulphuric Acid freights'!$D$3:$D$513=D41)*('Sulphuric Acid freights'!$M$3:$M$513))/SUMPRODUCT(('Sulphuric Acid freights'!$B$3:$B$513=B51)*('Sulphuric Acid freights'!$D$3:$D$513=D41)*1)*2/3, AVERAGE('Sulphuric Acid freights'!$M$3:$M$513))} -> 23.573123 | N41: =IFERROR(L41*0.9, "") -> 48.699605 | O41: {=IF(SUMPRODUCT(('Sulphur freight'!$B$3:$B$1976=B51)*('Sulphur freight'!$D$3:$D$1976=D41)*('Sulphur freight'!$G$3:$G$1976))/SUMPRODUCT(('Sulphur freight'!$B$3:$B$1976=B51)*('Sulphur freight'!$D$3:$D$1976=D41)*1)=0, AVERAGE('Sulphur freight'!$G$3:$G$1976),SUMPRODUCT(('Sulphur freight'!$B$3:$B$1976=B51)*('Sulphur freight'!$D$3:$D$1976=D41)*('Sulphur freight'!$G$3:$G$1976))/SUMPRODUCT(('Sulphur freight'!$B$3:$B$1976=B51)*('Sulphur freight'!$D$3:$D$1976=D41)*1))} -> 29.165429 | P41: 20 | R41: =H41 | S41: =IF(F41=0, "", F41+M41) -> 41.073123 | T41: =IFERROR( E41+L41, "") | U41: =IFERROR( G41+N41, "") | V41: =IFERROR(I41+O41, "") -> 92.165429 | W41: =J41+P41 -> 80.5 | X41: =IFERROR((I41+O41)*0.33+18, "") -> 48.414592 | Y41: =IF(J41=0,0,(J41+P41)*0.33+18) -> 44.565 | AA41: =IF(OR(S41="", T41="", U41=""), "", MAX(R41,S41)*40%+T41*30%+U41*30%) | AB41: =IF(AA41="", "", MAX(X41, Y41)-AA41) | AD41: =IFERROR(MIN((MAX(R41,S41)*70%+U41*30%), Y41), "") | AE41: =IF(AD41="", "", MAX(AA41, AB41)-AD41)
B42: 2002 | C42: 3 | D42: 7 | E42: ='CRU historical'!F19 | F42: ='CRU historical'!I19 -> 22 | G42: ='CRU historical'!L19 | H42: ='CRU historical'!O19 | I42: ='CRU historical'!R19 -> 59 | J42: =AVERAGE('CRU historical'!U19, 'CRU historical'!X19, 'CRU historical'!AA19, 'CRU historical'!AD19) -> 65.333333 | L42: {=IFERROR(SUMPRODUCT(('Sulphuric Acid freights'!$B$3:$B$513=B52)*('Sulphuric Acid freights'!$D$3:$D$513=D42)*('Sulphuric Acid freights'!$P$3:$P$513))/SUMPRODUCT(('Sulphuric Acid freights'!$B$3:$B$513=B52)*('Sulphuric Acid freights'!$D$3:$D$513=D42)*1), AVERAGE('Sulphuric Acid freights'!$P$3:$P$513))*2/3} -> 54.110672 | M42: {=IFERROR(SUMPRODUCT(('Sulphuric Acid freights'!$B$3:$B$513=B52)*('Sulphuric Acid freights'!$D$3:$D$513=D42)*('Sulphuric Acid freights'!$M$3:$M$513))/SUMPRODUCT(('Sulphuric Acid freights'!$B$3:$B$513=B52)*('Sulphuric Acid freights'!$D$3:$D$513=D42)*1)*2/3, AVERAGE('Sulphuric Acid freights'!$M$3:$M$513))} -> 23.573123 | N42: =IFERROR(L42*0.9, "") -> 48.699605 | O42: {=IF(SUMPRODUCT(('Sulphur freight'!$B$3:$B$1976=B52)*('Sulphur freight'!$D$3:$D$1976=D42)*('Sulphur freight'!$G$3:$G$1976))/SUMPRODUCT(('Sulphur freight'!$B$3:$B$1976=B52)*('Sulphur freight'!$D$3:$D$1976=D42)*1)=0, AVERAGE('Sulphur freight'!$G$3:$G$1976),SUMPRODUCT(('Sulphur freight'!$B$3:$B$1976=B52)*('Sulphur freight'!$D$3:$D$1976=D42)*('Sulphur freight'!$G$3:$G$1976))/SUMPRODUCT(('Sulphur freight'!$B$3:$B$1976=B52)*('Sulphur freight'!$D$3:$D$1976=D42)*1))} -> 29.165429 | P42: 20 | R42: =H42 | S42: =IF(F42=0, "", F42+M42) -> 45.573123 | T42: =IFERROR( E42+L42, "") | U42: =IFERROR( G42+N42, "") | V42: =IFERROR(I42+O42, "") -> 88.165429 | W42: =J42+P42 -> 85.333333 | X42: =IFERROR((I42+O42)*0.33+18, "") -> 47.094592 | Y42: =IF(J42=0,0,(J42+P42)*0.33+18) -> 46.16 | AA42: =IF(OR(S42="", T42="", U42=""), "", MAX(R42,S42)*40%+T42*30%+U42*30%) | AB42: =IF(AA42="", "", MAX(X42, Y42)-AA42) | AD42: =IFERROR(MIN((MAX(R42,S42)*70%+U42*30%), Y42), "") | AE42: =IF(AD42="", "", MAX(AA42, AB42)-AD42)
B43: 2002 | C43: 3 | D43: 8 | E43: ='CRU historical'!F20 | F43: ='CRU historical'!I20 -> 22 | G43: ='CRU historical'!L20 | H43: ='CRU historical'!O20 | I43: ='CRU historical'!R20 -> 58 | J43: =AVERAGE('CRU historical'!U20, 'CRU historical'!X20, 'CRU historical'!AA20, 'CRU historical'!AD20) -> 69.5 | L43: {=IFERROR(SUMPRODUCT(('Sulphuric Acid freights'!$B$3:$B$513=B53)*('Sulphuric Acid freights'!$D$3:$D$513=D43)*('Sulphuric Acid freights'!$P$3:$P$513))/SUMPRODUCT(('Sulphuric Acid freights'!$B$3:$B$513=B53)*('Sulphuric Acid freights'!$D$3:$D$513=D43)*1), AVERAGE('Sulphuric Acid freights'!$P$3:$P$513))*2/3} -> 54.110672 | M43: {=IFERROR(SUMPRODUCT(('Sulphuric Acid freights'!$B$3:$B$513=B53)*('Sulphuric Acid freights'!$D$3:$D$513=D43)*('Sulphuric Acid freights'!$M$3:$M$513))/SUMPRODUCT(('Sulphuric Acid freights'!$B$3:$B$513=B53)*('Sulphuric Acid freights'!$D$3:$D$513=D43)*1)*2/3, AVERAGE('Sulphuric Acid freights'!$M$3:$M$513))} -> 23.573123 | N43: =IFERROR(L43*0.9, "") -> 48.699605 | O43: {=IF(SUMPRODUCT(('Sulphur freight'!$B$3:$B$1976=B53)*('Sulphur freight'!$D$3:$D$1976=D43)*('Sulphur freight'!$G$3:$G$1976))/SUMPRODUCT(('Sulphur freight'!$B$3:$B$1976=B53)*('Sulphur freight'!$D$3:$D$1976=D43)*1)=0, AVERAGE('Sulphur freight'!$G$3:$G$1976),SUMPRODUCT(('Sulphur freight'!$B$3:$B$1976=B53)*('Sulphur freight'!$D$3:$D$1976=D43)*('Sulphur freight'!$G$3:$G$1976))/SUMPRODUCT(('Sulphur freight'!$B$3:$B$1976=B53)*('Sulphur freight'!$D$3:$D$1976=D43)*1))} -> 29.165429 | P43: 20 | R43: =H43 | S43: =IF(F43=0, "", F43+M43) -> 45.573123 | T43: =IFERROR( E43+L43, "") | U43: =IFERROR( G43+N43, "") | V43: =IFERROR(I43+O43, "") -> 87.165429 | W43: =J43+P43 -> 89.5 | X43: =IFERROR((I43+O43)*0.33+18, "") -> 46.764592 | Y43: =IF(J43=0,0,(J43+P43)*0.33+18) -> 47.535 | AA43: =IF(OR(S43="", T43="", U43=""), "", MAX(R43,S43)*40%+T43*30%+U43*30%) | AB43: =IF(AA43="", "", MAX(X43, Y43)-AA43) | AD43: =IFERROR(MIN((MAX(R43,S43)*70%+U43*30%), Y43), "") | AE43: =IF(AD43="", "", MAX(AA43, AB43)-AD43)
B44: 2002 | C44: 3 | D44: 9 | E44: ='CRU historical'!F21 | F44: ='CRU historical'!I21 -> 22 | G44: ='CRU historical'!L21 | H44: ='CRU historical'!O21 | I44: ='CRU historical'!R21 -> 61.5 | J44: =AVERAGE('CRU historical'!U21, 'CRU historical'!X21, 'CRU historical'!AA21, 'CRU historical'!AD21) -> 69.5 | L44: {=IFERROR(SUMPRODUCT(('Sulphuric Acid freights'!$B$3:$B$513=B54)*('Sulphuric Acid freights'!$D$3:$D$513=D44)*('Sulphuric Acid freights'!$P$3:$P$513))/SUMPRODUCT(('Sulphuric Acid freights'!$B$3:$B$513=B54)*('Sulphuric Acid freights'!$D$3:$D$513=D44)*1), AVERAGE('Sulphuric Acid freights'!$P$3:$P$513))*2/3} -> 54.110672 | M44: {=IFERROR(SUMPRODUCT(('Sulphuric Acid freights'!$B$3:$B$513=B54)*('Sulphuric Acid freights'!$D$3:$D$513=D44)*('Sulphuric Acid freights'!$M$3:$M$513))/SUMPRODUCT(('Sulphuric Acid freights'!$B$3:$B$513=B54)*('Sulphuric Acid freights'!$D$3:$D$513=D44)*1)*2/3, AVERAGE('Sulphuric Acid freights'!$M$3:$M$513))} -> 23.573123 | N44: =IFERROR(L44*0.9, "") -> 48.699605 | O44: {=IF(SUMPRODUCT(('Sulphur freight'!$B$3:$B$1976=B54)*('Sulphur freight'!$D$3:$D$1976=D44)*('Sulphur freight'!$G$3:$G$1976))/SUMPRODUCT(('Sulphur freight'!$B$3:$B$1976=B54)*('Sulphur freight'!$D$3:$D$1976=D44)*1)=0, AVERAGE('Sulphur freight'!$G$3:$G$1976),SUMPRODUCT(('Sulphur freight'!$B$3:$B$1976=B54)*('Sulphur freight'!$D$3:$D$1976=D44)*('Sulphur freight'!$G$3:$G$1976))/SUMPRODUCT(('Sulphur freight'!$B$3:$B$1976=B54)*('Sulphur freight'!$D$3:$D$1976=D44)*1))} -> 29.165429 | P44: 20 | R44: =H44 | S44: =IF(F44=0, "", F44+M44) -> 45.573123 | T44: =IFERROR( E44+L44, "") | U44: =IFERROR( G44+N44, "") | V44: =IFERROR(I44+O44, "") -> 90.665429 | W44: =J44+P44 -> 89.5 | X44: =IFERROR((I44+O44)*0.33+18, "") -> 47.919592 | Y44: =IF(J44=0,0,(J44+P44)*0.33+18) -> 47.535 | AA44: =IF(OR(S44="", T44="", U44=""), "", MAX(R44,S44)*40%+T44*30%+U44*30%) | AB44: =IF(AA44="", "", MAX(X44, Y44)-AA44) | AD44: =IFERROR(MIN((MAX(R44,S44)*70%+U44*30%), Y44), "") | AE44: =IF(AD44="", "", MAX(AA44, AB44)-AD44)
B45: 2002 | C45: 4 | D45: 10 | E45: ='CRU historical'!F22 | F45: ='CRU historical'!I22 -> 28 | G45: ='CRU historical'!L22 | H45: ='CRU historical'!O22 | I45: ='CRU historical'!R22 -> 63 | J45: =AVERAGE('CRU historical'!U22, 'CRU historical'!X22, 'CRU historical'!AA22, 'CRU historical'!AD22) -> 69.75 | L45: {=IFERROR(SUMPRODUCT(('Sulphuric Acid freights'!$B$3:$B$513=B55)*('Sulphuric Acid freights'!$D$3:$D$513=D45)*('Sulphuric Acid freights'!$P$3:$P$513))/SUMPRODUCT(('Sulphuric Acid freights'!$B$3:$B$513=B55)*('Sulphuric Acid freights'!$D$3:$D$513=D45)*1), AVERAGE('Sulphuric Acid freights'!$P$3:$P$513))*2/3} -> 54.110672 | M45: {=IFERROR(SUMPRODUCT(('Sulphuric Acid freights'!$B$3:$B$513=B55)*('Sulphuric Acid freights'!$D$3:$D$513=D45)*('Sulphuric Acid freights'!$M$3:$M$513))/SUMPRODUCT(('Sulphuric Acid freights'!$B$3:$B$513=B55)*('Sulphuric Acid freights'!$D$3:$D$513=D45)*1)*2/3, AVERAGE('Sulphuric Acid freights'!$M$3:$M$513))} -> 23.573123 | N45: =IFERROR(L45*0.9, "") -> 48.699605 | O45: {=IF(SUMPRODUCT(('Sulphur freight'!$B$3:$B$1976=B55)*('Sulphur freight'!$D$3:$D$1976=D45)*('Sulphur freight'!$G$3:$G$1976))/SUMPRODUCT(('Sulphur freight'!$B$3:$B$1976=B55)*('Sulphur freight'!$D$3:$D$1976=D45)*1)=0, AVERAGE('Sulphur freight'!$G$3:$G$1976),SUMPRODUCT(('Sulphur freight'!$B$3:$B$1976=B55)*('Sulphur freight'!$D$3:$D$1976=D45)*('Sulphur freight'!$G$3:$G$1976))/SUMPRODUCT(('Sulphur freight'!$B$3:$B$1976=B55)*('Sulphur freight'!$D$3:$D$1976=D45)*1))} -> 29.165429 | P45: 20 | R45: =H45 | S45: =IF(F45=0, "", F45+M45) -> 51.573123 | T45: =IFERROR( E45+L45, "") | U45: =IFERROR( G45+N45, "") | V45: =IFERROR(I45+O45, "") -> 92.165429 | W45: =J45+P45 -> 89.75 | X45: =IFERROR((I45+O45)*0.33+18, "") -> 48.414592 | Y45: =IF(J45=0,0,(J45+P45)*0.33+18) -> 47.6175 | AA45: =IF(OR(S45="", T45="", U45=""), "", MAX(R45,S45)*40%+T45*30%+U45*30%) | AB45: =IF(AA45="", "", MAX(X45, Y45)-AA45) | AD45: =IFERROR(MIN((MAX(R45,S45)*70%+U45*30%), Y45), "") | AE45: =IF(AD45="", "", MAX(AA45, AB45)-AD45)
B46: 2003 | C46: 4 | D46: 11 | E46: ='CRU historical'!F23 | F46: ='CRU historical'!I23 -> 28 | G46: ='CRU historical'!L23 | H46: ='CRU historical'!O23 | I46: ='CRU historical'!R23 -> 68 | J46: =AVERAGE('CRU historical'!U23, 'CRU historical'!X23, 'CRU historical'!AA23, 'CRU historical'!AD23) -> 71 | L46: {=IFERROR(SUMPRODUCT(('Sulphuric Acid freights'!$B$3:$B$513=B56)*('Sulphuric Acid freights'!$D$3:$D$513=D46)*('Sulphuric Acid freights'!$P$3:$P$513))/SUMPRODUCT(('Sulphuric Acid freights'!$B$3:$B$513=B56)*('Sulphuric Acid freights'!$D$3:$D$513=D46)*1), AVERAGE('Sulphuric Acid freights'!$P$3:$P$513))*2/3} -> 54.110672 | M46: {=IFERROR(SUMPRODUCT(('Sulphuric Acid freights'!$B$3:$B$513=B56)*('Sulphuric Acid freights'!$D$3:$D$513=D46)*('Sulphuric Acid freights'!$M$3:$M$513))/SUMPRODUCT(('Sulphuric Acid freights'!$B$3:$B$513=B56)*('Sulphuric Acid freights'!$D$3:$D$513=D46)*1)*2/3, AVERAGE('Sulphuric Acid freights'!$M$3:$M$513))} -> 23.573123 | N46: =IFERROR(L46*0.9, "") -> 48.699605 | O46: {=IF(SUMPRODUCT(('Sulphur freight'!$B$3:$B$1976=B56)*('Sulphur freight'!$D$3:$D$1976=D46)*('Sulphur freight'!$G$3:$G$1976))/SUMPRODUCT(('Sulphur freight'!$B$3:$B$1976=B56)*('Sulphur freight'!$D$3:$D$1976=D46)*1)=0, AVERAGE('Sulphur freight'!$G$3:$G$1976),SUMPRODUCT(('Sulphur freight'!$B$3:$B$1976=B56)*('Sulphur freight'!$D$3:$D$1976=D46)*('Sulphur freight'!$G$3:$G$1976))/SUMPRODUCT(('Sulphur freight'!$B$3:$B$1976=B56)*('Sulphur freight'!$D$3:$D$1976=D46)*1))} -> 29.165429 | P46: 20 | R46: =H46 | S46: =IF(F46=0, "", F46+M46) -> 51.573123 | T46: =IFERROR( E46+L46, "") | U46: =IFERROR( G46+N46, "") | V46: =IFERROR(I46+O46, "") -> 97.165429 | W46: =J46+P46 -> 91 | X46: =IFERROR((I46+O46)*0.33+18, "") -> 50.064592 | Y46: =IF(J46=0,0,(J46+P46)*0.33+18) -> 48.03 | AA46: =IF(OR(S46="", T46="", U46=""), "", MAX(R46,S46)*40%+T46*30%+U46*30%) | AB46: =IF(AA46="", "", MAX(X46, Y46)-AA46) | AD46: =IFERROR(MIN((MAX(R46,S46)*70%+U46*30%), Y46), "") | AE46: =IF(AD46="", "", MAX(AA46, AB46)-AD46)
B47: 2003 | C47: 4 | D47: 12 | E47: ='CRU historical'!F24 | F47: ='CRU historical'!I24 -> 28 | G47: ='CRU historical'!L24 | H47: ='CRU historical'!O24 | I47: ='CRU historical'!R24 -> 72 | J47: =AVERAGE('CRU historical'!U24, 'CRU historical'!X24, 'CRU historical'!AA24, 'CRU historical'!AD24) -> 71 | L47: {=IFERROR(SUMPRODUCT(('Sulphuric Acid freights'!$B$3:$B$513=B57)*('Sulphuric Acid freights'!$D$3:$D$513=D47)*('Sulphuric Acid freights'!$P$3:$P$513))/SUMPRODUCT(('Sulphuric Acid freights'!$B$3:$B$513=B57)*('Sulphuric Acid freights'!$D$3:$D$513=D47)*1), AVERAGE('Sulphuric Acid freights'!$P$3:$P$513))*2/3} -> 54.110672 | M47: {=IFERROR(SUMPRODUCT(('Sulphuric Acid freights'!$B$3:$B$513=B57)*('Sulphuric Acid freights'!$D$3:$D$513=D47)*('Sulphuric Acid freights'!$M$3:$M$513))/SUMPRODUCT(('Sulphuric Acid freights'!$B$3:$B$513=B57)*('Sulphuric Acid freights'!$D$3:$D$513=D47)*1)*2/3, AVERAGE('Sulphuric Acid freights'!$M$3:$M$513))} -> 23.573123 | N47: =IFERROR(L47*0.9, "") -> 48.699605 | O47: {=IF(SUMPRODUCT(('Sulphur freight'!$B$3:$B$1976=B57)*('Sulphur freight'!$D$3:$D$1976=D47)*('Sulphur freight'!$G$3:$G$1976))/SUMPRODUCT(('Sulphur freight'!$B$3:$B$1976=B57)*('Sulphur freight'!$D$3:$D$1976=D47)*1)=0, AVERAGE('Sulphur freight'!$G$3:$G$1976),SUMPRODUCT(('Sulphur freight'!$B$3:$B$1976=B57)*('Sulphur freight'!$D$3:$D$1976=D47)*('Sulphur freight'!$G$3:$G$1976))/SUMPRODUCT(('Sulphur freight'!$B$3:$B$1976=B57)*('Sulphur freight'!$D$3:$D$1976=D47)*1))} -> 29.165429 | P47: 20 | R47: =H47 | S47: =IF(F47=0, "", F47+M47) -> 51.573123 | T47: =IFERROR( E47+L47, "") | U47: =IFERROR( G47+N47, "") | V47: =IFERROR(I47+O47, "") -> 101.16543 | W47: =J47+P47 -> 91 | X47: =IFERROR((I47+O47)*0.33+18, "") -> 51.384592 | Y47: =IF(J47=0,0,(J47+P47)*0.33+18) -> 48.03 | AA47: =IF(OR(S47="", T47="", U47=""), "", MAX(R47,S47)*40%+T47*30%+U47*30%) | AB47: =IF(AA47="", "", MAX(X47, Y47)-AA47) | AD47: =IFERROR(MIN((MAX(R47,S47)*70%+U47*30%), Y47), "") | AE47: =IF(AD47="", "", MAX(AA47, AB47)-AD47)
B48: 2003 | C48: 1 | D48: 1 | E48: ='CRU historical'!F25 | F48: ='CRU historical'!I25 -> 31.5 | G48: ='CRU historical'!L25 | H48: ='CRU historical'!O25 | I48: ='CRU historical'!R25 -> 74 | J48: =AVERAGE('CRU historical'!U25, 'CRU historical'!X25, 'CRU historical'!AA25, 'CRU historical'!AD25) -> 76 | L48: {=IFERROR(SUMPRODUCT(('Sulphuric Acid freights'!$B$3:$B$513=B58)*('Sulphuric Acid freights'!$D$3:$D$513=D48)*('Sulphuric Acid freights'!$P$3:$P$513))/SUMPRODUCT(('Sulphuric Acid freights'!$B$3:$B$513=B58)*('Sulphuric Acid freights'!$D$3:$D$513=D48)*1), AVERAGE('Sulphuric Acid freights'!$P$3:$P$513))*2/3} -> 54.110672 | M48: {=IFERROR(SUMPRODUCT(('Sulphuric Acid freights'!$B$3:$B$513=B58)*('Sulphuric Acid freights'!$D$3:$D$513=D48)*('Sulphuric Acid freights'!$M$3:$M$513))/SUMPRODUCT(('Sulphuric Acid freights'!$B$3:$B$513=B58)*('Sulphuric Acid freights'!$D$3:$D$513=D48)*1)*2/3, AVERAGE('Sulphuric Acid freights'!$M$3:$M$513))} -> 23.573123 | N48: =IFERROR(L48*0.9, "") -> 48.699605 | O48: {=IF(SUMPRODUCT(('Sulphur freight'!$B$3:$B$1976=B58)*('Sulphur freight'!$D$3:$D$1976=D48)*('Sulphur freight'!$G$3:$G$1976))/SUMPRODUCT(('Sulphur freight'!$B$3:$B$1976=B58)*('Sulphur freight'!$D$3:$D$1976=D48)*1)=0, AVERAGE('Sulphur freight'!$G$3:$G$1976),SUMPRODUCT(('Sulphur freight'!$B$3:$B$1976=B58)*('Sulphur freight'!$D$3:$D$1976=D48)*('Sulphur freight'!$G$3:$G$1976))/SUMPRODUCT(('Sulphur freight'!$B$3:$B$1976=B58)*('Sulphur freight'!$D$3:$D$1976=D48)*1))} -> 29.165429 | P48: 20 | R48: =H48 | S48: =IF(F48=0, "", F48+M48) -> 55.073123 | T48: =IFERROR( E48+L48, "") | U48: =IFERROR( G48+N48, "") | V48: =IFERROR(I48+O48, "") -> 103.16543 | W48: =J48+P48 -> 96 | X48: =IFERROR((I48+O48)*0.33+18, "") -> 52.044592 | Y48: =IF(J48=0,0,(J48+P48)*0.33+18) -> 49.68 | AA48: =IF(OR(S48="", T48="", U48=""), "", MAX(R48,S48)*40%+T48*30%+U48*30%) | AB48: =IF(AA48="", "", MAX(X48, Y48)-AA48) | AD48: =IFERROR(MIN((MAX(R48,S48)*70%+U48*30%), Y48), "") | AE48: =IF(AD48="", "", MAX(AA48, AB48)-AD48)
B49: 2003 | C49: 1 | D49: 2 | E49: ='CRU historical'!F26 | F49: ='CRU historical'!I26 -> 35 | G49: ='CRU historical'!L26 | H49: ='CRU historical'!O26 | I49: ='CRU historical'!R26 -> 66 | J49: =AVERAGE('CRU historical'!U26, 'CRU historical'!X26, 'CRU historical'!AA26, 'CRU historical'!AD26) -> 78 | L49: {=IFERROR(SUMPRODUCT(('Sulphuric Acid freights'!$B$3:$B$513=B59)*('Sulphuric Acid freights'!$D$3:$D$513=D49)*('Sulphuric Acid freights'!$P$3:$P$513))/SUMPRODUCT(('Sulphuric Acid freights'!$B$3:$B$513=B59)*('Sulphuric Acid freights'!$D$3:$D$513=D49)*1), AVERAGE('Sulphuric Acid freights'!$P$3:$P$513))*2/3} -> 54.110672 | M49: {=IFERROR(SUMPRODUCT(('Sulphuric Acid freights'!$B$3:$B$513=B59)*('Sulphuric Acid freights'!$D$3:$D$513=D49)*('Sulphuric Acid freights'!$M$3:$M$513))/SUMPRODUCT(('Sulphuric Acid freights'!$B$3:$B$513=B59)*('Sulphuric Acid freights'!$D$3:$D$513=D49)*1)*2/3, AVERAGE('Sulphuric Acid freights'!$M$3:$M$513))} -> 23.573123 | N49: =IFERROR(L49*0.9, "") -> 48.699605 | O49: {=IF(SUMPRODUCT(('Sulphur freight'!$B$3:$B$1976=B59)*('Sulphur freight'!$D$3:$D$1976=D49)*('Sulphur freight'!$G$3:$G$1976))/SUMPRODUCT(('Sulphur freight'!$B$3:$B$1976=B59)*('Sulphur freight'!$D$3:$D$1976=D49)*1)=0, AVERAGE('Sulphur freight'!$G$3:$G$1976),SUMPRODUCT(('Sulphur freight'!$B$3:$B$1976=B59)*('Sulphur freight'!$D$3:$D$1976=D49)*('Sulphur freight'!$G$3:$G$1976))/SUMPRODUCT(('Sulphur freight'!$B$3:$B$1976=B59)*('Sulphur freight'!$D$3:$D$1976=D49)*1))} -> 29.165429 | P49: 20 | R49: =H49 | S49: =IF(F49=0, "", F49+M49) -> 58.573123 | T49: =IFERROR( E49+L49, "") | U49: =IFERROR( G49+N49, "") | V49: =IFERROR(I49+O49, "") -> 95.165429 | W49: =J49+P49 -> 98 | X49: =IFERROR((I49+O49)*0.33+18, "") -> 49.404592 | Y49: =IF(J49=0,0,(J49+P49)*0.33+18) -> 50.34 | AA49: =IF(OR(S49="", T49="", U49=""), "", MAX(R49,S49)*40%+T49*30%+U49*30%) | AB49: =IF(AA49="", "", MAX(X49, Y49)-AA49) | AD49: =IFERROR(MIN((MAX(R49,S49)*70%+U49*30%), Y49), "") | AE49: =IF(AD49="", "", MAX(AA49, AB49)-AD49)
... B306: 2024 | C306: 3 | D306: 7 | E306: ='CRU historical'!F283 -> 52 | F306: ='CRU historical'!I283 -> 124 | G306: ='CRU historical'!L283 -> 94.2 | H306: ='CRU historical'!O283 -> 170 | I306: ='CRU historical'!R283 -> 260 | J306: =AVERAGE('CRU historical'!U283, 'CRU historical'!X283, 'CRU historical'!AA283, 'CRU historical'!AD283) -> 256 | L306: {=IFERROR(SUMPRODUCT(('Sulphuric Acid freights'!$B$3:$B$513=B316)*('Sulphuric Acid freights'!$D$3:$D$513=D306)*('Sulphuric Acid freights'!$P$3:$P$513))/SUMPRODUCT(('Sulphuric Acid freights'!$B$3:$B$513=B316)*('Sulphuric Acid freights'!$D$3:$D$513=D306)*1), AVERAGE('Sulphuric Acid freights'!$P$3:$P$513))*2/3} -> 67.6 | M306: {=IFERROR(SUMPRODUCT(('Sulphuric Acid freights'!$B$3:$B$513=B316)*('Sulphuric Acid freights'!$D$3:$D$513=D306)*('Sulphuric Acid freights'!$M$3:$M$513))/SUMPRODUCT(('Sulphuric Acid freights'!$B$3:$B$513=B316)*('Sulphuric Acid freights'!$D$3:$D$513=D306)*1)*2/3, AVERAGE('Sulphuric Acid freights'!$M$3:$M$513))} -> 14.666667 | N306: =IFERROR(L306*0.9, "") -> 60.84 | O306: {=IF(SUMPRODUCT(('Sulphur freight'!$B$3:$B$1976=B316)*('Sulphur freight'!$D$3:$D$1976=D306)*('Sulphur freight'!$G$3:$G$1976))/SUMPRODUCT(('Sulphur freight'!$B$3:$B$1976=B316)*('Sulphur freight'!$D$3:$D$1976=D306)*1)=0, AVERAGE('Sulphur freight'!$G$3:$G$1976),SUMPRODUCT(('Sulphur freight'!$B$3:$B$1976=B316)*('Sulphur freight'!$D$3:$D$1976=D306)*('Sulphur freight'!$G$3:$G$1976))/SUMPRODUCT(('Sulphur freight'!$B$3:$B$1976=B316)*('Sulphur freight'!$D$3:$D$1976=D306)*1))} -> 35 | P306: 20 | R306: =H306 -> 170 | S306: =IF(F306=0, "", F306+M306) -> 138.66667 | T306: =IFERROR( E306+L306, "") -> 119.6 | U306: =IFERROR( G306+N306, "") -> 155.04 | V306: =IFERROR(I306+O306, "") -> 295 | W306: =J306+P306 -> 276 | X306: =IFERROR((I306+O306)*0.33+18, "") -> 115.35 | Y306: =IF(J306=0,0,(J306+P306)*0.33+18) -> 109.08 | AA306: =IF(OR(S306="", T306="", U306=""), "", MAX(R306,S306)*40%+T306*30%+U306*30%) -> 150.392 | AB306: =IF(AA306="", "", MAX(X306, Y306)-AA306) -> -35.042 | AD306: =IFERROR(MIN((MAX(R306,S306)*70%+U306*30%), Y306), "") -> 109.08 | AE306: =IF(AD306="", "", MAX(AA306, AB306)-AD306) -> 41.312
B307: 2024 | C307: 3 | D307: 8 | E307: =E306*G307/G306 -> 52.993631 | F307: ='CRU historical'!I284 -> 116.25 | G307: ='CRU historical'!L284 -> 96 | H307: ='CRU historical'!O284 -> 165 | I307: ='CRU historical'!R284 -> 274.75 | J307: =AVERAGE('CRU historical'!U284, 'CRU historical'!X284, 'CRU historical'!AA284, 'CRU historical'!AD284) -> 268 | L307: {=IFERROR(SUMPRODUCT(('Sulphuric Acid freights'!$B$3:$B$513=B317)*('Sulphuric Acid freights'!$D$3:$D$513=D307)*('Sulphuric Acid freights'!$P$3:$P$513))/SUMPRODUCT(('Sulphuric Acid freights'!$B$3:$B$513=B317)*('Sulphuric Acid freights'!$D$3:$D$513=D307)*1), AVERAGE('Sulphuric Acid freights'!$P$3:$P$513))*2/3} -> 66 | M307: {=IFERROR(SUMPRODUCT(('Sulphuric Acid freights'!$B$3:$B$513=B317)*('Sulphuric Acid freights'!$D$3:$D$513=D307)*('Sulphuric Acid freights'!$M$3:$M$513))/SUMPRODUCT(('Sulphuric Acid freights'!$B$3:$B$513=B317)*('Sulphuric Acid freights'!$D$3:$D$513=D307)*1)*2/3, AVERAGE('Sulphuric Acid freights'!$M$3:$M$513))} -> 14.666667 | N307: =IFERROR(L307*0.9, "") -> 59.4 | O307: {=IF(SUMPRODUCT(('Sulphur freight'!$B$3:$B$1976=B317)*('Sulphur freight'!$D$3:$D$1976=D307)*('Sulphur freight'!$G$3:$G$1976))/SUMPRODUCT(('Sulphur freight'!$B$3:$B$1976=B317)*('Sulphur freight'!$D$3:$D$1976=D307)*1)=0, AVERAGE('Sulphur freight'!$G$3:$G$1976),SUMPRODUCT(('Sulphur freight'!$B$3:$B$1976=B317)*('Sulphur freight'!$D$3:$D$1976=D307)*('Sulphur freight'!$G$3:$G$1976))/SUMPRODUCT(('Sulphur freight'!$B$3:$B$1976=B317)*('Sulphur freight'!$D$3:$D$1976=D307)*1))} -> 35.75 | P307: 20 | R307: =H307 -> 165 | S307: =IF(F307=0, "", F307+M307) -> 130.91667 | T307: =T306*(U307/U306) -> 119.87771 | U307: =IFERROR( G307+N307, "") -> 155.4 | V307: =IFERROR(I307+O307, "") -> 310.5 | W307: =J307+P307 -> 288 | X307: =IFERROR((I307+O307)*0.33+18, "") -> 120.465 | Y307: =IF(J307=0,0,(J307+P307)*0.33+18) -> 113.04 | AA307: =IF(OR(S307="", T307="", U307=""), "", MAX(R307,S307)*40%+T307*30%+U307*30%) -> 148.58331 | AB307: =IF(AA307="", "", MAX(X307, Y307)-AA307) -> -28.118313 | AD307: =IFERROR(MIN((MAX(R307,S307)*70%+U307*30%), Y307), "") -> 113.04 | AE307: =IF(AD307="", "", MAX(AA307, AB307)-AD307) -> 35.543313
B308: 2024 | C308: 3 | D308: 9 | E308: =E307*G308/G307 -> 41.953291 | F308: ='CRU historical'!I285 -> 79.5 | G308: ='CRU historical'!L285 -> 76 | H308: ='CRU historical'!O285 -> 130 | I308: ='CRU historical'!R285 -> 307.75 | J308: =AVERAGE('CRU historical'!U285, 'CRU historical'!X285, 'CRU historical'!AA285, 'CRU historical'!AD285) -> 268 | L308: {=IFERROR(SUMPRODUCT(('Sulphuric Acid freights'!$B$3:$B$513=B318)*('Sulphuric Acid freights'!$D$3:$D$513=D308)*('Sulphuric Acid freights'!$P$3:$P$513))/SUMPRODUCT(('Sulphuric Acid freights'!$B$3:$B$513=B318)*('Sulphuric Acid freights'!$D$3:$D$513=D308)*1), AVERAGE('Sulphuric Acid freights'!$P$3:$P$513))*2/3} -> 66 | M308: {=IFERROR(SUMPRODUCT(('Sulphuric Acid freights'!$B$3:$B$513=B318)*('Sulphuric Acid freights'!$D$3:$D$513=D308)*('Sulphuric Acid freights'!$M$3:$M$513))/SUMPRODUCT(('Sulphuric Acid freights'!$B$3:$B$513=B318)*('Sulphuric Acid freights'!$D$3:$D$513=D308)*1)*2/3, AVERAGE('Sulphuric Acid freights'!$M$3:$M$513))} -> 14.666667 | N308: =IFERROR(L308*0.9, "") -> 59.4 | O308: {=IF(SUMPRODUCT(('Sulphur freight'!$B$3:$B$1976=B318)*('Sulphur freight'!$D$3:$D$1976=D308)*('Sulphur freight'!$G$3:$G$1976))/SUMPRODUCT(('Sulphur freight'!$B$3:$B$1976=B318)*('Sulphur freight'!$D$3:$D$1976=D308)*1)=0, AVERAGE('Sulphur freight'!$G$3:$G$1976),SUMPRODUCT(('Sulphur freight'!$B$3:$B$1976=B318)*('Sulphur freight'!$D$3:$D$1976=D308)*('Sulphur freight'!$G$3:$G$1976))/SUMPRODUCT(('Sulphur freight'!$B$3:$B$1976=B318)*('Sulphur freight'!$D$3:$D$1976=D308)*1))} -> 35.5 | P308: 20 | R308: =H308 -> 130 | S308: =IF(F308=0, "", F308+M308) -> 94.166667 | T308: =T307*(U308/U307) -> 104.44943 | U308: =IFERROR( G308+N308, "") -> 135.4 | V308: =IFERROR(I308+O308, "") -> 343.25 | W308: =J308+P308 -> 288 | X308: =IFERROR((I308+O308)*0.33+18, "") -> 131.2725 | Y308: =IF(J308=0,0,(J308+P308)*0.33+18) -> 113.04 | AA308: =IF(OR(S308="", T308="", U308=""), "", MAX(R308,S308)*40%+T308*30%+U308*30%) -> 123.95483 | AB308: =IF(AA308="", "", MAX(X308, Y308)-AA308) -> 7.3176703 | AD308: =IFERROR(MIN((MAX(R308,S308)*70%+U308*30%), Y308), "") -> 113.04 | AE308: =IF(AD308="", "", MAX(AA308, AB308)-AD308) -> 10.91483
B309: 2024 | C309: 4 | D309: 10 | E309: =E308*G309/G308 -> 43.719745 | F309: ='CRU historical'!I286 -> 80.2 | G309: ='CRU historical'!L286 -> 79.2 | H309: ='CRU historical'!O286 -> 130 | I309: ='CRU historical'!R286 -> 359.8 | J309: =AVERAGE('CRU historical'!U286, 'CRU historical'!X286, 'CRU historical'!AA286, 'CRU historical'!AD286) -> 301.6 | L309: {=IFERROR(SUMPRODUCT(('Sulphuric Acid freights'!$B$3:$B$513=B319)*('Sulphuric Acid freights'!$D$3:$D$513=D309)*('Sulphuric Acid freights'!$P$3:$P$513))/SUMPRODUCT(('Sulphuric Acid freights'!$B$3:$B$513=B319)*('Sulphuric Acid freights'!$D$3:$D$513=D309)*1), AVERAGE('Sulphuric Acid freights'!$P$3:$P$513))*2/3} -> 66 | M309: {=IFERROR(SUMPRODUCT(('Sulphuric Acid freights'!$B$3:$B$513=B319)*('Sulphuric Acid freights'!$D$3:$D$513=D309)*('Sulphuric Acid freights'!$M$3:$M$513))/SUMPRODUCT(('Sulphuric Acid freights'!$B$3:$B$513=B319)*('Sulphuric Acid freights'!$D$3:$D$513=D309)*1)*2/3, AVERAGE('Sulphuric Acid freights'!$M$3:$M$513))} -> 13.6 | N309: =IFERROR(L309*0.9, "") -> 59.4 | O309: {=IF(SUMPRODUCT(('Sulphur freight'!$B$3:$B$1976=B319)*('Sulphur freight'!$D$3:$D$1976=D309)*('Sulphur freight'!$G$3:$G$1976))/SUMPRODUCT(('Sulphur freight'!$B$3:$B$1976=B319)*('Sulphur freight'!$D$3:$D$1976=D309)*1)=0, AVERAGE('Sulphur freight'!$G$3:$G$1976),SUMPRODUCT(('Sulphur freight'!$B$3:$B$1976=B319)*('Sulphur freight'!$D$3:$D$1976=D309)*('Sulphur freight'!$G$3:$G$1976))/SUMPRODUCT(('Sulphur freight'!$B$3:$B$1976=B319)*('Sulphur freight'!$D$3:$D$1976=D309)*1))} -> 31 | P309: 20 | R309: =H309 -> 130 | S309: =IF(F309=0, "", F309+M309) -> 93.8 | T309: =T308*(U309/U308) -> 106.91796 | U309: =IFERROR( G309+N309, "") -> 138.6 | V309: =IFERROR(I309+O309, "") -> 390.8 | W309: =J309+P309 -> 321.6 | X309: =IFERROR((I309+O309)*0.33+18, "") -> 146.964 | Y309: =IF(J309=0,0,(J309+P309)*0.33+18) -> 124.128 | AA309: =IF(OR(S309="", T309="", U309=""), "", MAX(R309,S309)*40%+T309*30%+U309*30%) -> 125.65539 | AB309: =IF(AA309="", "", MAX(X309, Y309)-AA309) -> 21.308613 | AD309: =IFERROR(MIN((MAX(R309,S309)*70%+U309*30%), Y309), "") -> 124.128 | AE309: =IF(AD309="", "", MAX(AA309, AB309)-AD309) -> 1.527387
B310: 2025 | C310: 4 | D310: 11 | E310: =E309*G310/G309 -> 58.375796 | F310: ='CRU historical'!I287 -> 97.75 | G310: ='CRU historical'!L287 -> 105.75 | H310: ='CRU historical'!O287 -> 132.5 | I310: ='CRU historical'!R287 -> 452 | J310: =AVERAGE('CRU historical'!U287, 'CRU historical'!X287, 'CRU historical'!AA287, 'CRU historical'!AD287) -> 310 | L310: {=IFERROR(SUMPRODUCT(('Sulphuric Acid freights'!$B$3:$B$513=B320)*('Sulphuric Acid freights'!$D$3:$D$513=D310)*('Sulphuric Acid freights'!$P$3:$P$513))/SUMPRODUCT(('Sulphuric Acid freights'!$B$3:$B$513=B320)*('Sulphuric Acid freights'!$D$3:$D$513=D310)*1), AVERAGE('Sulphuric Acid freights'!$P$3:$P$513))*2/3} -> 66 | M310: {=IFERROR(SUMPRODUCT(('Sulphuric Acid freights'!$B$3:$B$513=B320)*('Sulphuric Acid freights'!$D$3:$D$513=D310)*('Sulphuric Acid freights'!$M$3:$M$513))/SUMPRODUCT(('Sulphuric Acid freights'!$B$3:$B$513=B320)*('Sulphuric Acid freights'!$D$3:$D$513=D310)*1)*2/3, AVERAGE('Sulphuric Acid freights'!$M$3:$M$513))} -> 14.666667 | N310: =IFERROR(L310*0.9, "") -> 59.4 | O310: {=IF(SUMPRODUCT(('Sulphur freight'!$B$3:$B$1976=B320)*('Sulphur freight'!$D$3:$D$1976=D310)*('Sulphur freight'!$G$3:$G$1976))/SUMPRODUCT(('Sulphur freight'!$B$3:$B$1976=B320)*('Sulphur freight'!$D$3:$D$1976=D310)*1)=0, AVERAGE('Sulphur freight'!$G$3:$G$1976),SUMPRODUCT(('Sulphur freight'!$B$3:$B$1976=B320)*('Sulphur freight'!$D$3:$D$1976=D310)*('Sulphur freight'!$G$3:$G$1976))/SUMPRODUCT(('Sulphur freight'!$B$3:$B$1976=B320)*('Sulphur freight'!$D$3:$D$1976=D310)*1))} -> 32 | P310: 20 | R310: =H310 -> 132.5 | S310: =IF(F310=0, "", F310+M310) -> 112.41667 | T310: =T309*(U310/U309) -> 127.39899 | U310: =IFERROR( G310+N310, "") -> 165.15 | V310: =IFERROR(I310+O310, "") -> 484 | W310: =J310+P310 -> 330 | X310: =IFERROR((I310+O310)*0.33+18, "") -> 177.72 | Y310: =IF(J310=0,0,(J310+P310)*0.33+18) -> 126.9 | AA310: =IF(OR(S310="", T310="", U310=""), "", MAX(R310,S310)*40%+T310*30%+U310*30%) -> 140.7647 | AB310: =IF(AA310="", "", MAX(X310, Y310)-AA310) -> 36.955302 | AD310: =IFERROR(MIN((MAX(R310,S310)*70%+U310*30%), Y310), "") -> 126.9 | AE310: =IF(AD310="", "", MAX(AA310, AB310)-AD310) -> 13.864698
B311: 2025 | C311: 4 | D311: 12 | E311: =E310*G311/G310 -> 62.377919 | F311: ='CRU historical'!I288 -> 106 | G311: ='CRU historical'!L288 -> 113 | H311: ='CRU historical'!O288 -> 136 | I311: ='CRU historical'!R288 -> 507 | J311: =AVERAGE('CRU historical'!U288, 'CRU historical'!X288, 'CRU historical'!AA288, 'CRU historical'!AD288) -> 310 | L311: {=IFERROR(SUMPRODUCT(('Sulphuric Acid freights'!$B$3:$B$513=B321)*('Sulphuric Acid freights'!$D$3:$D$513=D311)*('Sulphuric Acid freights'!$P$3:$P$513))/SUMPRODUCT(('Sulphuric Acid freights'!$B$3:$B$513=B321)*('Sulphuric Acid freights'!$D$3:$D$513=D311)*1), AVERAGE('Sulphuric Acid freights'!$P$3:$P$513))*2/3} -> 66 | M311: {=IFERROR(SUMPRODUCT(('Sulphuric Acid freights'!$B$3:$B$513=B321)*('Sulphuric Acid freights'!$D$3:$D$513=D311)*('Sulphuric Acid freights'!$M$3:$M$513))/SUMPRODUCT(('Sulphuric Acid freights'!$B$3:$B$513=B321)*('Sulphuric Acid freights'!$D$3:$D$513=D311)*1)*2/3, AVERAGE('Sulphuric Acid freights'!$M$3:$M$513))} -> 14.666667 | N311: =IFERROR(L311*0.9, "") -> 59.4 | O311: {=IF(SUMPRODUCT(('Sulphur freight'!$B$3:$B$1976=B321)*('Sulphur freight'!$D$3:$D$1976=D311)*('Sulphur freight'!$G$3:$G$1976))/SUMPRODUCT(('Sulphur freight'!$B$3:$B$1976=B321)*('Sulphur freight'!$D$3:$D$1976=D311)*1)=0, AVERAGE('Sulphur freight'!$G$3:$G$1976),SUMPRODUCT(('Sulphur freight'!$B$3:$B$1976=B321)*('Sulphur freight'!$D$3:$D$1976=D311)*('Sulphur freight'!$G$3:$G$1976))/SUMPRODUCT(('Sulphur freight'!$B$3:$B$1976=B321)*('Sulphur freight'!$D$3:$D$1976=D311)*1))} -> 32.666667 | P311: 20 | R311: =H311 -> 136 | S311: =IF(F311=0, "", F311+M311) -> 120.66667 | T311: =T310*(U311/U310) -> 132.99174 | U311: =IFERROR( G311+N311, "") -> 172.4 | V311: =IFERROR(I311+O311, "") -> 539.66667 | W311: =J311+P311 -> 330 | X311: =IFERROR(V311*0.33+18, "") -> 196.09 | Y311: =IF(J311=0,0,W311*0.33+18) -> 126.9 | AA311: =IF(OR(S311="", T311="", U311=""), "", MAX(R311,S311)*40%+T311*30%+U311*30%) -> 146.01752 | AB311: =IF(AA311="", "", MAX(X311, Y311)-AA311) -> 50.072477 | AD311: =IFERROR(MIN((MAX(R311,S311)*70%+U311*30%), Y311), "") -> 126.9 | AE311: =IF(AD311="", "", MAX(AA311, AB311)-AD311) -> 19.117523
B312: 2025 | C312: 1 | D312: 1 | E312: =INDEX(E$13:E$17, MATCH($B322, $B$13:$B$17, 0), 1)*$D$2*(1+RANDBETWEEN(-0.8, 0.8)) -> 71.736667 | F312: =INDEX(F$13:F$17, MATCH($B322, $B$13:$B$17, 0), 1)*$D$2*(1+RANDBETWEEN(-0.8, 0.8)) -> 66.785714 | G312: =INDEX(G$13:G$17, MATCH($B322, $B$13:$B$17, 0), 1)*$D$2*(1+RANDBETWEEN(-0.8, 0.8)) -> 67.403333 | H312: =INDEX(H$13:H$17, MATCH($B322, $B$13:$B$17, 0), 1)*$D$2*(1+RANDBETWEEN(-0.8, 0.8)) -> 86.785714 | I312: =INDEX(I$13:I$17, MATCH($B322, $B$13:$B$17, 0), 1)*$D$2*(1+RANDBETWEEN(-1, 1)) -> 281.83448 | J312: =INDEX(J$13:J$17, MATCH($B322, $B$13:$B$17, 0), 1)*$D$2*(1+RANDBETWEEN(-1, 1)) -> 291.45057
B313: 2025 | C313: 1 | D313: 2 | E313: =INDEX(E$13:E$17, MATCH($B323, $B$13:$B$17, 0), 1)*$D$2*(1+RANDBETWEEN(-0.8, 0.8)) -> 71.736667 | F313: =INDEX(F$13:F$17, MATCH($B323, $B$13:$B$17, 0), 1)*$D$2*(1+RANDBETWEEN(-0.8, 0.8)) -> 66.785714 | G313: =INDEX(G$13:G$17, MATCH($B323, $B$13:$B$17, 0), 1)*$D$2*(1+RANDBETWEEN(-0.8, 0.8)) -> 67.403333 | H313: =INDEX(H$13:H$17, MATCH($B323, $B$13:$B$17, 0), 1)*$D$2*(1+RANDBETWEEN(-0.8, 0.8)) -> 86.785714 | I313: =INDEX(I$13:I$17, MATCH($B323, $B$13:$B$17, 0), 1)*$D$2*(1+RANDBETWEEN(-1, 1)) -> 281.83448 | J313: =INDEX(J$13:J$17, MATCH($B323, $B$13:$B$17, 0), 1)*$D$2*(1+RANDBETWEEN(-1, 1)) -> 291.45057 | S313: ='ACS - CRU Outlook'!D18 -> 83.482143 | T313: ='ACS - CRU Outlook'!H18+'Simulateur furu'!$L$311 -> 155.67083 | U313: ='ACS - CRU Outlook'!I18+'Simulateur furu'!$N$311 -> 143.65417 | V313: ='S - CRU Outlook'!C18+$O$311 -> 384.95976 | W313: ='S - CRU Outlook'!J18+$P$311 -> 384.31322 | X313: =V313*0.33+18 -> 145.03672 | Y313: =W313*0.33+18 -> 144.82336 | AA313: =IF(OR(S313="", T313="", U313=""), "", MAX(R313,S313)*40%+T313*30%+U313*30%) -> 123.19036 | AB313: =IF(AA313="", "", MAX(X313, Y313)-AA313) -> 21.846365 | AD313: =IFERROR(MIN((MAX(R313,S313)*70%+U313*30%), Y313), "") -> 101.53375 | AE313: =IF(AD313="", "", MAX(AA313, AB313)-AD313) -> 21.656607
B314: 2025 | C314: 1 | D314: 3 | E314: =INDEX(E$13:E$17, MATCH($B324, $B$13:$B$17, 0), 1)*$D$2*(1+RANDBETWEEN(-0.8, 0.8)) -> 71.736667 | F314: =INDEX(F$13:F$17, MATCH($B324, $B$13:$B$17, 0), 1)*$D$2*(1+RANDBETWEEN(-0.8, 0.8)) -> 66.785714 | G314: =INDEX(G$13:G$17, MATCH($B324, $B$13:$B$17, 0), 1)*$D$2*(1+RANDBETWEEN(-0.8, 0.8)) -> 67.403333 | H314: =INDEX(H$13:H$17, MATCH($B324, $B$13:$B$17, 0), 1)*$D$2*(1+RANDBETWEEN(-0.8, 0.8)) -> 86.785714 | I314: =INDEX(I$13:I$17, MATCH($B324, $B$13:$B$17, 0), 1)*$D$2*(1+RANDBETWEEN(-1, 1)) -> 0 | J314: =INDEX(J$13:J$17, MATCH($B324, $B$13:$B$17, 0), 1)*$D$2*(1+RANDBETWEEN(-1, 1)) -> 582.90115 | S314: ='ACS - CRU Outlook'!D19 -> 80.929219 | T314: ='ACS - CRU Outlook'!H19+'Simulateur furu'!$L$311 -> 125.92922 | U314: ='ACS - CRU Outlook'!I19+'Simulateur furu'!$N$311 -> 125.32922 | V314: ='S - CRU Outlook'!C19+$O$311 -> 274.13203 | W314: ='S - CRU Outlook'!J19+$P$311 -> 273.30844 | X314: =V314*0.33+18 -> 108.46357 | Y314: =W314*0.33+18 -> 108.19178 | AA314: =IF(OR(S314="", T314="", U314=""), "", MAX(R314,S314)*40%+T314*30%+U314*30%) -> 107.74922 | AB314: =IF(AA314="", "", MAX(X314, Y314)-AA314) -> 0.71435076 | AD314: =IFERROR(MIN((MAX(R314,S314)*70%+U314*30%), Y314), "") -> 94.249219 | AE314: =IF(AD314="", "", MAX(AA314, AB314)-AD314) -> 13.5
B315: 2025 | C315: 2 | D315: 4 | E315: =INDEX(E$13:E$17, MATCH($B325, $B$13:$B$17, 0), 1)*$D$2*(1+RANDBETWEEN(-0.8, 0.8)) -> 71.736667 | F315: =INDEX(F$13:F$17, MATCH($B325, $B$13:$B$17, 0), 1)*$D$2*(1+RANDBETWEEN(-0.8, 0.8)) -> 66.785714 | G315: =INDEX(G$13:G$17, MATCH($B325, $B$13:$B$17, 0), 1)*$D$2*(1+RANDBETWEEN(-0.8, 0.8)) -> 67.403333 | H315: =INDEX(H$13:H$17, MATCH($B325, $B$13:$B$17, 0), 1)*$D$2*(1+RANDBETWEEN(-0.8, 0.8)) -> 86.785714 | I315: =INDEX(I$13:I$17, MATCH($B325, $B$13:$B$17, 0), 1)*$D$2*(1+RANDBETWEEN(-1, 1)) -> 563.66896 | J315: =INDEX(J$13:J$17, MATCH($B325, $B$13:$B$17, 0), 1)*$D$2*(1+RANDBETWEEN(-1, 1)) -> 291.45057 | S315: ='ACS - CRU Outlook'!D20 -> 66.644459 | T315: ='ACS - CRU Outlook'!H20+'Simulateur furu'!$L$311 -> 120.64446 | U315: ='ACS - CRU Outlook'!I20+'Simulateur furu'!$N$311 -> 120.04446 | V315: ='S - CRU Outlook'!C20+$O$311 -> 246.8432 | W315: ='S - CRU Outlook'!J20+$P$311 -> 246.23543 | X315: =V315*0.33+18 -> 99.458256 | Y315: =W315*0.33+18 -> 99.257691 | AA315: =IF(OR(S315="", T315="", U315=""), "", MAX(R315,S315)*40%+T315*30%+U315*30%) -> 98.864459 | AB315: =IF(AA315="", "", MAX(X315, Y315)-AA315) -> 0.59379657 | AD315: =IFERROR(MIN((MAX(R315,S315)*70%+U315*30%), Y315), "") -> 82.664459 | AE315: =IF(AD315="", "", MAX(AA315, AB315)-AD315) -> 16.2
B316: 2025 | C316: 2 | D316: 5 | E316: =INDEX(E$13:E$17, MATCH($B326, $B$13:$B$17, 0), 1)*$D$2*(1+RANDBETWEEN(-0.8, 0.8)) -> 71.736667 | F316: =INDEX(F$13:F$17, MATCH($B326, $B$13:$B$17, 0), 1)*$D$2*(1+RANDBETWEEN(-0.8, 0.8)) -> 66.785714 | G316: =INDEX(G$13:G$17, MATCH($B326, $B$13:$B$17, 0), 1)*$D$2*(1+RANDBETWEEN(-0.8, 0.8)) -> 67.403333 | H316: =INDEX(H$13:H$17, MATCH($B326, $B$13:$B$17, 0), 1)*$D$2*(1+RANDBETWEEN(-0.8, 0.8)) -> 86.785714 | I316: =INDEX(I$13:I$17, MATCH($B326, $B$13:$B$17, 0), 1)*$D$2*(1+RANDBETWEEN(-1, 1)) -> 281.83448 | J316: =INDEX(J$13:J$17, MATCH($B326, $B$13:$B$17, 0), 1)*$D$2*(1+RANDBETWEEN(-1, 1)) -> 0 | S316: ='ACS - CRU Outlook'!D21 -> 65.394434 | T316: ='ACS - CRU Outlook'!H21+'Simulateur furu'!$L$311 -> 114.39443 | U316: ='ACS - CRU Outlook'!I21+'Simulateur furu'!$N$311 -> 113.79443 | V316: ='S - CRU Outlook'!C21+$O$311 -> 239.17879 | W316: ='S - CRU Outlook'!J21+$P$311 -> 238.64587 | X316: =V316*0.33+18 -> 96.929001 | Y316: =W316*0.33+18 -> 96.753136 | AA316: =IF(OR(S316="", T316="", U316=""), "", MAX(R316,S316)*40%+T316*30%+U316*30%) -> 94.614434 | AB316: =IF(AA316="", "", MAX(X316, Y316)-AA316) -> 2.3145674 | AD316: =IFERROR(MIN((MAX(R316,S316)*70%+U316*30%), Y316), "") -> 79.914434 | AE316: =IF(AD316="", "", MAX(AA316, AB316)-AD316) -> 14.7
B317: 2025 | C317: 2 | D317: 6 | E317: =INDEX(E$13:E$17, MATCH($B327, $B$13:$B$17, 0), 1)*$D$2*(1+RANDBETWEEN(-0.8, 0.8)) -> 71.736667 | F317: =INDEX(F$13:F$17, MATCH($B327, $B$13:$B$17, 0), 1)*$D$2*(1+RANDBETWEEN(-0.8, 0.8)) -> 66.785714 | G317: =INDEX(G$13:G$17, MATCH($B327, $B$13:$B$17, 0), 1)*$D$2*(1+RANDBETWEEN(-0.8, 0.8)) -> 67.403333 | H317: =INDEX(H$13:H$17, MATCH($B327, $B$13:$B$17, 0), 1)*$D$2*(1+RANDBETWEEN(-0.8, 0.8)) -> 86.785714 | I317: =INDEX(I$13:I$17, MATCH($B327, $B$13:$B$17, 0), 1)*$D$2*(1+RANDBETWEEN(-1, 1)) -> 563.66896 | J317: =INDEX(J$13:J$17, MATCH($B327, $B$13:$B$17, 0), 1)*$D$2*(1+RANDBETWEEN(-1, 1)) -> 0 | S317: ='ACS - CRU Outlook'!D22 -> 61.438116 | T317: ='ACS - CRU Outlook'!H22+'Simulateur furu'!$L$311 -> 108.43812 | U317: ='ACS - CRU Outlook'!I22+'Simulateur furu'!$N$311 -> 107.83812 | V317: ='S - CRU Outlook'!C22+$O$311 -> 243.75994 | W317: ='S - CRU Outlook'!J22+$P$311 -> 243.21409 | X317: =V317*0.33+18 -> 98.440779 | Y317: =W317*0.33+18 -> 98.260649 | AA317: =IF(OR(S317="", T317="", U317=""), "", MAX(R317,S317)*40%+T317*30%+U317*30%) -> 89.458116 | AB317: =IF(AA317="", "", MAX(X317, Y317)-AA317) -> 8.9826628 | AD317: =IFERROR(MIN((MAX(R317,S317)*70%+U317*30%), Y317), "") -> 75.358116 | AE317: =IF(AD317="", "", MAX(AA317, AB317)-AD317) -> 14.1
B318: 2025 | C318: 3 | D318: 7 | E318: =INDEX(E$13:E$17, MATCH($B328, $B$13:$B$17, 0), 1)*$D$2*(1+RANDBETWEEN(-0.8, 0.8)) -> 71.736667 | F318: =INDEX(F$13:F$17, MATCH($B328, $B$13:$B$17, 0), 1)*$D$2*(1+RANDBETWEEN(-0.8, 0.8)) -> 66.785714 | G318: =INDEX(G$13:G$17, MATCH($B328, $B$13:$B$17, 0), 1)*$D$2*(1+RANDBETWEEN(-0.8, 0.8)) -> 67.403333 | H318: =INDEX(H$13:H$17, MATCH($B328, $B$13:$B$17, 0), 1)*$D$2*(1+RANDBETWEEN(-0.8, 0.8)) -> 86.785714 | I318: =INDEX(I$13:I$17, MATCH($B328, $B$13:$B$17, 0), 1)*$D$2*(1+RANDBETWEEN(-1, 1)) -> 0 | J318: =INDEX(J$13:J$17, MATCH($B328, $B$13:$B$17, 0), 1)*$D$2*(1+RANDBETWEEN(-1, 1)) -> 0
B319: 2025 | C319: 3 | D319: 8 | E319: =INDEX(E$13:E$17, MATCH($B329, $B$13:$B$17, 0), 1)*$D$2*(1+RANDBETWEEN(-0.8, 0.8)) -> 71.736667 | F319: =INDEX(F$13:F$17, MATCH($B329, $B$13:$B$17, 0), 1)*$D$2*(1+RANDBETWEEN(-0.8, 0.8)) -> 66.785714 | G319: =INDEX(G$13:G$17, MATCH($B329, $B$13:$B$17, 0), 1)*$D$2*(1+RANDBETWEEN(-0.8, 0.8)) -> 67.403333 | H319: =INDEX(H$13:H$17, MATCH($B329, $B$13:$B$17, 0), 1)*$D$2*(1+RANDBETWEEN(-0.8, 0.8)) -> 86.785714 | I319: =INDEX(I$13:I$17, MATCH($B329, $B$13:$B$17, 0), 1)*$D$2*(1+RANDBETWEEN(-1, 1)) -> 281.83448 | J319: =INDEX(J$13:J$17, MATCH($B329, $B$13:$B$17, 0), 1)*$D$2*(1+RANDBETWEEN(-1, 1)) -> 0
B320: 2025 | C320: 3 | D320: 9 | E320: =INDEX(E$13:E$17, MATCH($B330, $B$13:$B$17, 0), 1)*$D$2*(1+RANDBETWEEN(-0.8, 0.8)) -> 71.736667 | F320: =INDEX(F$13:F$17, MATCH($B330, $B$13:$B$17, 0), 1)*$D$2*(1+RANDBETWEEN(-0.8, 0.8)) -> 66.785714 | G320: =INDEX(G$13:G$17, MATCH($B330, $B$13:$B$17, 0), 1)*$D$2*(1+RANDBETWEEN(-0.8, 0.8)) -> 67.403333 | H320: =INDEX(H$13:H$17, MATCH($B330, $B$13:$B$17, 0), 1)*$D$2*(1+RANDBETWEEN(-0.8, 0.8)) -> 86.785714 | I320: =INDEX(I$13:I$17, MATCH($B330, $B$13:$B$17, 0), 1)*$D$2*(1+RANDBETWEEN(-1, 1)) -> 563.66896 | J320: =INDEX(J$13:J$17, MATCH($B330, $B$13:$B$17, 0), 1)*$D$2*(1+RANDBETWEEN(-1, 1)) -> 0
B321: 2025 | C321: 4 | D321: 10 | E321: =INDEX(E$13:E$17, MATCH($B331, $B$13:$B$17, 0), 1)*$D$2*(1+RANDBETWEEN(-0.8, 0.8)) -> 71.736667 | F321: =INDEX(F$13:F$17, MATCH($B331, $B$13:$B$17, 0), 1)*$D$2*(1+RANDBETWEEN(-0.8, 0.8)) -> 66.785714 | G321: =INDEX(G$13:G$17, MATCH($B331, $B$13:$B$17, 0), 1)*$D$2*(1+RANDBETWEEN(-0.8, 0.8)) -> 67.403333 | H321: =INDEX(H$13:H$17, MATCH($B331, $B$13:$B$17, 0), 1)*$D$2*(1+RANDBETWEEN(-0.8, 0.8)) -> 86.785714 | I321: =INDEX(I$13:I$17, MATCH($B331, $B$13:$B$17, 0), 1)*$D$2*(1+RANDBETWEEN(-1, 1)) -> 563.66896 | J321: =INDEX(J$13:J$17, MATCH($B331, $B$13:$B$17, 0), 1)*$D$2*(1+RANDBETWEEN(-1, 1)) -> 291.45057
B322: 2026 | C322: 4 | D322: 11 | E322: =INDEX(E$13:E$17, MATCH($B332, $B$13:$B$17, 0), 1)*$D$2*(1+RANDBETWEEN(-0.8, 0.8)) -> 71.736667 | F322: =INDEX(F$13:F$17, MATCH($B332, $B$13:$B$17, 0), 1)*$D$2*(1+RANDBETWEEN(-0.8, 0.8)) -> 66.785714 | G322: =INDEX(G$13:G$17, MATCH($B332, $B$13:$B$17, 0), 1)*$D$2*(1+RANDBETWEEN(-0.8, 0.8)) -> 67.403333 | H322: =INDEX(H$13:H$17, MATCH($B332, $B$13:$B$17, 0), 1)*$D$2*(1+RANDBETWEEN(-0.8, 0.8)) -> 86.785714 | I322: =INDEX(I$13:I$17, MATCH($B332, $B$13:$B$17, 0), 1)*$D$2*(1+RANDBETWEEN(-1, 1)) -> 0 | J322: =INDEX(J$13:J$17, MATCH($B332, $B$13:$B$17, 0), 1)*$D$2*(1+RANDBETWEEN(-1, 1)) -> 291.45057
B323: 2026 | C323: 4 | D323: 12 | E323: =INDEX(E$13:E$17, MATCH($B333, $B$13:$B$17, 0), 1)*$D$2*(1+RANDBETWEEN(-0.8, 0.8)) -> 71.736667 | F323: =INDEX(F$13:F$17, MATCH($B333, $B$13:$B$17, 0), 1)*$D$2*(1+RANDBETWEEN(-0.8, 0.8)) -> 66.785714 | G323: =INDEX(G$13:G$17, MATCH($B333, $B$13:$B$17, 0), 1)*$D$2*(1+RANDBETWEEN(-0.8, 0.8)) -> 67.403333 | H323: =INDEX(H$13:H$17, MATCH($B333, $B$13:$B$17, 0), 1)*$D$2*(1+RANDBETWEEN(-0.8, 0.8)) -> 86.785714 | I323: =INDEX(I$13:I$17, MATCH($B333, $B$13:$B$17, 0), 1)*$D$2*(1+RANDBETWEEN(-1, 1)) -> 281.83448 | J323: =INDEX(J$13:J$17, MATCH($B333, $B$13:$B$17, 0), 1)*$D$2*(1+RANDBETWEEN(-1, 1)) -> 291.45057
B324: 2026 | C324: 1 | D324: 1 | E324: =INDEX(E$13:E$17, MATCH($B334, $B$13:$B$17, 0), 1)*$D$2*(1+RANDBETWEEN(-0.8, 0.8)) -> 47.943375 | F324: =INDEX(F$13:F$17, MATCH($B334, $B$13:$B$17, 0), 1)*$D$2*(1+RANDBETWEEN(-0.8, 0.8)) -> 64.743375 | G324: =INDEX(G$13:G$17, MATCH($B334, $B$13:$B$17, 0), 1)*$D$2*(1+RANDBETWEEN(-0.8, 0.8)) -> 52.743375 | H324: =INDEX(H$13:H$17, MATCH($B334, $B$13:$B$17, 0), 1)*$D$2*(1+RANDBETWEEN(-0.8, 0.8)) -> 84.743375 | I324: =INDEX(I$13:I$17, MATCH($B334, $B$13:$B$17, 0), 1)*$D$2*(1+RANDBETWEEN(-1, 1)) -> 193.17229 | J324: =INDEX(J$13:J$17, MATCH($B334, $B$13:$B$17, 0), 1)*$D$2*(1+RANDBETWEEN(-1, 1)) -> 405.2935
B325: 2026 | C325: 1 | D325: 2 | E325: =INDEX(E$13:E$17, MATCH($B335, $B$13:$B$17, 0), 1)*$D$2*(1+RANDBETWEEN(-0.8, 0.8)) -> 47.943375 | F325: =INDEX(F$13:F$17, MATCH($B335, $B$13:$B$17, 0), 1)*$D$2*(1+RANDBETWEEN(-0.8, 0.8)) -> 64.743375 | G325: =INDEX(G$13:G$17, MATCH($B335, $B$13:$B$17, 0), 1)*$D$2*(1+RANDBETWEEN(-0.8, 0.8)) -> 52.743375 | H325: =INDEX(H$13:H$17, MATCH($B335, $B$13:$B$17, 0), 1)*$D$2*(1+RANDBETWEEN(-0.8, 0.8)) -> 84.743375 | I325: =INDEX(I$13:I$17, MATCH($B335, $B$13:$B$17, 0), 1)*$D$2*(1+RANDBETWEEN(-1, 1)) -> 386.34458 | J325: =INDEX(J$13:J$17, MATCH($B335, $B$13:$B$17, 0), 1)*$D$2*(1+RANDBETWEEN(-1, 1)) -> 0
B326: 2026 | C326: 1 | D326: 3 | E326: =INDEX(E$13:E$17, MATCH($B336, $B$13:$B$17, 0), 1)*$D$2*(1+RANDBETWEEN(-0.8, 0.8)) -> 47.943375 | F326: =INDEX(F$13:F$17, MATCH($B336, $B$13:$B$17, 0), 1)*$D$2*(1+RANDBETWEEN(-0.8, 0.8)) -> 64.743375 | G326: =INDEX(G$13:G$17, MATCH($B336, $B$13:$B$17, 0), 1)*$D$2*(1+RANDBETWEEN(-0.8, 0.8)) -> 52.743375 | H326: =INDEX(H$13:H$17, MATCH($B336, $B$13:$B$17, 0), 1)*$D$2*(1+RANDBETWEEN(-0.8, 0.8)) -> 84.743375 | I326: =INDEX(I$13:I$17, MATCH($B336, $B$13:$B$17, 0), 1)*$D$2*(1+RANDBETWEEN(-1, 1)) -> 386.34458 | J326: =INDEX(J$13:J$17, MATCH($B336, $B$13:$B$17, 0), 1)*$D$2*(1+RANDBETWEEN(-1, 1)) -> 202.64675
B327: 2026 | C327: 2 | D327: 4 | E327: =INDEX(E$13:E$17, MATCH($B337, $B$13:$B$17, 0), 1)*$D$2*(1+RANDBETWEEN(-0.8, 0.8)) -> 47.943375 | F327: =INDEX(F$13:F$17, MATCH($B337, $B$13:$B$17, 0), 1)*$D$2*(1+RANDBETWEEN(-0.8, 0.8)) -> 64.743375 | G327: =INDEX(G$13:G$17, MATCH($B337, $B$13:$B$17, 0), 1)*$D$2*(1+RANDBETWEEN(-0.8, 0.8)) -> 52.743375 | H327: =INDEX(H$13:H$17, MATCH($B337, $B$13:$B$17, 0), 1)*$D$2*(1+RANDBETWEEN(-0.8, 0.8)) -> 84.743375 | I327: =INDEX(I$13:I$17, MATCH($B337, $B$13:$B$17, 0), 1)*$D$2*(1+RANDBETWEEN(-1, 1)) -> 386.34458 | J327: =INDEX(J$13:J$17, MATCH($B337, $B$13:$B$17, 0), 1)*$D$2*(1+RANDBETWEEN(-1, 1)) -> 0
B328: 2026 | C328: 2 | D328: 5 | E328: =INDEX(E$13:E$17, MATCH($B338, $B$13:$B$17, 0), 1)*$D$2*(1+RANDBETWEEN(-0.8, 0.8)) -> 47.943375 | F328: =INDEX(F$13:F$17, MATCH($B338, $B$13:$B$17, 0), 1)*$D$2*(1+RANDBETWEEN(-0.8, 0.8)) -> 64.743375 | G328: =INDEX(G$13:G$17, MATCH($B338, $B$13:$B$17, 0), 1)*$D$2*(1+RANDBETWEEN(-0.8, 0.8)) -> 52.743375 | H328: =INDEX(H$13:H$17, MATCH($B338, $B$13:$B$17, 0), 1)*$D$2*(1+RANDBETWEEN(-0.8, 0.8)) -> 84.743375 | I328: =INDEX(I$13:I$17, MATCH($B338, $B$13:$B$17, 0), 1)*$D$2*(1+RANDBETWEEN(-1, 1)) -> 193.17229 | J328: =INDEX(J$13:J$17, MATCH($B338, $B$13:$B$17, 0), 1)*$D$2*(1+RANDBETWEEN(-1, 1)) -> 405.2935
B329: 2026 | C329: 2 | D329: 6 | E329: =INDEX(E$13:E$17, MATCH($B339, $B$13:$B$17, 0), 1)*$D$2*(1+RANDBETWEEN(-0.8, 0.8)) -> 47.943375 | F329: =INDEX(F$13:F$17, MATCH($B339, $B$13:$B$17, 0), 1)*$D$2*(1+RANDBETWEEN(-0.8, 0.8)) -> 64.743375 | G329: =INDEX(G$13:G$17, MATCH($B339, $B$13:$B$17, 0), 1)*$D$2*(1+RANDBETWEEN(-0.8, 0.8)) -> 52.743375 | H329: =INDEX(H$13:H$17, MATCH($B339, $B$13:$B$17, 0), 1)*$D$2*(1+RANDBETWEEN(-0.8, 0.8)) -> 84.743375 | I329: =INDEX(I$13:I$17, MATCH($B339, $B$13:$B$17, 0), 1)*$D$2*(1+RANDBETWEEN(-1, 1)) -> 193.17229 | J329: =INDEX(J$13:J$17, MATCH($B339, $B$13:$B$17, 0), 1)*$D$2*(1+RANDBETWEEN(-1, 1)) -> 202.64675
... B335: 2027 | C335: 4 | D335: 12 | E335: =INDEX(E$13:E$17, MATCH($B345, $B$13:$B$17, 0), 1)*$D$2*(1+RANDBETWEEN(-0.8, 0.8)) -> 47.943375 | F335: =INDEX(F$13:F$17, MATCH($B345, $B$13:$B$17, 0), 1)*$D$2*(1+RANDBETWEEN(-0.8, 0.8)) -> 64.743375 | G335: =INDEX(G$13:G$17, MATCH($B345, $B$13:$B$17, 0), 1)*$D$2*(1+RANDBETWEEN(-0.8, 0.8)) -> 52.743375 | H335: =INDEX(H$13:H$17, MATCH($B345, $B$13:$B$17, 0), 1)*$D$2*(1+RANDBETWEEN(-0.8, 0.8)) -> 84.743375 | I335: =INDEX(I$13:I$17, MATCH($B345, $B$13:$B$17, 0), 1)*$D$2*(1+RANDBETWEEN(-1, 1)) -> 193.17229 | J335: =INDEX(J$13:J$17, MATCH($B345, $B$13:$B$17, 0), 1)*$D$2*(1+RANDBETWEEN(-1, 1)) -> 202.64675
B336: 2027 | C336: =C324 -> 1 | D336: =D324 -> 1 | E336: =INDEX(E$13:E$17, MATCH($B346, $B$13:$B$17, 0), 1)*$D$2*(1+RANDBETWEEN(-0.8, 0.8)) -> 43.715568 | F336: =INDEX(F$13:F$17, MATCH($B346, $B$13:$B$17, 0), 1)*$D$2*(1+RANDBETWEEN(-0.8, 0.8)) -> 53.315568 | G336: =INDEX(G$13:G$17, MATCH($B346, $B$13:$B$17, 0), 1)*$D$2*(1+RANDBETWEEN(-0.8, 0.8)) -> 48.515568 | H336: =INDEX(H$13:H$17, MATCH($B346, $B$13:$B$17, 0), 1)*$D$2*(1+RANDBETWEEN(-0.8, 0.8)) -> 73.315568 | I336: =INDEX(I$13:I$17, MATCH($B346, $B$13:$B$17, 0), 1)*$D$2*(1+RANDBETWEEN(-1, 1)) -> 171.34123 | J336: =INDEX(J$13:J$17, MATCH($B346, $B$13:$B$17, 0), 1)*$D$2*(1+RANDBETWEEN(-1, 1)) -> 361.97668
B337: 2027 | C337: =C325 -> 1 | D337: =D325 -> 2 | E337: =INDEX(E$13:E$17, MATCH($B347, $B$13:$B$17, 0), 1)*$D$2*(1+RANDBETWEEN(-0.8, 0.8)) -> 43.715568 | F337: =INDEX(F$13:F$17, MATCH($B347, $B$13:$B$17, 0), 1)*$D$2*(1+RANDBETWEEN(-0.8, 0.8)) -> 53.315568 | G337: =INDEX(G$13:G$17, MATCH($B347, $B$13:$B$17, 0), 1)*$D$2*(1+RANDBETWEEN(-0.8, 0.8)) -> 48.515568 | H337: =INDEX(H$13:H$17, MATCH($B347, $B$13:$B$17, 0), 1)*$D$2*(1+RANDBETWEEN(-0.8, 0.8)) -> 73.315568 | I337: =INDEX(I$13:I$17, MATCH($B347, $B$13:$B$17, 0), 1)*$D$2*(1+RANDBETWEEN(-1, 1)) -> 171.34123 | J337: =INDEX(J$13:J$17, MATCH($B347, $B$13:$B$17, 0), 1)*$D$2*(1+RANDBETWEEN(-1, 1)) -> 180.98834
B338: 2027 | C338: =C326 -> 1 | D338: =D326 -> 3 | E338: =INDEX(E$13:E$17, MATCH($B348, $B$13:$B$17, 0), 1)*$D$2*(1+RANDBETWEEN(-0.8, 0.8)) -> 43.715568 | F338: =INDEX(F$13:F$17, MATCH($B348, $B$13:$B$17, 0), 1)*$D$2*(1+RANDBETWEEN(-0.8, 0.8)) -> 53.315568 | G338: =INDEX(G$13:G$17, MATCH($B348, $B$13:$B$17, 0), 1)*$D$2*(1+RANDBETWEEN(-0.8, 0.8)) -> 48.515568 | H338: =INDEX(H$13:H$17, MATCH($B348, $B$13:$B$17, 0), 1)*$D$2*(1+RANDBETWEEN(-0.8, 0.8)) -> 73.315568 | I338: =INDEX(I$13:I$17, MATCH($B348, $B$13:$B$17, 0), 1)*$D$2*(1+RANDBETWEEN(-1, 1)) -> 342.68245 | J338: =INDEX(J$13:J$17, MATCH($B348, $B$13:$B$17, 0), 1)*$D$2*(1+RANDBETWEEN(-1, 1)) -> 361.97668
B339: 2027 | C339: =C327 -> 2 | D339: =D327 -> 4 | E339: =INDEX(E$13:E$17, MATCH($B349, $B$13:$B$17, 0), 1)*$D$2*(1+RANDBETWEEN(-0.8, 0.8)) -> 43.715568 | F339: =INDEX(F$13:F$17, MATCH($B349, $B$13:$B$17, 0), 1)*$D$2*(1+RANDBETWEEN(-0.8, 0.8)) -> 53.315568 | G339: =INDEX(G$13:G$17, MATCH($B349, $B$13:$B$17, 0), 1)*$D$2*(1+RANDBETWEEN(-0.8, 0.8)) -> 48.515568 | H339: =INDEX(H$13:H$17, MATCH($B349, $B$13:$B$17, 0), 1)*$D$2*(1+RANDBETWEEN(-0.8, 0.8)) -> 73.315568 | I339: =INDEX(I$13:I$17, MATCH($B349, $B$13:$B$17, 0), 1)*$D$2*(1+RANDBETWEEN(-1, 1)) -> 171.34123 | J339: =INDEX(J$13:J$17, MATCH($B349, $B$13:$B$17, 0), 1)*$D$2*(1+RANDBETWEEN(-1, 1)) -> 0
B340: 2027 | C340: =C328 -> 2 | D340: =D328 -> 5 | E340: =INDEX(E$13:E$17, MATCH($B350, $B$13:$B$17, 0), 1)*$D$2*(1+RANDBETWEEN(-0.8, 0.8)) -> 43.715568 | F340: =INDEX(F$13:F$17, MATCH($B350, $B$13:$B$17, 0), 1)*$D$2*(1+RANDBETWEEN(-0.8, 0.8)) -> 53.315568 | G340: =INDEX(G$13:G$17, MATCH($B350, $B$13:$B$17, 0), 1)*$D$2*(1+RANDBETWEEN(-0.8, 0.8)) -> 48.515568 | H340: =INDEX(H$13:H$17, MATCH($B350, $B$13:$B$17, 0), 1)*$D$2*(1+RANDBETWEEN(-0.8, 0.8)) -> 73.315568 | I340: =INDEX(I$13:I$17, MATCH($B350, $B$13:$B$17, 0), 1)*$D$2*(1+RANDBETWEEN(-1, 1)) -> 171.34123 | J340: =INDEX(J$13:J$17, MATCH($B350, $B$13:$B$17, 0), 1)*$D$2*(1+RANDBETWEEN(-1, 1)) -> 180.98834
B341: 2027 | C341: =C329 -> 2 | D341: =D329 -> 6 | E341: =INDEX(E$13:E$17, MATCH($B351, $B$13:$B$17, 0), 1)*$D$2*(1+RANDBETWEEN(-0.8, 0.8)) -> 43.715568 | F341: =INDEX(F$13:F$17, MATCH($B351, $B$13:$B$17, 0), 1)*$D$2*(1+RANDBETWEEN(-0.8, 0.8)) -> 53.315568 | G341: =INDEX(G$13:G$17, MATCH($B351, $B$13:$B$17, 0), 1)*$D$2*(1+RANDBETWEEN(-0.8, 0.8)) -> 48.515568 | H341: =INDEX(H$13:H$17, MATCH($B351, $B$13:$B$17, 0), 1)*$D$2*(1+RANDBETWEEN(-0.8, 0.8)) -> 73.315568 | I341: =INDEX(I$13:I$17, MATCH($B351, $B$13:$B$17, 0), 1)*$D$2*(1+RANDBETWEEN(-1, 1)) -> 342.68245 | J341: =INDEX(J$13:J$17, MATCH($B351, $B$13:$B$17, 0), 1)*$D$2*(1+RANDBETWEEN(-1, 1)) -> 180.98834
B342: 2027 | C342: =C330 -> 3 | D342: =D330 -> 7 | E342: =INDEX(E$13:E$17, MATCH($B352, $B$13:$B$17, 0), 1)*$D$2*(1+RANDBETWEEN(-0.8, 0.8)) -> 43.715568 | F342: =INDEX(F$13:F$17, MATCH($B352, $B$13:$B$17, 0), 1)*$D$2*(1+RANDBETWEEN(-0.8, 0.8)) -> 53.315568 | G342: =INDEX(G$13:G$17, MATCH($B352, $B$13:$B$17, 0), 1)*$D$2*(1+RANDBETWEEN(-0.8, 0.8)) -> 48.515568 | H342: =INDEX(H$13:H$17, MATCH($B352, $B$13:$B$17, 0), 1)*$D$2*(1+RANDBETWEEN(-0.8, 0.8)) -> 73.315568 | I342: =INDEX(I$13:I$17, MATCH($B352, $B$13:$B$17, 0), 1)*$D$2*(1+RANDBETWEEN(-1, 1)) -> 0 | J342: =INDEX(J$13:J$17, MATCH($B352, $B$13:$B$17, 0), 1)*$D$2*(1+RANDBETWEEN(-1, 1)) -> 180.98834
B343: 2027 | C343: =C331 -> 3 | D343: =D331 -> 8 | E343: =INDEX(E$13:E$17, MATCH($B353, $B$13:$B$17, 0), 1)*$D$2*(1+RANDBETWEEN(-0.8, 0.8)) -> 43.715568 | F343: =INDEX(F$13:F$17, MATCH($B353, $B$13:$B$17, 0), 1)*$D$2*(1+RANDBETWEEN(-0.8, 0.8)) -> 53.315568 | G343: =INDEX(G$13:G$17, MATCH($B353, $B$13:$B$17, 0), 1)*$D$2*(1+RANDBETWEEN(-0.8, 0.8)) -> 48.515568 | H343: =INDEX(H$13:H$17, MATCH($B353, $B$13:$B$17, 0), 1)*$D$2*(1+RANDBETWEEN(-0.8, 0.8)) -> 73.315568 | I343: =INDEX(I$13:I$17, MATCH($B353, $B$13:$B$17, 0), 1)*$D$2*(1+RANDBETWEEN(-1, 1)) -> 0 | J343: =INDEX(J$13:J$17, MATCH($B353, $B$13:$B$17, 0), 1)*$D$2*(1+RANDBETWEEN(-1, 1)) -> 0
B344: 2027 | C344: =C332 -> 3 | D344: =D332 -> 9 | E344: =INDEX(E$13:E$17, MATCH($B354, $B$13:$B$17, 0), 1)*$D$2*(1+RANDBETWEEN(-0.8, 0.8)) -> 43.715568 | F344: =INDEX(F$13:F$17, MATCH($B354, $B$13:$B$17, 0), 1)*$D$2*(1+RANDBETWEEN(-0.8, 0.8)) -> 53.315568 | G344: =INDEX(G$13:G$17, MATCH($B354, $B$13:$B$17, 0), 1)*$D$2*(1+RANDBETWEEN(-0.8, 0.8)) -> 48.515568 | H344: =INDEX(H$13:H$17, MATCH($B354, $B$13:$B$17, 0), 1)*$D$2*(1+RANDBETWEEN(-0.8, 0.8)) -> 73.315568 | I344: =INDEX(I$13:I$17, MATCH($B354, $B$13:$B$17, 0), 1)*$D$2*(1+RANDBETWEEN(-1, 1)) -> 342.68245 | J344: =INDEX(J$13:J$17, MATCH($B354, $B$13:$B$17, 0), 1)*$D$2*(1+RANDBETWEEN(-1, 1)) -> 180.98834
B345: 2027 | C345: =C333 -> 4 | D345: =D333 -> 10 | E345: =INDEX(E$13:E$17, MATCH($B355, $B$13:$B$17, 0), 1)*$D$2*(1+RANDBETWEEN(-0.8, 0.8)) -> 43.715568 | F345: =INDEX(F$13:F$17, MATCH($B355, $B$13:$B$17, 0), 1)*$D$2*(1+RANDBETWEEN(-0.8, 0.8)) -> 53.315568 | G345: =INDEX(G$13:G$17, MATCH($B355, $B$13:$B$17, 0), 1)*$D$2*(1+RANDBETWEEN(-0.8, 0.8)) -> 48.515568 | H345: =INDEX(H$13:H$17, MATCH($B355, $B$13:$B$17, 0), 1)*$D$2*(1+RANDBETWEEN(-0.8, 0.8)) -> 73.315568 | I345: =INDEX(I$13:I$17, MATCH($B355, $B$13:$B$17, 0), 1)*$D$2*(1+RANDBETWEEN(-1, 1)) -> 171.34123 | J345: =INDEX(J$13:J$17, MATCH($B355, $B$13:$B$17, 0), 1)*$D$2*(1+RANDBETWEEN(-1, 1)) -> 361.97668
B346: =B334+1 -> 2028 | C346: =C334 -> 4 | D346: =D334 -> 11 | E346: =INDEX(E$13:E$17, MATCH($B356, $B$13:$B$17, 0), 1)*$D$2*(1+RANDBETWEEN(-0.8, 0.8)) -> 43.715568 | F346: =INDEX(F$13:F$17, MATCH($B356, $B$13:$B$17, 0), 1)*$D$2*(1+RANDBETWEEN(-0.8, 0.8)) -> 53.315568 | G346: =INDEX(G$13:G$17, MATCH($B356, $B$13:$B$17, 0), 1)*$D$2*(1+RANDBETWEEN(-0.8, 0.8)) -> 48.515568 | H346: =INDEX(H$13:H$17, MATCH($B356, $B$13:$B$17, 0), 1)*$D$2*(1+RANDBETWEEN(-0.8, 0.8)) -> 73.315568 | I346: =INDEX(I$13:I$17, MATCH($B356, $B$13:$B$17, 0), 1)*$D$2*(1+RANDBETWEEN(-1, 1)) -> 0 | J346: =INDEX(J$13:J$17, MATCH($B356, $B$13:$B$17, 0), 1)*$D$2*(1+RANDBETWEEN(-1, 1)) -> 361.97668
B347: =B335+1 -> 2028 | C347: =C335 -> 4 | D347: =D335 -> 12 | E347: =INDEX(E$13:E$17, MATCH($B357, $B$13:$B$17, 0), 1)*$D$2*(1+RANDBETWEEN(-0.8, 0.8)) -> 43.715568 | F347: =INDEX(F$13:F$17, MATCH($B357, $B$13:$B$17, 0), 1)*$D$2*(1+RANDBETWEEN(-0.8, 0.8)) -> 53.315568 | G347: =INDEX(G$13:G$17, MATCH($B357, $B$13:$B$17, 0), 1)*$D$2*(1+RANDBETWEEN(-0.8, 0.8)) -> 48.515568 | H347: =INDEX(H$13:H$17, MATCH($B357, $B$13:$B$17, 0), 1)*$D$2*(1+RANDBETWEEN(-0.8, 0.8)) -> 73.315568 | I347: =INDEX(I$13:I$17, MATCH($B357, $B$13:$B$17, 0), 1)*$D$2*(1+RANDBETWEEN(-1, 1)) -> 171.34123 | J347: =INDEX(J$13:J$17, MATCH($B357, $B$13:$B$17, 0), 1)*$D$2*(1+RANDBETWEEN(-1, 1)) -> 361.97668
B348: =B336+1 -> 2028 | C348: =C336 -> 1 | D348: =D336 -> 1 | E348: =INDEX(E$13:E$17, MATCH($B358, $B$13:$B$17, 0), 1)*$D$2*(1+RANDBETWEEN(-0.8, 0.8)) -> 38.715547 | F348: =INDEX(F$13:F$17, MATCH($B358, $B$13:$B$17, 0), 1)*$D$2*(1+RANDBETWEEN(-0.8, 0.8)) -> 52.315547 | G348: =INDEX(G$13:G$17, MATCH($B358, $B$13:$B$17, 0), 1)*$D$2*(1+RANDBETWEEN(-0.8, 0.8)) -> 43.515547 | H348: =INDEX(H$13:H$17, MATCH($B358, $B$13:$B$17, 0), 1)*$D$2*(1+RANDBETWEEN(-0.8, 0.8)) -> 72.315547 | I348: =INDEX(I$13:I$17, MATCH($B358, $B$13:$B$17, 0), 1)*$D$2*(1+RANDBETWEEN(-1, 1)) -> 0 | J348: =INDEX(J$13:J$17, MATCH($B358, $B$13:$B$17, 0), 1)*$D$2*(1+RANDBETWEEN(-1, 1)) -> 0
B349: =B337+1 -> 2028 | C349: =C337 -> 1 | D349: =D337 -> 2 | E349: =INDEX(E$13:E$17, MATCH($B359, $B$13:$B$17, 0), 1)*$D$2*(1+RANDBETWEEN(-0.8, 0.8)) -> 38.715547 | F349: =INDEX(F$13:F$17, MATCH($B359, $B$13:$B$17, 0), 1)*$D$2*(1+RANDBETWEEN(-0.8, 0.8)) -> 52.315547 | G349: =INDEX(G$13:G$17, MATCH($B359, $B$13:$B$17, 0), 1)*$D$2*(1+RANDBETWEEN(-0.8, 0.8)) -> 43.515547 | H349: =INDEX(H$13:H$17, MATCH($B359, $B$13:$B$17, 0), 1)*$D$2*(1+RANDBETWEEN(-0.8, 0.8)) -> 72.315547 | I349: =INDEX(I$13:I$17, MATCH($B359, $B$13:$B$17, 0), 1)*$D$2*(1+RANDBETWEEN(-1, 1)) -> 0 | J349: =INDEX(J$13:J$17, MATCH($B359, $B$13:$B$17, 0), 1)*$D$2*(1+RANDBETWEEN(-1, 1)) -> 174.91669
B350: =B338+1 -> 2028 | C350: =C338 -> 1 | D350: =D338 -> 3 | E350: =INDEX(E$13:E$17, MATCH($B360, $B$13:$B$17, 0), 1)*$D$2*(1+RANDBETWEEN(-0.8, 0.8)) -> 38.715547 | F350: =INDEX(F$13:F$17, MATCH($B360, $B$13:$B$17, 0), 1)*$D$2*(1+RANDBETWEEN(-0.8, 0.8)) -> 52.315547 | G350: =INDEX(G$13:G$17, MATCH($B360, $B$13:$B$17, 0), 1)*$D$2*(1+RANDBETWEEN(-0.8, 0.8)) -> 43.515547 | H350: =INDEX(H$13:H$17, MATCH($B360, $B$13:$B$17, 0), 1)*$D$2*(1+RANDBETWEEN(-0.8, 0.8)) -> 72.315547 | I350: =INDEX(I$13:I$17, MATCH($B360, $B$13:$B$17, 0), 1)*$D$2*(1+RANDBETWEEN(-1, 1)) -> 330.4194 | J350: =INDEX(J$13:J$17, MATCH($B360, $B$13:$B$17, 0), 1)*$D$2*(1+RANDBETWEEN(-1, 1)) -> 174.91669
B351: =B339+1 -> 2028 | C351: =C339 -> 2 | D351: =D339 -> 4 | E351: =INDEX(E$13:E$17, MATCH($B361, $B$13:$B$17, 0), 1)*$D$2*(1+RANDBETWEEN(-0.8, 0.8)) -> 38.715547 | F351: =INDEX(F$13:F$17, MATCH($B361, $B$13:$B$17, 0), 1)*$D$2*(1+RANDBETWEEN(-0.8, 0.8)) -> 52.315547 | G351: =INDEX(G$13:G$17, MATCH($B361, $B$13:$B$17, 0), 1)*$D$2*(1+RANDBETWEEN(-0.8, 0.8)) -> 43.515547 | H351: =INDEX(H$13:H$17, MATCH($B361, $B$13:$B$17, 0), 1)*$D$2*(1+RANDBETWEEN(-0.8, 0.8)) -> 72.315547 | I351: =INDEX(I$13:I$17, MATCH($B361, $B$13:$B$17, 0), 1)*$D$2*(1+RANDBETWEEN(-1, 1)) -> 0 | J351: =INDEX(J$13:J$17, MATCH($B361, $B$13:$B$17, 0), 1)*$D$2*(1+RANDBETWEEN(-1, 1)) -> 349.83339
B352: =B340+1 -> 2028 | C352: =C340 -> 2 | D352: =D340 -> 5 | E352: =INDEX(E$13:E$17, MATCH($B362, $B$13:$B$17, 0), 1)*$D$2*(1+RANDBETWEEN(-0.8, 0.8)) -> 38.715547 | F352: =INDEX(F$13:F$17, MATCH($B362, $B$13:$B$17, 0), 1)*$D$2*(1+RANDBETWEEN(-0.8, 0.8)) -> 52.315547 | G352: =INDEX(G$13:G$17, MATCH($B362, $B$13:$B$17, 0), 1)*$D$2*(1+RANDBETWEEN(-0.8, 0.8)) -> 43.515547 | H352: =INDEX(H$13:H$17, MATCH($B362, $B$13:$B$17, 0), 1)*$D$2*(1+RANDBETWEEN(-0.8, 0.8)) -> 72.315547 | I352: =INDEX(I$13:I$17, MATCH($B362, $B$13:$B$17, 0), 1)*$D$2*(1+RANDBETWEEN(-1, 1)) -> 165.2097 | J352: =INDEX(J$13:J$17, MATCH($B362, $B$13:$B$17, 0), 1)*$D$2*(1+RANDBETWEEN(-1, 1)) -> 174.91669
B353: =B341+1 -> 2028 | C353: =C341 -> 2 | D353: =D341 -> 6 | E353: =INDEX(E$13:E$17, MATCH($B363, $B$13:$B$17, 0), 1)*$D$2*(1+RANDBETWEEN(-0.8, 0.8)) -> 38.715547 | F353: =INDEX(F$13:F$17, MATCH($B363, $B$13:$B$17, 0), 1)*$D$2*(1+RANDBETWEEN(-0.8, 0.8)) -> 52.315547 | G353: =INDEX(G$13:G$17, MATCH($B363, $B$13:$B$17, 0), 1)*$D$2*(1+RANDBETWEEN(-0.8, 0.8)) -> 43.515547 | H353: =INDEX(H$13:H$17, MATCH($B363, $B$13:$B$17, 0), 1)*$D$2*(1+RANDBETWEEN(-0.8, 0.8)) -> 72.315547 | I353: =INDEX(I$13:I$17, MATCH($B363, $B$13:$B$17, 0), 1)*$D$2*(1+RANDBETWEEN(-1, 1)) -> 330.4194 | J353: =INDEX(J$13:J$17, MATCH($B363, $B$13:$B$17, 0), 1)*$D$2*(1+RANDBETWEEN(-1, 1)) -> 0
B354: =B342+1 -> 2028 | C354: =C342 -> 3 | D354: =D342 -> 7 | E354: =INDEX(E$13:E$17, MATCH($B364, $B$13:$B$17, 0), 1)*$D$2*(1+RANDBETWEEN(-0.8, 0.8)) -> 38.715547 | F354: =INDEX(F$13:F$17, MATCH($B364, $B$13:$B$17, 0), 1)*$D$2*(1+RANDBETWEEN(-0.8, 0.8)) -> 52.315547 | G354: =INDEX(G$13:G$17, MATCH($B364, $B$13:$B$17, 0), 1)*$D$2*(1+RANDBETWEEN(-0.8, 0.8)) -> 43.515547 | H354: =INDEX(H$13:H$17, MATCH($B364, $B$13:$B$17, 0), 1)*$D$2*(1+RANDBETWEEN(-0.8, 0.8)) -> 72.315547 | I354: =INDEX(I$13:I$17, MATCH($B364, $B$13:$B$17, 0), 1)*$D$2*(1+RANDBETWEEN(-1, 1)) -> 165.2097 | J354: =INDEX(J$13:J$17, MATCH($B364, $B$13:$B$17, 0), 1)*$D$2*(1+RANDBETWEEN(-1, 1)) -> 0
B355: =B343+1 -> 2028 | C355: =C343 -> 3 | D355: =D343 -> 8 | E355: =INDEX(E$13:E$17, MATCH($B365, $B$13:$B$17, 0), 1)*$D$2*(1+RANDBETWEEN(-0.8, 0.8)) -> 38.715547 | F355: =INDEX(F$13:F$17, MATCH($B365, $B$13:$B$17, 0), 1)*$D$2*(1+RANDBETWEEN(-0.8, 0.8)) -> 52.315547 | G355: =INDEX(G$13:G$17, MATCH($B365, $B$13:$B$17, 0), 1)*$D$2*(1+RANDBETWEEN(-0.8, 0.8)) -> 43.515547 | H355: =INDEX(H$13:H$17, MATCH($B365, $B$13:$B$17, 0), 1)*$D$2*(1+RANDBETWEEN(-0.8, 0.8)) -> 72.315547 | I355: =INDEX(I$13:I$17, MATCH($B365, $B$13:$B$17, 0), 1)*$D$2*(1+RANDBETWEEN(-1, 1)) -> 0 | J355: =INDEX(J$13:J$17, MATCH($B365, $B$13:$B$17, 0), 1)*$D$2*(1+RANDBETWEEN(-1, 1)) -> 174.91669
B356: =B344+1 -> 2028 | C356: =C344 -> 3 | D356: =D344 -> 9 | E356: =INDEX(E$13:E$17, MATCH($B366, $B$13:$B$17, 0), 1)*$D$2*(1+RANDBETWEEN(-0.8, 0.8)) -> 38.715547 | F356: =INDEX(F$13:F$17, MATCH($B366, $B$13:$B$17, 0), 1)*$D$2*(1+RANDBETWEEN(-0.8, 0.8)) -> 52.315547 | G356: =INDEX(G$13:G$17, MATCH($B366, $B$13:$B$17, 0), 1)*$D$2*(1+RANDBETWEEN(-0.8, 0.8)) -> 43.515547 | H356: =INDEX(H$13:H$17, MATCH($B366, $B$13:$B$17, 0), 1)*$D$2*(1+RANDBETWEEN(-0.8, 0.8)) -> 72.315547 | I356: =INDEX(I$13:I$17, MATCH($B366, $B$13:$B$17, 0), 1)*$D$2*(1+RANDBETWEEN(-1, 1)) -> 0 | J356: =INDEX(J$13:J$17, MATCH($B366, $B$13:$B$17, 0), 1)*$D$2*(1+RANDBETWEEN(-1, 1)) -> 0
B357: =B345+1 -> 2028 | C357: =C345 -> 4 | D357: =D345 -> 10 | E357: =INDEX(E$13:E$17, MATCH($B367, $B$13:$B$17, 0), 1)*$D$2*(1+RANDBETWEEN(-0.8, 0.8)) -> 38.715547 | F357: =INDEX(F$13:F$17, MATCH($B367, $B$13:$B$17, 0), 1)*$D$2*(1+RANDBETWEEN(-0.8, 0.8)) -> 52.315547 | G357: =INDEX(G$13:G$17, MATCH($B367, $B$13:$B$17, 0), 1)*$D$2*(1+RANDBETWEEN(-0.8, 0.8)) -> 43.515547 | H357: =INDEX(H$13:H$17, MATCH($B367, $B$13:$B$17, 0), 1)*$D$2*(1+RANDBETWEEN(-0.8, 0.8)) -> 72.315547 | I357: =INDEX(I$13:I$17, MATCH($B367, $B$13:$B$17, 0), 1)*$D$2*(1+RANDBETWEEN(-1, 1)) -> 330.4194 | J357: =INDEX(J$13:J$17, MATCH($B367, $B$13:$B$17, 0), 1)*$D$2*(1+RANDBETWEEN(-1, 1)) -> 0
... B443: =B431+1 -> 2036 | C443: =C431 -> 4 | D443: =D431 -> 12 | E443: =INDEX(E$13:E$17, MATCH($B453, $B$13:$B$17, 0), 1)*$D$2*(1+RANDBETWEEN(-0.8, 0.8)) -> #N/A | F443: =INDEX(F$13:F$17, MATCH($B453, $B$13:$B$17, 0), 1)*$D$2*(1+RANDBETWEEN(-0.8, 0.8)) -> #N/A | G443: =INDEX(G$13:G$17, MATCH($B453, $B$13:$B$17, 0), 1)*$D$2*(1+RANDBETWEEN(-0.8, 0.8)) -> #N/A | H443: =INDEX(H$13:H$17, MATCH($B453, $B$13:$B$17, 0), 1)*$D$2*(1+RANDBETWEEN(-0.8, 0.8)) -> #N/A | I443: =INDEX(I$13:I$17, MATCH($B453, $B$13:$B$17, 0), 1)*$D$2*(1+RANDBETWEEN(-1, 1)) -> #N/A | J443: =INDEX(J$13:J$17, MATCH($B453, $B$13:$B$17, 0), 1)*$D$2*(1+RANDBETWEEN(-1, 1)) -> #N/A
B444: =B432+1 -> 2036
B445: =B433+1 -> 2036
B446: =B434+1 -> 2036
B447: =B435+1 -> 2036
B448: =B436+1 -> 2036
B449: =B437+1 -> 2036
B450: =B438+1 -> 2036
B451: =B439+1 -> 2036
B452: =B440+1 -> 2036
B453: =B441+1 -> 2036

Sheet Feuil3

Sheet Graph

Sheet Feuil1
A1: # | B1: Formule | C1: Logique | D1: Hypothèses nécessaires | E1: 👍 Avantages | F1: ⚠️ Inconvénients / risques | G1: Cas d’usage recommandé
A2: 1 | B2: IPP-CAPPED | C2: IPP = plafond dur | D2: IPP robuste et accepté par les deux parties | E2: Protection maximale OCP ; discipline économique forte | F2: Faible acceptabilité fournisseur ; peu “relationnel” | G2: Position d’ouverture ; marché très tendu
A3: 2 | B3: COLLAR autour de l’IPP | C3: Partage de risque | D3: Floor crédible fournisseur ; IPP comme cap | E3: Équilibrée ; bankable ; robuste long terme | F3: Moins protectrice qu’un cap pur | G3: Formule cœur recommandée
A4: 3 | B4: IPP-REFERENCED | C4: IPP comme garde-fou implicite | D4: IPP suivi en interne ; confiance contractuelle | E4: Acceptable fournisseur ; flexible | F4: Protection OCP plus faible ; dépend du design | G4: Concession tactique
A5: 4 | B5: Cost-plus hybride indexé | C5: Reconnaître l’économie réelle | D5: Transparence coûts ; gouvernance solide | E5: Crédible entre intégrés ; stabilité 10 ans | F5: Complexité ; risque de dérive sans cap IPP | G5: Partenariat stratégique
A6: 5 | B6: IPP-Sharing (scarcity rent) | C6: Partage de la rente de rareté | D6: IPP reconnu comme coût marginal | E6: “Fair” en undersupply ; relationnel | F6: OCP accepte de payer au-dessus de l’index | G6: Marché structurellement tendu
A7: 6 | B7: Baseload + Flex volumes | C7: Séparer sécurité & optionalité | D7: Capacité fournisseur ; flex logistique | E7: Sécurise volumes + arbitrage OCP | F7: Plus complexe contractuellement | G7: Très adapté contrat 10 ans
A8: 7 | B8: Re-opener structurel | C8: Adapter sans renégocier | D8: Gouvernance claire ; déclencheurs objectifs | E8: Robustesse long terme ; réduit conflits | F8: Pas un pricing en soi | G8: Indispensable >7–8 ans
A9: 8 | B9: Engrais as cycle adjuster | C9: Partage du cycle aval | D9: Indice engrais pertinent (DAP/MAP) | E9: Alignement chaîne valeur ; subtil | F9: Peut être mal perçu politiquement | G9: Complément intelligent
A10: 9 | B10: Engrais-triggered sharing | C10: Upside conditionnel | D10: Seuil engrais bien calibré | E10: Acceptable en extrême tension | F10: Complexité ; usage rare | G10: Clause optionnelle
A11: 10 | B11: Dual index (soufre + engrais) | C11: Deux drivers pondérés | D11: Poids engrais limité (<30%) | E11: Partage élargi du cycle | F11: Risque de sur-indexation | G11: À manier avec précaution
A12: 11 | B12: Energy pass-through Maroc (capé) | C12: Partage coûts structurels | D12: Indice énergie Maroc fiable | E12: Légitime ; crédible ; long terme | F12: Sensible politiquement | G12: Correcteur structurel
A13: 12 | B13: Energy/carbon as re-opener | C13: Sécurité long terme | D13: Déclencheurs objectifs | E13: Zéro volatilité mensuelle | F13: Pas de signal prix immédiat | G13: Best practice 10 ans
A14: 13 | B14: Decarbonization incentive | C14: Alignement ESG | D14: Mesure intensité carbone | E14: Image ESG ; incitatif | F14: Mise en œuvre exigeante | G14: Option “premium”

Sheet CRU historical
D1: Sulphuric Acid Bulk FOB | G1: Sulphuric Acid Bulk FOB | J1: Sulphuric Acid Bulk FOB | M1: Sulphuric Acid Bulk CFR | P1: Sulphur Bulk FOB | S1: Sulphur Bulk CFR | V1: Sulphur Bulk CFR | Y1: Sulphur Bulk CFR | AB1: Sulphur Bulk CFR
D2: Japan/South Korea Spot | G2: NW Europe 30 days Spot | J2: China Spot | M2: North Africa, Spot | P2: Middle East Spot | S2: North Africa Quarterly Contract | V2: North Africa Half Yearly Contract | Y2: Mediterranean small lots Spot | AB2: Mediterranean (incl. North Africa) Spot
D3: USD/t | G3: USD/t | J3: USD/t | M3: USD/t | P3: USD/t | S3: USD/t | V3: USD/t | Y3: USD/t | AB3: USD/t
A4: Year | B4: Quarter | C4: Month | D4: Max | E4: Min | F4: Avg | G4: Max | H4: Min | I4: Avg | J4: Max | K4: Min | L4: Avg | M4: Max | N4: Min | O4: Avg | P4: Max | Q4: Min | R4: Avg | S4: Max | T4: Min | U4: Avg | V4: Max | W4: Min | X4: Avg | Y4: Max | Z4: Min | AA4: Avg | AB4: Max | AC4: Min | AD4: Avg
A5: 2002 | B5: 2 | C5: 5 | G5: 7 | H5: 5 | I5: 6 | V5: 34 | W5: 32 | X5: 33
A6: 2002 | B6: 2 | C6: 6 | G6: 7 | H6: 5 | I6: 6 | V6: 34 | W6: 32 | X6: 33
A7: 2002 | B7: 3 | C7: 7 | G7: 9 | H7: 7 | I7: 8 | V7: 39 | W7: 38 | X7: 39
A8: 2002 | B8: 3 | C8: 8 | G8: 9 | H8: 7 | I8: 8 | V8: 40 | W8: 37 | X8: 38.5
A9: 2002 | B9: 3 | C9: 9 | G9: 9 | H9: 7 | I9: 8 | V9: 40 | W9: 36 | X9: 38
A10: 2002 | B10: 4 | C10: 10 | G10: 9 | H10: 7 | I10: 8 | V10: 40 | W10: 36 | X10: 38
A11: 2002 | B11: 4 | C11: 11 | G11: 15 | H11: 7 | I11: 11 | V11: 40 | W11: 38 | X11: 39
A12: 2002 | B12: 4 | C12: 12 | G12: 15 | H12: 7 | I12: 11 | V12: 40 | W12: 38 | X12: 39
A13: 2003 | B13: 1 | C13: 1 | G13: 15 | H13: 8 | I13: 11.666667 | V13: 62.666667 | W13: 51.333333 | X13: 57.333333
A14: 2003 | B14: 1 | C14: 2 | G14: 15 | H14: 10 | I14: 13 | V14: 63 | W14: 58 | X14: 61
A15: 2003 | B15: 1 | C15: 3 | G15: 15 | H15: 10 | I15: 13 | V15: 63 | W15: 61 | X15: 62
A16: 2003 | B16: 2 | C16: 4 | G16: 15 | H16: 10 | I16: 13 | V16: 63 | W16: 61 | X16: 62 | Y16: 63 | Z16: 55 | AA16: 59
A17: 2003 | B17: 2 | C17: 5 | G17: 15 | H17: 10 | I17: 13 | V17: 63 | W17: 61 | X17: 62 | Y17: 63 | Z17: 55 | AA17: 59
A18: 2003 | B18: 2 | C18: 6 | G18: 19.5 | H18: 15 | I18: 17.5 | P18: 65 | Q18: 61 | R18: 63 | V18: 63 | W18: 61 | X18: 62 | Y18: 63 | Z18: 55 | AA18: 59
A19: 2003 | B19: 3 | C19: 7 | G19: 24 | H19: 20 | I19: 22 | P19: 60.666667 | Q19: 57 | R19: 59 | V19: 66.333333 | W19: 62.333333 | X19: 64.333333 | Y19: 70.333333 | Z19: 61.666667 | AA19: 66.333333
A20: 2003 | B20: 3 | C20: 8 | G20: 24 | H20: 20 | I20: 22 | P20: 59 | Q20: 56.5 | R20: 58 | V20: 73 | W20: 65 | X20: 69 | Y20: 74 | Z20: 65 | AA20: 70
A21: 2003 | B21: 3 | C21: 9 | G21: 24 | H21: 20 | I21: 22 | P21: 61.5 | Q21: 61 | R21: 61.5 | V21: 73 | W21: 65 | X21: 69 | Y21: 74 | Z21: 65 | AA21: 70
A22: 2003 | B22: 4 | C22: 10 | G22: 30 | H22: 25 | I22: 28 | P22: 63 | Q22: 62 | R22: 63 | V22: 73 | W22: 68 | X22: 70.5 | Y22: 73 | Z22: 65 | AA22: 69
A23: 2003 | B23: 4 | C23: 11 | G23: 30 | H23: 25 | I23: 28 | P23: 69 | Q23: 67 | R23: 68 | V23: 73 | W23: 71 | X23: 72 | Y23: 75 | Z23: 65 | AA23: 70
A24: 2003 | B24: 4 | C24: 12 | G24: 30 | H24: 25 | I24: 28 | P24: 72.5 | Q24: 71.5 | R24: 72 | V24: 73 | W24: 71 | X24: 72 | Y24: 75 | Z24: 65 | AA24: 70
A25: 2004 | B25: 1 | C25: 1 | G25: 35 | H25: 27.5 | I25: 31.5 | P25: 75 | Q25: 72 | R25: 74 | V25: 82 | W25: 81 | X25: 82 | Y25: 75 | Z25: 65 | AA25: 70
A26: 2004 | B26: 1 | C26: 2 | G26: 40 | H26: 30 | I26: 35 | P26: 67 | Q26: 65 | R26: 66 | V26: 82 | W26: 81 | X26: 82 | Y26: 81 | Z26: 66.5 | AA26: 74
A27: 2004 | B27: 1 | C27: 3 | G27: 40 | H27: 30 | I27: 35 | P27: 65.333333 | Q27: 63.333333 | R27: 64.333333 | V27: 82 | W27: 81 | X27: 82 | Y27: 78 | Z27: 68 | AA27: 73
A28: 2004 | B28: 2 | C28: 4 | G28: 40 | H28: 30 | I28: 35 | P28: 61.666667 | Q28: 60.333333 | R28: 61.333333 | V28: 82 | W28: 81 | X28: 82 | Y28: 76.666667 | Z28: 68 | AA28: 72.666667
A29: 2004 | B29: 2 | C29: 5 | G29: 40 | H29: 30 | I29: 35 | P29: 65 | Q29: 64 | R29: 65 | V29: 82 | W29: 81 | X29: 82 | Y29: 80 | Z29: 68 | AA29: 74
... A85: 2009 | B85: 1 | C85: 1 | G85: 40 | H85: 30 | I85: 35 | P85: 48.6 | Q85: 42.4 | R85: 45.8 | V85: 480 | W85: 200 | X85: 340 | Y85: 50 | Z85: 20 | AA85: 35
A86: 2009 | B86: 1 | C86: 2 | G86: 32.5 | H86: 15 | I86: 23.75 | P86: 53 | Q86: 46 | R86: 49.5 | Y86: 40 | Z86: 15 | AA86: 27.5
A87: 2009 | B87: 1 | C87: 3 | G87: 20 | H87: 0 | I87: 10 | P87: 51.25 | Q87: 45.25 | R87: 48.25 | V87: 60 | W87: 30 | X87: 45 | Y87: 28.5 | Z87: 17.5 | AA87: 23
A88: 2009 | B88: 2 | C88: 4 | G88: 20 | H88: -5 | I88: 8 | P88: 54 | Q88: 49.8 | R88: 52.2 | V88: 60 | W88: 30 | X88: 45 | Y88: 27 | Z88: 25 | AA88: 26
A89: 2009 | B89: 2 | C89: 5 | G89: 20 | H89: -5 | I89: 8 | P89: 48 | Q89: 42 | R89: 45 | V89: 60 | W89: 30 | X89: 45 | Y89: 27 | Z89: 25 | AA89: 26
A90: 2009 | B90: 2 | C90: 6 | G90: 17.5 | H90: -8.75 | I90: 4.75 | P90: 43.75 | Q90: 38.75 | R90: 41.75 | V90: 60 | W90: 30 | X90: 45 | Y90: 27 | Z90: 20 | AA90: 24
A91: 2009 | B91: 3 | C91: 7 | G91: 10 | H91: -20 | I91: -5 | P91: 35 | Q91: 30 | R91: 33 | V91: 54.4 | W91: 44.4 | X91: 49.8 | Y91: 27 | Z91: 20 | AA91: 24
A92: 2009 | B92: 3 | C92: 8 | G92: 10 | H92: -20 | I92: -5 | P92: 37 | Q92: 31.75 | R92: 34.75 | V92: 53 | W92: 48 | X92: 51 | Y92: 27 | Z92: 20 | AA92: 24
A93: 2009 | B93: 3 | C93: 9 | G93: 10 | H93: -10 | I93: 0 | P93: 43 | Q93: 37 | R93: 40 | V93: 53 | W93: 48 | X93: 51 | Y93: 27 | Z93: 20 | AA93: 24
A94: 2009 | B94: 4 | C94: 10 | G94: 6 | H94: -16 | I94: -5.2 | P94: 45.4 | Q94: 43 | R94: 44.6 | V94: 53 | W94: 48 | X94: 51 | Y94: 27 | Z94: 20 | AA94: 24
A95: 2009 | B95: 4 | C95: 11 | G95: 0 | H95: -25 | I95: -13 | P95: 55.75 | Q95: 54.75 | R95: 55.75 | V95: 53 | W95: 48 | X95: 51 | Y95: 27 | Z95: 20 | AA95: 24
A96: 2009 | B96: 4 | C96: 12 | G96: 7 | H96: -8 | I96: -0.6 | P96: 68.2 | Q96: 67.2 | R96: 68.2 | V96: 53 | W96: 48 | X96: 51 | Y96: 27 | Z96: 20 | AA96: 24
A97: 2010 | B97: 1 | C97: 1 | G97: 25 | H97: 15 | I97: 20 | P97: 124.75 | Q97: 120 | R97: 122.75 | V97: 90 | W97: 80 | X97: 85 | Y97: 58 | Z97: 26.75 | AA97: 42.75
A98: 2010 | B98: 1 | C98: 2 | G98: 52.5 | H98: 42.5 | I98: 47.5 | P98: 169.5 | Q98: 164.25 | R98: 167 | V98: 100 | W98: 72.5 | X98: 86.25 | Y98: 68 | Z98: 29 | AA98: 49
... A106: 2010 | B106: 4 | C106: 10 | G106: 60 | H106: 50 | I106: 55 | P106: 168 | Q106: 162.25 | R106: 165.25 | V106: 93 | W106: 84 | X106: 89 | Y106: 70 | Z106: 40 | AA106: 55
A107: 2010 | B107: 4 | C107: 11 | G107: 75 | H107: 65 | I107: 70 | P107: 174.75 | Q107: 169.5 | R107: 172.5 | V107: 93 | W107: 84 | X107: 89 | Y107: 70 | Z107: 40 | AA107: 55 | AB107: 130 | AC107: 120 | AD107: 125
A108: 2010 | B108: 4 | C108: 12 | G108: 80 | H108: 70 | I108: 75 | P108: 164.8 | Q108: 153.2 | R108: 159 | V108: 93 | W108: 84 | X108: 89 | Y108: 70 | Z108: 40 | AA108: 55 | AB108: 130 | AC108: 120 | AD108: 125
A109: 2011 | B109: 1 | C109: 1 | G109: 82.5 | H109: 70 | I109: 76.25 | P109: 165 | Q109: 147.5 | R109: 156.25 | V109: 183 | W109: 175 | X109: 179 | Y109: 90 | Z109: 51.25 | AA109: 70.75 | AB109: 152.5 | AC109: 142.5 | AD109: 147.5
A110: 2011 | B110: 1 | C110: 2 | G110: 90 | H110: 70 | I110: 80 | P110: 191.25 | Q110: 177.5 | R110: 184.75 | V110: 183 | W110: 175 | X110: 179 | Y110: 150 | Z110: 55 | AA110: 103 | AB110: 175 | AC110: 165 | AD110: 170
A111: 2011 | B111: 1 | C111: 3 | G111: 92 | H111: 74 | I111: 83 | P111: 209 | Q111: 184 | R111: 196.8 | V111: 183 | W111: 175 | X111: 179 | AB111: 175 | AC111: 165 | AD111: 170
A112: 2011 | B112: 2 | C112: 4 | G112: 100 | H112: 90 | I112: 95 | P112: 215.25 | Q112: 185 | R112: 200.25 | V112: 214.5 | W112: 208.75 | X112: 212 | AB112: 175 | AC112: 165 | AD112: 170
A113: 2011 | B113: 2 | C113: 5 | G113: 100 | H113: 90 | I113: 95 | P113: 223.75 | Q113: 200 | R113: 212 | V113: 225 | W113: 220 | X113: 223 | AB113: 175 | AC113: 165 | AD113: 170
A114: 2011 | B114: 2 | C114: 6 | G114: 108 | H114: 90 | I114: 99 | P114: 225 | Q114: 215 | R114: 220 | V114: 225 | W114: 220 | X114: 223 | AB114: 175 | AC114: 165 | AD114: 170
A115: 2011 | B115: 3 | C115: 7 | G115: 110 | H115: 92.5 | I115: 101.25 | P115: 206.25 | Q115: 192.5 | R115: 199.5 | V115: 225 | W115: 220 | X115: 223 | AB115: 175 | AC115: 165 | AD115: 170
A116: 2011 | B116: 3 | C116: 8 | G116: 110 | H116: 100 | I116: 105 | P116: 212.5 | Q116: 192.5 | R116: 202.5 | V116: 236.25 | W116: 231.25 | X116: 234.25 | AB116: 175 | AC116: 165 | AD116: 170
A117: 2011 | B117: 3 | C117: 9 | G117: 110 | H117: 100 | I117: 105 | P117: 220 | Q117: 210 | R117: 215 | V117: 240 | W117: 235 | X117: 238 | AB117: 175 | AC117: 165 | AD117: 170
A118: 2011 | B118: 4 | C118: 10 | G118: 110 | H118: 100 | I118: 105 | P118: 221.25 | Q118: 210 | R118: 215.75 | V118: 243.75 | W118: 236.25 | X118: 240.5 | AB118: 240 | AC118: 235 | AD118: 238
A119: 2011 | B119: 4 | C119: 11 | G119: 110 | H119: 100 | I119: 105 | P119: 208.75 | Q119: 200 | R119: 204.75 | V119: 255 | W119: 240 | X119: 248 | AB119: 240 | AC119: 235 | AD119: 238
A120: 2011 | B120: 4 | C120: 12 | G120: 104 | H120: 94 | I120: 99 | P120: 197 | Q120: 184 | R120: 190.8 | V120: 255 | W120: 240 | X120: 248 | AB120: 240 | AC120: 235 | AD120: 238
A121: 2012 | B121: 1 | C121: 1 | G121: 90 | H121: 80 | I121: 85 | P121: 176.25 | Q121: 171.25 | R121: 174.25 | V121: 255 | W121: 240 | X121: 248
A122: 2012 | B122: 1 | C122: 2 | G122: 60 | H122: 50 | I122: 55 | P122: 171.25 | Q122: 165 | R122: 168.5 | V122: 235 | W122: 223.75 | X122: 229.75
A123: 2012 | B123: 1 | C123: 3 | G123: 40 | H123: 30 | I123: 35 | P123: 195 | Q123: 177 | R123: 186 | V123: 175 | W123: 175 | X123: 175 | AB123: 140 | AC123: 140 | AD123: 140
A124: 2012 | B124: 2 | C124: 4 | G124: 40 | H124: 30 | I124: 35 | P124: 195 | Q124: 187.5 | R124: 191.5 | V124: 187.5 | W124: 175 | X124: 181.25 | AB124: 170 | AC124: 170 | AD124: 170
A125: 2012 | B125: 2 | C125: 5 | G125: 42 | H125: 32 | I125: 37 | P125: 205 | Q125: 195 | R125: 200 | V125: 225 | W125: 198 | X125: 212 | AB125: 218 | AC125: 210 | AD125: 214
A126: 2012 | B126: 2 | C126: 6 | G126: 55 | H126: 45 | I126: 50 | P126: 192.5 | Q126: 182.5 | R126: 187.5 | V126: 225 | W126: 198 | X126: 212 | AB126: 227.5 | AC126: 218.75 | AD126: 223.25
A127: 2012 | B127: 3 | C127: 7 | D127: 42.5 | E127: 35 | F127: 39 | G127: 55 | H127: 45 | I127: 50 | P127: 181.25 | Q127: 171.25 | R127: 176.25 | V127: 221.25 | W127: 196 | X127: 209 | AB127: 211.25 | AC127: 206.25 | AD127: 209.25
A128: 2012 | B128: 3 | C128: 8 | D128: 48 | E128: 38 | F128: 43 | G128: 54 | H128: 48 | I128: 51.4 | P128: 183 | Q128: 172 | R128: 177.6 | V128: 210 | W128: 190 | X128: 200 | AB128: 185 | AC128: 180 | AD128: 183
A129: 2012 | B129: 3 | C129: 9 | D129: 50 | E129: 40 | F129: 45 | G129: 55 | H129: 50 | I129: 53 | P129: 192.5 | Q129: 180 | R129: 186.5 | V129: 210 | W129: 190 | X129: 200 | AB129: 185 | AC129: 180 | AD129: 183
A130: 2012 | B130: 4 | C130: 10 | D130: 42.5 | E130: 33.75 | F130: 38.25 | G130: 58.75 | H130: 53.75 | I130: 56.75 | P130: 177.5 | Q130: 163.75 | R130: 170.75 | V130: 210 | W130: 190 | X130: 200 | AB130: 185 | AC130: 180 | AD130: 183
A131: 2012 | B131: 4 | C131: 11 | D131: 20 | E131: 15 | F131: 18 | G131: 56 | H131: 50 | I131: 53.4 | P131: 156.4 | Q131: 151 | R131: 154.2 | V131: 194 | W131: 182 | X131: 188 | AB131: 181 | AC131: 176 | AD131: 179
A132: 2012 | B132: 4 | C132: 12 | D132: 15 | E132: 5 | F132: 10 | G132: 45 | H132: 40 | I132: 43 | P132: 150 | Q132: 142.75 | R132: 146.5 | V132: 190 | W132: 180 | X132: 185 | AB132: 165 | AC132: 155 | AD132: 160
A133: 2013 | B133: 1 | C133: 1 | D133: 11 | E133: 3 | F133: 7.2 | G133: 30 | H133: 22 | I133: 26.2 | P133: 147 | Q133: 142.6 | R133: 145.2 | V133: 165 | W133: 156 | X133: 160.8 | AB133: 165 | AC133: 155 | AD133: 160
A134: 2013 | B134: 1 | C134: 2 | D134: 5 | E134: 0 | F134: 3 | G134: 18.75 | H134: 8.75 | I134: 13.75 | P134: 151.5 | Q134: 146 | R134: 149 | V134: 155 | W134: 135 | X134: 145 | AB134: 165 | AC134: 155 | AD134: 160
A135: 2013 | B135: 1 | C135: 3 | D135: 5 | E135: 0 | F135: 3 | G135: 15 | H135: 5 | I135: 10 | P135: 152.75 | Q135: 146.75 | R135: 150 | V135: 155 | W135: 135 | X135: 145 | AB135: 165 | AC135: 155 | AD135: 160
A136: 2013 | B136: 2 | C136: 4 | D136: 5 | E136: 0 | F136: 3 | G136: 15 | H136: 5 | I136: 10 | P136: 152 | Q136: 149 | R136: 151 | V136: 155 | W136: 135 | X136: 145 | AB136: 165 | AC136: 155 | AD136: 160
A137: 2013 | B137: 2 | C137: 5 | D137: 13 | E137: 4 | F137: 8.6 | G137: 15 | H137: 5 | I137: 10 | P137: 143.4 | Q137: 137.2 | R137: 140.6 | V137: 155 | W137: 135 | X137: 145 | AB137: 159 | AC137: 149 | AD137: 154
A138: 2013 | B138: 2 | C138: 6 | D138: 5 | E138: 0 | F138: 3 | G138: 16.25 | H138: 10 | I138: 13.5 | P138: 119 | Q138: 105 | R138: 112.25 | V138: 155 | W138: 135 | X138: 145 | AB138: 150 | AC138: 140 | AD138: 145
... A147: 2014 | B147: 1 | C147: 3 | D147: 10 | E147: 5 | F147: 8 | G147: 6.25 | H147: 1.25 | I147: 4.25 | P147: 186.25 | Q147: 180 | R147: 183.5 | V147: 109 | W147: 102.5 | X147: 106 | AB147: 120 | AC147: 110 | AD147: 115
A148: 2014 | B148: 2 | C148: 4 | D148: 10 | E148: 5 | F148: 8 | G148: 10 | H148: 5 | I148: 8 | P148: 143.25 | Q148: 135 | R148: 139.5 | V148: 135 | W148: 130 | X148: 133
A149: 2014 | B149: 2 | C149: 5 | D149: 10 | E149: 5 | F149: 8 | G149: 10 | H149: 5 | I149: 8 | P149: 139.8 | Q149: 128 | R149: 134.4 | V149: 132 | W149: 126 | X149: 129.4
A150: 2014 | B150: 2 | C150: 6 | D150: 10 | E150: 5 | F150: 8 | G150: 13.75 | H150: 8.75 | I150: 11.75 | P150: 159 | Q150: 148.75 | R150: 154 | V150: 135 | W150: 130 | X150: 133
A151: 2014 | B151: 3 | C151: 7 | D151: 10 | E151: 5 | F151: 8 | G151: 15 | H151: 10 | I151: 13 | P151: 168.4 | Q151: 160 | R151: 164.6 | V151: 135 | W151: 130 | X151: 133
A152: 2014 | B152: 3 | C152: 8 | D152: 10 | E152: 5 | F152: 8 | G152: 15 | H152: 10 | I152: 13 | P152: 168.75 | Q152: 158.75 | R152: 164 | V152: 135 | W152: 130 | X152: 133
A153: 2014 | B153: 3 | C153: 9 | D153: 12.5 | E153: 10 | F153: 11.5 | G153: 23.75 | H153: 18.75 | I153: 21.75 | P153: 157.5 | Q153: 150 | R153: 154 | V153: 135 | W153: 130 | X153: 133
A154: 2014 | B154: 4 | C154: 10 | D154: 15 | E154: 10 | F154: 13 | G154: 29 | H154: 24 | I154: 27 | P154: 146.8 | Q154: 137.4 | R154: 142.6 | V154: 135 | W154: 130 | X154: 133
A155: 2014 | B155: 4 | C155: 11 | D155: 20 | E155: 10 | F155: 15 | G155: 35 | H155: 30 | I155: 33 | P155: 140 | Q155: 119 | R155: 129.5 | V155: 135 | W155: 130 | X155: 133
A156: 2014 | B156: 4 | C156: 12 | D156: 17.5 | E156: 7.5 | F156: 12.5 | G156: 35 | H156: 30 | I156: 33 | P156: 159.75 | Q156: 141.25 | R156: 151 | V156: 135 | W156: 130 | X156: 133
A157: 2015 | B157: 1 | C157: 1 | D157: 15 | E157: 6 | F157: 10.6 | G157: 35 | H157: 29.4 | I157: 32.6 | P157: 182.2 | Q157: 156.4 | R157: 169.8 | V157: 135 | W157: 130 | X157: 133
A158: 2015 | B158: 1 | C158: 2 | D158: 21 | E158: 11.25 | F158: 16.25 | G158: 35 | H158: 27 | I158: 31 | P158: 183.75 | Q158: 168.5 | R158: 176.5 | S158: 165 | T158: 160 | U158: 163 | V158: 135 | W158: 130 | X158: 133
A159: 2015 | B159: 1 | C159: 3 | D159: 22 | E159: 15 | F159: 19 | G159: 35 | H159: 27 | I159: 31 | P159: 175 | Q159: 160.75 | R159: 168.25 | S159: 165 | T159: 160 | U159: 163 | V159: 135 | W159: 130 | X159: 133
A160: 2015 | B160: 2 | C160: 4 | D160: 22 | E160: 17 | F160: 20 | G160: 35 | H160: 27 | I160: 31 | P160: 158 | Q160: 140 | R160: 149.4 | S160: 165 | T160: 160 | U160: 163 | V160: 135 | W160: 130 | X160: 133
A161: 2015 | B161: 2 | C161: 5 | D161: 22.75 | E161: 17 | F161: 20.25 | G161: 35 | H161: 27 | I161: 31 | P161: 141.25 | Q161: 139.25 | R161: 140.75 | S161: 165 | T161: 160 | U161: 163 | V161: 135 | W161: 130 | X161: 133
A162: 2015 | B162: 2 | C162: 6 | D162: 30 | E162: 20 | F162: 25 | G162: 35 | H162: 27 | I162: 31 | P162: 146 | Q162: 140 | R162: 143 | S162: 152 | T162: 145 | U162: 149 | V162: 135 | W162: 130 | X162: 133
A163: 2015 | B163: 3 | C163: 7 | D163: 25 | E163: 15 | F163: 20 | G163: 35 | H163: 25.4 | I163: 30.2 | P163: 153.6 | Q163: 147 | R163: 150.4 | S163: 152 | T163: 145 | U163: 149 | V163: 135 | W163: 130 | X163: 133
A164: 2015 | B164: 3 | C164: 8 | D164: 20 | E164: 10 | F164: 15 | G164: 32.5 | H164: 21.25 | I164: 27 | P164: 156 | Q164: 150 | R164: 153 | S164: 150 | T164: 145 | U164: 148 | V164: 135 | W164: 130 | X164: 133
A165: 2015 | B165: 3 | C165: 9 | D165: 21.5 | E165: 13.75 | F165: 18 | G165: 23.75 | H165: 12.5 | I165: 18.25 | P165: 140 | Q165: 126.5 | R165: 133.5 | S165: 150 | T165: 145 | U165: 148 | V165: 135 | W165: 130 | X165: 133
A166: 2015 | B166: 4 | C166: 10 | D166: 19.2 | E166: 11 | F166: 15.4 | G166: 14 | H166: 1 | I166: 7.8 | P166: 120 | Q166: 107.2 | R166: 113.8 | S166: 150 | T166: 145 | U166: 148 | V166: 135 | W166: 130 | X166: 133
A167: 2015 | B167: 4 | C167: 11 | D167: 13.75 | E167: 3.75 | F167: 8.75 | G167: 10 | H167: 0 | I167: 5 | P167: 130 | Q167: 122.5 | R167: 126.5 | S167: 132.5 | T167: 122.5 | U167: 128 | V167: 125 | W167: 115 | X167: 120.5
A168: 2015 | B168: 4 | C168: 12 | D168: 10 | E168: 0 | F168: 5 | G168: 10 | H168: 0 | I168: 5 | P168: 135 | Q168: 128 | R168: 132 | S168: 115 | T168: 100 | U168: 108 | V168: 115 | W168: 100 | X168: 108
A169: 2016 | B169: 1 | C169: 1 | D169: 10 | E169: 0 | F169: 5 | G169: 10 | H169: 0 | I169: 5 | P169: 121.75 | Q169: 115.25 | R169: 118.75 | S169: 115 | T169: 100 | U169: 108
A170: 2016 | B170: 1 | C170: 2 | D170: 7.5 | E170: -2.5 | F170: 2.5 | G170: 10 | H170: 0 | I170: 5 | P170: 103.75 | Q170: 88 | R170: 96 | S170: 116.5 | T170: 94 | U170: 105.75
...

Sheet Sulphuric Acid freights
A1: Back to Contents | E1: NW Europe - US Gulf 17-20,000 mt | H1: NW Europe - Brazil 18-20,000 mt | K1: NW Europe - North Africa 20-27,000 mt | N1: Japan/South Korea - Chile 20-27,000 mt | Q1: Japan/South Korea - China 10-15,000 mt | T1: Japan/South Korea - India 15-20,000 mt | W1: NW Europe - Chile 17-20,000mt | Z1: China - India 15-20,000mt | AC1: China - SEA 8-20,000mt | AF1: China - Chile 27-33,000mt
B2: Year | C2: quarter | D2: month | E2: low | F2: high | G2: ave | H2: low | I2: high | J2: ave | K2: low | L2: high | M2: ave | N2: low | O2: high | P2: ave | Q2: low | R2: high | S2: ave | T2: low | U2: high | V2: ave | W2: low | X2: high | Y2: ave | Z2: low | AA2: high | AB2: ave | AC2: low | AD2: high | AE2: ave | AF2: low | AG2: high | AH2: ave
A3: 42439 | B3: =YEAR(A3) -> 2016 | D3: =MONTH(A3) -> 3 | E3: 30 | F3: 32 | G3: 31 | H3: 37 | I3: 39 | J3: 38 | K3: 22 | L3: 27 | M3: 24 | N3: 53 | O3: 55 | P3: 54 | Q3: 18 | R3: 20 | S3: 19 | T3: 28 | U3: 30 | V3: 29
A4: 42446 | B4: =YEAR(A4) -> 2016 | D4: =MONTH(A4) -> 3 | E4: 30 | F4: 32 | G4: 31 | H4: 37 | I4: 39 | J4: 38 | K4: 22 | L4: 27 | M4: 24 | N4: 53 | O4: 55 | P4: 54 | Q4: 18 | R4: 20 | S4: 19 | T4: 28 | U4: 30 | V4: 29
A5: 42453 | B5: =YEAR(A5) -> 2016 | D5: =MONTH(A5) -> 3 | E5: 30 | F5: 32 | G5: 31 | H5: 37 | I5: 39 | J5: 38 | K5: 22 | L5: 27 | M5: 24 | N5: 53 | O5: 55 | P5: 54 | Q5: 18 | R5: 20 | S5: 19 | T5: 28 | U5: 30 | V5: 29
A6: 42460 | B6: =YEAR(A6) -> 2016 | D6: =MONTH(A6) -> 3 | E6: 30 | F6: 32 | G6: 31 | H6: 37 | I6: 39 | J6: 38 | K6: 22 | L6: 27 | M6: 24 | N6: 53 | O6: 55 | P6: 54 | Q6: 18 | R6: 20 | S6: 19 | T6: 28 | U6: 30 | V6: 29
A7: 42467 | B7: =YEAR(A7) -> 2016 | D7: =MONTH(A7) -> 4 | E7: 30 | F7: 32 | G7: 31 | H7: 37 | I7: 39 | J7: 38 | K7: 22 | L7: 27 | M7: 24 | N7: 53 | O7: 55 | P7: 54 | Q7: 18 | R7: 20 | S7: 19 | T7: 28 | U7: 30 | V7: 29
A8: 42474 | B8: =YEAR(A8) -> 2016 | D8: =MONTH(A8) -> 4 | E8: 30 | F8: 32 | G8: 31 | H8: 37 | I8: 39 | J8: 38 | K8: 22 | L8: 27 | M8: 24 | N8: 53 | O8: 55 | P8: 54 | Q8: 18 | R8: 20 | S8: 19 | T8: 28 | U8: 30 | V8: 29
A9: 42481 | B9: =YEAR(A9) -> 2016 | D9: =MONTH(A9) -> 4 | E9: 30 | F9: 32 | G9: 31 | H9: 37 | I9: 39 | J9: 38 | K9: 22 | L9: 27 | M9: 24 | N9: 53 | O9: 55 | P9: 54 | Q9: 18 | R9: 20 | S9: 19 | T9: 28 | U9: 30 | V9: 29
A10: 42488 | B10: =YEAR(A10) -> 2016 | D10: =MONTH(A10) -> 4 | E10: 30 | F10: 32 | G10: 31 | H10: 37 | I10: 39 | J10: 38 | K10: 22 | L10: 27 | M10: 24 | N10: 53 | O10: 55 | P10: 54 | Q10: 18 | R10: 20 | S10: 19 | T10: 28 | U10: 30 | V10: 29
A11: 42495 | B11: =YEAR(A11) -> 2016 | D11: =MONTH(A11) -> 5 | E11: 30 | F11: 32 | G11: 31 | H11: 37 | I11: 39 | J11: 38 | K11: 22 | L11: 27 | M11: 24 | N11: 53 | O11: 55 | P11: 54 | Q11: 18 | R11: 20 | S11: 19 | T11: 28 | U11: 30 | V11: 29
A12: 42502 | B12: =YEAR(A12) -> 2016 | D12: =MONTH(A12) -> 5 | E12: 30 | F12: 32 | G12: 31 | H12: 37 | I12: 39 | J12: 38 | K12: 22 | L12: 27 | M12: 24 | N12: 53 | O12: 55 | P12: 54 | Q12: 18 | R12: 20 | S12: 19 | T12: 28 | U12: 30 | V12: 29
A13: 42509 | B13: =YEAR(A13) -> 2016 | D13: =MONTH(A13) -> 5 | E13: 30 | F13: 32 | G13: 31 | H13: 37 | I13: 39 | J13: 38 | K13: 22 | L13: 27 | M13: 24 | N13: 53 | O13: 55 | P13: 54 | Q13: 18 | R13: 20 | S13: 19 | T13: 28 | U13: 30 | V13: 29
A14: 42516 | B14: =YEAR(A14) -> 2016 | D14: =MONTH(A14) -> 5 | E14: 30 | F14: 32 | G14: 31 | H14: 37 | I14: 39 | J14: 38 | K14: 22 | L14: 27 | M14: 24 | N14: 53 | O14: 55 | P14: 54 | Q14: 18 | R14: 20 | S14: 19 | T14: 28 | U14: 30 | V14: 29
... A253: 44189 | B253: =YEAR(A253) -> 2020 | D253: =MONTH(A253) -> 12 | E253: 25 | F253: 26 | G253: 26 | H253: 34 | I253: 35 | J253: 34 | K253: 15 | L253: 22 | M253: 18 | N253: 54 | O253: 60 | P253: 57 | Q253: 10 | R253: 16 | S253: 13 | T253: 23 | U253: 25 | V253: 24
A254: 44196 | B254: =YEAR(A254) -> 2020 | D254: =MONTH(A254) -> 12
A255: 44203 | B255: =YEAR(A255) -> 2021 | D255: =MONTH(A255) -> 1 | E255: 25 | F255: 26 | G255: 26 | H255: 34 | I255: 35 | J255: 34 | K255: 15 | L255: 22 | M255: 18 | N255: 54 | O255: 60 | P255: 57 | Q255: 10 | R255: 16 | S255: 13 | T255: 23 | U255: 25 | V255: 24
A256: 44210 | B256: =YEAR(A256) -> 2021 | D256: =MONTH(A256) -> 1 | E256: 25 | F256: 26 | G256: 26 | H256: 31 | I256: 32 | J256: 32 | K256: 14 | L256: 21 | M256: 18 | N256: 52 | O256: 58 | P256: 55 | Q256: 10 | R256: 16 | S256: 13 | T256: 23 | U256: 25 | V256: 24
A257: 44217 | B257: =YEAR(A257) -> 2021 | D257: =MONTH(A257) -> 1 | E257: 25 | F257: 26 | G257: 26 | H257: 31 | I257: 32 | J257: 32 | K257: 14 | L257: 21 | M257: 18 | N257: 52 | O257: 58 | P257: 55 | Q257: 9 | R257: 15 | S257: 12 | T257: 21 | U257: 23 | V257: 22
A258: 44224 | B258: =YEAR(A258) -> 2021 | D258: =MONTH(A258) -> 1 | E258: 25 | F258: 26 | G258: 26 | H258: 31 | I258: 32 | J258: 32 | K258: 14 | L258: 21 | M258: 18 | N258: 52 | O258: 58 | P258: 55 | Q258: 11 | R258: 17 | S258: 14 | T258: 22 | U258: 24 | V258: 23
A259: 44231 | B259: =YEAR(A259) -> 2021 | D259: =MONTH(A259) -> 2 | E259: 25 | F259: 26 | G259: 26 | H259: 31 | I259: 32 | J259: 32 | K259: 14 | L259: 21 | M259: 18 | N259: 52 | O259: 58 | P259: 55 | Q259: 11 | R259: 17 | S259: 14 | T259: 22 | U259: 24 | V259: 23
A260: 44238 | B260: =YEAR(A260) -> 2021 | D260: =MONTH(A260) -> 2 | E260: 25 | F260: 26 | G260: 26 | H260: 31 | I260: 32 | J260: 32 | K260: 14 | L260: 21 | M260: 18 | N260: 53 | O260: 59 | P260: 56 | Q260: 11 | R260: 17 | S260: 14 | T260: 23 | U260: 24 | V260: 24
A261: 44245 | B261: =YEAR(A261) -> 2021 | D261: =MONTH(A261) -> 2 | E261: 25 | F261: 26 | G261: 26 | H261: 31 | I261: 32 | J261: 32 | K261: 14 | L261: 21 | M261: 18 | N261: 53 | O261: 59 | P261: 56 | Q261: 11 | R261: 17 | S261: 14 | T261: 23 | U261: 24 | V261: 24
A262: 44252 | B262: =YEAR(A262) -> 2021 | D262: =MONTH(A262) -> 2 | E262: 25 | F262: 26 | G262: 26 | H262: 31 | I262: 32 | J262: 32 | K262: 14 | L262: 21 | M262: 18 | N262: 53 | O262: 59 | P262: 56 | Q262: 11 | R262: 17 | S262: 14 | T262: 24 | U262: 25 | V262: 24
A263: 44259 | B263: =YEAR(A263) -> 2021 | D263: =MONTH(A263) -> 3 | E263: 25 | F263: 26 | G263: 26 | H263: 31 | I263: 32 | J263: 32 | K263: 14 | L263: 21 | M263: 18 | N263: 54 | O263: 60 | P263: 57 | Q263: 12 | R263: 18 | S263: 15 | T263: 25 | U263: 26 | V263: 26
A264: 44266 | B264: =YEAR(A264) -> 2021 | D264: =MONTH(A264) -> 3 | E264: 25 | F264: 26 | G264: 26 | H264: 31 | I264: 32 | J264: 32 | K264: 14 | L264: 21 | M264: 18 | N264: 56 | O264: 62 | P264: 59 | Q264: 13 | R264: 19 | S264: 16 | T264: 26 | U264: 27 | V264: 26
A265: 44273 | B265: =YEAR(A265) -> 2021 | D265: =MONTH(A265) -> 3 | E265: 25 | F265: 26 | G265: 26 | H265: 31 | I265: 32 | J265: 32 | K265: 14 | L265: 21 | M265: 18 | N265: 54 | O265: 60 | P265: 57 | Q265: 13 | R265: 19 | S265: 16 | T265: 26 | U265: 27 | V265: 26
A266: 44280 | B266: =YEAR(A266) -> 2021 | D266: =MONTH(A266) -> 3 | E266: 25 | F266: 26 | G266: 26 | H266: 31 | I266: 32 | J266: 32 | K266: 14 | L266: 21 | M266: 18 | N266: 54 | O266: 60 | P266: 57 | Q266: 14 | R266: 20 | S266: 17 | T266: 27 | U266: 28 | V266: 28
... A305: 44553 | B305: =YEAR(A305) -> 2021 | D305: =MONTH(A305) -> 12 | E305: 27 | F305: 28 | G305: 28 | H305: 36 | I305: 37 | J305: 36 | K305: 16 | L305: 23 | M305: 20 | N305: 92 | O305: 99 | P305: 96 | Q305: 25 | R305: 32 | S305: 28 | T305: 40 | U305: 43 | V305: 42
A306: 44560 | B306: =YEAR(A306) -> 2021 | D306: =MONTH(A306) -> 12
A307: 44567 | B307: =YEAR(A307) -> 2022 | D307: =MONTH(A307) -> 1 | E307: 27 | F307: 28 | G307: 28 | H307: 38 | I307: 39 | J307: 38 | K307: 17 | L307: 24 | M307: 20 | N307: 93 | O307: 100 | P307: 96 | Q307: 25 | R307: 32 | S307: 28 | T307: 40 | U307: 43 | V307: 42
A308: 44574 | B308: =YEAR(A308) -> 2022 | D308: =MONTH(A308) -> 1 | E308: 27 | F308: 28 | G308: 28 | H308: 38 | I308: 39 | J308: 38 | K308: 17 | L308: 24 | M308: 20 | N308: 92 | O308: 99 | P308: 96 | Q308: 24 | R308: 31 | S308: 28 | T308: 39 | U308: 42 | V308: 40
A309: 44581 | B309: =YEAR(A309) -> 2022 | D309: =MONTH(A309) -> 1 | E309: 26 | F309: 27 | G309: 26 | H309: 38 | I309: 39 | J309: 38 | K309: 17 | L309: 24 | M309: 20 | N309: 91 | O309: 98 | P309: 94 | Q309: 23 | R309: 30 | S309: 26 | T309: 38 | U309: 41 | V309: 40
A310: 44588 | B310: =YEAR(A310) -> 2022 | D310: =MONTH(A310) -> 1 | E310: 26 | F310: 27 | G310: 26 | H310: 38 | I310: 39 | J310: 38 | K310: 17 | L310: 24 | M310: 20 | N310: 91 | O310: 98 | P310: 94 | Q310: 23 | R310: 30 | S310: 26 | T310: 38 | U310: 41 | V310: 40
A311: 44595 | B311: =YEAR(A311) -> 2022 | D311: =MONTH(A311) -> 2 | E311: 26 | F311: 27 | G311: 26 | H311: 38 | I311: 39 | J311: 38 | K311: 17 | L311: 24 | M311: 20 | N311: 91 | O311: 98 | P311: 94 | Q311: 23 | R311: 30 | S311: 26 | T311: 38 | U311: 41 | V311: 40
A312: 44602 | B312: =YEAR(A312) -> 2022 | D312: =MONTH(A312) -> 2 | E312: 26 | F312: 27 | G312: 26 | H312: 38 | I312: 39 | J312: 38 | K312: 17 | L312: 24 | M312: 20 | N312: 91 | O312: 98 | P312: 94 | Q312: 23 | R312: 30 | S312: 26 | T312: 38 | U312: 41 | V312: 40
A313: 44609 | B313: =YEAR(A313) -> 2022 | D313: =MONTH(A313) -> 2 | E313: 27 | F313: 28 | G313: 28 | H313: 38 | I313: 40 | J313: 39 | K313: 18 | L313: 25 | M313: 22 | N313: 91 | O313: 98 | P313: 94 | Q313: 23 | R313: 30 | S313: 26 | T313: 38 | U313: 41 | V313: 40
A314: 44616 | B314: =YEAR(A314) -> 2022 | D314: =MONTH(A314) -> 2 | E314: 27 | F314: 28 | G314: 28 | H314: 38 | I314: 40 | J314: 39 | K314: 18 | L314: 25 | M314: 22 | N314: 91 | O314: 98 | P314: 94 | Q314: 23 | R314: 30 | S314: 26 | T314: 38 | U314: 41 | V314: 40
A315: 44623 | B315: =YEAR(A315) -> 2022 | D315: =MONTH(A315) -> 3 | E315: 27 | F315: 28 | G315: 28 | H315: 38 | I315: 40 | J315: 39 | K315: 18 | L315: 25 | M315: 22 | N315: 91 | O315: 98 | P315: 94 | Q315: 23 | R315: 30 | S315: 26 | T315: 38 | U315: 41 | V315: 40
A316: 44630 | B316: =YEAR(A316) -> 2022 | D316: =MONTH(A316) -> 3 | E316: 27 | F316: 28 | G316: 28 | H316: 38 | I316: 40 | J316: 39 | K316: 18 | L316: 25 | M316: 22 | N316: 91 | O316: 98 | P316: 94 | Q316: 23 | R316: 30 | S316: 26 | T316: 38 | U316: 41 | V316: 40
A317: 44637 | B317: =YEAR(A317) -> 2022 | D317: =MONTH(A317) -> 3 | E317: 30 | F317: 31 | G317: 30 | H317: 42 | I317: 43 | J317: 42 | K317: 21 | L317: 28 | M317: 24 | N317: 100 | O317: 107 | P317: 104 | Q317: 30 | R317: 35 | S317: 32 | T317: 44 | U317: 47 | V317: 46
A318: 44644 | B318: =YEAR(A318) -> 2022 | D318: =MONTH(A318) -> 3 | E318: 31 | F318: 32 | G318: 32 | H318: 43 | I318: 44 | J318: 44 | K318: 22 | L318: 29 | M318: 26 | N318: 101 | O318: 108 | P318: 104 | Q318: 35 | R318: 40 | S318: 38 | T318: 49 | U318: 53 | V318: 51
... A357: 44917 | B357: =YEAR(A357) -> 2022 | D357: =MONTH(A357) -> 12 | E357: 51 | F357: 52 | G357: 52 | H357: 66 | I357: 72 | J357: 69 | K357: 36 | L357: 42 | M357: 39 | N357: 135 | O357: 138 | P357: 136 | Q357: 66 | R357: 70 | S357: 68 | T357: 76 | U357: 78 | V357: 77
A358: 44924 | B358: =YEAR(A358) -> 2022 | D358: =MONTH(A358) -> 12
A359: 44931 | B359: =YEAR(A359) -> 2023 | D359: =MONTH(A359) -> 1 | E359: 51 | F359: 52 | G359: 52 | H359: 66 | I359: 72 | J359: 69 | K359: 36 | L359: 42 | M359: 39 | N359: 135 | O359: 138 | P359: 136 | Q359: 64 | R359: 68 | S359: 66 | T359: 74 | U359: 76 | V359: 75
A360: 44938 | B360: =YEAR(A360) -> 2023 | D360: =MONTH(A360) -> 1 | E360: 51 | F360: 52 | G360: 52 | H360: 66 | I360: 72 | J360: 69 | K360: 36 | L360: 42 | M360: 39 | N360: 134 | O360: 137 | P360: 136 | Q360: 63 | R360: 67 | S360: 65 | T360: 73 | U360: 75 | V360: 74
A361: 44945 | B361: =YEAR(A361) -> 2023 | D361: =MONTH(A361) -> 1 | E361: 51 | F361: 52 | G361: 52 | H361: 67 | I361: 73 | J361: 70 | K361: 36 | L361: 42 | M361: 39 | N361: 132 | O361: 135 | P361: 134 | Q361: 62 | R361: 65 | S361: 64 | T361: 72 | U361: 73 | V361: 72
A362: 44952 | B362: =YEAR(A362) -> 2023 | D362: =MONTH(A362) -> 1 | E362: 50 | F362: 51 | G362: 50 | H362: 67 | I362: 73 | J362: 70 | K362: 36 | L362: 42 | M362: 39 | N362: 131 | O362: 134 | P362: 132 | Q362: 61 | R362: 64 | S362: 62 | T362: 71 | U362: 72 | V362: 72
A363: 44959 | B363: =YEAR(A363) -> 2023 | D363: =MONTH(A363) -> 2 | E363: 50 | F363: 51 | G363: 50 | H363: 68 | I363: 74 | J363: 71 | K363: 36 | L363: 42 | M363: 39 | N363: 129 | O363: 132 | P363: 130 | Q363: 60 | R363: 63 | S363: 62 | T363: 70 | U363: 71 | V363: 70
A364: 44966 | B364: =YEAR(A364) -> 2023 | D364: =MONTH(A364) -> 2 | E364: 49 | F364: 50 | G364: 50 | H364: 68 | I364: 74 | J364: 71 | K364: 37 | L364: 43 | M364: 40 | N364: 129 | O364: 132 | P364: 130 | Q364: 60 | R364: 63 | S364: 62 | T364: 70 | U364: 71 | V364: 70
A365: 44973 | B365: =YEAR(A365) -> 2023 | D365: =MONTH(A365) -> 2 | E365: 49 | F365: 50 | G365: 50 | H365: 68 | I365: 74 | J365: 71 | K365: 37 | L365: 43 | M365: 40 | N365: 129 | O365: 132 | P365: 130 | Q365: 60 | R365: 63 | S365: 62 | T365: 70 | U365: 71 | V365: 70
A366: 44980 | B366: =YEAR(A366) -> 2023 | D366: =MONTH(A366) -> 2 | E366: 49 | F366: 50 | G366: 50 | H366: 66 | I366: 72 | J366: 69 | K366: 36 | L366: 42 | M366: 39 | N366: 126 | O366: 129 | P366: 128 | Q366: 57 | R366: 60 | S366: 58 | T366: 67 | U366: 68 | V366: 68
A367: 44987 | B367: =YEAR(A367) -> 2023 | D367: =MONTH(A367) -> 3 | E367: 49 | F367: 50 | G367: 50 | H367: 65 | I367: 71 | J367: 68 | K367: 35 | L367: 41 | M367: 38 | N367: 125 | O367: 128 | P367: 126 | Q367: 56 | R367: 59 | S367: 58 | T367: 66 | U367: 67 | V367: 66
A368: 44994 | B368: =YEAR(A368) -> 2023 | D368: =MONTH(A368) -> 3 | E368: 48 | F368: 49 | G368: 48 | H368: 64 | I368: 70 | J368: 67 | K368: 34 | L368: 40 | M368: 37 | N368: 124 | O368: 127 | P368: 126 | Q368: 55 | R368: 68 | S368: 62 | T368: 65 | U368: 66 | V368: 66
A369: 45001 | B369: =YEAR(A369) -> 2023 | D369: =MONTH(A369) -> 3 | E369: 50 | F369: 51 | G369: 50 | H369: 64 | I369: 70 | J369: 67 | K369: 34 | L369: 40 | M369: 37 | N369: 124 | O369: 127 | P369: 126 | Q369: 55 | R369: 68 | S369: 62 | T369: 65 | U369: 66 | V369: 66
A370: 45008 | B370: =YEAR(A370) -> 2023 | D370: =MONTH(A370) -> 3 | E370: 50 | F370: 51 | G370: 50 | H370: 64 | I370: 70 | J370: 67 | K370: 34 | L370: 40 | M370: 37 | N370: 124 | O370: 127 | P370: 126 | Q370: 55 | R370: 68 | S370: 62 | T370: 65 | U370: 66 | V370: 66
... A409: 45281 | B409: =YEAR(A409) -> 2023 | D409: =MONTH(A409) -> 12 | E409: 45 | F409: 46 | G409: 46 | H409: 59 | I409: 60 | J409: 60 | K409: 31 | L409: 34 | M409: 32 | N409: 120 | O409: 127 | P409: 124 | Q409: 53 | R409: 60 | S409: 56 | T409: 58 | U409: 64 | V409: 61
A410: 45288 | B410: =YEAR(A410) -> 2023 | D410: =MONTH(A410) -> 12
A411: 45295 | B411: =YEAR(A411) -> 2024 | D411: =MONTH(A411) -> 1 | E411: 45 | F411: 46 | G411: 46 | H411: 59 | I411: 60 | J411: 60 | K411: 31 | L411: 34 | M411: 32 | N411: 120 | O411: 127 | P411: 124 | Q411: 53 | R411: 60 | S411: 56 | T411: 58 | U411: 64 | V411: 61
A412: 45302 | B412: =YEAR(A412) -> 2024 | D412: =MONTH(A412) -> 1 | E412: 45 | F412: 46 | G412: 46 | H412: 59 | I412: 60 | J412: 60 | K412: 31 | L412: 34 | M412: 32 | N412: 120 | O412: 127 | P412: 124 | Q412: 53 | R412: 60 | S412: 56 | T412: 58 | U412: 64 | V412: 61
A413: 45309 | B413: =YEAR(A413) -> 2024 | D413: =MONTH(A413) -> 1 | E413: 45 | F413: 46 | G413: 46 | H413: 59 | I413: 60 | J413: 60 | K413: 31 | L413: 34 | M413: 32 | N413: 120 | O413: 127 | P413: 124 | Q413: 53 | R413: 60 | S413: 56 | T413: 58 | U413: 64 | V413: 61
A414: 45316 | B414: =YEAR(A414) -> 2024 | D414: =MONTH(A414) -> 1 | E414: 45 | F414: 46 | G414: 46 | H414: 59 | I414: 60 | J414: 60 | K414: 31 | L414: 34 | M414: 32 | N414: 120 | O414: 127 | P414: 124 | Q414: 53 | R414: 60 | S414: 56 | T414: 58 | U414: 64 | V414: 61
A415: 45323 | B415: =YEAR(A415) -> 2024 | D415: =MONTH(A415) -> 2 | E415: 45 | F415: 46 | G415: 46 | H415: 59 | I415: 60 | J415: 60 | K415: 31 | L415: 34 | M415: 32 | N415: 120 | O415: 127 | P415: 124 | Q415: 53 | R415: 60 | S415: 56 | T415: 58 | U415: 64 | V415: 61
A416: 45330 | B416: =YEAR(A416) -> 2024 | D416: =MONTH(A416) -> 2 | E416: 43 | F416: 45 | G416: 44 | H416: 59 | I416: 60 | J416: 60 | K416: 33 | L416: 36 | M416: 34 | N416: 122 | O416: 129 | P416: 126 | Q416: 55 | R416: 62 | S416: 58 | T416: 60 | U416: 66 | V416: 63
A417: 45337 | B417: =YEAR(A417) -> 2024 | D417: =MONTH(A417) -> 2 | E417: 43 | F417: 45 | G417: 44 | H417: 58 | I417: 59 | J417: 58 | K417: 33 | L417: 36 | M417: 34 | N417: 122 | O417: 129 | P417: 126 | Q417: 55 | R417: 62 | S417: 58 | T417: 60 | U417: 66 | V417: 63
A418: 45344 | B418: =YEAR(A418) -> 2024 | D418: =MONTH(A418) -> 2 | E418: 44 | F418: 46 | G418: 45 | H418: 58 | I418: 59 | J418: 58 | K418: 33 | L418: 36 | M418: 34 | N418: 122 | O418: 129 | P418: 126 | Q418: 55 | R418: 62 | S418: 58 | T418: 60 | U418: 66 | V418: 63
A419: 45351 | B419: =YEAR(A419) -> 2024 | D419: =MONTH(A419) -> 2 | E419: 44 | F419: 46 | G419: 45 | H419: 57 | I419: 58 | J419: 58 | K419: 33 | L419: 36 | M419: 34 | N419: 122 | O419: 129 | P419: 126 | Q419: 55 | R419: 62 | S419: 58 | T419: 60 | U419: 66 | V419: 63
A420: 45358 | B420: =YEAR(A420) -> 2024 | D420: =MONTH(A420) -> 3 | E420: 44 | F420: 46 | G420: 45 | H420: 57 | I420: 58 | J420: 58 | K420: 33 | L420: 36 | M420: 34 | N420: 122 | O420: 129 | P420: 126 | Q420: 55 | R420: 62 | S420: 58 | T420: 60 | U420: 66 | V420: 63
A421: 45365 | B421: =YEAR(A421) -> 2024 | D421: =MONTH(A421) -> 3 | E421: 43 | F421: 45 | G421: 44 | H421: 66 | I421: 69 | J421: 68 | K421: 33 | L421: 36 | M421: 34 | N421: 122 | O421: 129 | P421: 126 | Q421: 55 | R421: 62 | S421: 58 | T421: 60 | U421: 66 | V421: 63
A422: 45372 | B422: =YEAR(A422) -> 2024 | D422: =MONTH(A422) -> 3 | E422: 43 | F422: 45 | G422: 44 | H422: 66 | I422: 69 | J422: 68 | K422: 33 | L422: 36 | M422: 34 | N422: 122 | O422: 129 | P422: 126 | Q422: 55 | R422: 62 | S422: 58 | T422: 60 | U422: 66 | V422: 63
... A460: 45638 | B460: =YEAR(A460) -> 2024 | D460: =MONTH(A460) -> 12 | E460: 34 | F460: 37 | G460: 36 | H460: 49 | I460: 52 | J460: 50 | K460: 25 | L460: 28 | M460: 26 | N460: 129 | O460: 141 | P460: 135 | Q460: 27 | R460: 34 | S460: 30 | T460: 57 | U460: 64 | V460: 60
A461: 45645 | B461: =YEAR(A461) -> 2024 | D461: =MONTH(A461) -> 12 | E461: 33 | F461: 36 | G461: 34 | H461: 48 | I461: 51 | J461: 50 | K461: 25 | L461: 28 | M461: 26 | N461: 129 | O461: 141 | P461: 135 | T461: 57 | U461: 64 | V461: 60
A462: 45652 | B462: =YEAR(A462) -> 2024 | D462: =MONTH(A462) -> 12
A463: 45659 | B463: =YEAR(A463) -> 2025 | D463: =MONTH(A463) -> 1 | E463: 33 | F463: 36 | G463: 34 | H463: 48 | I463: 51 | J463: 50 | K463: 25 | L463: 28 | M463: 26 | N463: 129 | O463: 141 | P463: 135 | T463: 57 | U463: 64 | V463: 60
A464: 45666 | B464: =YEAR(A464) -> 2025 | D464: =MONTH(A464) -> 1 | E464: 33 | F464: 36 | G464: 34 | H464: 48 | I464: 51 | J464: 50 | K464: 25 | L464: 28 | M464: 26 | N464: 129 | O464: 141 | P464: 135 | T464: 57 | U464: 64 | V464: 60
A465: 45673 | B465: =YEAR(A465) -> 2025 | D465: =MONTH(A465) -> 1 | E465: 27 | F465: 30 | G465: 28 | H465: 47 | I465: 50 | J465: 48 | K465: 25 | L465: 28 | M465: 26 | N465: 129 | O465: 141 | P465: 135 | T465: 59 | U465: 65 | V465: 62
A466: 45680 | B466: =YEAR(A466) -> 2025 | D466: =MONTH(A466) -> 1 | E466: 27 | F466: 30 | G466: 28 | H466: 47 | I466: 50 | J466: 48 | K466: 25 | L466: 28 | M466: 26 | N466: 129 | O466: 141 | P466: 135 | T466: 59 | U466: 65 | V466: 62
A467: 45687 | B467: =YEAR(A467) -> 2025 | D467: =MONTH(A467) -> 1 | E467: 27 | F467: 30 | G467: 28 | H467: 47 | I467: 50 | J467: 48 | K467: 25 | L467: 28 | M467: 26 | N467: 119 | O467: 131 | P467: 125 | T467: 59 | U467: 65 | V467: 62
A468: 45694 | B468: =YEAR(A468) -> 2025 | D468: =MONTH(A468) -> 2 | E468: 27 | F468: 30 | G468: 28 | H468: 47 | I468: 50 | J468: 48 | K468: 25 | L468: 28 | M468: 26 | N468: 119 | O468: 131 | P468: 125 | T468: 59 | U468: 65 | V468: 62
A469: 45701 | B469: =YEAR(A469) -> 2025 | D469: =MONTH(A469) -> 2 | E469: 28 | F469: 31 | G469: 30 | H469: 47 | I469: 50 | J469: 48 | K469: 25 | L469: 28 | M469: 26 | N469: 115 | O469: 127 | P469: 121 | T469: 59 | U469: 65 | V469: 62 | W469: 73 | X469: 78 | Y469: 76 | Z469: 60 | AA469: 65 | AB469: 62 | AC469: 38 | AD469: 51 | AE469: 44 | AF469: 116 | AG469: 126 | AH469: 121
A470: 45708 | B470: =YEAR(A470) -> 2025 | D470: =MONTH(A470) -> 2 | E470: 28 | F470: 31 | G470: 30 | H470: 44 | I470: 47 | J470: 46 | K470: 22 | L470: 25 | M470: 24 | N470: 114 | O470: 126 | P470: 120 | T470: 57 | U470: 63 | V470: 60 | W470: 73 | X470: 78 | Y470: 76 | Z470: 58 | AA470: 63 | AB470: 60 | AC470: 36 | AD470: 49 | AE470: 42 | AF470: 114 | AG470: 124 | AH470: 119
A471: 45715 | B471: =YEAR(A471) -> 2025 | D471: =MONTH(A471) -> 2 | E471: 27 | F471: 30 | G471: 28 | H471: 44 | I471: 47 | J471: 46 | K471: 22 | L471: 25 | M471: 24 | N471: 114 | O471: 126 | P471: 120 | T471: 57 | U471: 63 | V471: 60 | W471: 73 | X471: 78 | Y471: 76 | Z471: 58 | AA471: 63 | AB471: 60 | AC471: 36 | AD471: 49 | AE471: 42 | AF471: 114 | AG471: 124 | AH471: 119
A472: 45722 | B472: =YEAR(A472) -> 2025 | D472: =MONTH(A472) -> 3 | E472: 27 | F472: 30 | G472: 28 | H472: 44 | I472: 47 | J472: 46 | K472: 22 | L472: 25 | M472: 24 | N472: 107 | O472: 119 | P472: 113 | T472: 55 | U472: 61 | V472: 58 | W472: 73 | X472: 78 | Y472: 76 | Z472: 56 | AA472: 61 | AB472: 58 | AC472: 35 | AD472: 48 | AE472: 42 | AF472: 105 | AG472: 115 | AH472: 110
A473: 45729 | B473: =YEAR(A473) -> 2025 | D473: =MONTH(A473) -> 3 | E473: 27 | F473: 30 | G473: 28 | H473: 44 | I473: 47 | J473: 46 | K473: 22 | L473: 25 | M473: 24 | N473: 107 | O473: 119 | P473: 113 | T473: 55 | U473: 61 | V473: 58 | W473: 73 | X473: 78 | Y473: 76 | Z473: 56 | AA473: 61 | AB473: 58 | AC473: 35 | AD473: 48 | AE473: 42 | AF473: 105 | AG473: 115 | AH473: 110
A474: 45736 | B474: =YEAR(A474) -> 2025 | D474: =MONTH(A474) -> 3 | E474: 27 | F474: 30 | G474: 28 | H474: 44 | I474: 47 | J474: 46 | K474: 22 | L474: 25 | M474: 24 | N474: 107 | O474: 119 | P474: 113 | T474: 55 | U474: 61 | V474: 58 | W474: 73 | X474: 78 | Y474: 76 | Z474: 50 | AA474: 55 | AB474: 52 | AC474: 35 | AD474: 48 | AE474: 42 | AF474: 105 | AG474: 115 | AH474: 110
A475: 45743 | B475: =YEAR(A475) -> 2025 | D475: =MONTH(A475) -> 3 | E475: 27 | F475: 30 | G475: 28 | H475: 44 | I475: 47 | J475: 46 | K475: 22 | L475: 25 | M475: 24 | N475: 107 | O475: 119 | P475: 113 | T475: 55 | U475: 61 | V475: 58 | W475: 73 | X475: 78 | Y475: 76 | Z475: 50 | AA475: 55 | AB475: 52 | AC475: 35 | AD475: 48 | AE475: 42 | AF475: 105 | AG475: 115 | AH475: 110
A476: 45750 | B476: =YEAR(A476) -> 2025 | D476: =MONTH(A476) -> 4 | E476: 27 | F476: 30 | G476: 28 | H476: 44 | I476: 47 | J476: 46 | K476: 22 | L476: 25 | M476: 24 | N476: 107 | O476: 119 | P476: 113 | T476: 55 | U476: 61 | V476: 58 | W476: 73 | X476: 78 | Y476: 76 | Z476: 50 | AA476: 55 | AB476: 52 | AC476: 35 | AD476: 48 | AE476: 42 | AF476: 105 | AG476: 115 | AH476: 110
A477: 45757 | B477: =YEAR(A477) -> 2025 | D477: =MONTH(A477) -> 4 | E477: 27 | F477: 30 | G477: 28 | H477: 44 | I477: 47 | J477: 46 | K477: 22 | L477: 25 | M477: 24 | N477: 105 | O477: 117 | P477: 111 | T477: 53 | U477: 59 | V477: 56 | W477: 73 | X477: 78 | Y477: 76 | Z477: 50 | AA477: 55 | AB477: 52 | AC477: 35 | AD477: 48 | AE477: 42 | AF477: 105 | AG477: 115 | AH477: 110
A478: 45764 | B478: =YEAR(A478) -> 2025 | D478: =MONTH(A478) -> 4 | E478: 27 | F478: 30 | G478: 28 | H478: 44 | I478: 47 | J478: 46 | K478: 22 | L478: 25 | M478: 24 | N478: 105 | O478: 117 | P478: 111 | T478: 53 | U478: 59 | V478: 56 | W478: 73 | X478: 78 | Y478: 76 | Z478: 50 | AA478: 55 | AB478: 52 | AC478: 35 | AD478: 48 | AE478: 42 | AF478: 105 | AG478: 115 | AH478: 110
A479: 45771 | B479: =YEAR(A479) -> 2025 | D479: =MONTH(A479) -> 4 | E479: 27 | F479: 30 | G479: 28 | H479: 44 | I479: 47 | J479: 46 | K479: 22 | L479: 25 | M479: 24 | N479: 105 | O479: 117 | P479: 111 | T479: 53 | U479: 59 | V479: 56 | W479: 73 | X479: 78 | Y479: 76 | Z479: 50 | AA479: 55 | AB479: 52 | AC479: 35 | AD479: 48 | AE479: 42 | AF479: 105 | AG479: 115 | AH479: 110
A480: 45778 | B480: =YEAR(A480) -> 2025 | D480: =MONTH(A480) -> 5 | E480: 27 | F480: 30 | G480: 28 | H480: 44 | I480: 47 | J480: 46 | K480: 22 | L480: 25 | M480: 24 | N480: 105 | O480: 117 | P480: 111 | T480: 53 | U480: 59 | V480: 56 | W480: 73 | X480: 78 | Y480: 76 | Z480: 50 | AA480: 55 | AB480: 52 | AC480: 35 | AD480: 48 | AE480: 42 | AF480: 105 | AG480: 115 | AH480: 110
... A513: 46009 | B513: =YEAR(A513) -> 2025 | D513: =MONTH(A513) -> 12 | E513: 30 | F513: 33 | G513: 32 | H513: 42 | I513: 45 | J513: 44 | K513: 21 | L513: 24 | M513: 22 | N513: 93 | O513: 105 | P513: 99 | T513: 44 | U513: 50 | V513: 47 | W513: 69 | X513: 74 | Y513: 72 | Z513: 43 | AA513: 48 | AB513: 46 | AC513: 29 | AD513: 39 | AE513: 34 | AF513: 93 | AG513: 103 | AH513: 98

Sheet Sulphur freight
E1: Middle East - Morocco 35-40,000 mt 10,000c/5,000x | H1: Black Sea - Morocco 25-30,000 mt 8,000c/5,000x
B2: year | C2: quarter | D2: month | E2: low | F2: high | G2: ave | H2: low | I2: high | J2: ave
A3: 31897 | B3: =YEAR(A3) -> 1987 | D3: =MONTH(A3) -> 4
A4: 31904 | B4: =YEAR(A4) -> 1987 | D4: =MONTH(A4) -> 5
A5: 31911 | B5: =YEAR(A5) -> 1987 | D5: =MONTH(A5) -> 5
A6: 31918 | B6: =YEAR(A6) -> 1987 | D6: =MONTH(A6) -> 5
A7: 31925 | B7: =YEAR(A7) -> 1987 | D7: =MONTH(A7) -> 5
A8: 31932 | B8: =YEAR(A8) -> 1987 | D8: =MONTH(A8) -> 6
A9: 31939 | B9: =YEAR(A9) -> 1987 | D9: =MONTH(A9) -> 6
A10: 31946 | B10: =YEAR(A10) -> 1987 | D10: =MONTH(A10) -> 6
A11: 31953 | B11: =YEAR(A11) -> 1987 | D11: =MONTH(A11) -> 6
A12: 31960 | B12: =YEAR(A12) -> 1987 | D12: =MONTH(A12) -> 7
A13: 31967 | B13: =YEAR(A13) -> 1987 | D13: =MONTH(A13) -> 7
A14: 31974 | B14: =YEAR(A14) -> 1987 | D14: =MONTH(A14) -> 7
... A1024: 39303 | B1024: =YEAR(A1024) -> 2007 | D1024: =MONTH(A1024) -> 8
A1025: 39310 | B1025: =YEAR(A1025) -> 2007 | D1025: =MONTH(A1025) -> 8 | E1025: 45 | F1025: 47 | G1025: 46 | H1025: 34 | I1025: 36 | J1025: 35
A1026: 39317 | B1026: =YEAR(A1026) -> 2007 | D1026: =MONTH(A1026) -> 8 | E1026: 45 | F1026: 47 | G1026: 46 | H1026: 34 | I1026: 36 | J1026: 35
A1027: 39324 | B1027: =YEAR(A1027) -> 2007 | D1027: =MONTH(A1027) -> 8 | E1027: 45 | F1027: 47 | G1027: 46 | H1027: 34 | I1027: 36 | J1027: 35
A1028: 39331 | B1028: =YEAR(A1028) -> 2007 | D1028: =MONTH(A1028) -> 9 | E1028: 45 | F1028: 47 | G1028: 46 | H1028: 34 | I1028: 36 | J1028: 35
A1029: 39338 | B1029: =YEAR(A1029) -> 2007 | D1029: =MONTH(A1029) -> 9 | E1029: 45 | F1029: 47 | G1029: 46 | H1029: 34 | I1029: 36 | J1029: 35
A1030: 39345 | B1030: =YEAR(A1030) -> 2007 | D1030: =MONTH(A1030) -> 9 | E1030: 45 | F1030: 47 | G1030: 46 | H1030: 34 | I1030: 36 | J1030: 35
A1031: 39352 | B1031: =YEAR(A1031) -> 2007 | D1031: =MONTH(A1031) -> 9 | E1031: 45 | F1031: 47 | G1031: 46 | H1031: 34 | I1031: 36 | J1031: 35
A1032: 39359 | B1032: =YEAR(A1032) -> 2007 | D1032: =MONTH(A1032) -> 10 | E1032: 45 | F1032: 47 | G1032: 46 | H1032: 34 | I1032: 36 | J1032: 35
A1033: 39366 | B1033: =YEAR(A1033) -> 2007 | D1033: =MONTH(A1033) -> 10 | E1033: 45 | F1033: 47 | G1033: 46 | H1033: 34 | I1033: 36 | J1033: 35
A1034: 39373 | B1034: =YEAR(A1034) -> 2007 | D1034: =MONTH(A1034) -> 10 | E1034: 45 | F1034: 47 | G1034: 46 | H1034: 34 | I1034: 36 | J1034: 35
A1035: 39380 | B1035: =YEAR(A1035) -> 2007 | D1035: =MONTH(A1035) -> 10 | E1035: 51 | F1035: 55 | G1035: 53 | H1035: 40 | I1035: 44 | J1035: 42
A1036: 39387 | B1036: =YEAR(A1036) -> 2007 | D1036: =MONTH(A1036) -> 11 | E1036: 51 | F1036: 55 | G1036: 53 | H1036: 40 | I1036: 44 | J1036: 42
... A1107: 39905 | B1107: =YEAR(A1107) -> 2009 | D1107: =MONTH(A1107) -> 4 | E1107: 17 | F1107: 19 | G1107: 18 | H1107: 16 | I1107: 18 | J1107: 17
A1108: 39912 | B1108: =YEAR(A1108) -> 2009 | D1108: =MONTH(A1108) -> 4
A1109: 39919 | B1109: =YEAR(A1109) -> 2009 | D1109: =MONTH(A1109) -> 4 | E1109: 18 | F1109: 20 | G1109: 19 | H1109: 16 | I1109: 18 | J1109: 17
A1110: 39926 | B1110: =YEAR(A1110) -> 2009 | D1110: =MONTH(A1110) -> 4 | E1110: 18 | F1110: 20 | G1110: 19 | H1110: 17 | I1110: 19 | J1110: 18
A1111: 39933 | B1111: =YEAR(A1111) -> 2009 | D1111: =MONTH(A1111) -> 4 | E1111: 17 | F1111: 19 | G1111: 18 | H1111: 17 | I1111: 19 | J1111: 18
A1112: 39940 | B1112: =YEAR(A1112) -> 2009 | D1112: =MONTH(A1112) -> 5 | E1112: 18 | F1112: 20 | G1112: 19 | H1112: 17 | I1112: 19 | J1112: 18
A1113: 39947 | B1113: =YEAR(A1113) -> 2009 | D1113: =MONTH(A1113) -> 5 | E1113: 21 | F1113: 23 | G1113: 22 | H1113: 18 | I1113: 20 | J1113: 19
A1114: 39954 | B1114: =YEAR(A1114) -> 2009 | D1114: =MONTH(A1114) -> 5
A1115: 39961 | B1115: =YEAR(A1115) -> 2009 | D1115: =MONTH(A1115) -> 5 | E1115: 22 | F1115: 24 | G1115: 23 | H1115: 19 | I1115: 21 | J1115: 20
A1116: 39968 | B1116: =YEAR(A1116) -> 2009 | D1116: =MONTH(A1116) -> 6 | E1116: 22 | F1116: 24 | G1116: 23 | H1116: 20 | I1116: 22 | J1116: 21
A1117: 39975 | B1117: =YEAR(A1117) -> 2009 | D1117: =MONTH(A1117) -> 6 | E1117: 22 | F1117: 24 | G1117: 23 | H1117: 19 | I1117: 21 | J1117: 20
A1118: 39982 | B1118: =YEAR(A1118) -> 2009 | D1118: =MONTH(A1118) -> 6 | E1118: 22 | F1118: 24 | G1118: 23 | H1118: 18 | I1118: 20 | J1118: 19
A1119: 39989 | B1119: =YEAR(A1119) -> 2009 | D1119: =MONTH(A1119) -> 6 | E1119: 21 | F1119: 23 | G1119: 22 | H1119: 17 | I1119: 19 | J1119: 18
A1120: 39996 | B1120: =YEAR(A1120) -> 2009 | D1120: =MONTH(A1120) -> 7 | E1120: 22 | F1120: 24 | G1120: 23 | H1120: 17 | I1120: 19 | J1120: 18
A1121: 40003 | B1121: =YEAR(A1121) -> 2009 | D1121: =MONTH(A1121) -> 7 | E1121: 21 | F1121: 23 | G1121: 22 | H1121: 17 | I1121: 19 | J1121: 18
A1122: 40010 | B1122: =YEAR(A1122) -> 2009 | D1122: =MONTH(A1122) -> 7 | E1122: 22 | F1122: 24 | G1122: 23 | H1122: 18 | I1122: 20 | J1122: 19
A1123: 40017 | B1123: =YEAR(A1123) -> 2009 | D1123: =MONTH(A1123) -> 7 | E1123: 24 | F1123: 26 | G1123: 25 | H1123: 20 | I1123: 22 | J1123: 21
A1124: 40024 | B1124: =YEAR(A1124) -> 2009 | D1124: =MONTH(A1124) -> 7 | E1124: 24 | F1124: 26 | G1124: 25 | H1124: 20 | I1124: 22 | J1124: 21
A1125: 40031 | B1125: =YEAR(A1125) -> 2009 | D1125: =MONTH(A1125) -> 8 | E1125: 23 | F1125: 25 | G1125: 24 | H1125: 20 | I1125: 22 | J1125: 21
A1126: 40038 | B1126: =YEAR(A1126) -> 2009 | D1126: =MONTH(A1126) -> 8 | E1126: 24 | F1126: 26 | G1126: 25 | H1126: 20 | I1126: 22 | J1126: 21
... A1403: 41998 | B1403: =YEAR(A1403) -> 2014 | D1403: =MONTH(A1403) -> 12 | E1403: 22 | F1403: 24 | G1403: 23 | H1403: 14 | I1403: 16 | J1403: 15
A1404: 42003 | B1404: =YEAR(A1404) -> 2014 | D1404: =MONTH(A1404) -> 12
A1405: 42012 | B1405: =YEAR(A1405) -> 2015 | D1405: =MONTH(A1405) -> 1 | E1405: 21 | F1405: 23 | G1405: 22 | H1405: 12 | I1405: 14 | J1405: 13
A1406: 42019 | B1406: =YEAR(A1406) -> 2015 | D1406: =MONTH(A1406) -> 1 | E1406: 21 | F1406: 23 | G1406: 22 | H1406: 12 | I1406: 14 | J1406: 13
A1407: 42026 | B1407: =YEAR(A1407) -> 2015 | D1407: =MONTH(A1407) -> 1 | E1407: 21 | F1407: 23 | G1407: 22 | H1407: 12 | I1407: 14 | J1407: 13
A1408: 42033 | B1408: =YEAR(A1408) -> 2015 | D1408: =MONTH(A1408) -> 1 | E1408: 21 | F1408: 23 | G1408: 22 | H1408: 12 | I1408: 14 | J1408: 13
A1409: 42040 | B1409: =YEAR(A1409) -> 2015 | D1409: =MONTH(A1409) -> 2 | E1409: 21 | F1409: 23 | G1409: 22 | H1409: 12 | I1409: 14 | J1409: 13
A1410: 42047 | B1410: =YEAR(A1410) -> 2015 | D1410: =MONTH(A1410) -> 2 | E1410: 21 | F1410: 23 | G1410: 22 | H1410: 12 | I1410: 14 | J1410: 13
A1411: 42054 | B1411: =YEAR(A1411) -> 2015 | D1411: =MONTH(A1411) -> 2 | E1411: 22 | F1411: 24 | G1411: 23 | H1411: 12 | I1411: 14 | J1411: 13
A1412: 42061 | B1412: =YEAR(A1412) -> 2015 | D1412: =MONTH(A1412) -> 2 | E1412: 21 | F1412: 23 | G1412: 22 | H1412: 12 | I1412: 14 | J1412: 13
A1413: 42068 | B1413: =YEAR(A1413) -> 2015 | D1413: =MONTH(A1413) -> 3 | E1413: 21 | F1413: 23 | G1413: 22 | H1413: 12 | I1413: 14 | J1413: 13
A1414: 42075 | B1414: =YEAR(A1414) -> 2015 | D1414: =MONTH(A1414) -> 3 | E1414: 21 | F1414: 23 | G1414: 22 | H1414: 12 | I1414: 14 | J1414: 13
A1415: 42082 | B1415: =YEAR(A1415) -> 2015 | D1415: =MONTH(A1415) -> 3 | E1415: 21 | F1415: 23 | G1415: 22 | H1415: 12 | I1415: 14 | J1415: 13
A1416: 42089 | B1416: =YEAR(A1416) -> 2015 | D1416: =MONTH(A1416) -> 3 | E1416: 21 | F1416: 23 | G1416: 22 | H1416: 12 | I1416: 14 | J1416: 13
... A1455: 42362 | B1455: =YEAR(A1455) -> 2015 | D1455: =MONTH(A1455) -> 12 | E1455: 14 | F1455: 16 | G1455: 15 | H1455: 10 | I1455: 12 | J1455: 11
A1456: 42369 | B1456: =YEAR(A1456) -> 2015 | D1456: =MONTH(A1456) -> 12
A1457: 42376 | B1457: =YEAR(A1457) -> 2016 | D1457: =MONTH(A1457) -> 1 | E1457: 12 | F1457: 14 | G1457: 13 | H1457: 9 | I1457: 11 | J1457: 10
A1458: 42383 | B1458: =YEAR(A1458) -> 2016 | D1458: =MONTH(A1458) -> 1 | E1458: 12 | F1458: 14 | G1458: 13 | H1458: 8 | I1458: 10 | J1458: 9
A1459: 42390 | B1459: =YEAR(A1459) -> 2016 | D1459: =MONTH(A1459) -> 1 | E1459: 12 | F1459: 14 | G1459: 13 | H1459: 8 | I1459: 10 | J1459: 9
A1460: 42397 | B1460: =YEAR(A1460) -> 2016 | D1460: =MONTH(A1460) -> 1 | E1460: 12 | F1460: 14 | G1460: 13 | H1460: 8 | I1460: 10 | J1460: 9
A1461: 42404 | B1461: =YEAR(A1461) -> 2016 | D1461: =MONTH(A1461) -> 2 | E1461: 11 | F1461: 13 | G1461: 12 | H1461: 8 | I1461: 10 | J1461: 9
A1462: 42411 | B1462: =YEAR(A1462) -> 2016 | D1462: =MONTH(A1462) -> 2 | E1462: 11 | F1462: 13 | G1462: 12 | H1462: 8 | I1462: 10 | J1462: 9
A1463: 42418 | B1463: =YEAR(A1463) -> 2016 | D1463: =MONTH(A1463) -> 2 | E1463: 11 | F1463: 13 | G1463: 12 | H1463: 8 | I1463: 10 | J1463: 9
A1464: 42425 | B1464: =YEAR(A1464) -> 2016 | D1464: =MONTH(A1464) -> 2 | E1464: 12 | F1464: 14 | G1464: 13 | H1464: 9 | I1464: 11 | J1464: 10
A1465: 42432 | B1465: =YEAR(A1465) -> 2016 | D1465: =MONTH(A1465) -> 3 | E1465: 13 | F1465: 15 | G1465: 14 | H1465: 10 | I1465: 12 | J1465: 11
A1466: 42439 | B1466: =YEAR(A1466) -> 2016 | D1466: =MONTH(A1466) -> 3 | E1466: 15 | F1466: 17 | G1466: 16 | H1466: 10 | I1466: 12 | J1466: 11
A1467: 42446 | B1467: =YEAR(A1467) -> 2016 | D1467: =MONTH(A1467) -> 3 | E1467: 16 | F1467: 18 | G1467: 17 | H1467: 10 | I1467: 12 | J1467: 11
A1468: 42453 | B1468: =YEAR(A1468) -> 2016 | D1468: =MONTH(A1468) -> 3 | E1468: 14 | F1468: 16 | G1468: 15 | H1468: 10 | I1468: 12 | J1468: 11
... A1716: 44189 | B1716: =YEAR(A1716) -> 2020 | D1716: =MONTH(A1716) -> 12 | E1716: 17 | F1716: 19 | G1716: 18 | H1716: 21 | I1716: 23 | J1716: 22
A1717: 44196 | B1717: =YEAR(A1717) -> 2020 | D1717: =MONTH(A1717) -> 12
A1718: 44203 | B1718: =YEAR(A1718) -> 2021 | D1718: =MONTH(A1718) -> 1 | E1718: 19 | F1718: 21 | G1718: 20 | H1718: 21 | I1718: 23 | J1718: 22
A1719: 44210 | B1719: =YEAR(A1719) -> 2021 | D1719: =MONTH(A1719) -> 1 | E1719: 22 | F1719: 24 | G1719: 23 | H1719: 21 | I1719: 23 | J1719: 22
A1720: 44217 | B1720: =YEAR(A1720) -> 2021 | D1720: =MONTH(A1720) -> 1 | E1720: 22 | F1720: 24 | G1720: 23 | H1720: 19 | I1720: 21 | J1720: 20
A1721: 44224 | B1721: =YEAR(A1721) -> 2021 | D1721: =MONTH(A1721) -> 1 | E1721: 23 | F1721: 25 | G1721: 24 | H1721: 22 | I1721: 24 | J1721: 23
A1722: 44231 | B1722: =YEAR(A1722) -> 2021 | D1722: =MONTH(A1722) -> 2 | E1722: 24 | F1722: 26 | G1722: 25 | H1722: 23 | I1722: 25 | J1722: 24
A1723: 44238 | B1723: =YEAR(A1723) -> 2021 | D1723: =MONTH(A1723) -> 2 | E1723: 27 | F1723: 29 | G1723: 28 | H1723: 23 | I1723: 25 | J1723: 24
A1724: 44245 | B1724: =YEAR(A1724) -> 2021 | D1724: =MONTH(A1724) -> 2 | E1724: 27 | F1724: 29 | G1724: 28 | H1724: 26 | I1724: 28 | J1724: 27
A1725: 44252 | B1725: =YEAR(A1725) -> 2021 | D1725: =MONTH(A1725) -> 2 | E1725: 29 | F1725: 31 | G1725: 30 | H1725: 26 | I1725: 28 | J1725: 27
A1726: 44259 | B1726: =YEAR(A1726) -> 2021 | D1726: =MONTH(A1726) -> 3 | E1726: 31 | F1726: 33 | G1726: 32 | H1726: 31 | I1726: 33 | J1726: 32
A1727: 44266 | B1727: =YEAR(A1727) -> 2021 | D1727: =MONTH(A1727) -> 3 | E1727: 31 | F1727: 33 | G1727: 32 | H1727: 31 | I1727: 33 | J1727: 32
A1728: 44273 | B1728: =YEAR(A1728) -> 2021 | D1728: =MONTH(A1728) -> 3 | E1728: 29 | F1728: 31 | G1728: 30 | H1728: 31 | I1728: 33 | J1728: 32
A1729: 44280 | B1729: =YEAR(A1729) -> 2021 | D1729: =MONTH(A1729) -> 3 | E1729: 41 | F1729: 43 | G1729: 42 | H1729: 29 | I1729: 31 | J1729: 30
... A1768: 44553 | B1768: =YEAR(A1768) -> 2021 | D1768: =MONTH(A1768) -> 12 | E1768: 42 | F1768: 44 | G1768: 43 | H1768: 40 | I1768: 42 | J1768: 41
A1769: 44560 | B1769: =YEAR(A1769) -> 2021 | D1769: =MONTH(A1769) -> 12
A1770: 44567 | B1770: =YEAR(A1770) -> 2022 | D1770: =MONTH(A1770) -> 1 | E1770: 37 | F1770: 39 | G1770: 38 | H1770: 35 | I1770: 37 | J1770: 36
A1771: 44574 | B1771: =YEAR(A1771) -> 2022 | D1771: =MONTH(A1771) -> 1 | E1771: 35 | F1771: 37 | G1771: 36 | H1771: 34 | I1771: 36 | J1771: 35
A1772: 44581 | B1772: =YEAR(A1772) -> 2022 | D1772: =MONTH(A1772) -> 1 | E1772: 35 | F1772: 37 | G1772: 36 | H1772: 30 | I1772: 32 | J1772: 31
A1773: 44588 | B1773: =YEAR(A1773) -> 2022 | D1773: =MONTH(A1773) -> 1 | E1773: 35 | F1773: 37 | G1773: 36 | H1773: 27 | I1773: 29 | J1773: 28
A1774: 44595 | B1774: =YEAR(A1774) -> 2022 | D1774: =MONTH(A1774) -> 2 | E1774: 35 | F1774: 37 | G1774: 36 | H1774: 26 | I1774: 28 | J1774: 27
A1775: 44602 | B1775: =YEAR(A1775) -> 2022 | D1775: =MONTH(A1775) -> 2 | E1775: 40 | F1775: 42 | G1775: 41 | H1775: 28 | I1775: 30 | J1775: 29
A1776: 44609 | B1776: =YEAR(A1776) -> 2022 | D1776: =MONTH(A1776) -> 2 | E1776: 45 | F1776: 47 | G1776: 46 | H1776: 30 | I1776: 32 | J1776: 31
A1777: 44616 | B1777: =YEAR(A1777) -> 2022 | D1777: =MONTH(A1777) -> 2 | E1777: 54 | F1777: 56 | G1777: 55 | H1777: 33 | I1777: 35 | J1777: 34
A1778: 44623 | B1778: =YEAR(A1778) -> 2022 | D1778: =MONTH(A1778) -> 3 | E1778: 66 | F1778: 68 | G1778: 67 | H1778: 24 | I1778: 26 | J1778: 25
...

Sheet S - CRU Outlook
B1: FOB Vancouver (spot) | C1: FOB Middle East (spot) | D1: FOB Baltic Sea (spot) | E1: FOB US Gulf (spot) | F1: CFR China (spot) | G1: CFR India (spot) | H1: CFR Brazil (spot) | I1: CFR Indonesia (spot) | J1: CFR North Africa (contract) | K1: FOB Tampa (contract) | L1: CFR BENELUX (contract)
A2: 2010 | B2: 121.63462 | C2: 140.34615 | D2: 138.7451 | E2: 98.610819 | F2: 147.86538 | G2: 164.51923 | H2: 162.84615 | J2: 87.211538 | K2: 117.78846 | L2: 111.07692
A3: 2011 | B3: 208.96154 | C3: 200.30769 | D3: 204.67308 | E3: 163.6577 | F3: 226.5 | G3: 226.76923 | H3: 238.78846 | J3: 219.13462 | K3: 208.46154 | L3: 214.76923
A4: 2012 | B4: 181.83019 | C4: 176.24528 | D4: 178.66038 | E4: 184.97356 | F4: 198.43396 | G4: 199.11321 | H4: 210.39623 | J4: 202.26415 | K4: 174.22642 | L4: 214.83019
A5: 2013 | B5: 108.55769 | C5: 109.42308 | D5: 102.48077 | E5: 109.79716 | F5: 128.36538 | G5: 132.38462 | H5: 133.84615 | J5: 121.67308 | K5: 121.53846 | L5: 155.82692
A6: 2014 | B6: 150.86538 | C6: 153.96154 | D6: 140.26923 | E6: 136.38147 | F6: 158.34615 | G6: 173.80769 | H6: 168 | J6: 122.26923 | K6: 127.15385 | L6: 156.15385
A7: 2015 | B7: 138.71154 | C7: 145.84615 | D7: 135.90385 | E7: 140.18548 | F7: 149.26923 | G7: 162.65385 | H7: 156.25 | J7: 129.63462 | K7: 131.17308 | L7: 160.92308
A8: 2016 | B8: 80.346154 | C8: 85.096154 | D8: 69.923077 | E8: 79.353727 | F8: 88.557692 | G8: 99.288462 | H8: 88.807692 | J8: 84.346154 | K8: 76.442308 | L8: 120.53846
A9: 2017 | B9: 101.37255 | C9: 107.43137 | D9: 89.54902 | E9: 90.056944 | F9: 122 | G9: 125 | H9: 112.52941 | J9: 84.980392 | K9: 78.823529 | L9: 96.137255
A10: 2018 | B10: 131.09615 | C10: 136.63462 | D10: 123.40385 | E10: 127.21154 | F10: 154.42308 | G10: 156.65385 | H10: 148.53846 | J10: 137.51923 | K10: 122.44231 | L10: 120.96154
A11: 2019 | B11: 80.192308 | C11: 80.538462 | D11: 72.384615 | E11: 76.884615 | F11: 98.461538 | G11: 100 | H11: 93.75 | J11: 91 | K11: 81.192308 | L11: 131.23077
A12: 2020 | B12: 58.431373 | C12: 60.039216 | D12: 52.647059 | E12: 47.136364 | F12: 78.117647 | G12: 79.294118 | H12: 76.392157 | J12: 60.901961 | K12: 53.392157 | L12: 99.607843
A13: 2021 | B13: 176.54902 | C13: 187.78431 | D13: 179.17647 | E13: - | F13: 212.92157 | G13: 226.35294 | H13: 219.15686 | I13: 242.35484 | J13: 170.58824 | K13: 165.52941 | L13: 180.92157
A14: 2022 | B14: 264.03922 | C14: 277.29412 | D14: 202.94118 | E14: 257.70588 | F14: 303.33333 | G14: 304.23529 | H14: 307.58824 | I14: 304.4902 | J14: 275.37255 | K14: 311.82353 | L14: 292.90196
A15: 2023 | B15: 96.647059 | C15: 100 | D15: 74.098039 | E15: 94.901961 | F15: 121.86275 | G15: 122.39216 | H15: 120.29412 | I15: 124.70588 | J15: 121 | K15: 96.921569 | L15: 120.92157
A16: 2024 | B16: 92.076923 | C16: 103.96154 | D16: 68.211538 | E16: 93.673077 | F16: 126.36538 | G16: 125.28846 | H16: 123.88462 | I16: 126.67308 | J16: 105.44231 | K16: 84.538462 | L16: 138.32692
A17: 2025 | B17: 285.125 | C17: 300.91731 | D17: 253.03077 | E17: 280.69808 | F17: 313.03462 | G17: 313.29423 | H17: 310.14038 | I17: 318.24808 | J17: 248.57692 | K17: 248.90385 | L17: 251.69231
A18: 2026 | B18: 341.5431 | C18: 352.2931 | D18: 327.85218 | E18: 333.70838 | F18: 367.31825 | G18: 367.31825 | H18: 362.91087 | I18: 372.32663 | J18: 364.31322 | K18: 362.2931 | L18: 381.56825
A19: 2027 | B19: 234.46536 | C19: 241.46536 | D19: 218.77592 | E19: 224.54586 | F19: 256.2692 | G19: 256.2692 | H19: 253.31822 | I19: 261.20382 | J19: 253.30844 | K19: 244.46536 | L19: 281.2692
A20: 2028 | B20: 207.17653 | C20: 214.17653 | D20: 191.57362 | E20: 197.44871 | F20: 229.25015 | G20: 229.25015 | H20: 226.74539 | I20: 234.27469 | J20: 226.23543 | K20: 217.17653 | L20: 254.25015
A21: 2029 | B21: 199.51213 | C21: 206.51213 | D21: 185.27323 | E21: 191.18478 | F21: 221.6793 | G21: 221.6793 | H21: 220.66331 | I21: 226.73503 | J21: 218.64587 | K21: 209.51213 | L21: 246.6793
A22: 2030 | B22: 204.09327 | C22: 211.09327 | D22: 189.877 | E22: 195.78225 | F22: 226.24429 | G22: 226.24429 | H22: 225.22938 | I22: 231.29463 | J22: 223.21409 | K22: 214.09327 | L22: 251.24429

Sheet ACS - CRU Outlook
B1: CFR NW Europe – (€/t) | C1: CFR US Gulf | D1: FOB NW Europe | E1: CFR Brazil | F1: CFR India | G1: FOB Japan/South Korea (Spot/Contract) | H1: FOB Japan/South Korea (Spot) | I1: FOB China | J1: CFR Chile – contract
A2: 2010 | B2: 54.25 | C2: 98.583333 | D2: 52 | E2: 106.08333 | F2: - | G2: - | I2: - | J2: 56
A3: 2011 | B3: 91.25 | C3: 137.83333 | D3: 95.666667 | E3: 145.41667 | F3: - | G3: - | I3: - | J3: 109.58333
A4: 2012 | B4: 77.166667 | C4: 91.333333 | D4: 50.25 | E4: 96.083333 | F4: - | G4: 32.166667 | I4: - | J4: 155
A5: 2013 | B5: 69 | C5: 49.5 | D5: 12.166667 | E5: 58.5 | F5: - | G5: 3.8333333 | I5: - | J5: 96
A6: 2014 | B6: 67.416667 | C6: 53.916667 | D6: 13.916667 | E6: 62.083333 | F6: - | G6: 9.0833333 | I6: - | J6: 66.333333
A7: 2015 | B7: 68.083333 | C7: 67.75 | D7: 23.333333 | E7: 74.416667 | F7: 41 | G7: 16.083333 | I7: - | J7: 80
A8: 2016 | B8: 58.25 | C8: 39.583333 | D8: 7.4166667 | E8: 46.416667 | F8: 21 | G8: -1.0833333 | I8: - | J8: 55
A9: 2017 | B9: 58.916667 | C9: 46.166667 | D9: 18.333333 | E9: 60.833333 | F9: 43.083333 | G9: 9 | I9: - | J9: 30
A10: 2018 | B10: 72.25 | C10: 95 | D10: 59.166667 | E10: 100.91667 | F10: 73.5 | G10: 30.916667 | I10: - | J10: 71
A11: 2019 | B11: 87.416667 | C11: 86.75 | D11: 53 | E11: 89.416667 | F11: 59.083333 | G11: 21.5 | I11: 45.965 | J11: 133
A12: 2020 | B12: 85.583333 | C12: 45 | D12: 11.916667 | E12: 47.916667 | F12: 14.75 | G12: -10.916667 | I12: 8.2125 | J12: 72
A13: 2021 | B13: 100.33333 | C13: 173.08333 | D13: 138.75 | E13: 191.33333 | F13: 136.16667 | G13: 66.583333 | H13: 102.41667 | I13: 110.44 | J13: 63
A14: 2022 | B14: 158 | C14: 203.58333 | D14: 155.41667 | E14: 216.91667 | F14: 143 | G14: 63.833333 | H14: 89.583333 | I14: 89.166667 | J14: 240
A15: 2023 | B15: 131 | C15: 85 | D15: 29.833333 | E15: 92.25 | F15: 63.083333 | G15: 5 | H15: 11.916667 | I15: 14.083333 | J15: 148
A16: 2024 | B16: 138.08333 | C16: 119.16667 | D16: 75.166667 | E16: 139.66667 | F16: 84.5 | G16: 10.5 | H16: 25.916667 | I16: 34.5 | J16: 130
A17: 2025 | B17: 169.68081 | C17: 141.82071 | D17: 101.92308 | E17: 157.65686 | F17: 120.23333 | G17: 37.5 | H17: 49 | I17: 80.65 | J17: 155
A18: 2026 | B18: 156.9773 | C18: 141.15619 | D18: 83.482143 | E18: 158.64951 | F18: 129.67083 | G18: - | H18: 89.670833 | I18: 84.254167 | J18: 175
A19: 2027 | B19: 152.90592 | C19: 154.92922 | D19: 80.929219 | E19: 158.92922 | F19: 133.92922 | G19: - | H19: 59.929219 | I19: 65.929219 | J19: 164.92922
A20: 2028 | B20: 139.89543 | C20: 144.64446 | D20: 66.644459 | E20: 144.64446 | F20: 130.64446 | G20: - | H20: 54.644459 | I20: 60.644459 | J20: 159.64446
